Workbook
Name Ccy: MAIN!$C$6
Name circ: MAIN!$C$9
Name CoName: MAIN!$C$4
Name g: #REF!
Name IQ_CH: 110000
Name IQ_CQ: 5000
Name IQ_CY: 10000
Name IQ_DAILY: 500000
Name IQ_FH: 100000
Name IQ_FQ: 500
Name IQ_FY: 1000
Name IQ_LTM: 2000
Name IQ_MONTH: 15000
Name IQ_NTM: 6000
Name IQ_WEEK: 50000
Name IQ_YTD: 3000
Name OpCase: [1]DCF!$E$98
Name ScenarioREV: Assumptions!$D$4
Name TTS: #REF!
Name Units: MAIN!$C$7

Sheet MAIN
A1: =CoName -> BJ's Resturant Inc.
A2: Model Details
B4: Company name | C4: BJ's Resturant Inc. | E4: Current Stock Price | F4: 40 | H4: Operating Case One | I4: Perpetuity | J4: Terminal Mult | K4: Average
B5: Latest BS date | C5: =TODAY() -> 46007 | E5: S/O | F5: 21134 | H5: Implied Price | I5: ='DCF Model'!C18 -> 19.05675 | J5: ='DCF Model'!G18 -> 68.614651 | K5: =AVERAGE(I5:J5) -> 43.8357
B6: Currency | C6: USD | E6: Mkt Cap | F6: =F5*F4 -> 845360 | H6: Difference | I6: =I5/$F$4-1 -> -0.52358126 | J6: =J5/$F$4-1 -> 0.71536627 | K6: =K5/$F$4-1 -> 0.095892508
B7: Units | C7: m | E7: Cash | F7: 25431
B8: Analyst name | C8: Alan Chen | E8: Debt | F8: =43734+89500+367808 -> 501042
B9: Circular switch | C9: 0 | E9: EV | F9: =F6-F7+F8 -> 1320971

Sheet Quarterly Projections

Sheet Assumptions
A1: =CoName -> BJ's Resturant Inc. | C1: Hist. | D1: Hist. | E1: Hist. | F1: Proj. | G1: Proj. | H1: Proj. | I1: Proj. | J1: Proj.
A2: * | B2: Income Statement | C2: 2022 | D2: =C2+1 -> 2023 | E2: =D2+1 -> 2024 | F2: =E2+1 -> 2025 | G2: =F2+1 -> 2026 | H2: =G2+1 -> 2027 | I2: =H2+1 -> 2028 | J2: =I2+1 -> 2029
B4: Operating Case | D4: 1
D5: Variance
B6: Street Case | D6: 0 | F6: 0.03 | G6: 0.026 | H6: 0.025 | I6: 0.03 | J6: 0.03
B7: Optimistic Case | D7: 0.025 | F7: =F6+$D$7 -> 0.055 | G7: =G6+$D$7 -> 0.051 | H7: =H6+$D$7 -> 0.05 | I7: =I6+$D$7 -> 0.055 | J7: =J6+$D$7 -> 0.055
B8: Pessimistic Case | D8: -0.025 | F8: =F6+$D$8 -> 0.005 | G8: =G6+$D$8 -> 0.001 | H8: =H6+$D$8 -> 0 | I8: =I6+$D$8 -> 0.005 | J8: =J6+$D$8 -> 0.005
B10: Revenue Growth | D10: =IncState!D15/IncState!C15-1 -> 0.038400188 | E10: =IncState!E15/IncState!D15-1 -> 0.018056163 | F10: =CHOOSE(ScenarioREV,F6,F7,F8) -> 0.03 | G10: =CHOOSE(ScenarioREV,G6,G7,G8) -> 0.026 | H10: =CHOOSE(ScenarioREV,H6,H7,H8) -> 0.025 | I10: =CHOOSE(ScenarioREV,I6,I7,I8) -> 0.03 | J10: =CHOOSE(ScenarioREV,J6,J7,J8) -> 0.03
B11: COGS % of sales | C11: =IncState!C16/IncState!C15 -> 0.88724895 | D11: =IncState!D16/IncState!D15 -> 0.86664932 | E11: =IncState!E16/IncState!E15 -> 0.85589574 | F11: =E11-0.005 -> 0.85089574 | G11: =F11-0.005 -> 0.84589574 | H11: =G11-0.005 -> 0.84089574 | I11: =H11-0.005 -> 0.83589574 | J11: =I11-0.005 -> 0.83089574
B12: SG&A % of sales | C12: =IncState!C17/IncState!C15 -> 0.11477453 | D12: =IncState!D17/IncState!D15 -> 0.1169364 | E12: =IncState!E17/IncState!E15 -> 0.12016412 | F12: =AVERAGE(C12:E12) -> 0.11729168 | G12: =F12 -> 0.11729168 | H12: =G12 -> 0.11729168 | I12: =H12 -> 0.11729168 | J12: =I12 -> 0.11729168
B13: Amortization $ Amt | C13: =IncState!C21 -> 0 | D13: =IncState!D21 -> 0 | E13: =IncState!E21 -> 0 | F13: =E13 -> 0 | G13: =F13 -> 0 | H13: =G13 -> 0 | I13: =H13 -> 0 | J13: =I13 -> 0
B14: Non recurring income / (expense) | C14: =IncState!C24 -> -2882 | D14: =IncState!D24 -> -8125 | E14: =IncState!E24 -> -18414 | F14: 0 | G14: 0 | H14: 0 | I14: 0 | J14: 0
B15: Other Income / (expense) | C15: =IncState!C25 -> 60 | D15: =IncState!D25 -> 1256 | E15: =IncState!E25 -> -331 | F15: 0 | G15: 0 | H15: 0 | I15: 0 | J15: 0
B16: Effective tax rate | C16: =IncState!C32/IncState!C30 -> 2.2823443 | D16: =IncState!D32/IncState!D30 -> -0.52455418 | E16: =IncState!E32/IncState!E30 -> -1.0189958 | F16: 0.21 | G16: =F16 -> 0.21 | H16: =G16 -> 0.21 | I16: =H16 -> 0.21 | J16: =I16 -> 0.21
B17: Basic WASO | C17: =IncState!C35 -> 23405 | D17: =IncState!D35 -> 23452 | E17: =IncState!E35 -> 23132 | F17: =E17 -> 23132 | G17: =F17 -> 23132 | H17: =G17 -> 23132 | I17: =H17 -> 23132 | J17: =I17 -> 23132
B18: Diluted WASO | C18: =IncState!C36 -> 23662 | D18: =IncState!D36 -> 23923 | E18: =IncState!E36 -> 23768 | F18: =E18 -> 23768 | G18: =F18 -> 23768 | H18: =G18 -> 23768 | I18: =H18 -> 23768 | J18: =I18 -> 23768
A20: * | B20: Debt | C20: =C2 -> 2022 | D20: =D2 -> 2023 | E20: =E2 -> 2024 | F20: =F2 -> 2025 | G20: =G2 -> 2026 | H20: =H2 -> 2027 | I20: =I2 -> 2028 | J20: =J2 -> 2029
B22: Interest rate on Revolver | E22: =E23+1% -> 0.092466165 | F22: =E22 -> 0.092466165 | G22: =F22 -> 0.092466165 | H22: =G22 -> 0.092466165 | I22: =H22 -> 0.092466165 | J22: =I22 -> 0.092466165
B23: Interest rate on long-term debt | C23: =-IncState!C28/BalSheet!C37 -> 0.048133333 | D23: =-IncState!D28/BalSheet!D37 -> 0.072279412 | E23: =-IncState!E28/BalSheet!E37 -> 0.082466165 | F23: =E23 -> 0.082466165 | G23: =F23 -> 0.082466165 | H23: =G23 -> 0.082466165 | I23: =H23 -> 0.082466165 | J23: =I23 -> 0.082466165
B24: Interest rate on cash | E24: 0.04 | F24: =E24 -> 0.04 | G24: =F24 -> 0.04 | H24: =G24 -> 0.04 | I24: =H24 -> 0.04 | J24: =I24 -> 0.04
B26: Issuance of long-term debt | F26: 0 | G26: 0 | H26: 0 | I26: 0 | J26: 0
B27: Repayment of long-term debt | F27: 0 | G27: 0 | H27: 0 | I27: 0 | J27: 0
A29: * | B29: Calcs | C29: =C20 -> 2022 | D29: =D20 -> 2023 | E29: =E20 -> 2024 | F29: =F20 -> 2025 | G29: =G20 -> 2026 | H29: =H20 -> 2027 | I29: =I20 -> 2028 | J29: =J20 -> 2029
B31: CapEx % of Sales | C31: =78606/IncState!C15 -> 0.061223155 | D31: =98914/IncState!D15 -> 0.074191305 | E31: =76900/IncState!E15 -> 0.056656514 | F31: =AVERAGE(C31:E31) -> 0.064023658 | G31: =F31 -> 0.064023658 | H31: =G31 -> 0.064023658 | I31: =H31 -> 0.064023658 | J31: =I31 -> 0.064023658
B32: Depreciation % of beginning PP&E | D32: =IncState!D20/BalSheet!C24 -> 0.081050348 | E32: =IncState!E20/BalSheet!D24 -> 0.083110453 | F32: =E32 -> 0.083110453 | G32: =F32 -> 0.083110453 | H32: =G32 -> 0.083110453 | I32: =H32 -> 0.083110453 | J32: =I32 -> 0.083110453
B33: Share issuance / (repurchases) | F33: 0 | G33: 0 | H33: 0 | I33: 0 | J33: 0
A35: * | B35: Balance Sheet - Assets | C35: =C29 -> 2022 | D35: =D29 -> 2023 | E35: =E29 -> 2024 | F35: =F29 -> 2025 | G35: =G29 -> 2026 | H35: =H29 -> 2027 | I35: =I29 -> 2028 | J35: =J29 -> 2029
B37: Operating Cash % of sales | C37: =BalSheet!C17/IncState!C15 -> 0.01 | D37: =BalSheet!D17/IncState!D15 -> 0.01 | E37: =BalSheet!E17/IncState!E15 -> 0.01 | F37: =E37 -> 0.01 | G37: =F37 -> 0.01 | H37: =G37 -> 0.01 | I37: =H37 -> 0.01 | J37: =I37 -> 0.01
B38: Accounts receivable % of sales | C38: =BalSheet!C19/IncState!C15 -> 0.022269975 | D38: =BalSheet!D19/IncState!D15 -> 0.014602893 | E38: =BalSheet!E19/IncState!E15 -> 0.01503129 | F38: =E38 -> 0.01503129 | G38: =F38 -> 0.01503129 | H38: =G38 -> 0.01503129 | I38: =H38 -> 0.01503129 | J38: =I38 -> 0.01503129
B39: Inventories % of COGS | C39: =BalSheet!C20/IncState!C16 -> 0.010434864 | D39: =BalSheet!D20/IncState!D16 -> 0.011463146 | E39: =BalSheet!E20/IncState!E16 -> 0.010990704 | F39: =E39 -> 0.010990704 | G39: =F39 -> 0.010990704 | H39: =G39 -> 0.010990704 | I39: =H39 -> 0.010990704 | J39: =I39 -> 0.010990704
B40: Other current assets % of sales | C40: =BalSheet!C21/IncState!C15 -> 0.013166647 | D40: =BalSheet!D21/IncState!D15 -> 0.015928996 | E40: =BalSheet!E21/IncState!E15 -> 0.014955404 | F40: =E40 -> 0.014955404 | G40: =F40 -> 0.014955404 | H40: =G40 -> 0.014955404 | I40: =H40 -> 0.014955404 | J40: =I40 -> 0.014955404
B42: Investments in unconsolidated entities | C42: =BalSheet!C26 -> 5000 | D42: =BalSheet!D26 -> 4770 | E42: =BalSheet!E26 -> 4266 | F42: =E42 -> 4266 | G42: =F42 -> 4266 | H42: =G42 -> 4266 | I42: =H42 -> 4266 | J42: =I42 -> 4266
B43: Other long-term assets % of sales | C43: =BalSheet!C27/IncState!C15 -> 0.060822041 | D43: =BalSheet!D27/IncState!D15 -> 0.068037074 | E43: =BalSheet!E27/IncState!E15 -> 0.07739103 | F43: =E43 -> 0.07739103 | G43: =F43 -> 0.07739103 | H43: =G43 -> 0.07739103 | I43: =H43 -> 0.07739103 | J43: =I43 -> 0.07739103
A45: * | B45: Balance Sheet - Liabilities | C45: =C35 -> 2022 | D45: =D35 -> 2023 | E45: =E35 -> 2024 | F45: =F35 -> 2025 | G45: =G35 -> 2026 | H45: =H35 -> 2027 | I45: =I35 -> 2028 | J45: =J35 -> 2029
B47: Accounts payable % of COGS | C47: =BalSheet!C33/IncState!C16 -> 0.052286681 | D47: =BalSheet!D33/IncState!D16 -> 0.052482946 | E47: =BalSheet!E33/IncState!E16 -> 0.043910308 | F47: =E47 -> 0.043910308 | G47: =F47 -> 0.043910308 | H47: =G47 -> 0.043910308 | I47: =H47 -> 0.043910308 | J47: =I47 -> 0.043910308
B48: Other current liabilities % of sales | C48: =BalSheet!C34/IncState!C15 -> 0.10693373 | D48: =BalSheet!D34/IncState!D15 -> 0.10402114 | E48: =BalSheet!E34/IncState!E15 -> 0.10704913 | F48: =E48 -> 0.10704913 | G48: =F48 -> 0.10704913 | H48: =G48 -> 0.10704913 | I48: =H48 -> 0.10704913 | J48: =I48 -> 0.10704913
B49: Other long-term liabilities % of sales | C49: =BalSheet!C38/IncState!C15 -> 0.34546306 | D49: =BalSheet!D38/IncState!D15 -> 0.31907347 | E49: =BalSheet!E38/IncState!E15 -> 0.30077168 | F49: =E49 -> 0.30077168 | G49: =F49 -> 0.30077168 | H49: =G49 -> 0.30077168 | I49: =H49 -> 0.30077168 | J49: =I49 -> 0.30077168

Sheet Calcs
A1: =CoName -> BJ's Resturant Inc. | C1: Hist. | D1: Hist. | E1: Hist. | F1: Proj. | G1: Proj. | H1: Proj. | I1: Proj. | J1: Proj.
A2: Net PP&E | C2: 2022 | D2: =C2+1 -> 2023 | E2: =D2+1 -> 2024 | F2: =E2+1 -> 2025 | G2: =F2+1 -> 2026 | H2: =G2+1 -> 2027 | I2: =H2+1 -> 2028 | J2: =I2+1 -> 2029
B3: Capital expenditure % of sales | F3: =Assumptions!F31 -> 0.064023658 | G3: =Assumptions!G31 -> 0.064023658 | H3: =Assumptions!H31 -> 0.064023658 | I3: =Assumptions!I31 -> 0.064023658 | J3: =Assumptions!J31 -> 0.064023658
B4: Depreciation % of PP&E | F4: =Assumptions!F32 -> 0.083110453 | G4: =F4 -> 0.083110453 | H4: =G4 -> 0.083110453 | I4: =H4 -> 0.083110453 | J4: =I4 -> 0.083110453
B6: Beginning PP&E | F6: =E9 -> 847517 | G6: =F9 -> 866585.9 | H6: =G9 -> 886397.14 | I6: =H9 -> 906857.71 | J6: =I9 -> 928441.66
B7: Capex | F7: =F3*IncState!F15 -> 89506.422 | G7: =G3*IncState!G15 -> 91833.589 | H7: =H3*IncState!H15 -> 94129.429 | I7: =I3*IncState!I15 -> 96953.312 | J7: =J3*IncState!J15 -> 99861.911
B8: Depreciation | F8: =F6*F4 -> 70437.521 | G8: =G6*G4 -> 72022.346 | H8: =H6*H4 -> 73668.868 | I8: =I6*I4 -> 75369.354 | J8: =J6*J4 -> 77163.207
B9: Ending PP&E | E9: =BalSheet!E24 -> 847517 | F9: =F6+F7-F8 -> 866585.9 | G9: =G6+G7-G8 -> 886397.14 | H9: =H6+H7-H8 -> 906857.71 | I9: =I6+I7-I8 -> 928441.66 | J9: =J6+J7-J8 -> 951140.37
A10: Equity | C10: =C2 -> 2022 | D10: =D2 -> 2023 | E10: =E2 -> 2024 | F10: =F2 -> 2025 | G10: =G2 -> 2026 | H10: =H2 -> 2027 | I10: =I2 -> 2028 | J10: =J2 -> 2029
B11: Share issuance/(repurchases) | F11: =Assumptions!F33 -> 0 | G11: =Assumptions!G33 -> 0 | H11: =Assumptions!H33 -> 0 | I11: =Assumptions!I33 -> 0 | J11: =Assumptions!J33 -> 0
B13: Beginning balance | F13: =E16 -> 370017 | G13: =F16 -> 405151.98 | H13: =G16 -> 446866.22 | I13: =H16 -> 495430.73 | J13: =I16 -> 551433.79
B14: Net income | F14: =IncState!F33 -> 35134.976 | G14: =IncState!G33 -> 41714.245 | H14: =IncState!H33 -> 48564.505 | I14: =IncState!I33 -> 56003.067 | J14: =IncState!J33 -> 63844.233
B15: Share issuance / (repurchase) | F15: =F11 -> 0 | G15: =G11 -> 0 | H15: =H11 -> 0 | I15: =I11 -> 0 | J15: =J11 -> 0
B16: Ending balance | E16: =BalSheet!E41 -> 370017 | F16: =SUM(F13:F15) -> 405151.98 | G16: =SUM(G13:G15) -> 446866.22 | H16: =SUM(H13:H15) -> 495430.73 | I16: =SUM(I13:I15) -> 551433.79 | J16: =SUM(J13:J15) -> 615278.03
A17: OWC | C17: =C10 -> 2022 | D17: =D10 -> 2023 | E17: =E10 -> 2024 | F17: =F10 -> 2025 | G17: =G10 -> 2026 | H17: =H10 -> 2027 | I17: =I10 -> 2028 | J17: =J10 -> 2029
B18: Operating Cash | E18: =BalSheet!E17 -> 13573.02 | F18: =BalSheet!F17 -> 13980.211 | G18: =BalSheet!G17 -> 14343.696 | H18: =BalSheet!H17 -> 14702.288 | I18: =BalSheet!I17 -> 15143.357 | J18: =BalSheet!J17 -> 15597.658
B19: =BalSheet!B19 -> Accounts receivable | E19: =BalSheet!E19 -> 20402 | F19: =BalSheet!F19 -> 21014.06 | G19: =BalSheet!G19 -> 21560.426 | H19: =BalSheet!H19 -> 22099.436 | I19: =BalSheet!I19 -> 22762.419 | J19: =BalSheet!J19 -> 23445.292
B20: =BalSheet!B20 -> Inventories | E20: =BalSheet!E20 -> 12768 | F20: =BalSheet!F20 -> 13074.214 | G20: =BalSheet!G20 -> 13335.32 | H20: =BalSheet!H20 -> 13587.908 | I20: =BalSheet!I20 -> 13912.328 | J20: =BalSheet!J20 -> 14243.983
B21: Other current assets | E21: =BalSheet!E21 -> 20299 | F21: =BalSheet!F21 -> 20907.97 | G21: =BalSheet!G21 -> 21451.577 | H21: =BalSheet!H21 -> 21987.867 | I21: =BalSheet!I21 -> 22647.503 | J21: =BalSheet!J21 -> 23326.928
B22: Accounts payables | E22: =BalSheet!E33 -> 51011 | F22: =BalSheet!F33 -> 52234.392 | G22: =BalSheet!G33 -> 53277.568 | H22: =BalSheet!H33 -> 54286.717 | I22: =BalSheet!I33 -> 55582.843 | J22: =BalSheet!J33 -> 56907.88
B23: Other current liabilities | E23: =BalSheet!E34 -> 145298 | F23: =BalSheet!F34 -> 149656.94 | G23: =BalSheet!G34 -> 153548.02 | H23: =BalSheet!H34 -> 157386.72 | I23: =BalSheet!I34 -> 162108.32 | J23: =BalSheet!J34 -> 166971.57
A24: * | B24: OWC | E24: =SUM(E18:E21)-SUM(E22:E23) -> -129266.98 | F24: =SUM(F18:F21)-SUM(F22:F23) -> -132914.88 | G24: =SUM(G18:G21)-SUM(G22:G23) -> -136134.57 | H24: =SUM(H18:H21)-SUM(H22:H23) -> -139295.94 | I24: =SUM(I18:I21)-SUM(I22:I23) -> -143225.56 | J24: =SUM(J18:J21)-SUM(J22:J23) -> -147265.59
B25: Change in OWC | F25: =E24-F24 -> 3647.8979 | G25: =F24-G24 -> 3219.6924 | H25: =G24-H24 -> 3161.3675 | I25: =H24-I24 -> 3929.6215 | J25: =I24-J24 -> 4040.0324

Sheet Debt
A1: =CoName -> BJ's Resturant Inc. | C1: Hist. | D1: Hist. | E1: Hist. | F1: Proj. | G1: Proj. | H1: Proj. | I1: Proj. | J1: Proj.
A2: Assumptions | C2: 2022 | D2: =C2+1 -> 2023 | E2: =D2+1 -> 2024 | F2: =E2+1 -> 2025 | G2: =F2+1 -> 2026 | H2: =G2+1 -> 2027 | I2: =H2+1 -> 2028 | J2: =I2+1 -> 2029
B4: Interest rate on revolver | F4: =Assumptions!F22 -> 0.092466165 | G4: =Assumptions!G22 -> 0.092466165 | H4: =Assumptions!H22 -> 0.092466165 | I4: =Assumptions!I22 -> 0.092466165 | J4: =Assumptions!J22 -> 0.092466165
B5: Interest rate on long-term debt | F5: =Assumptions!F23 -> 0.082466165 | G5: =Assumptions!G23 -> 0.082466165 | H5: =Assumptions!H23 -> 0.082466165 | I5: =Assumptions!I23 -> 0.082466165 | J5: =Assumptions!J23 -> 0.082466165
B6: Interest rate on cash | F6: =Assumptions!F24 -> 0.04 | G6: =Assumptions!G24 -> 0.04 | H6: =Assumptions!H24 -> 0.04 | I6: =Assumptions!I24 -> 0.04 | J6: =Assumptions!J24 -> 0.04
B8: Issuance of long-term debt | F8: =Assumptions!F26 -> 0 | G8: =Assumptions!G26 -> 0 | H8: =Assumptions!H26 -> 0 | I8: =Assumptions!I26 -> 0 | J8: =Assumptions!J26 -> 0
B9: Repayment of long-term debt | F9: =Assumptions!F27 -> 0 | G9: =Assumptions!G27 -> 0 | H9: =Assumptions!H27 -> 0 | I9: =Assumptions!I27 -> 0 | J9: =Assumptions!J27 -> 0
A11: Revolver | C11: =C2 -> 2022 | D11: =D2 -> 2023 | E11: =E2 -> 2024 | F11: =F2 -> 2025 | G11: =G2 -> 2026 | H11: =H2 -> 2027 | I11: =I2 -> 2028 | J11: =J2 -> 2029
B12: Balance | F12: =BalSheet!F32 -> 0 | G12: =BalSheet!G32 -> 0 | H12: =BalSheet!H32 -> 0 | I12: =BalSheet!I32 -> 0 | J12: =BalSheet!J32 -> 0
B13: Interest rate | F13: =F4 -> 0.092466165 | G13: =G4 -> 0.092466165 | H13: =H4 -> 0.092466165 | I13: =I4 -> 0.092466165 | J13: =J4 -> 0.092466165
B14: Interest expense | F14: =-F12*F13 -> 0 | G14: =-G12*G13 -> 0 | H14: =-H12*H13 -> 0 | I14: =-I12*I13 -> 0 | J14: =-J12*J13 -> 0
A16: Long term debt | C16: =C11 -> 2022 | D16: =D11 -> 2023 | E16: =E11 -> 2024 | F16: =F11 -> 2025 | G16: =G11 -> 2026 | H16: =H11 -> 2027 | I16: =I11 -> 2028 | J16: =J11 -> 2029
B17: Beginning balance | F17: =E20 -> 66500 | G17: =F20 -> 66500 | H17: =G20 -> 66500 | I17: =H20 -> 66500 | J17: =I20 -> 66500
B18: Issuance | F18: =F8 -> 0 | G18: =G8 -> 0 | H18: =H8 -> 0 | I18: =I8 -> 0 | J18: =J8 -> 0
B19: Repayment | F19: =F9 -> 0 | G19: =G9 -> 0 | H19: =H9 -> 0 | I19: =I9 -> 0 | J19: =J9 -> 0
B20: Ending balance | E20: =BalSheet!E37 -> 66500 | F20: =SUM(F17:F19) -> 66500 | G20: =SUM(G17:G19) -> 66500 | H20: =SUM(H17:H19) -> 66500 | I20: =SUM(I17:I19) -> 66500 | J20: =SUM(J17:J19) -> 66500
B21: Interest rate | F21: =F5 -> 0.082466165 | G21: =G5 -> 0.082466165 | H21: =H5 -> 0.082466165 | I21: =I5 -> 0.082466165 | J21: =J5 -> 0.082466165
B22: Interest expense | F22: =-F20*F21 -> -5484 | G22: =-G20*G21 -> -5484 | H22: =-H20*H21 -> -5484 | I22: =-I20*I21 -> -5484 | J22: =-J20*J21 -> -5484
A24: Debt summary | C24: =C16 -> 2022 | D24: =D16 -> 2023 | E24: =E16 -> 2024 | F24: =F16 -> 2025 | G24: =G16 -> 2026 | H24: =H16 -> 2027 | I24: =I16 -> 2028 | J24: =J16 -> 2029
B25: Revolver | F25: =F12 -> 0 | G25: =G12 -> 0 | H25: =H12 -> 0 | I25: =I12 -> 0 | J25: =J12 -> 0
B26: Total long term debt | F26: =F20 -> 66500 | G26: =G20 -> 66500 | H26: =H20 -> 66500 | I26: =I20 -> 66500 | J26: =J20 -> 66500
B27: Total debt | F27: =SUM(F25:F26) -> 66500 | G27: =SUM(G25:G26) -> 66500 | H27: =SUM(H25:H26) -> 66500 | I27: =SUM(I25:I26) -> 66500 | J27: =SUM(J25:J26) -> 66500
B28: Total interest expense | F28: =SUM(F22,F14) -> -5484 | G28: =SUM(G22,G14) -> -5484 | H28: =SUM(H22,H14) -> -5484 | I28: =SUM(I22,I14) -> -5484 | J28: =SUM(J22,J14) -> -5484
A30: Interest income | C30: =C11 -> 2022 | D30: =D11 -> 2023 | E30: =E11 -> 2024 | F30: =F11 -> 2025 | G30: =G11 -> 2026 | H30: =H11 -> 2027 | I30: =I11 -> 2028 | J30: =J11 -> 2029
B31: Excess Cash | F31: =BalSheet!F18 -> 41332.803 | G31: =BalSheet!G18 -> 74575.06 | H31: =BalSheet!H18 -> 113850.63 | I31: =BalSheet!I18 -> 162051.98 | J31: =BalSheet!J18 -> 217385.74
B32: Interest rate | F32: =F6 -> 0.04 | G32: =G6 -> 0.04 | H32: =H6 -> 0.04 | I32: =I6 -> 0.04 | J32: =J6 -> 0.04
B33: Interest income | F33: =F31*F32 -> 1653.3121 | G33: =G31*G32 -> 2983.0024 | H33: =H31*H32 -> 4554.0253 | I33: =I31*I32 -> 6482.0793 | J33: =J31*J32 -> 8695.4297

Sheet IncState
A1: =CoName -> BJ's Resturant Inc. | C1: Hist. | D1: Hist. | E1: Hist. | F1: Proj. | G1: Proj. | H1: Proj. | I1: Proj. | J1: Proj.
A2: Assumptions | C2: 2022 | D2: =C2+1 -> 2023 | E2: =D2+1 -> 2024 | F2: =E2+1 -> 2025 | G2: =F2+1 -> 2026 | H2: =G2+1 -> 2027 | I2: =H2+1 -> 2028 | J2: =I2+1 -> 2029
B4: Revenue growth | F4: =Assumptions!F10 -> 0.03 | G4: =Assumptions!G10 -> 0.026 | H4: =Assumptions!H10 -> 0.025 | I4: =Assumptions!I10 -> 0.03 | J4: =Assumptions!J10 -> 0.03
B5: Cost of goods sold as % of sales | F5: =Assumptions!F11 -> 0.85089574 | G5: =Assumptions!G11 -> 0.84589574 | H5: =Assumptions!H11 -> 0.84089574 | I5: =Assumptions!I11 -> 0.83589574 | J5: =Assumptions!J11 -> 0.83089574
B6: SG&A % of sales | F6: =Assumptions!F12 -> 0.11729168 | G6: =Assumptions!G12 -> 0.11729168 | H6: =Assumptions!H12 -> 0.11729168 | I6: =Assumptions!I12 -> 0.11729168 | J6: =Assumptions!J12 -> 0.11729168
B7: Amortization amount | F7: =Assumptions!F13 -> 0 | G7: =Assumptions!G13 -> 0 | H7: =Assumptions!H13 -> 0 | I7: =Assumptions!I13 -> 0 | J7: =Assumptions!J13 -> 0
B8: Non recurring items, amount | F8: =Assumptions!F14 -> 0 | G8: =Assumptions!G14 -> 0 | H8: =Assumptions!H14 -> 0 | I8: =Assumptions!I14 -> 0 | J8: =Assumptions!J14 -> 0
B9: Other income (expense), amt | F9: =Assumptions!F15 -> 0 | G9: =Assumptions!G15 -> 0 | H9: =Assumptions!H15 -> 0 | I9: =Assumptions!I15 -> 0 | J9: =Assumptions!J15 -> 0
B10: Effective tax rate | F10: =Assumptions!F16 -> 0.21 | G10: =Assumptions!G16 -> 0.21 | H10: =Assumptions!H16 -> 0.21 | I10: =Assumptions!I16 -> 0.21 | J10: =Assumptions!J16 -> 0.21
B11: Basic WASO | F11: =Assumptions!F17 -> 23132 | G11: =Assumptions!G17 -> 23132 | H11: =Assumptions!H17 -> 23132 | I11: =Assumptions!I17 -> 23132 | J11: =Assumptions!J17 -> 23132
B12: Diluted WASO | F12: =Assumptions!F18 -> 23768 | G12: =Assumptions!G18 -> 23768 | H12: =Assumptions!H18 -> 23768 | I12: =Assumptions!I18 -> 23768 | J12: =Assumptions!J18 -> 23768
A14: Income statement | C14: =C2 -> 2022 | D14: =D2 -> 2023 | E14: =E2 -> 2024 | F14: =F2 -> 2025 | G14: =G2 -> 2026 | H14: =H2 -> 2027 | I14: =I2 -> 2028 | J14: =J2 -> 2029
B15: Revenue | C15: 1283926 | D15: 1333229 | E15: 1357302 | F15: =E15*(1+F4) -> 1398021.1 | G15: =F15*(1+G4) -> 1434369.6 | H15: =G15*(1+H4) -> 1470228.8 | I15: =H15*(1+I4) -> 1514335.7 | J15: =I15*(1+J4) -> 1559765.8
B16: COGS | C16: =349645+483367+306150 -> 1139162 | D16: =346569+491314+317559 -> 1155442 | E16: =350560+495466+315683 -> 1161709 | F16: =F15*F5 -> 1189570.2 | G16: =G15*G5 -> 1213327.1 | H16: =H15*H5 -> 1236309.2 | I16: =I15*I5 -> 1265826.8 | J16: =J15*J5 -> 1296002.7
B17: SG&A | C17: =1289406-C16-6200+3318 -> 147362 | D17: =1319470-D16-8125 -> 155903 | E17: =1343222-E16-18414 -> 163099 | F17: =F15*F6 -> 163976.24 | G17: =G15*G6 -> 168239.62 | H17: =H15*H6 -> 172445.62 | I17: =I15*I6 -> 177618.98 | J17: =J15*J6 -> 182947.55
A18: * | B18: EBIT | C18: =C15-SUM(C16:C17) -> -2598 | D18: =D15-SUM(D16:D17) -> 21884 | E18: =E15-SUM(E16:E17) -> 32494 | F18: =F15-SUM(F16:F17) -> 44474.653 | G18: =G15-SUM(G16:G17) -> 52802.842 | H18: =H15-SUM(H16:H17) -> 61474.057 | I18: =I15-SUM(I16:I17) -> 70889.958 | J18: =J15-SUM(J16:J17) -> 80815.485
B20: Depreciation | C20: 70385 | D20: 70992 | E20: 72745 | F20: =Calcs!F8 -> 70437.521 | G20: =Calcs!G8 -> 72022.346 | H20: =Calcs!H8 -> 73668.868 | I20: =Calcs!I8 -> 75369.354 | J20: =Calcs!J8 -> 77163.207
B21: Amortization | C21: 0 | D21: 0 | E21: 0 | F21: =F7 -> 0 | G21: =G7 -> 0 | H21: =H7 -> 0 | I21: =I7 -> 0 | J21: =J7 -> 0
A22: * | B22: EBITDA | C22: =SUM(C18,C20:C21) -> 67787 | D22: =SUM(D18,D20:D21) -> 92876 | E22: =SUM(E18,E20:E21) -> 105239 | F22: =SUM(F18,F20:F21) -> 114912.17 | G22: =SUM(G18,G20:G21) -> 124825.19 | H22: =SUM(H18,H20:H21) -> 135142.93 | I22: =SUM(I18,I20:I21) -> 146259.31 | J22: =SUM(J18,J20:J21) -> 157978.69
B24: Non-recurring items | C24: =-6200+3318 -> -2882 | D24: -8125 | E24: -18414 | F24: =F8 -> 0 | G24: =G8 -> 0 | H24: =H8 -> 0 | I24: =I8 -> 0 | J24: =J8 -> 0
B25: Other income (expense) | C25: 60 | D25: 1256 | E25: -331 | F25: =F9 -> 0 | G25: =G9 -> 0 | H25: =H9 -> 0 | I25: =I9 -> 0 | J25: =J9 -> 0
B27: Interest income | C27: 0 | D27: 0 | E27: 0 | F27: =IF(circ=1,Debt!F33,0) -> 0 | G27: =IF(circ=1,Debt!G33,0) -> 0 | H27: =IF(circ=1,Debt!H33,0) -> 0 | I27: =IF(circ=1,Debt!I33,0) -> 0 | J27: =IF(circ=1,Debt!J33,0) -> 0
B28: Interest expense | C28: -2888 | D28: -4915 | E28: -5484 | F28: =IF(circ=1,Debt!F28,0) -> 0 | G28: =IF(circ=1,Debt!G28,0) -> 0 | H28: =IF(circ=1,Debt!H28,0) -> 0 | I28: =IF(circ=1,Debt!I28,0) -> 0 | J28: =IF(circ=1,Debt!J28,0) -> 0
A30: * | B30: Pretax Income | C30: =C18+SUM(C25:C28) -> -5426 | D30: =D18+SUM(D25:D28) -> 18225 | E30: =E18+SUM(E24:E28) -> 8265 | F30: =F18+SUM(F24:F28) -> 44474.653 | G30: =G18+SUM(G24:G28) -> 52802.842 | H30: =H18+SUM(H24:H28) -> 61474.057 | I30: =I18+SUM(I24:I28) -> 70889.958 | J30: =J18+SUM(J24:J28) -> 80815.485
B32: Tax expense | C32: -12384 | D32: -9560 | E32: -8422 | F32: =F30*F10 -> 9339.6771 | G32: =G30*G10 -> 11088.597 | H32: =H30*H10 -> 12909.552 | I32: =I30*I10 -> 14886.891 | J32: =J30*J10 -> 16971.252
A33: * | B33: Net income | C33: =C30-C32 -> 6958 | D33: =D30-D32 -> 27785 | E33: =E30-E32 -> 16687 | F33: =F30-F32 -> 35134.976 | G33: =G30-G32 -> 41714.245 | H33: =H30-H32 -> 48564.505 | I33: =I30-I32 -> 56003.067 | J33: =J30-J32 -> 63844.233
A34: Shareholder information | C34: =C14 -> 2022 | D34: =D14 -> 2023 | E34: =E14 -> 2024 | F34: =F14 -> 2025 | G34: =G14 -> 2026 | H34: =H14 -> 2027 | I34: =I14 -> 2028 | J34: =J14 -> 2029
B35: Basic WASO | C35: 23405 | D35: 23452 | E35: 23132 | F35: =F11 -> 23132 | G35: =G11 -> 23132 | H35: =H11 -> 23132 | I35: =I11 -> 23132 | J35: =J11 -> 23132
B36: Diluted WASO | C36: 23662 | D36: 23923 | E36: 23768 | F36: =F12 -> 23768 | G36: =G12 -> 23768 | H36: =H12 -> 23768 | I36: =I12 -> 23768 | J36: =J12 -> 23768
B37: Basic earnings per share | C37: =C33/C35 -> 0.2972869 | D37: =D33/D35 -> 1.1847604 | E37: =E33/E35 -> 0.72138164 | F37: =F33/F35 -> 1.5188905 | G37: =G33/G35 -> 1.8033134 | H37: =H33/H35 -> 2.0994512 | I37: =I33/I35 -> 2.4210214 | J37: =J33/J35 -> 2.7599963
A38: * | B38: Diluted earnings per share | C38: =C33/C36 -> 0.29405798 | D38: =D33/D36 -> 1.1614346 | E38: =E33/E36 -> 0.70207842 | F38: =F33/F36 -> 1.478247 | G38: =G33/G36 -> 1.7550591 | H38: =H33/H36 -> 2.0432727 | I38: =I33/I36 -> 2.3562381 | J38: =J33/J36 -> 2.6861424

Sheet BalSheet
A1: =CoName -> BJ's Resturant Inc. | C1: Hist. | D1: Hist. | E1: Hist. | F1: Proj. | G1: Proj. | H1: Proj. | I1: Proj. | J1: Proj.
A2: Assumptions | C2: 2022 | D2: =C2+1 -> 2023 | E2: =D2+1 -> 2024 | F2: =E2+1 -> 2025 | G2: =F2+1 -> 2026 | H2: =G2+1 -> 2027 | I2: =H2+1 -> 2028 | J2: =I2+1 -> 2029
B4: Operating Cash % of sales | F4: =Assumptions!F37 -> 0.01 | G4: =F4 -> 0.01 | H4: =G4 -> 0.01 | I4: =H4 -> 0.01 | J4: =I4 -> 0.01
B5: Accounts receivable % of sales | F5: =Assumptions!F38 -> 0.01503129 | G5: =Assumptions!G38 -> 0.01503129 | H5: =Assumptions!H38 -> 0.01503129 | I5: =Assumptions!I38 -> 0.01503129 | J5: =Assumptions!J38 -> 0.01503129
B6: Inventories % of COGS | F6: =Assumptions!F39 -> 0.010990704 | G6: =Assumptions!G39 -> 0.010990704 | H6: =Assumptions!H39 -> 0.010990704 | I6: =Assumptions!I39 -> 0.010990704 | J6: =Assumptions!J39 -> 0.010990704
B7: Other current assets % of sales | F7: =Assumptions!F40 -> 0.014955404 | G7: =Assumptions!G40 -> 0.014955404 | H7: =Assumptions!H40 -> 0.014955404 | I7: =Assumptions!I40 -> 0.014955404 | J7: =Assumptions!J40 -> 0.014955404
B9: Other long-term assets % of sales | F9: =Assumptions!F43 -> 0.07739103 | G9: =Assumptions!G43 -> 0.07739103 | H9: =Assumptions!H43 -> 0.07739103 | I9: =Assumptions!I43 -> 0.07739103 | J9: =Assumptions!J43 -> 0.07739103
B10: Investment in unconsolidated entities $ balance | F10: =Assumptions!F42 -> 4266 | G10: =Assumptions!G42 -> 4266 | H10: =Assumptions!H42 -> 4266 | I10: =Assumptions!I42 -> 4266 | J10: =Assumptions!J42 -> 4266
B12: Accounts payable/Accural % of COGS | F12: =Assumptions!F47 -> 0.043910308 | G12: =Assumptions!G47 -> 0.043910308 | H12: =Assumptions!H47 -> 0.043910308 | I12: =Assumptions!I47 -> 0.043910308 | J12: =Assumptions!J47 -> 0.043910308
B13: Other current liabilities % of sales | F13: =Assumptions!F48 -> 0.10704913 | G13: =Assumptions!G48 -> 0.10704913 | H13: =Assumptions!H48 -> 0.10704913 | I13: =Assumptions!I48 -> 0.10704913 | J13: =Assumptions!J48 -> 0.10704913
B14: Other long-term liabilities % of sales | F14: =Assumptions!F49 -> 0.30077168 | G14: =Assumptions!G49 -> 0.30077168 | H14: =Assumptions!H49 -> 0.30077168 | I14: =Assumptions!I49 -> 0.30077168 | J14: =Assumptions!J49 -> 0.30077168
A16: Balance sheet | C16: =C2 -> 2022 | D16: =D2 -> 2023 | E16: =E2 -> 2024 | F16: =F2 -> 2025 | G16: =G2 -> 2026 | H16: =H2 -> 2027 | I16: =I2 -> 2028 | J16: =J2 -> 2029
B17: Operating Cash | C17: =1%*IncState!C15 -> 12839.26 | D17: =1%*IncState!D15 -> 13332.29 | E17: =1%*IncState!E15 -> 13573.02 | F17: =F4*IncState!F15 -> 13980.211 | G17: =G4*IncState!G15 -> 14343.696 | H17: =H4*IncState!H15 -> 14702.288 | I17: =I4*IncState!I15 -> 15143.357 | J17: =J4*IncState!J15 -> 15597.658
B18: Excess cash | C18: =24873-C17 -> 12033.74 | D18: =29070-D17 -> 15737.71 | E18: =26096-E17 -> 12522.98 | F18: =MAX(CashFlow!F22,0) -> 41332.803 | G18: =MAX(CashFlow!G22,0) -> 74575.06 | H18: =MAX(CashFlow!H22,0) -> 113850.63 | I18: =MAX(CashFlow!I22,0) -> 162051.98 | J18: =MAX(CashFlow!J22,0) -> 217385.74
B19: Accounts receivable | C19: 28593 | D19: 19469 | E19: 20402 | F19: =F5*IncState!F15 -> 21014.06 | G19: =G5*IncState!G15 -> 21560.426 | H19: =H5*IncState!H15 -> 22099.436 | I19: =I5*IncState!I15 -> 22762.419 | J19: =J5*IncState!J15 -> 23445.292
B20: Inventories | C20: 11887 | D20: 13245 | E20: 12768 | F20: =F6*IncState!F16 -> 13074.214 | G20: =G6*IncState!G16 -> 13335.32 | H20: =H6*IncState!H16 -> 13587.908 | I20: =I6*IncState!I16 -> 13912.328 | J20: =J6*IncState!J16 -> 14243.983
B21: Other current assets | C21: 16905 | D21: 21237 | E21: 20299 | F21: =F7*IncState!F15 -> 20907.97 | G21: =G7*IncState!G15 -> 21451.577 | H21: =H7*IncState!H15 -> 21987.867 | I21: =I7*IncState!I15 -> 22647.503 | J21: =J7*IncState!J15 -> 23326.928
B22: Total current assets | C22: =SUM(C17:C21) -> 82258 | D22: =SUM(D17:D21) -> 83021 | E22: =SUM(E17:E21) -> 79565 | F22: =SUM(F17:F21) -> 110309.26 | G22: =SUM(G17:G21) -> 145266.08 | H22: =SUM(H17:H21) -> 186228.13 | I22: =SUM(I17:I21) -> 236517.59 | J22: =SUM(J17:J21) -> 293999.6
B24: Property, plant & equipment, net | C24: =507116+368784 -> 875900 | D24: =525190+350091 -> 875281 | E24: =510581+336936 -> 847517 | F24: =Calcs!F9 -> 866585.9 | G24: =Calcs!G9 -> 886397.14 | H24: =Calcs!H9 -> 906857.71 | I24: =Calcs!I9 -> 928441.66 | J24: =Calcs!J9 -> 951140.37
B25: Intangible assets | C25: 4673 | D25: 4673 | E25: =4673 -> 4673 | F25: =E25-IncState!F21 -> 4673 | G25: =F25-IncState!G21 -> 4673 | H25: =G25-IncState!H21 -> 4673 | I25: =H25-IncState!I21 -> 4673 | J25: =I25-IncState!J21 -> 4673
B26: Investment in unconsolidated entities | C26: 5000 | D26: 4770 | E26: 4266 | F26: =F10 -> 4266 | G26: =G10 -> 4266 | H26: =H10 -> 4266 | I26: =I10 -> 4266 | J26: =J10 -> 4266
B27: Other assets | C27: =38312+39779 -> 78091 | D27: =50147+40562 -> 90709 | E27: =62318+42725 -> 105043 | F27: =F9*IncState!F15 -> 108194.29 | G27: =G9*IncState!G15 -> 111007.34 | H27: =H9*IncState!H15 -> 113782.53 | I27: =I9*IncState!I15 -> 117196 | J27: =J9*IncState!J15 -> 120711.88
B28: Total non-current assets | C28: =SUM(C24:C27) -> 963664 | D28: =SUM(D24:D27) -> 975433 | E28: =SUM(E24:E27) -> 961499 | F28: =SUM(F24:F27) -> 983719.19 | G28: =SUM(G24:G27) -> 1006343.5 | H28: =SUM(H24:H27) -> 1029579.2 | I28: =SUM(I24:I27) -> 1054576.7 | J28: =SUM(J24:J27) -> 1080791.2
A30: * | B30: TOTAL ASSETS | C30: =SUM(C28,C22) -> 1045922 | D30: =SUM(D28,D22) -> 1058454 | E30: =SUM(E28,E22) -> 1041064 | F30: =SUM(F28,F22) -> 1094028.4 | G30: =SUM(G28,G22) -> 1151609.6 | H30: =SUM(H28,H22) -> 1215807.4 | I30: =SUM(I28,I22) -> 1291094.3 | J30: =SUM(J28,J22) -> 1374790.9
B32: Revolver/Short term debt | C32: 0 | D32: 0 | E32: 0 | F32: =-MIN(CashFlow!F22,0) -> 0 | G32: =-MIN(CashFlow!G22,0) -> 0 | H32: =-MIN(CashFlow!H22,0) -> 0 | I32: =-MIN(CashFlow!I22,0) -> 0 | J32: =-MIN(CashFlow!J22,0) -> 0
B33: Accounts payable/Accurals | C33: 59563 | D33: =60641 -> 60641 | E33: 51011 | F33: =F12*IncState!F16 -> 52234.392 | G33: =G12*IncState!G16 -> 53277.568 | H33: =H12*IncState!H16 -> 54286.717 | I33: =I12*IncState!I16 -> 55582.843 | J33: =J12*IncState!J16 -> 56907.88
B34: Other current liabilities | C34: =97258+40037 -> 137295 | D34: =101295+37389 -> 138684 | E34: =105316+39982 -> 145298 | F34: =F13*IncState!F15 -> 149656.94 | G34: =G13*IncState!G15 -> 153548.02 | H34: =H13*IncState!H15 -> 157386.72 | I34: =I13*IncState!I15 -> 162108.32 | J34: =J13*IncState!J15 -> 166971.57
B35: Total current liabilities | C35: =SUM(C32:C34) -> 196858 | D35: =SUM(D32:D34) -> 199325 | E35: =SUM(E32:E34) -> 196309 | F35: =SUM(F32:F34) -> 201891.33 | G35: =SUM(G32:G34) -> 206825.59 | H35: =SUM(H32:H34) -> 211673.44 | I35: =SUM(I32:I34) -> 217691.17 | J35: =SUM(J32:J34) -> 223879.45
B37: Long-term debt, including current maturities | C37: 60000 | D37: 68000 | E37: 66500 | F37: =Debt!F20 -> 66500 | G37: =Debt!G20 -> 66500 | H37: =Debt!H20 -> 66500 | I37: =Debt!I20 -> 66500 | J37: =Debt!J20 -> 66500
B38: Other long-term liabilities | C38: =432676+10873 -> 443549 | D38: =414144+11254 -> 425398 | E38: =394129+14109 -> 408238 | F38: =F14*IncState!F15 -> 420485.14 | G38: =G14*IncState!G15 -> 431417.75 | H38: =H14*IncState!H15 -> 442203.2 | I38: =I14*IncState!I15 -> 455469.29 | J38: =J14*IncState!J15 -> 469133.37
B39: Total non-current liabilities | C39: =SUM(C37:C38) -> 503549 | D39: =SUM(D37:D38) -> 493398 | E39: =SUM(E37:E38) -> 474738 | F39: =SUM(F37:F38) -> 486985.14 | G39: =SUM(G37:G38) -> 497917.75 | H39: =SUM(H37:H38) -> 508703.2 | I39: =SUM(I37:I38) -> 521969.29 | J39: =SUM(J37:J38) -> 535633.37
B41: Equity | C41: 345515 | D41: 365731 | E41: 370017 | F41: =Calcs!F16 -> 405151.98 | G41: =Calcs!G16 -> 446866.22 | H41: =Calcs!H16 -> 495430.73 | I41: =Calcs!I16 -> 551433.79 | J41: =Calcs!J16 -> 615278.03
A42: * | B42: TOTAL LIABILITIES & EQUITY | C42: =SUM(C41,C39,C35) -> 1045922 | D42: =SUM(D41,D39,D35) -> 1058454 | E42: =SUM(E41,E39,E35) -> 1041064 | F42: =SUM(F41,F39,F35) -> 1094028.4 | G42: =SUM(G41,G39,G35) -> 1151609.6 | H42: =SUM(H41,H39,H35) -> 1215807.4 | I42: =SUM(I41,I39,I35) -> 1291094.3 | J42: =SUM(J41,J39,J35) -> 1374790.9
A44: * | B44: Balance check | C44: =C42-C30 -> 0 | D44: =D42-D30 -> 0 | E44: =E42-E30 -> 0 | F44: =F42-F30 -> 0 | G44: =G42-G30 -> 0 | H44: =H42-H30 -> 0 | I44: =I42-I30 -> 0 | J44: =J42-J30 -> 0

Sheet CashFlow
A1: =CoName -> BJ's Resturant Inc. | C1: Hist. | D1: Hist. | E1: Hist. | F1: Proj. | G1: Proj. | H1: Proj. | I1: Proj. | J1: Proj.
A2: Cash flow statement | C2: 2022 | D2: =C2+1 -> 2023 | E2: =D2+1 -> 2024 | F2: =E2+1 -> 2025 | G2: =F2+1 -> 2026 | H2: =G2+1 -> 2027 | I2: =H2+1 -> 2028 | J2: =I2+1 -> 2029
B3: Net Income | F3: =IncState!F33 -> 35134.976 | G3: =IncState!G33 -> 41714.245 | H3: =IncState!H33 -> 48564.505 | I3: =IncState!I33 -> 56003.067 | J3: =IncState!J33 -> 63844.233
B4: Depreciation | F4: =IncState!F20 -> 70437.521 | G4: =IncState!G20 -> 72022.346 | H4: =IncState!H20 -> 73668.868 | I4: =IncState!I20 -> 75369.354 | J4: =IncState!J20 -> 77163.207
B5: Amortization | F5: =IncState!F21 -> 0 | G5: =IncState!G21 -> 0 | H5: =IncState!H21 -> 0 | I5: =IncState!I21 -> 0 | J5: =IncState!J21 -> 0
B6: (inc) / dec in OWC | F6: =Calcs!F25 -> 3647.8979 | G6: =Calcs!G25 -> 3219.6924 | H6: =Calcs!H25 -> 3161.3675 | I6: =Calcs!I25 -> 3929.6215 | J6: =Calcs!J25 -> 4040.0324
B7: (inc) / dec in LT assets | F7: =BalSheet!E27-BalSheet!F27 -> -3151.29 | G7: =BalSheet!F27-BalSheet!G27 -> -2813.0515 | H7: =BalSheet!G27-BalSheet!H27 -> -2775.1835 | I7: =BalSheet!H27-BalSheet!I27 -> -3413.4758 | J7: =BalSheet!I27-BalSheet!J27 -> -3515.88
B8: inc / (dec) in LT liabilities | F8: =BalSheet!F38-BalSheet!E38 -> 12247.14 | G8: =BalSheet!G38-BalSheet!F38 -> 10932.614 | H8: =BalSheet!H38-BalSheet!G38 -> 10785.444 | I8: =BalSheet!I38-BalSheet!H38 -> 13266.096 | J8: =BalSheet!J38-BalSheet!I38 -> 13664.079
B9: CFFO | F9: =SUM(F3:F8) -> 118316.25 | G9: =SUM(G3:G8) -> 125075.85 | H9: =SUM(H3:H8) -> 133405 | I9: =SUM(I3:I8) -> 145154.66 | J9: =SUM(J3:J8) -> 155195.67
B11: Capex | F11: =-Calcs!F7 -> -89506.422 | G11: =-Calcs!G7 -> -91833.589 | H11: =-Calcs!H7 -> -94129.429 | I11: =-Calcs!I7 -> -96953.312 | J11: =-Calcs!J7 -> -99861.911
B12: CFFI | F12: =SUM(F11) -> -89506.422 | G12: =SUM(G11) -> -91833.589 | H12: =SUM(H11) -> -94129.429 | I12: =SUM(I11) -> -96953.312 | J12: =SUM(J11) -> -99861.911
B14: Debt Issuance | F14: =SUM(Debt!F8:F9) -> 0 | G14: =SUM(Debt!G8:G9) -> 0 | H14: =SUM(Debt!H8:H9) -> 0 | I14: =SUM(Debt!I8:I9) -> 0 | J14: =SUM(Debt!J8:J9) -> 0
B15: Share Issuance | F15: =Calcs!F11 -> 0 | G15: =Calcs!G11 -> 0 | H15: =Calcs!H11 -> 0 | I15: =Calcs!I11 -> 0 | J15: =Calcs!J11 -> 0
B16: CFFF | F16: =SUM(F14:F15) -> 0 | G16: =SUM(G14:G15) -> 0 | H16: =SUM(H14:H15) -> 0 | I16: =SUM(I14:I15) -> 0 | J16: =SUM(J14:J15) -> 0
B18: net changes in cash | F18: =SUM(F16,F12,F9) -> 28809.823 | G18: =SUM(G16,G12,G9) -> 33242.257 | H18: =SUM(H16,H12,H9) -> 39275.572 | I18: =SUM(I16,I12,I9) -> 48201.35 | J18: =SUM(J16,J12,J9) -> 55333.76
B20: Beginning cash | F20: =E22 -> 12522.98 | G20: =F22 -> 41332.803 | H20: =G22 -> 74575.06 | I20: =H22 -> 113850.63 | J20: =I22 -> 162051.98
B21: =B18 -> net changes in cash | F21: =F18 -> 28809.823 | G21: =G18 -> 33242.257 | H21: =H18 -> 39275.572 | I21: =I18 -> 48201.35 | J21: =J18 -> 55333.76
B22: Ending cash | E22: =BalSheet!E18 -> 12522.98 | F22: =SUM(F20:F21) -> 41332.803 | G22: =SUM(G20:G21) -> 74575.06 | H22: =SUM(H20:H21) -> 113850.63 | I22: =SUM(I20:I21) -> 162051.98 | J22: =SUM(J20:J21) -> 217385.74

Sheet Free Cash Flow
A1: =CoName -> BJ's Resturant Inc. | C1: Hist. | D1: Hist. | E1: Hist. | F1: Proj. | G1: Proj. | H1: Proj. | I1: Proj. | J1: Proj.
A2: Free Cash Flows | C2: 2022 | D2: =C2+1 -> 2023 | E2: =D2+1 -> 2024 | F2: =E2+1 -> 2025 | G2: =F2+1 -> 2026 | H2: =G2+1 -> 2027 | I2: =H2+1 -> 2028 | J2: =I2+1 -> 2029
A3: * | B3: Sales | F3: =IncState!F15 -> 1398021.1 | G3: =IncState!G15 -> 1434369.6 | H3: =IncState!H15 -> 1470228.8 | I3: =IncState!I15 -> 1514335.7 | J3: =IncState!J15 -> 1559765.8
B4: EBIT | F4: =IncState!F18 -> 44474.653 | G4: =IncState!G18 -> 52802.842 | H4: =IncState!H18 -> 61474.057 | I4: =IncState!I18 -> 70889.958 | J4: =IncState!J18 -> 80815.485
B5: Effective Tax Rate | F5: =Assumptions!F16 -> 0.21 | G5: =Assumptions!G16 -> 0.21 | H5: =Assumptions!H16 -> 0.21 | I5: =Assumptions!I16 -> 0.21 | J5: =Assumptions!J16 -> 0.21
A7: * | B7: NOPAT | F7: =F4*(1-F5) -> 35134.976 | G7: =G4*(1-G5) -> 41714.245 | H7: =H4*(1-H5) -> 48564.505 | I7: =I4*(1-I5) -> 56003.067 | J7: =J4*(1-J5) -> 63844.233
B8: Depreciation | F8: =CashFlow!F4 -> 70437.521 | G8: =CashFlow!G4 -> 72022.346 | H8: =CashFlow!H4 -> 73668.868 | I8: =CashFlow!I4 -> 75369.354 | J8: =CashFlow!J4 -> 77163.207
B9: Amortization | F9: =CashFlow!F5 -> 0 | G9: =CashFlow!G5 -> 0 | H9: =CashFlow!H5 -> 0 | I9: =CashFlow!I5 -> 0 | J9: =CashFlow!J5 -> 0
B10: (inc) / dec in OWC | F10: =CashFlow!F6 -> 3647.8979 | G10: =CashFlow!G6 -> 3219.6924 | H10: =CashFlow!H6 -> 3161.3675 | I10: =CashFlow!I6 -> 3929.6215 | J10: =CashFlow!J6 -> 4040.0324
B11: (inc) / dec in other long-term assets | F11: =CashFlow!F7 -> -3151.29 | G11: =CashFlow!G7 -> -2813.0515 | H11: =CashFlow!H7 -> -2775.1835 | I11: =CashFlow!I7 -> -3413.4758 | J11: =CashFlow!J7 -> -3515.88
B12: inc / (dec) other long-term liabilities | F12: =CashFlow!F8 -> 12247.14 | G12: =CashFlow!G8 -> 10932.614 | H12: =CashFlow!H8 -> 10785.444 | I12: =CashFlow!I8 -> 13266.096 | J12: =CashFlow!J8 -> 13664.079
B13: (Capex) | F13: =CashFlow!F11 -> -89506.422 | G13: =CashFlow!G11 -> -91833.589 | H13: =CashFlow!H11 -> -94129.429 | I13: =CashFlow!I11 -> -96953.312 | J13: =CashFlow!J11 -> -99861.911
A15: * | B15: Free Cash Flow | F15: =SUM(F7:F13) -> 28809.823 | G15: =SUM(G7:G13) -> 33242.257 | H15: =SUM(H7:H13) -> 39275.572 | I15: =SUM(I7:I13) -> 48201.35 | J15: =SUM(J7:J13) -> 55333.76

Sheet WACC
A1: =CoName -> BJ's Resturant Inc.
A3: * | B3: WACC | G3: Comp | H3: Levered beta | I3: Gross debt | J3: Market cap | K3: Debt/Mcap | L3: MTR | M3: Unlevered beta
B4: Tax Rate | E4: =Assumptions!F16 -> 0.21 | L4: =E4 -> 0.21 | M4: =H4/((1+K4*(1-L4))) -> 0
B5: Risk free rate | E5: 0.041 | L5: =L4 -> 0.21 | M5: =H5/((1+K5*(1-L5))) -> 0
B6: Market risk Premium | E6: 0.05 | L6: =L5 -> 0.21 | M6: =H6/((1+K6*(1-L6))) -> 0
B7: Beta | E7: 0.67 | L7: =L6 -> 0.21 | M7: =H7/((1+K7*(1-L7))) -> 0
B8: Cost of Equity | E8: =E5+E6*E7 -> 0.0745
B9: % Equity | E9: =1-E10 -> 0.4073034 | G9: Industry beta (average) | M9: =AVERAGE(M4:M7) -> 0
B10: % Debt | E10: =MAIN!F8/MAIN!F6 -> 0.5926966
B11: Cost of debt | E11: =Assumptions!F23 -> 0.082466165 | G11: Re-levered beta | M11: =M9*(1+E10*(1-E4)) -> 0
B12: Post tax cost of debt | E12: =E11*(1-E4) -> 0.065148271
A13: * | B13: WACC | E13: =WACC!E8*WACC!E9+WACC!E12*WACC!E10 -> 0.068957262
B14: Long Term growth rate | E14: 0.025

Sheet DCF Model
A1: =CoName -> BJ's Resturant Inc. | D1: Proj. | E1: Proj. | F1: Proj. | G1: Proj. | H1: Proj.
A2: Discount Model Year count | D2: 0.5 | E2: =D2+1 -> 1.5 | F2: =E2+1 -> 2.5 | G2: =F2+1 -> 3.5 | H2: =G2+1 -> 4.5
B3: Discount Factor | D3: =1/(1+$K$17)^D2 -> 0.96720789 | E3: =1/(1+$K$17)^E2 -> 0.90481437 | F3: =1/(1+$K$17)^F2 -> 0.84644578 | G3: =1/(1+$K$17)^G2 -> 0.79184249 | H3: =1/(1+$K$17)^H2 -> 0.7407616
B4: PV FCF | D4: =D3*'Free Cash Flow'!F15 -> 27865.088 | E4: =E3*'Free Cash Flow'!G15 -> 30078.071 | F4: =F3*'Free Cash Flow'!H15 -> 33244.642 | G4: =G3*'Free Cash Flow'!I15 -> 38167.877 | H4: =H3*'Free Cash Flow'!J15 -> 40989.125
H5: =(H4*(1+$K$18))/($K$17-$K$18) -> 955788.67
A6: Value Calculation | E6: Multiples Calculation
B7: Total PV of FCFs | C7: =SUM(D4:H4) -> 170344.8 | E7: Total PV of FCFs | G7: =C7 -> 170344.8
B8: PV of TV | C8: =H5*H3 -> 708011.54 | E8: Multiple TV | G8: =H3*G10*IncState!J22 -> 1755368.2
B9: EV | C9: =C7+C8 -> 878356.35 | E9: EV | G9: =G7+G8 -> 1925713
E10: Implied EBITDA multiple | G10: 15
B12: Cash & Cash Equiv | C12: =MAIN!F7 -> 25431 | E12: Cash & Cash Equiv | G12: =C12 -> 25431
B13: Debt & Claims | C13: =MAIN!F8 -> 501042 | E13: Debt & Claims | G13: =C13 -> 501042
B14: NCI | C14: 0 | E14: NCI | G14: 0
B15: Equity Value | C15: =C9+C12-SUM(C13:C14) -> 402745.35 | E15: Equity Value | G15: =G9+G12-SUM(G13:G14) -> 1450102
B17: Diluted S/O | C17: =MAIN!F5 -> 21134 | E17: Diluted S/O | G17: =C17 -> 21134 | I17: WACC | K17: =WACC!E13 -> 0.068957262
A18: * | B18: Implied Share Price | C18: =C15/C17 -> 19.05675 | E18: Implied Share Price | G18: =G15/G17 -> 68.614651 | I18: Long Term growth rate | K18: 0.025
A20: Sensitivity analysis
C22: Discount rate variance | E22: 0.005 | H22: Discount rate variance | J22: 0.005
C23: Implied growth rate variance | E23: 0.0025 | H23: TV multiple variance | J23: 2
E25: LTGR | J25: Exit Multiple
C26: =C18 -> 19.05675 | D26: =E26-E23 -> 0.0225 | E26: 0.025 | F26: =E26+E23 -> 0.0275 | H26: =G18 -> 68.614651 | I26: =J26-J23 -> 13 | J26: 15 | K26: =J26+J23 -> 17
C27: =C28+$E$22 -> 0.078957262 | D27: 9.2845347 | E27: 10.454424 | F27: 11.737989 | H27: =C27 -> 0.078957262 | I27: 54.386635 | J27: 65.006713 | K27: 75.626792
C28: =C29+$E$22 -> 0.073957262 | D28: 12.82912 | E28: 14.297332 | F28: 15.923561 | H28: =C28 -> 0.073957262 | I28: 55.943441 | J28: 66.787836 | K28: 77.63223
C29: 0.068957262 | D29: 17.176647 | E29: 19.05675 | F29: 21.163604 | H29: =C29 -> 0.068957262 | I29: 57.540122 | J29: 68.614651 | K29: 79.68918
C30: =C29-$E$22 -> 0.063957262 | D30: 22.620437 | E30: 25.088556 | F30: 27.895169 | H30: =C30 -> 0.063957262 | I30: 59.177898 | J30: 70.488558 | K30: 81.799219
C31: =C30-$E$22 -> 0.058957262 | D31: 29.614927 | E31: 32.95845 | F31: 36.833412 | H31: =C31 -> 0.058957262 | I31: 60.858032 | J31: 72.411007 | K31: 83.963983
