Workbook
Name Ccy: MAIN!$C$6
Name circ: MAIN!$C$9
Name CoName: MAIN!$C$4
Name g: #REF!
Name IQ_CH: 110000
Name IQ_CQ: 5000
Name IQ_CY: 10000
Name IQ_DAILY: 500000
Name IQ_FH: 100000
Name IQ_FQ: 500
Name IQ_FY: 1000
Name IQ_LTM: 2000
Name IQ_MONTH: 15000
Name IQ_NTM: 6000
Name IQ_WEEK: 50000
Name IQ_YTD: 3000
Name OpCase: [1]DCF!$E$98
Name ScenarioREV: Assumptions!$D$4
Name TTS: #REF!
Name Units: MAIN!$C$7

Sheet MAIN
A1: =CoName -> CoName
A2: Model Details
B4: Company name | C4: CoName | E4: Current Stock Price | F4: 58.4 | H4: Operating Case One | I4: Terminal Mult | J4: Perpetuity | K4: Average
B5: Latest BS date | C5: 247.43 | E5: Diluted s/o | F5: 177560 | H5: Implied Price | I5: ='DCF Model'!G18 -> 77.624078 | J5: ='DCF Model'!C18 -> 48.51685 | K5: =AVERAGE(I5:J5) -> 63.070464
B6: Currency | C6: USD | E6: Mkt Cap | F6: =F5*F4 -> 10369504 | H6: Difference | I6: =I5/$F$4-1 -> 0.32917941 | J6: =J5/$F$4-1 -> -0.16923203 | K6: =K5/$F$4-1 -> 0.079973693
B7: Units | C7: m | E7: Cash | F7: =267195 -> 267195
B8: Analyst name | C8: Alan Chen | E8: Debt | F8: =3879+17228+413403+825302 -> 1259812
B9: Circular switch | C9: 0 | E9: EV | F9: =F6-F7+F8 -> 11362121

Sheet Quarterly Projections
A1: =CoName -> CoName
A2: Income Statement | C2: Q122 | D2: Q222 | E2: Q322 | F2: Q422 | G2: 2022 | H2: Q123 | I2: Q223 | J2: Q323 | K2: Q423 | L2: 2023 | M2: Q124 | N2: Q224 | O2: Q324 | P2: Q424 | Q2: 2024 | R2: Q125 | S2: Q225 | T2: Q325 | U2: Q425E | V2: 2025E | W2: Q126E | X2: Q226E | Y2: Q326E | Z2: Q426E | AA2: 2026E | AB2: 2027E | AC2: 2028E | AD2: 2029E | AE2: 2030E | AF2: 2031E
B3: Company-operated shops | C3: 130187 | D3: 160512 | E3: 173501 | F3: 175510 | G3: =SUM(C3:F3) -> 639710 | H3: 173164 | I3: 220952 | J3: 236472 | K3: 227351 | L3: =SUM(H3:K3) -> 857939 | M3: 248085 | N3: 295268 | O3: 308295 | P3: 314182 | Q3: =SUM(M3:P3) -> 1165830 | R3: 326421 | S3: 380500 | T3: 392833 | U3: =P3*(1+U4) -> 392727.5 | V3: =SUM(R3:U3) -> 1492481.5 | W3: =R3*(1+W4) -> 424347.3 | X3: =S3*(1+X4) -> 494650 | Y3: =T3*(1+Y4) -> 510682.9 | Z3: =U3*(1+Z4) -> 510545.75 | AA3: =SUM(W3:Z3) -> 1940226 | AB3: =AA3*(1+AB4) -> 2502891.5 | AC3: =AB3*(1+AC4) -> 3203701.1 | AD3: =AC3*(1+AD4) -> 4068700.4 | AE3: =AD3*(1+AE4) -> 5126562.5 | AF3: =AE3*(1+AF4) -> 6408203.1
B4: y/y | C4: n/a | D4: n/a | E4: n/a | F4: n/a | G4: n/a | H4: =H3/C3-1 -> 0.33011745 | I4: =I3/D3-1 -> 0.37654506 | J4: =J3/E3-1 -> 0.36294315 | K4: =K3/F3-1 -> 0.29537348 | L4: =L3/G3-1 -> 0.34113739 | M4: =M3/H3-1 -> 0.43265921 | N4: =N3/I3-1 -> 0.33634455 | O4: =O3/J3-1 -> 0.30372729 | ... T4: =T3/O3-1 -> 0.27421139 | U4: 0.25 | V4: =V3/Q3-1 -> 0.28018793 | W4: 0.3 | X4: 0.3 | Y4: 0.3 | Z4: 0.3 | AA4: =AA3/V3-1 -> 0.3 | AB4: =AA4-0.01 -> 0.29 | AC4: =AB4-0.01 -> 0.28 | AD4: =AC4-0.01 -> 0.27 | AE4: =AD4-0.01 -> 0.26 | AF4: =AE4-0.01 -> 0.25
B5: Franchising | C5: 21969 | D5: 25869 | E5: 25147 | F5: 26317 | G5: =SUM(C5:F5) -> 99302 | H5: 24103 | I5: 28927 | J5: 28035 | K5: 26772 | L5: =SUM(H5:K5) -> 107837 | M5: 27014 | N5: 29650 | O5: 29917 | P5: 28604 | Q5: =SUM(M5:P5) -> 115185 | R5: 28731 | S5: 35313 | T5: 30751 | U5: =P5*(1+U6) -> 29401.397 | V5: =SUM(R5:U5) -> 124196.4 | W5: =R5*(1+W6) -> 30978.745 | X5: =S5*(1+X6) -> 38075.682 | Y5: =T5*(1+Y6) -> 33156.777 | Z5: =U5*(1+Z6) -> 31701.59 | AA5: =SUM(W5:Z5) -> 133912.79 | AB5: =AA5*(1+AB6) -> 143050.22 | AC5: =AB5*(1+AC6) -> 151380.62 | AD5: =AC5*(1+AD6) -> 158682.33 | AE5: =AD5*(1+AE6) -> 164749.41 | AF5: =AE5*(1+AF6) -> 169400.96
B6: y/y | C6: n/a | D6: n/a | E6: n/a | F6: n/a | G6: n/a | H6: =H5/C5-1 -> 0.097136875 | I6: =I5/D5-1 -> 0.11821099 | J6: =J5/E5-1 -> 0.11484471 | K6: =K5/F5-1 -> 0.017289205 | L6: =L5/G5-1 -> 0.085949931 | M6: =M5/H5-1 -> 0.12077335 | N6: =N5/I5-1 -> 0.02499395 | O6: =O5/J5-1 -> 0.067130373 | ... T6: =T5/O5-1 -> 0.027877127 | U6: =T6 -> 0.027877127 | V6: =V5/Q5-1 -> 0.078234122 | W6: =V6 -> 0.078234122 | X6: =W6 -> 0.078234122 | Y6: =X6 -> 0.078234122 | Z6: =Y6 -> 0.078234122 | AA6: =AA5/V5-1 -> 0.078234122 | AB6: =AA6-0.01 -> 0.068234122 | AC6: =AB6-0.01 -> 0.058234122 | AD6: =AC6-0.01 -> 0.048234122 | AE6: =AD6-0.01 -> 0.038234122 | AF6: =AE6-0.01 -> 0.028234122
A7: Revenues | C7: =C3+C5 -> 152156 | D7: =D3+D5 -> 186381 | E7: =E3+E5 -> 198648 | F7: =F3+F5 -> 201827 | G7: =G3+G5 -> 739012 | H7: =H3+H5 -> 197267 | I7: =I3+I5 -> 249879 | J7: =J3+J5 -> 264507 | ... AF7: =AF3+AF5 -> 6577604.1
B8: y/y | C8: n/a | D8: n/a | E8: n/a | F8: n/a | G8: n/a | H8: =H7/C7-1 -> 0.29647861 | I8: =I7/D7-1 -> 0.34068923 | J8: =J7/E7-1 -> 0.33153618 | K8: =K7/F7-1 -> 0.259113 | L8: =L7/G7-1 -> 0.30684752 | M8: =M7/H7-1 -> 0.39455155 | N8: =N7/I7-1 -> 0.30030135 | O8: =O7/J7-1 -> 0.27865047 | ... AA8: =AA7/V7-1 -> 0.28296351 | AB8: =AB7/AA7-1 -> 0.27568211 | AC8: =AC7/AB7-1 -> 0.26801045 | AD8: =AD7/AC7-1 -> 0.25999397 | AE8: =AE7/AD7-1 -> 0.25167562 | AF8: =AF7/AE7-1 -> 0.24309513
B10: COGS | C10: 121167 | D10: 141370 | E10: 148092 | F10: 147467 | G10: =SUM(C10:F10) -> 558096 | H10: 151523 | I10: 178636 | J10: 189323 | K10: 194998 | L10: =SUM(H10:K10) -> 714480 | M10: 203326 | N10: 234637 | O10: 248161 | P10: 254838 | Q10: =SUM(M10:P10) -> 940962 | R10: 265159 | S10: 295769 | T10: 316805 | U10: =U7*U11 -> 310380.88 | V10: =SUM(R10:U10) -> 1188113.9 | W10: =W7*W11 -> 334623.98 | X10: =X7*X11 -> 391505.8 | Y10: =Y7*Y11 -> 399673.6 | Z10: =Z7*Z11 -> 398503.37 | AA10: =SUM(W10:Z10) -> 1524306.8 | AB10: =AB7*AB11 -> 1918071.4 | AC10: =AC7*AC11 -> 2398583.8 | AD10: =AD7*AD11 -> 2979927.3 | AE10: =AE7*AE11 -> 3676989.2 | AF10: =AF7*AF11 -> 4505071.4
B11: Margins | C11: =C10/C7 -> 0.79633403 | D11: =D10/D7 -> 0.75850006 | E11: =E10/E7 -> 0.74549958 | F11: =F10/F7 -> 0.73066042 | G11: =G10/G7 -> 0.75519207 | H11: =H10/H7 -> 0.76811124 | I11: =I10/I7 -> 0.71489001 | J11: =J10/J7 -> 0.715758 | ... T11: =T10/T7 -> 0.74791541 | U11: =AVERAGE(R11:T11) -> 0.73527514 | V11: =V10/V7 -> 0.7349107 | W11: =V11 -> 0.7349107 | X11: =W11 -> 0.7349107 | Y11: =X11 -> 0.7349107 | Z11: =Y11 -> 0.7349107 | AA11: =AA10/AA7 -> 0.7349107 | AB11: =AA11-0.01 -> 0.7249107 | AC11: =AB11-0.01 -> 0.7149107 | AD11: =AC11-0.01 -> 0.7049107 | AE11: =AD11-0.01 -> 0.6949107 | AF11: =AE11-0.01 -> 0.6849107
B12: SG&A | C12: 45214 | D12: 42342 | E12: 45378 | F12: 50594 | G12: =SUM(C12:F12) -> 183528 | H12: 45976 | I12: 51662 | J12: 50490 | K12: 56946 | L12: =SUM(H12:K12) -> 205074 | M12: 46194 | N12: 58097 | O12: 57536 | P12: 72170 | Q12: =SUM(M12:P12) -> 233997 | R12: 58921 | S12: 65385 | T12: 65289 | U12: =U7*U13 -> 67158.526 | V12: =SUM(R12:U12) -> 256753.53 | W12: =W7*W13 -> 72312.838 | X12: =X7*X13 -> 84605.101 | Y12: =Y7*Y13 -> 86370.176 | Z12: =Z7*Z13 -> 86117.288 | AA12: =SUM(W12:Z12) -> 329405.4 | AB12: =AB7*AB13 -> 393757.16 | AC12: =AC7*AC13 -> 465737.38 | AD12: =AD7*AD13 -> 544552.46 | AE12: =AE7*AE13 -> 628689.93 | AF12: =AF7*AF13 -> 715745.35
B13: Margins | C13: =C12/C7 -> 0.29715555 | D13: =D12/D7 -> 0.22717981 | E13: =E12/E7 -> 0.22843422 | F13: =F12/F7 -> 0.25068004 | G13: =G12/G7 -> 0.24834238 | H13: =H12/H7 -> 0.23306483 | I13: =I12/I7 -> 0.20674807 | J13: =J12/J7 -> 0.19088342 | ... T13: =T12/T7 -> 0.15413472 | U13: =AVERAGE(R13:T13) -> 0.15909483 | V13: =V12/V7 -> 0.15881551 | W13: =V13 -> 0.15881551 | X13: =W13 -> 0.15881551 | Y13: =X13 -> 0.15881551 | Z13: =Y13 -> 0.15881551 | AA13: =AA12/AA7 -> 0.15881551 | AB13: =AA13-0.01 -> 0.14881551 | AC13: =AB13-0.01 -> 0.13881551 | AD13: =AC13-0.01 -> 0.12881551 | AE13: =AD13-0.01 -> 0.11881551 | AF13: =AE13-0.01 -> 0.10881551
A14: Operating Income | C14: =C7-C10-C12 -> -14225 | D14: =D7-D10-D12 -> 2669 | E14: =E7-E10-E12 -> 5178 | F14: =F7-F10-F12 -> 3766 | G14: =G7-G10-G12 -> -2612 | H14: =H7-H10-H12 -> -232 | I14: =I7-I10-I12 -> 19581 | J14: =J7-J10-J12 -> 24694 | ... AF14: =AF7-AF10-AF12 -> 1356787.3
B15: Margins | C15: =C14/C7 -> -0.093489576 | D15: =D14/D7 -> 0.014320129 | E15: =E14/E7 -> 0.026066208 | F15: =F14/F7 -> 0.018659545 | G15: =G14/G7 -> -0.0035344487 | H15: =H14/H7 -> -0.001176071 | I15: =I14/I7 -> 0.078361927 | J15: =J14/J7 -> 0.093358588 | ... AF15: =AF14/AF7 -> 0.20627379

Sheet Assumptions
A1: =CoName -> CoName | C1: Hist. | D1: Hist. | E1: Hist. | F1: Proj. | G1: Proj. | H1: Proj. | I1: Proj. | J1: Proj. | K1: Proj. | L1: Proj.
A2: * | B2: Income Statement | C2: 2022 | D2: =C2+1 -> 2023 | E2: =D2+1 -> 2024 | F2: =E2+1 -> 2025 | G2: =F2+1 -> 2026 | H2: =G2+1 -> 2027 | I2: =H2+1 -> 2028 | J2: =I2+1 -> 2029 | K2: =J2+1 -> 2030 | L2: =K2+1 -> 2031
B4: Operating Case | D4: 1
D5: Variance
B6: Street Case | D6: 0 | F6: ='Quarterly Projections'!V8 -> 0.26202886 | G6: ='Quarterly Projections'!AA8 -> 0.28296351 | H6: ='Quarterly Projections'!AB8 -> 0.27568211 | I6: ='Quarterly Projections'!AC8 -> 0.26801045 | J6: ='Quarterly Projections'!AD8 -> 0.25999397 | K6: ='Quarterly Projections'!AE8 -> 0.25167562 | L6: ='Quarterly Projections'!AF8 -> 0.24309513
B7: Optimistic Case | D7: 0.025 | F7: =F6+$D$7 -> 0.28702886 | G7: =G6+$D$7 -> 0.30796351 | H7: =H6+$D$7 -> 0.30068211 | I7: =I6+$D$7 -> 0.29301045 | J7: =J6+$D$7 -> 0.28499397 | K7: =K6+$D$7 -> 0.27667562 | L7: =L6+$D$7 -> 0.26809513
B8: Pessimistic Case | D8: -0.025 | F8: =F6+$D$8 -> 0.23702886 | G8: =G6+$D$8 -> 0.25796351 | H8: =H6+$D$8 -> 0.25068211 | I8: =I6+$D$8 -> 0.24301045 | J8: =J6+$D$8 -> 0.23499397 | K8: =K6+$D$8 -> 0.22667562 | L8: =L6+$D$8 -> 0.21809513
B10: Revenue Growth | D10: =IncState!D15/IncState!C15-1 -> 0.30684752 | E10: =IncState!E15/IncState!D15-1 -> 0.32641006 | F10: =CHOOSE(ScenarioREV,F6,F7,F8) -> 0.26202886 | G10: =CHOOSE(ScenarioREV,G6,G7,G8) -> 0.28296351 | H10: =CHOOSE(ScenarioREV,H6,H7,H8) -> 0.27568211 | I10: =CHOOSE(ScenarioREV,I6,I7,I8) -> 0.26801045 | J10: =CHOOSE(ScenarioREV,J6,J7,J8) -> 0.25999397 | K10: =CHOOSE(ScenarioREV,K6,K7,K8) -> 0.25167562 | L10: =CHOOSE(ScenarioREV,L6,L7,L8) -> 0.24309513
B11: COGS % of sales | C11: =IncState!C16/IncState!C15 -> 0.75519207 | D11: =IncState!D16/IncState!D15 -> 0.73979888 | E11: =IncState!E16/IncState!E15 -> 0.73454409 | F11: ='Quarterly Projections'!V11 -> 0.7349107 | G11: ='Quarterly Projections'!AA11 -> 0.7349107 | H11: ='Quarterly Projections'!AB11 -> 0.7249107 | I11: ='Quarterly Projections'!AC11 -> 0.7149107 | J11: ='Quarterly Projections'!AD11 -> 0.7049107 | K11: ='Quarterly Projections'!AE11 -> 0.6949107 | L11: ='Quarterly Projections'!AF11 -> 0.6849107
B12: SG&A % of sales | C12: =IncState!C17/IncState!C15 -> 0.24834238 | D12: =IncState!D17/IncState!D15 -> 0.21234116 | E12: =IncState!E17/IncState!E15 -> 0.18266531 | F12: ='Quarterly Projections'!V13 -> 0.15881551 | G12: ='Quarterly Projections'!AA13 -> 0.15881551 | H12: ='Quarterly Projections'!AB13 -> 0.14881551 | I12: ='Quarterly Projections'!AC13 -> 0.13881551 | J12: ='Quarterly Projections'!AD13 -> 0.12881551 | K12: ='Quarterly Projections'!AE13 -> 0.11881551 | L12: ='Quarterly Projections'!AF13 -> 0.10881551
B13: Amortization $ Amt | C13: =IncState!C21 -> 0 | D13: =IncState!D21 -> 0 | E13: =IncState!E21 -> 0 | F13: =E13 -> 0 | G13: =F13 -> 0 | H13: =G13 -> 0 | I13: =H13 -> 0 | J13: =I13 -> 0 | K13: =J13 -> 0 | L13: =K13 -> 0
B14: Non recurring income / (expense) | C14: =IncState!C24 -> 0 | D14: =IncState!D24 -> 0 | E14: =IncState!E24 -> 0 | F14: 0 | G14: 0 | H14: 0 | I14: 0 | J14: 0 | K14: 0 | L14: 0
B15: Other Income / (expense) | C15: =IncState!C25 -> 3976 | D15: =IncState!D25 -> 3018 | E15: =IncState!E25 -> 5812 | F15: =E15+(E15-D15) -> 8606 | G15: =F15+(F15-E15) -> 11400 | H15: =G15+(G15-F15) -> 14194 | I15: =H15+(H15-G15) -> 16988 | J15: =I15+(I15-H15) -> 19782 | K15: =J15+(J15-I15) -> 22576 | L15: =K15+(K15-J15) -> 25370
B16: Effective tax rate | C16: =IncState!C32/IncState!C30 -> -0.1560586 | D16: =IncState!D32/IncState!D30 -> 0.41178557 | E16: =IncState!E32/IncState!E30 -> 0.21727088 | F16: =E16 -> 0.21727088 | G16: =F16 -> 0.21727088 | H16: =G16 -> 0.21727088 | I16: =H16 -> 0.21727088 | J16: =I16 -> 0.21727088 | K16: =J16 -> 0.21727088 | L16: =K16 -> 0.21727088
B17: Basic WASO | C17: =IncState!C35 -> 51871 | D17: =IncState!D35 -> 62074 | E17: =IncState!E35 -> 103504 | F17: =E17 -> 103504 | G17: =F17 -> 103504 | H17: =G17 -> 103504 | I17: =H17 -> 103504 | J17: =I17 -> 103504 | K17: =J17 -> 103504 | L17: =K17 -> 103504
B18: Diluted WASO | C18: =IncState!C36 -> 51871 | D18: =IncState!D36 -> 62074 | E18: =IncState!E36 -> 104129 | F18: =E18 -> 104129 | G18: =F18 -> 104129 | H18: =G18 -> 104129 | I18: =H18 -> 104129 | J18: =I18 -> 104129 | K18: =J18 -> 104129 | L18: =K18 -> 104129
A20: * | B20: Debt | C20: =C2 -> 2022 | D20: =D2 -> 2023 | E20: =E2 -> 2024 | F20: =F2 -> 2025 | G20: =G2 -> 2026 | H20: =H2 -> 2027 | I20: =I2 -> 2028 | J20: =J2 -> 2029 | ... L20: =L2 -> 2031
B22: Interest rate on Revolver | E22: 0.0536 | F22: =E22 -> 0.0536 | G22: =F22 -> 0.0536 | H22: =G22 -> 0.0536 | I22: =H22 -> 0.0536 | J22: =I22 -> 0.0536 | K22: =J22 -> 0.0536 | L22: =K22 -> 0.0536
B23: Interest rate on long-term debt | E23: 0.0696 | F23: =E23 -> 0.0696 | G23: =F23 -> 0.0696 | H23: =G23 -> 0.0696 | I23: =H23 -> 0.0696 | J23: =I23 -> 0.0696 | K23: =J23 -> 0.0696 | L23: =K23 -> 0.0696
B24: Interest rate on cash | E24: 0.04 | F24: =E24 -> 0.04 | G24: =F24 -> 0.04 | H24: =G24 -> 0.04 | I24: =H24 -> 0.04 | J24: =I24 -> 0.04 | K24: =J24 -> 0.04 | L24: =K24 -> 0.04
B26: Issuance of long-term debt | F26: 0 | G26: 0 | H26: 0 | I26: 0 | J26: 0 | K26: 0 | L26: 0
B27: Repayment of long-term debt | F27: 0 | G27: 0 | H27: 0 | I27: 0 | J27: 0 | K27: 0 | L27: 0
A29: * | B29: Calcs | C29: =C20 -> 2022 | D29: =D20 -> 2023 | E29: =E20 -> 2024 | F29: =F20 -> 2025 | G29: =G20 -> 2026 | H29: =H20 -> 2027 | I29: =I20 -> 2028 | J29: =J20 -> 2029 | ... L29: =L20 -> 2031
B31: CapEx % of Sales | C31: =118444/IncState!C15 -> 0.16027345 | D31: =187880/IncState!D15 -> 0.19453786 | E31: =228457/IncState!E15 -> 0.17834061 | F31: =E31 -> 0.17834061 | G31: =F31 -> 0.17834061 | H31: =G31 -> 0.17834061 | I31: =H31 -> 0.17834061 | J31: =I31 -> 0.17834061 | K31: =J31 -> 0.17834061 | L31: =K31 -> 0.17834061
B32: Depreciation % of beginning PP&E | D32: =IncState!D20/BalSheet!C23 -> 0.088327395 | E32: =IncState!E20/BalSheet!D23 -> 0.082682356 | F32: =E32 -> 0.082682356 | G32: =F32 -> 0.082682356 | H32: =G32 -> 0.082682356 | I32: =H32 -> 0.082682356 | J32: =I32 -> 0.082682356 | K32: =J32 -> 0.082682356 | L32: =K32 -> 0.082682356
B33: Share issuance / (repurchases) | F33: 0 | G33: 0 | H33: 0 | I33: 0 | J33: 0 | K33: 0 | L33: 0
A35: * | B35: Balance Sheet - Assets | C35: =#REF! -> #REF! | D35: =#REF! -> #REF! | E35: =#REF! -> #REF! | F35: =#REF! -> #REF! | G35: =#REF! -> #REF! | H35: =#REF! -> #REF! | I35: =#REF! -> #REF! | J35: =#REF! -> #REF! | ... L35: =#REF! -> #REF!
B37: Operating Cash % of sales | C37: =BalSheet!C16/IncState!C15 -> 0.02 | D37: =BalSheet!D16/IncState!D15 -> 0.02 | E37: =BalSheet!E16/IncState!E15 -> 0.02 | F37: =E37 -> 0.02 | G37: =F37 -> 0.02 | H37: =G37 -> 0.02 | I37: =H37 -> 0.02 | J37: =I37 -> 0.02 | K37: =J37 -> 0.02 | L37: =K37 -> 0.02
B38: Accounts receivable % of sales | C38: =BalSheet!C18/IncState!C15 -> 0.016191889 | D38: =BalSheet!D18/IncState!D15 -> 0.0094473253 | E38: =BalSheet!E18/IncState!E15 -> 0.0082731272 | F38: =E38 -> 0.0082731272 | G38: =F38 -> 0.0082731272 | H38: =G38 -> 0.0082731272 | I38: =H38 -> 0.0082731272 | J38: =I38 -> 0.0082731272 | K38: =J38 -> 0.0082731272 | L38: =K38 -> 0.0082731272
B39: Inventories % of COGS | C39: =BalSheet!C19/IncState!C16 -> 0.070290774 | D39: =BalSheet!D19/IncState!D16 -> 0.065716325 | E39: =BalSheet!E19/IncState!E16 -> 0.038777336 | F39: =E39 -> 0.038777336 | G39: =F39 -> 0.038777336 | H39: =G39 -> 0.038777336 | I39: =H39 -> 0.038777336 | J39: =I39 -> 0.038777336 | K39: =J39 -> 0.038777336 | L39: =K39 -> 0.038777336
B40: Other current assets % of sales | C40: =BalSheet!C20/IncState!C15 -> 0.014815727 | D40: =BalSheet!D20/IncState!D15 -> 0.016191125 | E40: =BalSheet!E20/IncState!E15 -> 0.013661823 | F40: =E40 -> 0.013661823 | G40: =F40 -> 0.013661823 | H40: =G40 -> 0.013661823 | I40: =H40 -> 0.013661823 | J40: =I40 -> 0.013661823 | K40: =J40 -> 0.013661823 | L40: =K40 -> 0.013661823
B42: Other long-term assets % of sales | C42: =BalSheet!C25/IncState!C15 -> 0.39362284 | D42: =BalSheet!D25/IncState!D15 -> 0.42127781 | E42: =BalSheet!E25/IncState!E15 -> 0.58134995 | F42: =E42 -> 0.58134995 | G42: =F42 -> 0.58134995 | H42: =G42 -> 0.58134995 | I42: =H42 -> 0.58134995 | J42: =I42 -> 0.58134995 | K42: =J42 -> 0.58134995 | L42: =K42 -> 0.58134995
A44: * | B44: Balance Sheet - Liabilities | C44: =C35 -> #REF! | D44: =D35 -> #REF! | E44: =E35 -> #REF! | F44: =F35 -> #REF! | G44: =G35 -> #REF! | H44: =H35 -> #REF! | I44: =I35 -> #REF! | J44: =J35 -> #REF! | ... L44: =L35 -> #REF!
B46: Accounts payable % of COGS | C46: =BalSheet!C31/IncState!C16 -> 0.10138399 | D46: =BalSheet!D31/IncState!D16 -> 0.11694519 | E46: =BalSheet!E31/IncState!E16 -> 0.12283812 | F46: =E46 -> 0.12283812 | G46: =F46 -> 0.12283812 | H46: =G46 -> 0.12283812 | I46: =H46 -> 0.12283812 | J46: =I46 -> 0.12283812 | K46: =J46 -> 0.12283812 | L46: =K46 -> 0.12283812
B47: Other current liabilities % of sales | C47: =BalSheet!C32/IncState!C15 -> 0.057675653 | D47: =BalSheet!D32/IncState!D15 -> 0.05184432 | E47: =BalSheet!E32/IncState!E15 -> 0.054779999 | F47: =E47 -> 0.054779999 | G47: =F47 -> 0.054779999 | H47: =G47 -> 0.054779999 | I47: =H47 -> 0.054779999 | J47: =I47 -> 0.054779999 | K47: =J47 -> 0.054779999 | L47: =K47 -> 0.054779999
B48: Other long-term liabilities % of sales | C48: =BalSheet!C36/IncState!C15 -> 0.84627584 | D48: =BalSheet!D36/IncState!D15 -> 0.88715189 | E48: =BalSheet!E36/IncState!E15 -> 1.0260567 | F48: =E48 -> 1.0260567 | G48: =F48 -> 1.0260567 | H48: =G48 -> 1.0260567 | I48: =H48 -> 1.0260567 | J48: =I48 -> 1.0260567 | K48: =J48 -> 1.0260567 | L48: =K48 -> 1.0260567

Sheet Calcs
A1: =CoName -> CoName | C1: Hist. | D1: Hist. | E1: Hist. | F1: Proj. | G1: Proj. | H1: Proj. | I1: Proj. | J1: Proj. | K1: Proj. | L1: Proj.
A2: Net PP&E | C2: 2022 | D2: =C2+1 -> 2023 | E2: =D2+1 -> 2024 | F2: =E2+1 -> 2025 | G2: =F2+1 -> 2026 | H2: =G2+1 -> 2027 | I2: =H2+1 -> 2028 | J2: =I2+1 -> 2029 | K2: =J2+1 -> 2030 | L2: =K2+1 -> 2031
B3: Capital expenditure % of sales | F3: =Assumptions!F31 -> 0.17834061 | G3: =Assumptions!G31 -> 0.17834061 | H3: =Assumptions!H31 -> 0.17834061 | I3: =Assumptions!I31 -> 0.17834061 | J3: =Assumptions!J31 -> 0.17834061 | K3: =Assumptions!K31 -> 0.17834061 | L3: =Assumptions!L31 -> 0.17834061
B4: Depreciation % of PP&E | F4: =Assumptions!F32 -> 0.082682356 | G4: =F4 -> 0.082682356 | H4: =G4 -> 0.082682356 | I4: =H4 -> 0.082682356 | J4: =I4 -> 0.082682356 | K4: =J4 -> 0.082682356 | L4: =K4 -> 0.082682356
B6: Beginning PP&E | F6: =E9 -> 1373850 | G6: =F9 -> 1548576.2 | H6: =G9 -> 1790439.4 | I6: =H9 -> 2114280.5 | J6: =I9 -> 2537814.2 | K6: =J9 -> 3081895.7 | L6: =K9 -> 3770733.1
B7: Capex | F7: =F3*IncState!F15 -> 288319.33 | G7: =G3*IncState!G15 -> 369903.17 | H7: =H3*IncState!H15 -> 471878.86 | I7: =I3*IncState!I15 -> 598347.33 | J7: =J3*IncState!J15 -> 753914.02 | K7: =K3*IncState!K15 -> 943655.8 | L7: =L3*IncState!L15 -> 1173053.9
B8: Depreciation | F8: =F6*F4 -> 113593.15 | G8: =G6*G4 -> 128039.93 | H8: =H6*H4 -> 148037.75 | I8: =I6*I4 -> 174813.7 | J8: =J6*J4 -> 209832.45 | K8: =K6*K4 -> 254818.4 | L8: =L6*L4 -> 311773.1
B9: Ending PP&E | E9: =BalSheet!E23 -> 1373850 | F9: =F6+F7-F8 -> 1548576.2 | G9: =G6+G7-G8 -> 1790439.4 | H9: =H6+H7-H8 -> 2114280.5 | I9: =I6+I7-I8 -> 2537814.2 | J9: =J6+J7-J8 -> 3081895.7 | K9: =K6+K7-K8 -> 3770733.1 | L9: =L6+L7-L8 -> 4632014
A10: Equity | C10: =C2 -> 2022 | D10: =D2 -> 2023 | E10: =E2 -> 2024 | F10: =F2 -> 2025 | G10: =G2 -> 2026 | H10: =H2 -> 2027 | I10: =I2 -> 2028 | J10: =J2 -> 2029 | ... L10: =L2 -> 2031
B11: Share issuance/(repurchases) | F11: =Assumptions!F33 -> 0 | G11: =Assumptions!G33 -> 0 | H11: =Assumptions!H33 -> 0 | I11: =Assumptions!I33 -> 0 | J11: =Assumptions!J33 -> 0 | K11: =Assumptions!K33 -> 0 | L11: =Assumptions!L33 -> 0
B13: Beginning balance | F13: =E16 -> 763865 | G13: =F16 -> 905082.24 | H13: =G16 -> 1086539.7 | I13: =H16 -> 1359169.8 | J13: =I16 -> 1756599.3 | K13: =J16 -> 2322265.9 | L13: =K16 -> 3111420.2
B14: Net income | F14: =IncState!F33 -> 141217.24 | G14: =IncState!G33 -> 181457.42 | H14: =IncState!H33 -> 272630.1 | I14: =IncState!I33 -> 397429.55 | J14: =IncState!J33 -> 565666.55 | K14: =IncState!K33 -> 789154.32 | L14: =IncState!L33 -> 1081854.8
B15: Share issuance / (repurchase) | F15: =F11 -> 0 | G15: =G11 -> 0 | H15: =H11 -> 0 | I15: =I11 -> 0 | J15: =J11 -> 0 | K15: =K11 -> 0 | L15: =L11 -> 0
B16: Ending balance | E16: =BalSheet!E39 -> 763865 | F16: =SUM(F13:F15) -> 905082.24 | G16: =SUM(G13:G15) -> 1086539.7 | H16: =SUM(H13:H15) -> 1359169.8 | I16: =SUM(I13:I15) -> 1756599.3 | J16: =SUM(J13:J15) -> 2322265.9 | K16: =SUM(K13:K15) -> 3111420.2 | L16: =SUM(L13:L15) -> 4193275
A17: OWC | C17: =C10 -> 2022 | D17: =D10 -> 2023 | E17: =E10 -> 2024 | F17: =F10 -> 2025 | G17: =G10 -> 2026 | H17: =H10 -> 2027 | I17: =I10 -> 2028 | J17: =J10 -> 2029 | ... L17: =L10 -> 2031
B18: Operating Cash | E18: =BalSheet!E16 -> 25620.3 | F18: =BalSheet!F16 -> 32333.558 | G18: =BalSheet!G16 -> 41482.775 | H18: =BalSheet!H16 -> 52918.834 | I18: =BalSheet!I16 -> 67101.634 | J18: =BalSheet!J16 -> 84547.654 | K18: =BalSheet!K16 -> 105826.24 | L18: =BalSheet!L16 -> 131552.08
B19: =BalSheet!B18 -> Accounts receivable | E19: =BalSheet!E18 -> 10598 | F19: =BalSheet!F18 -> 13374.982 | G19: =BalSheet!G18 -> 17159.614 | H19: =BalSheet!H18 -> 21890.212 | I19: =BalSheet!I18 -> 27757.018 | J19: =BalSheet!J18 -> 34973.675 | K19: =BalSheet!K18 -> 43775.696 | L19: =BalSheet!L18 -> 54417.355
B20: =BalSheet!B19 -> Inventories | E20: =BalSheet!E19 -> 36488 | F20: =BalSheet!F19 -> 46071.892 | G20: =BalSheet!G19 -> 59108.556 | H20: =BalSheet!H19 -> 74377.701 | I20: =BalSheet!I19 -> 93010.691 | J20: =BalSheet!J19 -> 115553.64 | K20: =BalSheet!K19 -> 142583.85 | L20: =BalSheet!L19 -> 174694.67
B21: Other current assets | E21: =BalSheet!E20 -> 17501 | F21: =BalSheet!F20 -> 22086.767 | G21: =BalSheet!G20 -> 28336.516 | H21: =BalSheet!H20 -> 36148.387 | I21: =BalSheet!I20 -> 45836.532 | J21: =BalSheet!J20 -> 57753.754 | K21: =BalSheet!K20 -> 72288.966 | L21: =BalSheet!L20 -> 89862.062
B22: Accounts payables | E22: =BalSheet!E31 -> 115586 | F22: =BalSheet!F31 -> 145945.67 | G22: =BalSheet!G31 -> 187242.97 | H22: =BalSheet!H31 -> 235612.28 | I22: =BalSheet!I31 -> 294637.52 | J22: =BalSheet!J31 -> 366048.66 | K22: =BalSheet!K31 -> 451674.43 | L22: =BalSheet!L31 -> 553394.49
B23: Other current liabilities | E23: =BalSheet!E32 -> 70174 | F23: =BalSheet!F32 -> 88561.613 | G23: =BalSheet!G32 -> 113621.32 | H23: =BalSheet!H32 -> 144944.68 | I23: =BalSheet!I32 -> 183791.37 | J23: =BalSheet!J32 -> 231576.02 | K23: =BalSheet!K32 -> 289858.06 | L23: =BalSheet!L32 -> 360321.14
A24: * | B24: OWC | E24: =SUM(E18:E21)-SUM(E22:E23) -> -95552.7 | F24: =SUM(F18:F21)-SUM(F22:F23) -> -120640.09 | G24: =SUM(G18:G21)-SUM(G22:G23) -> -154776.83 | H24: =SUM(H18:H21)-SUM(H22:H23) -> -195221.83 | I24: =SUM(I18:I21)-SUM(I22:I23) -> -244723.01 | J24: =SUM(J18:J21)-SUM(J22:J23) -> -304795.95 | K24: =SUM(K18:K21)-SUM(K22:K23) -> -377057.74 | L24: =SUM(L18:L21)-SUM(L22:L23) -> -463189.46
B25: Change in OWC | F25: =E24-F24 -> 25087.386 | G25: =F24-G24 -> 34136.742 | H25: =G24-H24 -> 40445.004 | I25: =H24-I24 -> 49501.183 | J25: =I24-J24 -> 60072.937 | K25: =J24-K24 -> 72261.793 | L25: =K24-L24 -> 86131.718

Sheet Debt
A1: =CoName -> CoName | C1: Hist. | D1: Hist. | E1: Hist. | F1: Proj. | G1: Proj. | H1: Proj. | I1: Proj. | J1: Proj. | K1: Proj. | L1: Proj.
A2: Assumptions | C2: 2022 | D2: =C2+1 -> 2023 | E2: =D2+1 -> 2024 | F2: =E2+1 -> 2025 | G2: =F2+1 -> 2026 | H2: =G2+1 -> 2027 | I2: =H2+1 -> 2028 | J2: =I2+1 -> 2029 | K2: =J2+1 -> 2030 | L2: =K2+1 -> 2031
B4: Interest rate on revolver | F4: =Assumptions!F22 -> 0.0536 | G4: =Assumptions!G22 -> 0.0536 | H4: =Assumptions!H22 -> 0.0536 | I4: =Assumptions!I22 -> 0.0536 | J4: =Assumptions!J22 -> 0.0536 | K4: =Assumptions!K22 -> 0.0536 | L4: =Assumptions!L22 -> 0.0536
B5: Interest rate on long-term debt | F5: =Assumptions!F23 -> 0.0696 | G5: =Assumptions!G23 -> 0.0696 | H5: =Assumptions!H23 -> 0.0696 | I5: =Assumptions!I23 -> 0.0696 | J5: =Assumptions!J23 -> 0.0696 | K5: =Assumptions!K23 -> 0.0696 | L5: =Assumptions!L23 -> 0.0696
B6: Interest rate on cash | F6: =Assumptions!F24 -> 0.04 | G6: =Assumptions!G24 -> 0.04 | H6: =Assumptions!H24 -> 0.04 | I6: =Assumptions!I24 -> 0.04 | J6: =Assumptions!J24 -> 0.04 | K6: =Assumptions!K24 -> 0.04 | L6: =Assumptions!L24 -> 0.04
B8: Issuance of long-term debt | F8: =Assumptions!F26 -> 0 | G8: =Assumptions!G26 -> 0 | H8: =Assumptions!H26 -> 0 | I8: =Assumptions!I26 -> 0 | J8: =Assumptions!J26 -> 0 | K8: =Assumptions!K26 -> 0 | L8: =Assumptions!L26 -> 0
B9: Repayment of long-term debt | F9: -17311 | G9: =Assumptions!G27 -> 0 | H9: =Assumptions!H27 -> 0 | I9: =Assumptions!I27 -> 0 | J9: =Assumptions!J27 -> 0 | K9: =Assumptions!K27 -> 0 | L9: =Assumptions!L27 -> 0
A11: Revolver | C11: =C2 -> 2022 | D11: =D2 -> 2023 | E11: =E2 -> 2024 | F11: =F2 -> 2025 | G11: =G2 -> 2026 | H11: =H2 -> 2027 | I11: =I2 -> 2028 | J11: =J2 -> 2029 | ... L11: =L2 -> 2031
B12: Balance | F12: 0 | G12: 0 | H12: 0 | I12: 0 | J12: 0 | K12: 0 | L12: 0
B13: Interest rate
B14: Interest expense
A16: Long term debt | C16: =C11 -> 2022 | D16: =D11 -> 2023 | E16: =E11 -> 2024 | F16: =F11 -> 2025 | G16: =G11 -> 2026 | H16: =H11 -> 2027 | I16: =I11 -> 2028 | J16: =J11 -> 2029 | ... L16: =L11 -> 2031
B17: Beginning balance | F17: =E20 -> 237066 | G17: =F20 -> 219755 | H17: =G20 -> 219755 | I17: =H20 -> 219755 | J17: =I20 -> 219755 | K17: =J20 -> 219755 | L17: =K20 -> 219755
B18: Issuance | F18: =F8 -> 0 | G18: =G8 -> 0 | H18: =H8 -> 0 | I18: =I8 -> 0 | J18: =J8 -> 0 | K18: =K8 -> 0 | L18: =L8 -> 0
B19: Repayment | F19: =F9 -> -17311 | G19: =G9 -> 0 | H19: =H9 -> 0 | I19: =I9 -> 0 | J19: =J9 -> 0 | K19: =K9 -> 0 | L19: =L9 -> 0
B20: Ending balance | E20: =BalSheet!E35 -> 237066 | F20: =SUM(F17:F19) -> 219755 | G20: =SUM(G17:G19) -> 219755 | H20: =SUM(H17:H19) -> 219755 | I20: =SUM(I17:I19) -> 219755 | J20: =SUM(J17:J19) -> 219755 | K20: =SUM(K17:K19) -> 219755 | L20: =SUM(L17:L19) -> 219755
B21: Interest rate | F21: =F5 -> 0.0696 | G21: =G5 -> 0.0696 | H21: =H5 -> 0.0696 | I21: =I5 -> 0.0696 | J21: =J5 -> 0.0696 | K21: =K5 -> 0.0696 | L21: =L5 -> 0.0696
B22: Interest expense | F22: =F20*F21 -> 15294.948 | G22: =G20*G21 -> 15294.948 | H22: =H20*H21 -> 15294.948 | I22: =I20*I21 -> 15294.948 | J22: =J20*J21 -> 15294.948 | K22: =K20*K21 -> 15294.948 | L22: =L20*L21 -> 15294.948
A24: Debt summary | C24: =C16 -> 2022 | D24: =D16 -> 2023 | E24: =E16 -> 2024 | F24: =F16 -> 2025 | G24: =G16 -> 2026 | H24: =H16 -> 2027 | I24: =I16 -> 2028 | J24: =J16 -> 2029 | ... L24: =L16 -> 2031
B25: Revolver | F25: =F12 -> 0 | G25: =G12 -> 0 | H25: =H12 -> 0 | I25: =I12 -> 0 | J25: =J12 -> 0 | K25: =K12 -> 0 | L25: =L12 -> 0
B26: Total long term debt | F26: =F20 -> 219755 | G26: =G20 -> 219755 | H26: =H20 -> 219755 | I26: =I20 -> 219755 | J26: =J20 -> 219755 | K26: =K20 -> 219755 | L26: =L20 -> 219755
B27: Total debt | F27: =SUM(F25:F26) -> 219755 | G27: =SUM(G25:G26) -> 219755 | H27: =SUM(H25:H26) -> 219755 | I27: =SUM(I25:I26) -> 219755 | J27: =SUM(J25:J26) -> 219755 | K27: =SUM(K25:K26) -> 219755 | L27: =SUM(L25:L26) -> 219755
B28: Total interest expense | F28: =F22 -> 15294.948 | G28: =G22 -> 15294.948 | H28: =H22 -> 15294.948 | I28: =I22 -> 15294.948 | J28: =J22 -> 15294.948 | K28: =K22 -> 15294.948 | L28: =L22 -> 15294.948
A30: Interest income | C30: =C11 -> 2022 | D30: =D11 -> 2023 | E30: =E11 -> 2024 | F30: =F11 -> 2025 | G30: =G11 -> 2026 | H30: =H11 -> 2027 | I30: =I11 -> 2028 | J30: =J11 -> 2029 | ... L30: =L11 -> 2031
B31: Excess Cash | F31: =BalSheet!F17 -> 391272.7 | G31: =BalSheet!G17 -> 568439.54 | H31: =BalSheet!H17 -> 811958.15 | I31: =BalSheet!I17 -> 1150714.6 | J31: =BalSheet!J17 -> 1620290.6 | K31: =BalSheet!K17 -> 2266005.8 | L31: =BalSheet!L17 -> 3144734.3
B32: Interest rate | F32: =F6 -> 0.04 | G32: =G6 -> 0.04 | H32: =H6 -> 0.04 | I32: =I6 -> 0.04 | J32: =J6 -> 0.04 | K32: =K6 -> 0.04 | L32: =L6 -> 0.04
B33: Interest income | F33: =F31*F32 -> 15650.908 | G33: =G31*G32 -> 22737.581 | H33: =H31*H32 -> 32478.326 | I33: =I31*I32 -> 46028.584 | J33: =J31*J32 -> 64811.626 | K33: =K31*K32 -> 90640.233 | L33: =L31*L32 -> 125789.37

Sheet IncState
A1: =CoName -> CoName | C1: Hist. | D1: Hist. | E1: Hist. | F1: Proj. | G1: Proj. | H1: Proj. | I1: Proj. | J1: Proj. | K1: Proj. | L1: Proj.
A2: Assumptions | C2: 2022 | D2: =C2+1 -> 2023 | E2: =D2+1 -> 2024 | F2: =E2+1 -> 2025 | G2: =F2+1 -> 2026 | H2: =G2+1 -> 2027 | I2: =H2+1 -> 2028 | J2: =I2+1 -> 2029 | K2: =J2+1 -> 2030 | L2: =K2+1 -> 2031
B4: Revenue growth | F4: =Assumptions!F10 -> 0.26202886 | G4: =Assumptions!G10 -> 0.28296351 | H4: =Assumptions!H10 -> 0.27568211 | I4: =Assumptions!I10 -> 0.26801045 | J4: =Assumptions!J10 -> 0.25999397 | K4: =Assumptions!K10 -> 0.25167562 | L4: =Assumptions!L10 -> 0.24309513
B5: Cost of goods sold as % of sales | F5: =Assumptions!F11 -> 0.7349107 | G5: =Assumptions!G11 -> 0.7349107 | H5: =Assumptions!H11 -> 0.7249107 | I5: =Assumptions!I11 -> 0.7149107 | J5: =Assumptions!J11 -> 0.7049107 | K5: =Assumptions!K11 -> 0.6949107 | L5: =Assumptions!L11 -> 0.6849107
B6: SG&A % of sales | F6: =Assumptions!F12 -> 0.15881551 | G6: =Assumptions!G12 -> 0.15881551 | H6: =Assumptions!H12 -> 0.14881551 | I6: =Assumptions!I12 -> 0.13881551 | J6: =Assumptions!J12 -> 0.12881551 | K6: =Assumptions!K12 -> 0.11881551 | L6: =Assumptions!L12 -> 0.10881551
B7: Amortization amount | F7: =Assumptions!F13 -> 0 | G7: =Assumptions!G13 -> 0 | H7: =Assumptions!H13 -> 0 | I7: =Assumptions!I13 -> 0 | J7: =Assumptions!J13 -> 0 | K7: =Assumptions!K13 -> 0 | L7: =Assumptions!L13 -> 0
B8: Non recurring items, amount | F8: =Assumptions!F14 -> 0 | G8: =Assumptions!G14 -> 0 | H8: =Assumptions!H14 -> 0 | I8: =Assumptions!I14 -> 0 | J8: =Assumptions!J14 -> 0 | K8: =Assumptions!K14 -> 0 | L8: =Assumptions!L14 -> 0
B9: Other income (expense), amt | F9: =Assumptions!F15 -> 8606 | G9: =Assumptions!G15 -> 11400 | H9: =Assumptions!H15 -> 14194 | I9: =Assumptions!I15 -> 16988 | J9: =Assumptions!J15 -> 19782 | K9: =Assumptions!K15 -> 22576 | L9: =Assumptions!L15 -> 25370
B10: Effective tax rate | F10: =Assumptions!F16 -> 0.21727088 | G10: =Assumptions!G16 -> 0.21727088 | H10: =Assumptions!H16 -> 0.21727088 | I10: =Assumptions!I16 -> 0.21727088 | J10: =Assumptions!J16 -> 0.21727088 | K10: =Assumptions!K16 -> 0.21727088 | L10: =Assumptions!L16 -> 0.21727088
B11: Basic WASO | F11: =Assumptions!F17 -> 103504 | G11: =Assumptions!G17 -> 103504 | H11: =Assumptions!H17 -> 103504 | I11: =Assumptions!I17 -> 103504 | J11: =Assumptions!J17 -> 103504 | K11: =Assumptions!K17 -> 103504 | L11: =Assumptions!L17 -> 103504
B12: Diluted WASO | F12: =Assumptions!F18 -> 104129 | G12: =Assumptions!G18 -> 104129 | H12: =Assumptions!H18 -> 104129 | I12: =Assumptions!I18 -> 104129 | J12: =Assumptions!J18 -> 104129 | K12: =Assumptions!K18 -> 104129 | L12: =Assumptions!L18 -> 104129
A14: Income statement | C14: =C34 -> 44926 | D14: =D34 -> 45291 | E14: =E34 -> 45657 | F14: =F34 -> 46022 | G14: =G34 -> 46022 | H14: =H34 -> 46022 | I14: =I34 -> 46022 | J14: =J34 -> 46022 | K14: 2030 | L14: 2031
B15: Revenue | C15: ='Quarterly Projections'!G7 -> 739012 | D15: ='Quarterly Projections'!L7 -> 965776 | E15: ='Quarterly Projections'!Q7 -> 1281015 | F15: =E15*(1+F4) -> 1616677.9 | G15: =F15*(1+G4) -> 2074138.7 | H15: =G15*(1+H4) -> 2645941.7 | I15: =H15*(1+I4) -> 3355081.7 | J15: =I15*(1+J4) -> 4227382.7 | K15: =J15*(1+K4) -> 5291311.9 | L15: =K15*(1+L4) -> 6577604.1
B16: COGS | C16: ='Quarterly Projections'!G10 -> 558096 | D16: ='Quarterly Projections'!L10 -> 714480 | E16: ='Quarterly Projections'!Q10 -> 940962 | F16: =F15*F5 -> 1188113.9 | G16: =G15*G5 -> 1524306.8 | H16: =H15*H5 -> 1918071.4 | I16: =I15*I5 -> 2398583.8 | J16: =J15*J5 -> 2979927.3 | K16: =K15*K5 -> 3676989.2 | L16: =L15*L5 -> 4505071.4
B17: SG&A | C17: ='Quarterly Projections'!G12 -> 183528 | D17: ='Quarterly Projections'!L12 -> 205074 | E17: ='Quarterly Projections'!Q12 -> 233997 | F17: =F15*F6 -> 256753.53 | G17: =G15*G6 -> 329405.4 | H17: =H15*H6 -> 393757.16 | I17: =I15*I6 -> 465737.38 | J17: =J15*J6 -> 544552.46 | K17: =K15*K6 -> 628689.93 | L17: =L15*L6 -> 715745.35
A18: * | B18: EBIT | C18: =C15-SUM(C16:C17) -> -2612 | D18: =D15-SUM(D16:D17) -> 46222 | E18: =E15-SUM(E16:E17) -> 106056 | F18: =F15-SUM(F16:F17) -> 171810.49 | G18: =G15-SUM(G16:G17) -> 220426.59 | H18: =H15-SUM(H16:H17) -> 334113.09 | I18: =I15-SUM(I16:I17) -> 490760.52 | J18: =J15-SUM(J16:J17) -> 702902.95 | ... L18: =L15-SUM(L16:L17) -> 1356787.3
B20: Depreciation | C20: 44728 | D20: 69135 | E20: 93005 | F20: =Calcs!F8 -> 113593.15 | G20: =Calcs!G8 -> 128039.93 | H20: =Calcs!H8 -> 148037.75 | I20: =Calcs!I8 -> 174813.7 | J20: =Calcs!J8 -> 209832.45 | K20: =Calcs!K8 -> 254818.4 | L20: =Calcs!L8 -> 311773.1
B21: Amortization | C21: 0 | D21: 0 | E21: 0 | F21: =F7 -> 0 | G21: =G7 -> 0 | H21: =H7 -> 0 | I21: =I7 -> 0 | J21: =J7 -> 0 | K21: =K7 -> 0 | L21: =L7 -> 0
A22: * | B22: EBITDA | C22: =SUM(C18,C20:C21) -> 42116 | D22: =SUM(D18,D20:D21) -> 115357 | E22: =SUM(E18,E20:E21) -> 199061 | F22: =SUM(F18,F20:F21) -> 285403.64 | G22: =SUM(G18,G20:G21) -> 348466.51 | H22: =SUM(H18,H20:H21) -> 482150.84 | I22: =SUM(I18,I20:I21) -> 665574.21 | J22: =SUM(J18,J20:J21) -> 912735.4 | ... L22: =SUM(L18,L20:L21) -> 1668560.4
B24: Non-recurring items | C24: 0 | D24: 0 | E24: 0 | F24: =F8 -> 0 | G24: =G8 -> 0 | H24: =H8 -> 0 | I24: =I8 -> 0 | J24: =J8 -> 0 | K24: =K8 -> 0 | L24: =L8 -> 0
B25: Other income (expense) | C25: 3976 | D25: 3018 | E25: 5812 | F25: =F9 -> 8606 | G25: =G9 -> 11400 | H25: =H9 -> 14194 | I25: =I9 -> 16988 | J25: =J9 -> 19782 | K25: =K9 -> 22576 | L25: =L9 -> 25370
B27: Interest income | F27: =IF(circ=1,Debt!F33,0) -> 0 | G27: =IF(circ=1,Debt!G33,0) -> 0 | H27: =IF(circ=1,Debt!H33,0) -> 0 | I27: =IF(circ=1,Debt!I33,0) -> 0 | J27: =IF(circ=1,Debt!J33,0) -> 0 | K27: =IF(circ=1,Debt!K33,0) -> 0 | L27: =IF(circ=1,Debt!L33,0) -> 0
B28: Interest expense | C28: -18018 | D28: -32321 | E28: -27020 | F28: =IF(circ=1,-Debt!F22,0) -> 0 | G28: =IF(circ=1,-Debt!G22,0) -> 0 | H28: =IF(circ=1,-Debt!H22,0) -> 0 | I28: =IF(circ=1,-Debt!I22,0) -> 0 | J28: =IF(circ=1,-Debt!J22,0) -> 0 | K28: =IF(circ=1,-Debt!K22,0) -> 0 | L28: =IF(circ=1,-Debt!L22,0) -> 0
A30: * | B30: Pretax Income | C30: =C18+SUM(C25:C28) -> -16654 | D30: =D18+SUM(D25:D28) -> 16919 | E30: =E18+SUM(E24:E28) -> 84848 | F30: =F18+SUM(F24:F28) -> 180416.49 | G30: =G18+SUM(G24:G28) -> 231826.59 | H30: =H18+SUM(H24:H28) -> 348307.09 | I30: =I18+SUM(I24:I28) -> 507748.52 | J30: =J18+SUM(J24:J28) -> 722684.95 | K30: =K18+SUM(K24:K28) -> 1008208.7 | L30: =L18+SUM(L24:L28) -> 1382157.3
B32: Tax expense | C32: 2599 | D32: 6967 | E32: 18435 | F32: =F30*F10 -> 39199.25 | G32: =G30*G10 -> 50369.168 | H32: =H30*H10 -> 75676.989 | I32: =I30*I10 -> 110318.97 | J32: =J30*J10 -> 157018.4 | K32: =K30*K10 -> 219054.4 | L32: =L30*L10 -> 300302.54
A33: * | B33: Net income | C33: =C30-C32 -> -19253 | D33: =D30-D32 -> 9952 | E33: =E30-E32 -> 66413 | F33: =F30-F32 -> 141217.24 | G33: =G30-G32 -> 181457.42 | H33: =H30-H32 -> 272630.1 | I33: =I30-I32 -> 397429.55 | J33: =J30-J32 -> 565666.55 | ... L33: =L30-L32 -> 1081854.8
A34: Shareholder information | C34: 44926 | D34: 45291 | E34: 45657 | F34: 46022 | G34: 46022 | H34: 46022 | I34: 46022 | J34: 46022 | K34: 46022 | L34: 46022
B35: Basic WASO | C35: 51871 | D35: 62074 | E35: 103504 | F35: =F11 -> 103504 | G35: =G11 -> 103504 | H35: =H11 -> 103504 | I35: =I11 -> 103504 | J35: =J11 -> 103504 | K35: =K11 -> 103504 | L35: =L11 -> 103504
B36: Diluted WASO | C36: 51871 | D36: 62074 | E36: 104129 | F36: =F12 -> 104129 | G36: =G12 -> 104129 | H36: =H12 -> 104129 | I36: =I12 -> 104129 | J36: =J12 -> 104129 | K36: =K12 -> 104129 | L36: =L12 -> 104129
B37: Basic earnings per share | C37: =C33/C35 -> -0.37117079 | D37: =D33/D35 -> 0.16032477 | E37: =E33/E35 -> 0.6416467 | F37: =F33/F35 -> 1.364365 | G37: =G33/G35 -> 1.753144 | H37: =H33/H35 -> 2.6340054 | I37: =I33/I35 -> 3.8397506 | J37: =J33/J35 -> 5.4651661 | ... L37: =L33/L35 -> 10.452299
A38: * | B38: Diluted earnings per share | C38: =C33/C36 -> -0.37117079 | D38: =D33/D36 -> 0.16032477 | E38: =E33/E36 -> 0.63779543 | F38: =F33/F36 -> 1.3561759 | G38: =G33/G36 -> 1.7426214 | H38: =H33/H36 -> 2.6181957 | I38: =I33/I36 -> 3.8167038 | J38: =J33/J36 -> 5.4323632 | ... L38: =L33/L36 -> 10.389563

Sheet BalSheet
A1: =CoName -> CoName | C1: Hist. | D1: Hist. | E1: Hist. | F1: Proj. | G1: Proj. | H1: Proj. | I1: Proj. | J1: Proj. | K1: Proj. | L1: Proj.
A2: Assumptions | C2: 2022 | D2: =C2+1 -> 2023 | E2: =D2+1 -> 2024 | F2: =E2+1 -> 2025 | G2: =F2+1 -> 2026 | H2: =G2+1 -> 2027 | I2: =H2+1 -> 2028 | J2: =I2+1 -> 2029 | K2: =J2+1 -> 2030 | L2: =K2+1 -> 2031
B4: Operating Cash % of sales | F4: =Assumptions!F37 -> 0.02 | G4: =F4 -> 0.02 | H4: =G4 -> 0.02 | I4: =H4 -> 0.02 | J4: =I4 -> 0.02 | K4: =J4 -> 0.02 | L4: =K4 -> 0.02
B5: Accounts receivable % of sales | F5: =Assumptions!F38 -> 0.0082731272 | G5: =Assumptions!G38 -> 0.0082731272 | H5: =Assumptions!H38 -> 0.0082731272 | I5: =Assumptions!I38 -> 0.0082731272 | J5: =Assumptions!J38 -> 0.0082731272 | K5: =Assumptions!K38 -> 0.0082731272 | L5: =Assumptions!L38 -> 0.0082731272
B6: Inventories % of COGS | F6: =Assumptions!F39 -> 0.038777336 | G6: =Assumptions!G39 -> 0.038777336 | H6: =Assumptions!H39 -> 0.038777336 | I6: =Assumptions!I39 -> 0.038777336 | J6: =Assumptions!J39 -> 0.038777336 | K6: =Assumptions!K39 -> 0.038777336 | L6: =Assumptions!L39 -> 0.038777336
B7: Other current assets % of sales | F7: =Assumptions!F40 -> 0.013661823 | G7: =Assumptions!G40 -> 0.013661823 | H7: =Assumptions!H40 -> 0.013661823 | I7: =Assumptions!I40 -> 0.013661823 | J7: =Assumptions!J40 -> 0.013661823 | K7: =Assumptions!K40 -> 0.013661823 | L7: =Assumptions!L40 -> 0.013661823
B9: Other long-term assets % of sales | F9: =Assumptions!F42 -> 0.58134995 | G9: =Assumptions!G42 -> 0.58134995 | H9: =Assumptions!H42 -> 0.58134995 | I9: =Assumptions!I42 -> 0.58134995 | J9: =Assumptions!J42 -> 0.58134995 | K9: =Assumptions!K42 -> 0.58134995 | L9: =Assumptions!L42 -> 0.58134995
B11: Accounts payable/Accural % of COGS | F11: =Assumptions!F46 -> 0.12283812 | G11: =Assumptions!G46 -> 0.12283812 | H11: =Assumptions!H46 -> 0.12283812 | I11: =Assumptions!I46 -> 0.12283812 | J11: =Assumptions!J46 -> 0.12283812 | K11: =Assumptions!K46 -> 0.12283812 | L11: =Assumptions!L46 -> 0.12283812
B12: Other current liabilities % of sales | F12: =Assumptions!F47 -> 0.054779999 | G12: =Assumptions!G47 -> 0.054779999 | H12: =Assumptions!H47 -> 0.054779999 | I12: =Assumptions!I47 -> 0.054779999 | J12: =Assumptions!J47 -> 0.054779999 | K12: =Assumptions!K47 -> 0.054779999 | L12: =Assumptions!L47 -> 0.054779999
B13: Other long-term liabilities % of sales | F13: =Assumptions!F48 -> 1.0260567 | G13: =Assumptions!G48 -> 1.0260567 | H13: =Assumptions!H48 -> 1.0260567 | I13: =Assumptions!I48 -> 1.0260567 | J13: =Assumptions!J48 -> 1.0260567 | K13: =Assumptions!K48 -> 1.0260567 | L13: =Assumptions!L48 -> 1.0260567
A15: Balance sheet | C15: =C2 -> 2022 | D15: =D2 -> 2023 | E15: =E2 -> 2024 | F15: =F2 -> 2025 | G15: =G2 -> 2026 | H15: =H2 -> 2027 | I15: =I2 -> 2028 | J15: =J2 -> 2029 | ... L15: =L2 -> 2031
B16: Operating Cash | C16: =2%*IncState!C15 -> 14780.24 | D16: =2%*IncState!D15 -> 19315.52 | E16: =2%*IncState!E15 -> 25620.3 | F16: =F4*IncState!F15 -> 32333.558 | G16: =G4*IncState!G15 -> 41482.775 | H16: =H4*IncState!H15 -> 52918.834 | I16: =I4*IncState!I15 -> 67101.634 | J16: =J4*IncState!J15 -> 84547.654 | K16: =K4*IncState!K15 -> 105826.24 | L16: =L4*IncState!L15 -> 131552.08
B17: Excess cash | C17: =20178-C16 -> 5397.76 | D17: =133545-D16 -> 114229.48 | E17: =293354-E16 -> 267733.7 | F17: =MAX(CashFlow!F22,0) -> 391272.7 | G17: =MAX(CashFlow!G22,0) -> 568439.54 | H17: =MAX(CashFlow!H22,0) -> 811958.15 | I17: =MAX(CashFlow!I22,0) -> 1150714.6 | J17: =MAX(CashFlow!J22,0) -> 1620290.6 | K17: =MAX(CashFlow!K22,0) -> 2266005.8 | L17: =MAX(CashFlow!L22,0) -> 3144734.3
B18: Accounts receivable | C18: 11966 | D18: 9124 | E18: 10598 | F18: =F5*IncState!F15 -> 13374.982 | G18: =G5*IncState!G15 -> 17159.614 | H18: =H5*IncState!H15 -> 21890.212 | I18: =I5*IncState!I15 -> 27757.018 | J18: =J5*IncState!J15 -> 34973.675 | K18: =K5*IncState!K15 -> 43775.696 | L18: =L5*IncState!L15 -> 54417.355
B19: Inventories | C19: 39229 | D19: 46953 | E19: 36488 | F19: =F6*IncState!F16 -> 46071.892 | G19: =G6*IncState!G16 -> 59108.556 | H19: =H6*IncState!H16 -> 74377.701 | I19: =I6*IncState!I16 -> 93010.691 | J19: =J6*IncState!J16 -> 115553.64 | K19: =K6*IncState!K16 -> 142583.85 | L19: =L6*IncState!L16 -> 174694.67
B20: Other current assets | C20: 10949 | D20: 15637 | E20: 17501 | F20: =F7*IncState!F15 -> 22086.767 | G20: =G7*IncState!G15 -> 28336.516 | H20: =H7*IncState!H15 -> 36148.387 | I20: =I7*IncState!I15 -> 45836.532 | J20: =J7*IncState!J15 -> 57753.754 | K20: =K7*IncState!K15 -> 72288.966 | L20: =L7*IncState!L15 -> 89862.062
B21: Total current assets | C21: =SUM(C16:C20) -> 82322 | D21: =SUM(D16:D20) -> 205259 | E21: =SUM(E16:E20) -> 357941 | F21: =SUM(F16:F20) -> 505139.9 | G21: =SUM(G16:G20) -> 714527 | H21: =SUM(H16:H20) -> 997293.28 | I21: =SUM(I16:I20) -> 1384420.5 | J21: =SUM(J16:J20) -> 1913119.4 | ... L21: =SUM(L16:L20) -> 3595260.4
B23: Property, plant & equipment, net | C23: =365468+247943+169302 -> 782713 | D23: =542440+382734+199673 -> 1124847 | E23: =683971+374623+315256 -> 1373850 | F23: =Calcs!F9 -> 1548576.2 | G23: =Calcs!G9 -> 1790439.4 | H23: =Calcs!H9 -> 2114280.5 | I23: =Calcs!I9 -> 2537814.2 | J23: =Calcs!J9 -> 3081895.7 | K23: =Calcs!K9 -> 3770733.1 | L23: =Calcs!L9 -> 4632014
B24: Intangible assets | C24: =8804+21629 -> 30433 | D24: =5415+21629 -> 27044 | E24: =2947+21629 -> 24576 | F24: =E24-IncState!F21 -> 24576 | G24: =F24-IncState!G21 -> 24576 | H24: =G24-IncState!H21 -> 24576 | I24: =H24-IncState!I21 -> 24576 | J24: =I24-IncState!J21 -> 24576 | K24: =J24-IncState!K21 -> 24576 | L24: =K24-IncState!L21 -> 24576
B25: Other assets | C25: =2127+288765 -> 290892 | D25: =402995+3865 -> 406860 | E25: =742126+2592 -> 744718 | F25: =F9*IncState!F15 -> 939855.61 | G25: =G9*IncState!G15 -> 1205800.4 | H25: =H9*IncState!H15 -> 1538218.1 | I25: =I9*IncState!I15 -> 1950476.6 | J25: =J9*IncState!J15 -> 2457588.7 | K25: =K9*IncState!K15 -> 3076103.9 | L25: =L9*IncState!L15 -> 3823889.8
B26: Total non-current assets | C26: =SUM(C23:C25) -> 1104038 | D26: =SUM(D23:D25) -> 1558751 | E26: =SUM(E23:E25) -> 2143144 | F26: =SUM(F23:F25) -> 2513007.8 | G26: =SUM(G23:G25) -> 3020815.9 | H26: =SUM(H23:H25) -> 3677074.6 | I26: =SUM(I23:I25) -> 4512866.7 | J26: =SUM(J23:J25) -> 5564060.4 | ... L26: =SUM(L23:L25) -> 8480479.7
A28: * | B28: TOTAL ASSETS | C28: =SUM(C26,C21) -> 1186360 | D28: =SUM(D26,D21) -> 1764010 | E28: =SUM(E26,E21) -> 2501085 | F28: =SUM(F26,F21) -> 3018147.7 | G28: =SUM(G26,G21) -> 3735342.9 | H28: =SUM(H26,H21) -> 4674367.9 | I28: =SUM(I26,I21) -> 5897287.2 | J28: =SUM(J26,J21) -> 7477179.8 | ... L28: =SUM(L26,L21) -> 12075740
B30: Revolver/Short term debt | C30: 110865 | D30: 0 | E30: 0 | F30: =MIN(CashFlow!F22,0) -> 0 | G30: =MIN(CashFlow!G22,0) -> 0 | H30: =MIN(CashFlow!H22,0) -> 0 | I30: =MIN(CashFlow!I22,0) -> 0 | J30: =MIN(CashFlow!J22,0) -> 0 | K30: =MIN(CashFlow!K22,0) -> 0 | L30: =MIN(CashFlow!L22,0) -> 0
B31: Accounts payable/Accurals | C31: =21270+19706+9667+5939 -> 56582 | D31: =29957+31405+15770+6423 -> 83555 | E31: =32225+49778+26516+7067 -> 115586 | F31: =F11*IncState!F16 -> 145945.67 | G31: =G11*IncState!G16 -> 187242.97 | H31: =H11*IncState!H16 -> 235612.28 | I31: =I11*IncState!I16 -> 294637.52 | J31: =J11*IncState!J16 -> 366048.66 | K31: =K11*IncState!K16 -> 451674.43 | L31: =L11*IncState!L16 -> 553394.49
B32: Other current liabilities | C32: =25335+7971+9317 -> 42623 | D32: =30349+9482+10239 -> 50070 | E32: =42868+71+13256+13979 -> 70174 | F32: =F12*IncState!F15 -> 88561.613 | G32: =G12*IncState!G15 -> 113621.32 | H32: =H12*IncState!H15 -> 144944.68 | I32: =I12*IncState!I15 -> 183791.37 | J32: =J12*IncState!J15 -> 231576.02 | K32: =K12*IncState!K15 -> 289858.06 | L32: =L12*IncState!L15 -> 360321.14
B33: Total current liabilities | C33: =SUM(C30:C32) -> 210070 | D33: =SUM(D30:D32) -> 133625 | E33: =SUM(E30:E32) -> 185760 | F33: =SUM(F30:F32) -> 234507.28 | G33: =SUM(G30:G32) -> 300864.29 | H33: =SUM(H30:H32) -> 380556.97 | I33: =SUM(I30:I32) -> 478428.89 | J33: =SUM(J30:J32) -> 597624.68 | ... L33: =SUM(L30:L32) -> 913715.63
B35: Long-term debt, including current maturities | C35: =2609+96297 -> 98906 | D35: =4491+93175 -> 97666 | E35: =17311+219755 -> 237066 | F35: =Debt!F20 -> 219755 | G35: =Debt!G20 -> 219755 | H35: =Debt!H20 -> 219755 | I35: =Debt!I20 -> 219755 | J35: =Debt!J20 -> 219755 | K35: =Debt!K20 -> 219755 | L35: =Debt!L20 -> 219755
B36: Other long-term liabilities | C36: =6119+237130+161228+220923+8 -> 625408 | D36: =290920+191419+367775+6676 -> 856790 | E36: =8015+369297+309311+627763+8 -> 1314394 | F36: =F13*IncState!F15 -> 1658803.2 | G36: =G13*IncState!G15 -> 2128183.9 | H36: =H13*IncState!H15 -> 2714886.2 | I36: =I13*IncState!I15 -> 3442504 | J36: =J13*IncState!J15 -> 4337534.3 | K36: =K13*IncState!K15 -> 5429185.9 | L36: =L13*IncState!L15 -> 6748994.6
B37: Total non-current liabilities | C37: =SUM(C35:C36) -> 724314 | D37: =SUM(D35:D36) -> 954456 | E37: =SUM(E35:E36) -> 1551460 | F37: =SUM(F35:F36) -> 1878558.2 | G37: =SUM(G35:G36) -> 2347938.9 | H37: =SUM(H35:H36) -> 2934641.2 | I37: =SUM(I35:I36) -> 3662259 | J37: =SUM(J35:J36) -> 4557289.3 | ... L37: =SUM(L35:L36) -> 6968749.6
B39: Equity | C39: 251976 | D39: 675929 | E39: 763865 | F39: =Calcs!F16 -> 905082.24 | G39: =Calcs!G16 -> 1086539.7 | H39: =Calcs!H16 -> 1359169.8 | I39: =Calcs!I16 -> 1756599.3 | J39: =Calcs!J16 -> 2322265.9 | K39: =Calcs!K16 -> 3111420.2 | L39: =Calcs!L16 -> 4193275
A40: * | B40: TOTAL LIABILITIES & EQUITY | C40: =SUM(C39,C37,C33) -> 1186360 | D40: =SUM(D39,D37,D33) -> 1764010 | E40: =SUM(E39,E37,E33) -> 2501085 | F40: =SUM(F39,F37,F33) -> 3018147.7 | G40: =SUM(G39,G37,G33) -> 3735342.9 | H40: =SUM(H39,H37,H33) -> 4674367.9 | I40: =SUM(I39,I37,I33) -> 5897287.2 | J40: =SUM(J39,J37,J33) -> 7477179.8 | ... L40: =SUM(L39,L37,L33) -> 12075740
A42: * | B42: Balance check | C42: =C40-C28 -> 0 | D42: =D40-D28 -> 0 | E42: =E40-E28 -> 0 | F42: =F40-F28 -> 0 | G42: =G40-G28 -> 0 | H42: =H40-H28 -> 0 | I42: =I40-I28 -> 0 | J42: =J40-J28 -> 0 | ... L42: =L40-L28 -> 0

Sheet CashFlow
A1: =CoName -> CoName | C1: Hist. | D1: Hist. | E1: Hist. | F1: Proj. | G1: Proj. | H1: Proj. | I1: Proj. | J1: Proj. | K1: Proj. | L1: Proj.
A2: Cash flow statement | C2: 2022 | D2: =C2+1 -> 2023 | E2: =D2+1 -> 2024 | F2: =E2+1 -> 2025 | G2: =F2+1 -> 2026 | H2: =G2+1 -> 2027 | I2: =H2+1 -> 2028 | J2: =I2+1 -> 2029 | K2: =J2+1 -> 2030 | L2: =K2+1 -> 2031
B3: Net Income | F3: =IncState!F33 -> 141217.24 | G3: =IncState!G33 -> 181457.42 | H3: =IncState!H33 -> 272630.1 | I3: =IncState!I33 -> 397429.55 | J3: =IncState!J33 -> 565666.55 | K3: =IncState!K33 -> 789154.32 | L3: =IncState!L33 -> 1081854.8
B4: Depreciation | F4: =IncState!F20 -> 113593.15 | G4: =IncState!G20 -> 128039.93 | H4: =IncState!H20 -> 148037.75 | I4: =IncState!I20 -> 174813.7 | J4: =IncState!J20 -> 209832.45 | K4: =IncState!K20 -> 254818.4 | L4: =IncState!L20 -> 311773.1
B5: Amortization | F5: =IncState!F21 -> 0 | G5: =IncState!G21 -> 0 | H5: =IncState!H21 -> 0 | I5: =IncState!I21 -> 0 | J5: =IncState!J21 -> 0 | K5: =IncState!K21 -> 0 | L5: =IncState!L21 -> 0
B6: (inc) / dec in OWC | F6: =Calcs!F25 -> 25087.386 | G6: =Calcs!G25 -> 34136.742 | H6: =Calcs!H25 -> 40445.004 | I6: =Calcs!I25 -> 49501.183 | J6: =Calcs!J25 -> 60072.937 | K6: =Calcs!K25 -> 72261.793 | L6: =Calcs!L25 -> 86131.718
B7: (inc) / dec in LT assets | F7: =BalSheet!E25-BalSheet!F25 -> -195137.61 | G7: =BalSheet!F25-BalSheet!G25 -> -265944.84 | H7: =BalSheet!G25-BalSheet!H25 -> -332417.61 | I7: =BalSheet!H25-BalSheet!I25 -> -412258.51 | J7: =BalSheet!I25-BalSheet!J25 -> -507112.14 | K7: =BalSheet!J25-BalSheet!K25 -> -618515.17 | L7: =BalSheet!K25-BalSheet!L25 -> -747785.89
B8: inc / (dec) in LT liabilities | F8: =BalSheet!F36-BalSheet!E36 -> 344409.16 | G8: =BalSheet!G36-BalSheet!F36 -> 469380.76 | H8: =BalSheet!H36-BalSheet!G36 -> 586702.23 | I8: =BalSheet!I36-BalSheet!H36 -> 727617.85 | J8: =BalSheet!J36-BalSheet!I36 -> 895030.27 | K8: =BalSheet!K36-BalSheet!J36 -> 1091651.6 | L8: =BalSheet!L36-BalSheet!K36 -> 1319808.7
B9: CFFO | F9: =SUM(F3:F8) -> 429169.33 | G9: =SUM(G3:G8) -> 547070.01 | H9: =SUM(H3:H8) -> 715397.47 | I9: =SUM(I3:I8) -> 937103.77 | J9: =SUM(J3:J8) -> 1223490.1 | K9: =SUM(K3:K8) -> 1589371 | L9: =SUM(L3:L8) -> 2051782.4
B11: Capex | F11: =-Calcs!F7 -> -288319.33 | G11: =-Calcs!G7 -> -369903.17 | H11: =-Calcs!H7 -> -471878.86 | I11: =-Calcs!I7 -> -598347.33 | J11: =-Calcs!J7 -> -753914.02 | K11: =-Calcs!K7 -> -943655.8 | L11: =-Calcs!L7 -> -1173053.9
B12: CFFI | F12: =SUM(F11) -> -288319.33 | G12: =SUM(G11) -> -369903.17 | H12: =SUM(H11) -> -471878.86 | I12: =SUM(I11) -> -598347.33 | J12: =SUM(J11) -> -753914.02 | K12: =SUM(K11) -> -943655.8 | L12: =SUM(L11) -> -1173053.9
B14: Debt repayment | F14: =SUM(Debt!F8:F9) -> -17311 | G14: =SUM(Debt!G8:G9) -> 0 | H14: =SUM(Debt!H8:H9) -> 0 | I14: =SUM(Debt!I8:I9) -> 0 | J14: =SUM(Debt!J8:J9) -> 0 | K14: =SUM(Debt!K8:K9) -> 0 | L14: =SUM(Debt!L8:L9) -> 0
B15: Share issuance | F15: =Calcs!F11 -> 0 | G15: =Calcs!G11 -> 0 | H15: =Calcs!H11 -> 0 | I15: =Calcs!I11 -> 0 | J15: =Calcs!J11 -> 0 | K15: =Calcs!K11 -> 0 | L15: =Calcs!L11 -> 0
B16: CFFI | F16: =SUM(F14:F15) -> -17311 | G16: =SUM(G14:G15) -> 0 | H16: =SUM(H14:H15) -> 0 | I16: =SUM(I14:I15) -> 0 | J16: =SUM(J14:J15) -> 0 | K16: =SUM(K14:K15) -> 0 | L16: =SUM(L14:L15) -> 0
B18: Net changes in cash | F18: =SUM(F16,F12,F9) -> 123539 | G18: =SUM(G16,G12,G9) -> 177166.83 | H18: =SUM(H16,H12,H9) -> 243518.61 | I18: =SUM(I16,I12,I9) -> 338756.44 | J18: =SUM(J16,J12,J9) -> 469576.05 | K18: =SUM(K16,K12,K9) -> 645715.18 | L18: =SUM(L16,L12,L9) -> 878728.45
B20: Beginning cash | F20: =BalSheet!E17 -> 267733.7 | G20: =BalSheet!F17 -> 391272.7 | H20: =BalSheet!G17 -> 568439.54 | I20: =BalSheet!H17 -> 811958.15 | J20: =BalSheet!I17 -> 1150714.6 | K20: =BalSheet!J17 -> 1620290.6 | L20: =BalSheet!K17 -> 2266005.8
B21: =B18 -> Net changes in cash | F21: =F18 -> 123539 | G21: =G18 -> 177166.83 | H21: =H18 -> 243518.61 | I21: =I18 -> 338756.44 | J21: =J18 -> 469576.05 | K21: =K18 -> 645715.18 | L21: =L18 -> 878728.45
B22: Ending cash | F22: =SUM(F20:F21) -> 391272.7 | G22: =SUM(G20:G21) -> 568439.54 | H22: =SUM(H20:H21) -> 811958.15 | I22: =SUM(I20:I21) -> 1150714.6 | J22: =SUM(J20:J21) -> 1620290.6 | K22: =SUM(K20:K21) -> 2266005.8 | L22: =SUM(L20:L21) -> 3144734.3

Sheet Free Cash Flow
A1: =CoName -> CoName | C1: Hist. | D1: Hist. | E1: Hist. | F1: Proj. | G1: Proj. | H1: Proj. | I1: Proj. | J1: Proj. | K1: Proj. | L1: Proj.
A2: Free Cash Flows | C2: 2022 | D2: =C2+1 -> 2023 | E2: =D2+1 -> 2024 | F2: =E2+1 -> 2025 | G2: =F2+1 -> 2026 | H2: =G2+1 -> 2027 | I2: =H2+1 -> 2028 | J2: =I2+1 -> 2029 | K2: =J2+1 -> 2030 | L2: =K2+1 -> 2031
A3: * | B3: Sales | F3: =IncState!F15 -> 1616677.9 | G3: =IncState!G15 -> 2074138.7 | H3: =IncState!H15 -> 2645941.7 | I3: =IncState!I15 -> 3355081.7 | J3: =IncState!J15 -> 4227382.7 | K3: =IncState!K15 -> 5291311.9 | L3: =IncState!L15 -> 6577604.1
B4: EBIT | F4: =IncState!F18 -> 171810.49 | G4: =IncState!G18 -> 220426.59 | H4: =IncState!H18 -> 334113.09 | I4: =IncState!I18 -> 490760.52 | J4: =IncState!J18 -> 702902.95 | K4: =IncState!K18 -> 985632.72 | L4: =IncState!L18 -> 1356787.3
B5: Effective Tax Rate | F5: =Assumptions!F16 -> 0.21727088 | G5: =Assumptions!G16 -> 0.21727088 | H5: =Assumptions!H16 -> 0.21727088 | I5: =Assumptions!I16 -> 0.21727088 | J5: =Assumptions!J16 -> 0.21727088 | K5: =Assumptions!K16 -> 0.21727088 | L5: =Assumptions!L16 -> 0.21727088
A7: * | B7: NOPAT | F7: =F4*(1-F5) -> 134481.07 | G7: =G4*(1-G5) -> 172534.31 | H7: =H4*(1-H5) -> 261520.04 | I7: =I4*(1-I5) -> 384132.55 | J7: =J4*(1-J5) -> 550182.6 | K7: =K4*(1-K5) -> 771483.43 | L7: =L4*(1-L5) -> 1061996.9
B8: Depreciation | F8: =CashFlow!F4 -> 113593.15 | G8: =CashFlow!G4 -> 128039.93 | H8: =CashFlow!H4 -> 148037.75 | I8: =CashFlow!I4 -> 174813.7 | J8: =CashFlow!J4 -> 209832.45 | K8: =CashFlow!K4 -> 254818.4 | L8: =CashFlow!L4 -> 311773.1
B9: Amortization | F9: =CashFlow!F5 -> 0 | G9: =CashFlow!G5 -> 0 | H9: =CashFlow!H5 -> 0 | I9: =CashFlow!I5 -> 0 | J9: =CashFlow!J5 -> 0 | K9: =CashFlow!K5 -> 0 | L9: =CashFlow!L5 -> 0
B10: (inc) / dec in OWC | F10: =CashFlow!F6 -> 25087.386 | G10: =CashFlow!G6 -> 34136.742 | H10: =CashFlow!H6 -> 40445.004 | I10: =CashFlow!I6 -> 49501.183 | J10: =CashFlow!J6 -> 60072.937 | K10: =CashFlow!K6 -> 72261.793 | L10: =CashFlow!L6 -> 86131.718
B11: (inc) / dec in other long-term assets | F11: =CashFlow!F7 -> -195137.61 | G11: =CashFlow!G7 -> -265944.84 | H11: =CashFlow!H7 -> -332417.61 | I11: =CashFlow!I7 -> -412258.51 | J11: =CashFlow!J7 -> -507112.14 | K11: =CashFlow!K7 -> -618515.17 | L11: =CashFlow!L7 -> -747785.89
B12: inc / (dec) other long-term liabilities | F12: =CashFlow!F8 -> 344409.16 | G12: =CashFlow!G8 -> 469380.76 | H12: =CashFlow!H8 -> 586702.23 | I12: =CashFlow!I8 -> 727617.85 | J12: =CashFlow!J8 -> 895030.27 | K12: =CashFlow!K8 -> 1091651.6 | L12: =CashFlow!L8 -> 1319808.7
B13: (Capex) | F13: =CashFlow!F11 -> -288319.33 | G13: =CashFlow!G11 -> -369903.17 | H13: =CashFlow!H11 -> -471878.86 | I13: =CashFlow!I11 -> -598347.33 | J13: =CashFlow!J11 -> -753914.02 | K13: =CashFlow!K11 -> -943655.8 | L13: =CashFlow!L11 -> -1173053.9
A15: * | B15: Free Cash Flow | F15: =SUM(F7:F13) -> 134113.84 | G15: =SUM(G7:G13) -> 168243.72 | H15: =SUM(H7:H13) -> 232408.55 | I15: =SUM(I7:I13) -> 325459.44 | J15: =SUM(J7:J13) -> 454092.1 | K15: =SUM(K7:K13) -> 628044.29 | L15: =SUM(L7:L13) -> 858870.62

Sheet WACC
A1: =CoName -> CoName
A3: * | B3: WACC | G3: Comp | H3: Levered beta | I3: Gross debt | J3: Market cap | K3: Debt/Mcap | L3: MTR | M3: Unlevered beta
B4: Tax Rate | E4: =Assumptions!F16 -> 0.21727088 | L4: =E4 -> 0.21727088 | M4: =H4/((1+K4*(1-L4))) -> 0
B5: Risk free rate | E5: 0.041 | L5: =L4 -> 0.21727088 | M5: =H5/((1+K5*(1-L5))) -> 0
B6: Market risk Premium | E6: 0.05 | L6: =L5 -> 0.21727088 | M6: =H6/((1+K6*(1-L6))) -> 0
B7: Beta | E7: 0.67 | L7: =L6 -> 0.21727088 | M7: =H7/((1+K7*(1-L7))) -> 0
B8: Cost of Equity | E8: =E5+E6*E7 -> 0.0745
B9: % Equity | E9: =1-E10 -> 0.87850798 | G9: Industry beta (average) | M9: =AVERAGE(M4:M7) -> 0
B10: % Debt | E10: =MAIN!F8/MAIN!F6 -> 0.12149202
B11: Cost of debt | E11: =Assumptions!F23 -> 0.0696 | G11: Re-levered beta | M11: =M9*(1+E10*(1-E4)) -> 0
B12: Post tax cost of debt | E12: =E11*(1-E4) -> 0.054477946
A13: * | B13: WACC | E13: =WACC!E8*WACC!E9+WACC!E12*WACC!E10 -> 0.07206748
B14: Long Term growth rate | E14: 0.025

Sheet DCF Model
A1: =CoName -> CoName | D1: Proj. | E1: Proj. | F1: Proj. | G1: Proj. | H1: Proj. | I1: Proj. | J1: Proj.
A2: Discount Model Year count | D2: 0.5 | E2: =D2+1 -> 1.5 | F2: =E2+1 -> 2.5 | G2: =F2+1 -> 3.5 | H2: =G2+1 -> 4.5 | I2: =H2+1 -> 5.5 | J2: =I2+1 -> 6.5
B3: Discount Factor | D3: =1/(1+$K$17)^D2 -> 0.96580386 | E3: =1/(1+$K$17)^E2 -> 0.90087973 | F3: =1/(1+$K$17)^F2 -> 0.84031999 | G3: =1/(1+$K$17)^G2 -> 0.78383125 | H3: =1/(1+$K$17)^H2 -> 0.73113984 | I3: =1/(1+$K$17)^I2 -> 0.6819905 | J3: =1/(1+$K$17)^J2 -> 0.63614513
B4: PV FCF | D4: =D3*'Free Cash Flow'!F15 -> 129527.66 | E4: =E3*'Free Cash Flow'!G15 -> 151567.36 | F4: =F3*'Free Cash Flow'!H15 -> 195297.55 | G4: =G3*'Free Cash Flow'!I15 -> 255105.28 | H4: =H3*'Free Cash Flow'!J15 -> 332004.83 | I4: =I3*'Free Cash Flow'!K15 -> 428320.24 | J4: =J3*'Free Cash Flow'!L15 -> 546366.36 | K4: =(J4*(1+K18))/(K17-K18) -> 11898353
A6: Value Calculation | E6: Multiples Calculation
B7: Total PV of FCFs | C7: =SUM(D4:J4) -> 2038189.3 | E7: Total PV of FCFs | G7: =C7 -> 2038189.3
B8: PV of TV | C8: =K4*J3 -> 7569079.5 | E8: Multiple TV | G8: =J3*G10*IncState!L22 -> 12737359
B9: EV | C9: =SUM(C7:C8) -> 9607268.8 | E9: EV | G9: =SUM(G7:G8) -> 14775548
E10: Implied EBITDA multiple | G10: 12
B12: Cash & Cash Equiv | C12: =MAIN!F7 -> 267195 | E12: Cash & Cash Equiv | G12: =C12 -> 267195
B13: Debt & Claims | C13: =MAIN!F8 -> 1259812 | E13: Debt & Claims | G13: =C13 -> 1259812
B14: NCI | C14: 0 | E14: NCI | G14: =C14 -> 0
B15: Equity Value | C15: =C9+C12-SUM(C13:C14) -> 8614651.8 | E15: Equity Value | G15: =G9+G12-SUM(G13:G14) -> 13782931
B17: Diluted S/O | C17: =MAIN!F5 -> 177560 | E17: Diluted S/O | G17: =C17 -> 177560 | I17: WACC | K17: =WACC!E13 -> 0.07206748
A18: * | B18: Implied Share Price | C18: =C15/C17 -> 48.51685 | E18: Implied Share Price | G18: =G15/G17 -> 77.624078 | I18: Long Term growth rate | K18: 0.025
A20: Sensitivity analysis
C22: Discount rate variance | E22: 0.005 | H22: Discount rate variance | J22: 0.005
C23: Implied growth rate variance | E23: 0.0025 | H23: TV multiple variance | J23: 2
E25: LTGR | J25: Exit Mult.
C26: =C18 -> 48.51685 | D26: =E26-E23 -> 0.0225 | E26: 0.025 | F26: =E26+E23 -> 0.0275 | H26: =G18 -> 77.624078 | I26: =J26-J23 -> 10 | J26: 12 | K26: =J26+J23 -> 14
C27: =C28+$E$22 -> 0.08206748 | D27: 35.205768 | E27: 36.586383 | F27: 38.093504 | H27: =C27 -> 0.08206748 | I27: 61.704026 | J27: 72.959753 | K27: 84.21548
C28: =C29+$E$22 -> 0.07706748 | D28: 40.180255 | E28: 41.926509 | F28: 43.848911 | H28: =C28 -> 0.07706748 | I28: 63.652276 | J28: 75.252005 | K28: 86.851735
C29: 0.07206748 | D29: 46.268109 | E29: 48.51685 | F29: 51.017875 | H29: =C29 -> 0.07206748 | I29: 65.668158 | J29: 77.624078 | K29: 89.579998
C30: =C29-$E$22 -> 0.06706748 | D30: 53.854032 | E30: 56.813784 | F30: 60.14755 | H30: =C30 -> 0.06706748 | I30: 67.754368 | J30: 80.079159 | K30: 92.40395
C31: =C30-$E$22 -> 0.06206748 | D31: 63.518116 | E31: 67.520934 | F31: 72.102738 | H31: =C31 -> 0.06206748 | I31: 69.913727 | J31: 82.620582 | K31: 95.327437
