Workbook
Name Ccy: MAIN!$C$6
Name circ: MAIN!$C$9
Name CoName: MAIN!$C$4
Name g: #REF!
Name IQ_CH: 110000
Name IQ_CQ: 5000
Name IQ_CY: 10000
Name IQ_DAILY: 500000
Name IQ_FH: 100000
Name IQ_FQ: 500
Name IQ_FY: 1000
Name IQ_LTM: 2000
Name IQ_MONTH: 15000
Name IQ_NTM: 6000
Name IQ_WEEK: 50000
Name IQ_YTD: 3000
Name OpCase: [1]DCF!$E$98
Name ScenarioREV: Assumptions!$D$4
Name TTS: #REF!
Name Units: MAIN!$C$7

Sheet MAIN
A1: =CoName -> Cheesecake Factory inc.
A2: Model Details
B4: Company name | C4: Cheesecake Factory inc. | E4: Current Stock Price | F4: 47 | H4: Operating Case One | I4: Terminal Mult | J4: Perpetuity | K4: DDM | L4: Average
B5: Latest BS date | C5: 247.43 | E5: Diluted s/o | F5: 49.8417 | H5: Implied Price | I5: ='DCF Model'!G18 -> 107.85873 | J5: ='DCF Model'!C18 -> 59.266136 | K5: ='DCF Model'!K11 -> 39.715901 | L5: =AVERAGE(I5:K5) -> 68.946922
B6: Currency | C6: USD | E6: Mkt Cap | F6: =F5*F4 -> 2342.5599 | H6: Difference | I6: =I5/$F$4-1 -> 1.2948666 | J6: =J5/$F$4-1 -> 0.26098161 | K6: =K5/$F$4-1 -> -0.15498082 | L6: =L5/$F$4-1 -> 0.46695578
B7: Units | C7: m | E7: Cash | F7: =189.978 -> 189.978
B8: Analyst name | C8: Alan Chen | E8: Debt | F8: =560.441+68.715 -> 629.156
B9: Circular switch | C9: 0 | E9: EV | F9: =F6-F7+F8 -> 2781.7379

Sheet Quarterly Projections

Sheet Assumptions
A1: =CoName -> Cheesecake Factory inc. | C1: Hist. | D1: Hist. | E1: Hist. | F1: Proj. | G1: Proj. | H1: Proj. | I1: Proj. | J1: Proj.
A2: * | B2: Income Statement | C2: 2022 | D2: =C2+1 -> 2023 | E2: =D2+1 -> 2024 | F2: =E2+1 -> 2025 | G2: =F2+1 -> 2026 | H2: =G2+1 -> 2027 | I2: =H2+1 -> 2028 | J2: =I2+1 -> 2029
B4: Operating Case | D4: 1
D5: Variance
B6: Street Case | D6: 0 | F6: 0.044 | G6: 0.046 | H6: 0.05 | I6: 0.04 | J6: 0.03
B7: Optimistic Case | D7: 0.025 | F7: =F6+$D$7 -> 0.069 | G7: =G6+$D$7 -> 0.071 | H7: =H6+$D$7 -> 0.075 | I7: =I6+$D$7 -> 0.065 | J7: =J6+$D$7 -> 0.055
B8: Pessimistic Case | D8: -0.025 | F8: =F6+$D$8 -> 0.019 | G8: =G6+$D$8 -> 0.021 | H8: =H6+$D$8 -> 0.025 | I8: =I6+$D$8 -> 0.015 | J8: =J6+$D$8 -> 0.005
B10: Revenue Growth | D10: =IncState!D16/IncState!C16-1 -> 0.041263018 | E10: =IncState!E16/IncState!D16-1 -> 0.041343218 | F10: =CHOOSE(ScenarioREV,F6,F7,F8) -> 0.044 | G10: =CHOOSE(ScenarioREV,G6,G7,G8) -> 0.046 | H10: =CHOOSE(ScenarioREV,H6,H7,H8) -> 0.05 | I10: =CHOOSE(ScenarioREV,I6,I7,I8) -> 0.04 | J10: =CHOOSE(ScenarioREV,J6,J7,J8) -> 0.03
B11: COGS % of sales | C11: =IncState!C17/IncState!C16 -> 0.87928403 | D11: =IncState!D17/IncState!D16 -> 0.85878761 | E11: =IncState!E17/IncState!E16 -> 0.8456878 | F11: =E11-0.005 -> 0.8406878 | G11: =F11-0.005 -> 0.8356878 | H11: =G11-0.005 -> 0.8306878 | I11: =H11-0.005 -> 0.8256878 | J11: =I11-0.005 -> 0.8206878
B12: SG&A % of sales | C12: =IncState!C18/IncState!C16 -> 0.095372063 | D12: =IncState!D18/IncState!D16 -> 0.098259922 | E12: =IncState!E18/IncState!E16 -> 0.099877712 | F12: =E12 -> 0.099877712 | G12: =F12 -> 0.099877712 | H12: =G12 -> 0.099877712 | I12: =H12 -> 0.099877712 | J12: =I12 -> 0.099877712
B13: Amortization $ Amt | C13: =IncState!C22 -> 0 | D13: =IncState!D22 -> 0 | E13: =IncState!E22 -> 0 | F13: =E13 -> 0 | G13: =F13 -> 0 | H13: =G13 -> 0 | I13: =H13 -> 0 | J13: =I13 -> 0
B14: Non recurring income / (expense) | C14: =IncState!C25 -> -44.74 | D14: =IncState!D25 -> -41.15 | E14: =IncState!E25 -> -16.076 | F14: 0 | G14: 0 | H14: 0 | I14: 0 | J14: 0
B15: Other Income / (expense) | C15: =IncState!C26 -> -6.088 | D15: =IncState!D26 -> -8.552 | E15: =IncState!E26 -> -7.27 | F15: 0 | G15: 0 | H15: 0 | I15: 0 | J15: 0
B16: Effective tax rate | C16: =IncState!C33/IncState!C31 -> -0.14586541 | D16: =IncState!D33/IncState!D31 -> -0.010363216 | E16: =IncState!E33/IncState!E31 -> 0.088313779 | F16: 0.22 | G16: =F16 -> 0.22 | H16: =G16 -> 0.22 | I16: =H16 -> 0.22 | J16: =I16 -> 0.22
B17: Dividend Payout Rate | C17: =IncState!C35 -> 0.84857975 | D17: =IncState!D35 -> 1.1010471 | E17: =IncState!E35 -> 1.1098998 | F17: =E17+0.2 -> 1.3098998 | G17: =F17+0.2 -> 1.5098998 | H17: =G17+0.2 -> 1.7098998 | I17: =H17+0.2 -> 1.9098998 | J17: =I17+0.2 -> 2.1098998
B18: Basic WASO | C18: =IncState!C38 -> 49.815 | D18: =IncState!D38 -> 48.324 | E18: =IncState!E38 -> 47.789 | F18: =E18 -> 47.789 | G18: =F18 -> 47.789 | H18: =G18 -> 47.789 | I18: =H18 -> 47.789 | J18: =I18 -> 47.789
B19: Diluted WASO | C19: =IncState!C39 -> 50.414 | D19: =IncState!D39 -> 49.05 | E19: =IncState!E39 -> 48.974 | F19: =E19 -> 48.974 | G19: =F19 -> 48.974 | H19: =G19 -> 48.974 | I19: =H19 -> 48.974 | J19: =I19 -> 48.974
A21: * | B21: Debt | C21: =C2 -> 2022 | D21: =D2 -> 2023 | E21: =E2 -> 2024 | F21: =F2 -> 2025 | G21: =G2 -> 2026 | H21: =H2 -> 2027 | I21: =I2 -> 2028 | J21: =J2 -> 2029
B23: Interest rate on Revolver | E23: 0.05 | F23: =E23 -> 0.05 | G23: =F23 -> 0.05 | H23: =G23 -> 0.05 | I23: =H23 -> 0.05 | J23: =I23 -> 0.05
B24: Interest rate on long-term debt | E24: 0.05 | F24: =E24 -> 0.05 | G24: =F24 -> 0.05 | H24: =G24 -> 0.05 | I24: =H24 -> 0.05 | J24: =I24 -> 0.05
B25: Interest rate on cash | E25: 0.04 | F25: =E25 -> 0.04 | G25: =F25 -> 0.04 | H25: =G25 -> 0.04 | I25: =H25 -> 0.04 | J25: =I25 -> 0.04
B27: Issuance of long-term debt | E27: 0 | F27: 0 | G27: 0 | H27: 0 | I27: 0 | J27: 0
B28: Repayment of long-term debt | E28: 0 | F28: 0 | G28: 0 | H28: 0 | I28: 0 | J28: 0
A30: * | B30: Calcs | C30: =C21 -> 2022 | D30: =D21 -> 2023 | E30: =E21 -> 2024 | F30: =F21 -> 2025 | G30: =G21 -> 2026 | H30: =H21 -> 2027 | I30: =I21 -> 2028 | J30: =J21 -> 2029
B32: CapEx % of Sales | C32: =112.646/IncState!C16 -> 0.034102083 | D32: =151.565/IncState!D16 -> 0.044065998 | E32: =160.4/IncState!E16 -> 0.044783204 | F32: =E32 -> 0.044783204 | G32: =F32 -> 0.044783204 | H32: =G32 -> 0.044783204 | I32: =H32 -> 0.044783204 | J32: =I32 -> 0.044783204
B33: Depreciation % of beginning PP&E | D33: =IncState!D21/BalSheet!C23 -> 0.046220491 | E33: =IncState!E21/BalSheet!D23 -> 0.048465467 | F33: =E33 -> 0.048465467 | G33: =F33 -> 0.048465467 | H33: =G33 -> 0.048465467 | I33: =H33 -> 0.048465467 | J33: =I33 -> 0.048465467
B34: Share issuance / (repurchases) | F34: 0 | G34: 0 | H34: 0 | I34: 0 | J34: 0
A36: * | B36: Balance Sheet - Assets | C36: =C30 -> 2022 | D36: =D30 -> 2023 | E36: =E30 -> 2024 | F36: =F30 -> 2025 | G36: =G30 -> 2026 | H36: =H30 -> 2027 | I36: =I30 -> 2028 | J36: =J30 -> 2029
B38: Operating Cash % of sales | C38: =BalSheet!C16/IncState!C16 -> 0.01 | D38: =BalSheet!D16/IncState!D16 -> 0.01 | E38: =BalSheet!E16/IncState!E16 -> 0.01 | F38: =E38 -> 0.01 | G38: =F38 -> 0.01 | H38: =G38 -> 0.01 | I38: =H38 -> 0.01 | J38: =I38 -> 0.01
B39: Accounts receivable % of sales | C39: =BalSheet!C18/IncState!C16 -> 0.031942056 | D39: =BalSheet!D18/IncState!D16 -> 0.029973543 | E39: =BalSheet!E18/IncState!E16 -> 0.031410503 | F39: =E39 -> 0.031410503 | G39: =F39 -> 0.031410503 | H39: =G39 -> 0.031410503 | I39: =H39 -> 0.031410503 | J39: =I39 -> 0.031410503
B40: Inventories % of COGS | C40: =BalSheet!C19/IncState!C17 -> 0.019128916 | D40: =BalSheet!D19/IncState!D17 -> 0.019518586 | E40: =BalSheet!E19/IncState!E17 -> 0.02130274 | F40: =E40 -> 0.02130274 | G40: =F40 -> 0.02130274 | H40: =G40 -> 0.02130274 | I40: =H40 -> 0.02130274 | J40: =I40 -> 0.02130274
B41: Other current assets % of sales | C41: =BalSheet!C20/IncState!C16 -> 0.021167656 | D41: =BalSheet!D20/IncState!D16 -> 0.024352377 | E41: =BalSheet!E20/IncState!E16 -> 0.020132339 | F41: =E41 -> 0.020132339 | G41: =F41 -> 0.020132339 | H41: =G41 -> 0.020132339 | I41: =H41 -> 0.020132339 | J41: =I41 -> 0.020132339
B43: Other long-term assets % of sales | C43: =BalSheet!C25/IncState!C16 -> 0.04931309 | D43: =BalSheet!D25/IncState!D16 -> 0.056582352 | E43: =BalSheet!E25/IncState!E16 -> 0.060176453 | F43: =E43 -> 0.060176453 | G43: =F43 -> 0.060176453 | H43: =G43 -> 0.060176453 | I43: =H43 -> 0.060176453 | J43: =I43 -> 0.060176453
A45: * | B45: Balance Sheet - Liabilities | C45: =C36 -> 2022 | D45: =D36 -> 2023 | E45: =E36 -> 2024 | F45: =F36 -> 2025 | G45: =G36 -> 2026 | H45: =H36 -> 2027 | I45: =I36 -> 2028 | J45: =J36 -> 2029
B47: Accounts payable % of COGS | C47: =BalSheet!C31/IncState!C17 -> 0.022943407 | D47: =BalSheet!D31/IncState!D17 -> 0.021379917 | E47: =BalSheet!E31/IncState!E17 -> 0.020499175 | F47: =E47 -> 0.020499175 | G47: =F47 -> 0.020499175 | H47: =G47 -> 0.020499175 | I47: =H47 -> 0.020499175 | J47: =I47 -> 0.020499175
B48: Other current liabilities % of sales | C48: =BalSheet!C32/IncState!C16 -> 0.17862679 | D48: =BalSheet!D32/IncState!D16 -> 0.17372263 | E48: =BalSheet!E32/IncState!E16 -> 0.18129045 | F48: =E48 -> 0.18129045 | G48: =F48 -> 0.18129045 | H48: =G48 -> 0.18129045 | I48: =H48 -> 0.18129045 | J48: =I48 -> 0.18129045
B49: Other long-term liabilities % of sales | C49: =BalSheet!C36/IncState!C16 -> 0.41126998 | D49: =BalSheet!D36/IncState!D16 -> 0.40459456 | E49: =BalSheet!E36/IncState!E16 -> 0.40059832 | F49: =E49 -> 0.40059832 | G49: =F49 -> 0.40059832 | H49: =G49 -> 0.40059832 | I49: =H49 -> 0.40059832 | J49: =I49 -> 0.40059832

Sheet Calcs
A1: =CoName -> Cheesecake Factory inc. | C1: Hist. | D1: Hist. | E1: Hist. | F1: Proj. | G1: Proj. | H1: Proj. | I1: Proj. | J1: Proj.
A2: Net PP&E | C2: 2022 | D2: =C2+1 -> 2023 | E2: =D2+1 -> 2024 | F2: =E2+1 -> 2025 | G2: =F2+1 -> 2026 | H2: =G2+1 -> 2027 | I2: =H2+1 -> 2028 | J2: =I2+1 -> 2029
B3: Capital expenditure % of sales | F3: =Assumptions!F32 -> 0.044783204 | G3: =Assumptions!G32 -> 0.044783204 | H3: =Assumptions!H32 -> 0.044783204 | I3: =Assumptions!I32 -> 0.044783204 | J3: =Assumptions!J32 -> 0.044783204
B4: Depreciation % of PP&E | F4: =Assumptions!F33 -> 0.048465467 | G4: =F4 -> 0.048465467 | H4: =G4 -> 0.048465467 | I4: =H4 -> 0.048465467 | J4: =I4 -> 0.048465467
B6: Beginning PP&E | F6: =E9 -> 2241.124 | G6: =F9 -> 2299.9645 | H6: =G9 -> 2363.6563 | I6: =H9 -> 2433.0193 | J6: =I9 -> 2506.3773
B7: Capex | F7: =F3*IncState!F16 -> 167.4576 | G7: =G3*IncState!G16 -> 175.16065 | H7: =H3*IncState!H16 -> 183.91868 | I7: =I3*IncState!I16 -> 191.27543 | J7: =J3*IncState!J16 -> 197.01369
B8: Depreciation | F8: =F6*F4 -> 108.61712 | G8: =G6*G4 -> 111.46885 | H8: =H6*H4 -> 114.55571 | I8: =I6*I4 -> 117.91741 | J8: =J6*J4 -> 121.47275
B9: Ending PP&E | E9: =BalSheet!E23 -> 2241.124 | F9: =F6+F7-F8 -> 2299.9645 | G9: =G6+G7-G8 -> 2363.6563 | H9: =H6+H7-H8 -> 2433.0193 | I9: =I6+I7-I8 -> 2506.3773 | J9: =J6+J7-J8 -> 2581.9182
A10: Equity | C10: =C2 -> 2022 | D10: =D2 -> 2023 | E10: =E2 -> 2024 | F10: =F2 -> 2025 | G10: =G2 -> 2026 | H10: =H2 -> 2027 | I10: =I2 -> 2028 | J10: =J2 -> 2029
B11: Share issuance/(repurchases) | F11: =Assumptions!F34 -> 0 | G11: =Assumptions!G34 -> 0 | H11: =Assumptions!H34 -> 0 | I11: =Assumptions!I34 -> 0 | J11: =Assumptions!J34 -> 0
B13: Beginning balance | F13: =E17 -> 443.455 | G13: =F17 -> 554.20579 | H13: =G17 -> 678.62694 | I13: =H17 -> 819.33597 | J13: =I17 -> 976.04158
B14: Net income | F14: =IncState!F34 -> 173.34959 | G14: =IncState!G34 -> 196.57775 | H14: =IncState!H34 -> 222.42342 | I14: =IncState!I34 -> 247.97781 | J14: =IncState!J34 -> 272.57433
B15: Dividends paid | F15: =-IncState!F36 -> -62.5988 | G15: =-IncState!G36 -> -72.1566 | H15: =-IncState!H36 -> -81.7144 | I15: =-IncState!I36 -> -91.2722 | J15: =-IncState!J36 -> -100.83
B16: Share issuance / (repurchase) | F16: =F11 -> 0 | G16: =G11 -> 0 | H16: =H11 -> 0 | I16: =I11 -> 0 | J16: =J11 -> 0
B17: Ending balance | E17: =BalSheet!E39 -> 443.455 | F17: =SUM(F13:F16) -> 554.20579 | G17: =SUM(G13:G16) -> 678.62694 | H17: =SUM(H13:H16) -> 819.33597 | I17: =SUM(I13:I16) -> 976.04158 | J17: =SUM(J13:J16) -> 1147.7859
A18: OWC | C18: =C10 -> 2022 | D18: =D10 -> 2023 | E18: =E10 -> 2024 | F18: =F10 -> 2025 | G18: =G10 -> 2026 | H18: =H10 -> 2027 | I18: =I10 -> 2028 | J18: =J10 -> 2029
B19: Operating Cash | E19: =BalSheet!E16 -> 35.817 | F19: =BalSheet!F16 -> 37.392948 | G19: =BalSheet!G16 -> 39.113024 | H19: =BalSheet!H16 -> 41.068675 | I19: =BalSheet!I16 -> 42.711422 | J19: =BalSheet!J16 -> 43.992764
B20: =BalSheet!B18 -> Accounts receivable | E20: =BalSheet!E18 -> 112.503 | F20: =BalSheet!F18 -> 117.45313 | G20: =BalSheet!G18 -> 122.85598 | H20: =BalSheet!H18 -> 128.99877 | I20: =BalSheet!I18 -> 134.15873 | J20: =BalSheet!J18 -> 138.18349
B21: =BalSheet!B19 -> Inventories | E21: =BalSheet!E19 -> 64.526 | F21: =BalSheet!F19 -> 66.966858 | G21: =BalSheet!G19 -> 69.630726 | H21: =BalSheet!H19 -> 72.674825 | I21: =BalSheet!I19 -> 75.126883 | J21: =BalSheet!J19 -> 76.912106
B22: Other current assets | E22: =BalSheet!E20 -> 72.108 | F22: =BalSheet!F20 -> 75.280752 | G22: =BalSheet!G20 -> 78.743667 | H22: =BalSheet!H20 -> 82.68085 | I22: =BalSheet!I20 -> 85.988084 | J22: =BalSheet!J20 -> 88.567726
B23: Accounts payables | E23: =BalSheet!E31 -> 62.092 | F23: =BalSheet!F31 -> 64.440786 | G23: =BalSheet!G31 -> 67.00417 | H23: =BalSheet!H31 -> 69.933441 | I23: =BalSheet!I31 -> 72.293004 | J23: =BalSheet!J31 -> 74.010887
B24: Other current liabilities | E24: =BalSheet!E32 -> 649.328 | F24: =BalSheet!F32 -> 677.89843 | G24: =BalSheet!G32 -> 709.08176 | H24: =BalSheet!H32 -> 744.53585 | I24: =BalSheet!I32 -> 774.31728 | J24: =BalSheet!J32 -> 797.5468
A25: * | B25: OWC | E25: =SUM(E19:E22)-SUM(E23:E24) -> -426.466 | F25: =SUM(F19:F22)-SUM(F23:F24) -> -445.24553 | G25: =SUM(G19:G22)-SUM(G23:G24) -> -465.74254 | H25: =SUM(H19:H22)-SUM(H23:H24) -> -489.04616 | I25: =SUM(I19:I22)-SUM(I23:I24) -> -508.62517 | J25: =SUM(J19:J22)-SUM(J23:J24) -> -523.9016
B26: Change in OWC | F26: =E25-F25 -> 18.779528 | G26: =F25-G25 -> 20.497009 | H26: =G25-H25 -> 23.303628 | I26: =H25-I25 -> 19.579007 | J26: =I25-J25 -> 15.276431

Sheet Debt
A1: =CoName -> Cheesecake Factory inc. | C1: Hist. | D1: Hist. | E1: Hist. | F1: Proj. | G1: Proj. | H1: Proj. | I1: Proj. | J1: Proj.
A2: Assumptions | C2: 2022 | D2: =C2+1 -> 2023 | E2: =D2+1 -> 2024 | F2: =E2+1 -> 2025 | G2: =F2+1 -> 2026 | H2: =G2+1 -> 2027 | I2: =H2+1 -> 2028 | J2: =I2+1 -> 2029
B4: Interest rate on revolver | F4: =Assumptions!F23 -> 0.05 | G4: =Assumptions!G23 -> 0.05 | H4: =Assumptions!H23 -> 0.05 | I4: =Assumptions!I23 -> 0.05 | J4: =Assumptions!J23 -> 0.05
B5: Interest rate on long-term debt | F5: =Assumptions!F24 -> 0.05 | G5: =Assumptions!G24 -> 0.05 | H5: =Assumptions!H24 -> 0.05 | I5: =Assumptions!I24 -> 0.05 | J5: =Assumptions!J24 -> 0.05
B6: Interest rate on cash | F6: =Assumptions!F25 -> 0.04 | G6: =Assumptions!G25 -> 0.04 | H6: =Assumptions!H25 -> 0.04 | I6: =Assumptions!I25 -> 0.04 | J6: =Assumptions!J25 -> 0.04
B8: Issuance of long-term debt | F8: =Assumptions!F27 -> 0 | G8: =Assumptions!G27 -> 0 | H8: =Assumptions!H27 -> 0 | I8: =Assumptions!I27 -> 0 | J8: =Assumptions!J27 -> 0
B9: Repayment of long-term debt | F9: =Assumptions!F28 -> 0 | G9: =Assumptions!G28 -> 0 | H9: =Assumptions!H28 -> 0 | I9: =Assumptions!I28 -> 0 | J9: =Assumptions!J28 -> 0
A11: Revolver | C11: =C2 -> 2022 | D11: =D2 -> 2023 | E11: =E2 -> 2024 | F11: =F2 -> 2025 | G11: =G2 -> 2026 | H11: =H2 -> 2027 | I11: =I2 -> 2028 | J11: =J2 -> 2029
B12: Balance | F12: 0 | G12: 0 | H12: 0 | I12: 0 | J12: 0
B13: Interest rate
B14: Interest expense
A16: Long term debt | C16: =C11 -> 2022 | D16: =D11 -> 2023 | E16: =E11 -> 2024 | F16: =F11 -> 2025 | G16: =G11 -> 2026 | H16: =H11 -> 2027 | I16: =I11 -> 2028 | J16: =J11 -> 2029
B17: Beginning balance | F17: =E20 -> 452.062 | G17: =F20 -> 452.062 | H17: =G20 -> 452.062 | I17: =H20 -> 452.062 | J17: =I20 -> 452.062
B18: Issuance | F18: =F8 -> 0 | G18: =G8 -> 0 | H18: =H8 -> 0 | I18: =I8 -> 0 | J18: =J8 -> 0
B19: Repayment | F19: =F9 -> 0 | G19: =G9 -> 0 | H19: =H9 -> 0 | I19: =I9 -> 0 | J19: =J9 -> 0
B20: Ending balance | E20: =BalSheet!E35 -> 452.062 | F20: =SUM(F17:F19) -> 452.062 | G20: =SUM(G17:G19) -> 452.062 | H20: =SUM(H17:H19) -> 452.062 | I20: =SUM(I17:I19) -> 452.062 | J20: =SUM(J17:J19) -> 452.062
B21: Interest rate | F21: =F5 -> 0.05 | G21: =G5 -> 0.05 | H21: =H5 -> 0.05 | I21: =I5 -> 0.05 | J21: =J5 -> 0.05
B22: Interest expense | F22: =-F21*F20 -> -22.6031 | G22: =-G21*G20 -> -22.6031 | H22: =-H21*H20 -> -22.6031 | I22: =-I21*I20 -> -22.6031 | J22: =-J21*J20 -> -22.6031
A24: Debt summary | C24: =C16 -> 2022 | D24: =D16 -> 2023 | E24: =E16 -> 2024 | F24: =F16 -> 2025 | G24: =G16 -> 2026 | H24: =H16 -> 2027 | I24: =I16 -> 2028 | J24: =J16 -> 2029
B25: Revolver | F25: =F12 -> 0 | G25: =G12 -> 0 | H25: =H12 -> 0 | I25: =I12 -> 0 | J25: =J12 -> 0
B26: Total long term debt | F26: =F20 -> 452.062 | G26: =G20 -> 452.062 | H26: =H20 -> 452.062 | I26: =I20 -> 452.062 | J26: =J20 -> 452.062
B27: Total debt | F27: =SUM(F25:F26) -> 452.062 | G27: =SUM(G25:G26) -> 452.062 | H27: =SUM(H25:H26) -> 452.062 | I27: =SUM(I25:I26) -> 452.062 | J27: =SUM(J25:J26) -> 452.062
B28: Total interest expense | F28: =F22 -> -22.6031 | G28: =G22 -> -22.6031 | H28: =H22 -> -22.6031 | I28: =I22 -> -22.6031 | J28: =J22 -> -22.6031
A30: Interest income | C30: =C11 -> 2022 | D30: =D11 -> 2023 | E30: =E11 -> 2024 | F30: =F11 -> 2025 | G30: =G11 -> 2026 | H30: =H11 -> 2027 | I30: =I11 -> 2028 | J30: =J11 -> 2029
B31: Excess Cash | F31: =BalSheet!F17 -> 172.69756 | G31: =BalSheet!G17 -> 312.47906 | H31: =BalSheet!H17 -> 473.70337 | I31: =BalSheet!I17 -> 632.55268 | J31: =BalSheet!J17 -> 787.6522
B32: Interest rate | F32: =F6 -> 0.04 | G32: =G6 -> 0.04 | H32: =H6 -> 0.04 | I32: =I6 -> 0.04 | J32: =J6 -> 0.04
B33: Interest income | F33: =F31*F32 -> 6.9079023 | G33: =G31*G32 -> 12.499162 | H33: =H31*H32 -> 18.948135 | I33: =I31*I32 -> 25.302107 | J33: =J31*J32 -> 31.506088

Sheet IncState
A1: =CoName -> Cheesecake Factory inc. | C1: Hist. | D1: Hist. | E1: Hist. | F1: Proj. | G1: Proj. | H1: Proj. | I1: Proj. | J1: Proj.
A2: Assumptions | C2: 2022 | D2: =C2+1 -> 2023 | E2: =D2+1 -> 2024 | F2: =E2+1 -> 2025 | G2: =F2+1 -> 2026 | H2: =G2+1 -> 2027 | I2: =H2+1 -> 2028 | J2: =I2+1 -> 2029
B4: Revenue growth | F4: =Assumptions!F10 -> 0.044 | G4: =Assumptions!G10 -> 0.046 | H4: =Assumptions!H10 -> 0.05 | I4: =Assumptions!I10 -> 0.04 | J4: =Assumptions!J10 -> 0.03
B5: Cost of goods sold as % of sales | F5: =Assumptions!F11 -> 0.8406878 | G5: =Assumptions!G11 -> 0.8356878 | H5: =Assumptions!H11 -> 0.8306878 | I5: =Assumptions!I11 -> 0.8256878 | J5: =Assumptions!J11 -> 0.8206878
B6: SG&A % of sales | F6: =Assumptions!F12 -> 0.099877712 | G6: =Assumptions!G12 -> 0.099877712 | H6: =Assumptions!H12 -> 0.099877712 | I6: =Assumptions!I12 -> 0.099877712 | J6: =Assumptions!J12 -> 0.099877712
B7: Amortization amount | F7: =Assumptions!F13 -> 0 | G7: =Assumptions!G13 -> 0 | H7: =Assumptions!H13 -> 0 | I7: =Assumptions!I13 -> 0 | J7: =Assumptions!J13 -> 0
B8: Non recurring items, amount | F8: =Assumptions!F14 -> 0 | G8: =Assumptions!G14 -> 0 | H8: =Assumptions!H14 -> 0 | I8: =Assumptions!I14 -> 0 | J8: =Assumptions!J14 -> 0
B9: Other income (expense), amt | F9: =Assumptions!F15 -> 0 | G9: =Assumptions!G15 -> 0 | H9: =Assumptions!H15 -> 0 | I9: =Assumptions!I15 -> 0 | J9: =Assumptions!J15 -> 0
B10: Effective tax rate | F10: =Assumptions!F16 -> 0.22 | G10: =Assumptions!G16 -> 0.22 | H10: =Assumptions!H16 -> 0.22 | I10: =Assumptions!I16 -> 0.22 | J10: =Assumptions!J16 -> 0.22
B11: Dividend Payout Rate | F11: =Assumptions!F17 -> 1.3098998 | G11: =Assumptions!G17 -> 1.5098998 | H11: =Assumptions!H17 -> 1.7098998 | I11: =Assumptions!I17 -> 1.9098998 | J11: =Assumptions!J17 -> 2.1098998
B12: Basic WASO | F12: =Assumptions!F18 -> 47.789 | G12: =Assumptions!G18 -> 47.789 | H12: =Assumptions!H18 -> 47.789 | I12: =Assumptions!I18 -> 47.789 | J12: =Assumptions!J18 -> 47.789
B13: Diluted WASO | F13: =Assumptions!F19 -> 48.974 | G13: =Assumptions!G19 -> 48.974 | H13: =Assumptions!H19 -> 48.974 | I13: =Assumptions!I19 -> 48.974 | J13: =Assumptions!J19 -> 48.974
A15: Income statement | C15: =C37 -> 44926 | D15: =D37 -> 45291 | E15: =E37 -> 45657 | F15: =F37 -> 46022 | G15: =G37 -> 46022 | H15: =H37 -> 46022 | I15: =I37 -> 46022 | J15: =J37 -> 46022
B16: Revenue | C16: 3303.2 | D16: 3439.5 | E16: 3581.7 | F16: =E16*(1+F4) -> 3739.2948 | G16: =F16*(1+G4) -> 3911.3024 | H16: =G16*(1+H4) -> 4106.8675 | I16: =H16*(1+I4) -> 4271.1422 | J16: =I16*(1+J4) -> 4399.2764
B17: COGS | C17: =810.9+1211.951+881.6 -> 2904.451 | D17: =803.5+1227.9+922.4 -> 2953.8 | E17: =806+1264+959 -> 3029 | F17: =F16*F5 -> 3143.5795 | G17: =G16*G5 -> 3268.6277 | H17: =H16*H5 -> 3411.5247 | I17: =I16*I5 -> 3526.63 | J17: =J16*J5 -> 3610.4325
B18: SG&A | C18: =205.753+92.38+16.9 -> 315.033 | D18: =219.45+93.136+25.379 -> 337.965 | E18: =228.737+101.5+27.495 -> 357.732 | F18: =F16*F6 -> 373.47221 | G18: =G16*G6 -> 390.65193 | H18: =H16*H6 -> 410.18453 | I18: =I16*I6 -> 426.59191 | J18: =J16*J6 -> 439.38966
A19: * | B19: EBIT | C19: =C16-SUM(C17:C18) -> 83.716 | D19: =D16-SUM(D17:D18) -> 147.735 | E19: =E16-SUM(E17:E18) -> 194.968 | F19: =F16-SUM(F17:F18) -> 222.24307 | G19: =G16-SUM(G17:G18) -> 252.02276 | H19: =H16-SUM(H17:H18) -> 285.15823 | I19: =I16-SUM(I17:I18) -> 317.92027 | J19: =J16-SUM(J17:J18) -> 349.45426
B21: Depreciation | C21: 92.38 | D21: 93.136 | E21: 101.45 | F21: =Calcs!F8 -> 108.61712 | G21: =Calcs!G8 -> 111.46885 | H21: =Calcs!H8 -> 114.55571 | I21: =Calcs!I8 -> 117.91741 | J21: =Calcs!J8 -> 121.47275
B22: Amortization | C22: 0 | D22: 0 | E22: 0 | F22: =F7 -> 0 | G22: =G7 -> 0 | H22: =H7 -> 0 | I22: =I7 -> 0 | J22: =J7 -> 0
A23: * | B23: EBITDA | C23: =SUM(C19,C21:C22) -> 176.096 | D23: =SUM(D19,D21:D22) -> 240.871 | E23: =SUM(E19,E21:E22) -> 296.418 | F23: =SUM(F19,F21:F22) -> 330.86019 | G23: =SUM(G19,G21:G22) -> 363.49161 | H23: =SUM(H19,H21:H22) -> 399.71394 | I23: =SUM(I19,I21:I22) -> 435.83769 | J23: =SUM(J19,J21:J22) -> 470.92701
B25: Non-recurring items | C25: =-31.38-13.36 -> -44.74 | D25: =-29.464-11.686 -> -41.15 | E25: =-13.647-2.429 -> -16.076 | F25: =F8 -> 0 | G25: =G8 -> 0 | H25: =H8 -> 0 | I25: =I8 -> 0 | J25: =J8 -> 0
B26: Other income (expense) | C26: =-7.488+1.4 -> -6.088 | D26: =-10.16+1.608 -> -8.552 | E26: =-10.107+2.837 -> -7.27 | F26: =F9 -> 0 | G26: =G9 -> 0 | H26: =H9 -> 0 | I26: =I9 -> 0 | J26: =J9 -> 0
B28: Interest income | F28: =IF(circ=1,Debt!F33,0) -> 0 | G28: =IF(circ=1,Debt!G33,0) -> 0 | H28: =IF(circ=1,Debt!H33,0) -> 0 | I28: =IF(circ=1,Debt!I33,0) -> 0 | J28: =IF(circ=1,Debt!J33,0) -> 0
B29: Interest expense | C29: -7.488 | D29: -10.169 | E29: -10.107 | F29: =IF(circ=1,Debt!F22,0) -> 0 | G29: =IF(circ=1,Debt!G22,0) -> 0 | H29: =IF(circ=1,Debt!H22,0) -> 0 | I29: =IF(circ=1,Debt!I22,0) -> 0 | J29: =IF(circ=1,Debt!J22,0) -> 0
A31: * | B31: Pretax Income | C31: =C19+SUM(C26:C29) -> 70.14 | D31: =D19+SUM(D26:D29) -> 129.014 | E31: =E19+SUM(E25:E29) -> 161.515 | F31: =F19+SUM(F25:F29) -> 222.24307 | G31: =G19+SUM(G25:G29) -> 252.02276 | H31: =H19+SUM(H25:H29) -> 285.15823 | I31: =I19+SUM(I25:I29) -> 317.92027 | J31: =J19+SUM(J25:J29) -> 349.45426
B33: Tax expense | C33: -10.231 | D33: -1.337 | E33: 14.264 | F33: =F31*F10 -> 48.893475 | G33: =G31*G10 -> 55.445007 | H33: =H31*H10 -> 62.734812 | I33: =I31*I10 -> 69.94246 | J33: =J31*J10 -> 76.879938
A34: * | B34: Net income | C34: =C31-C33 -> 80.371 | D34: =D31-D33 -> 130.351 | E34: =E31-E33 -> 147.251 | F34: =F31-F33 -> 173.34959 | G34: =G31-G33 -> 196.57775 | H34: =H31-H33 -> 222.42342 | I34: =I31-I33 -> 247.97781 | J34: =J31-J33 -> 272.57433
B35: Dividend payout rate | C35: =C36/C38 -> 0.84857975 | D35: =D36/D38 -> 1.1010471 | E35: =E36/E38 -> 1.1098998 | F35: =F11 -> 1.3098998 | G35: =G11 -> 1.5098998 | H35: =H11 -> 1.7098998 | I35: =I11 -> 1.9098998 | J35: =J11 -> 2.1098998
B36: Dividends | C36: 42.272 | D36: 53.207 | E36: 53.041 | F36: =F38*F35 -> 62.5988 | G36: =G38*G35 -> 72.1566 | H36: =H38*H35 -> 81.7144 | I36: =I38*I35 -> 91.2722 | J36: =J38*J35 -> 100.83
A37: Shareholder information | C37: 44926 | D37: 45291 | E37: 45657 | F37: 46022 | G37: 46022 | H37: 46022 | I37: 46022 | J37: 46022
B38: Basic WASO | C38: 49.815 | D38: 48.324 | E38: 47.789 | F38: =F12 -> 47.789 | G38: =G12 -> 47.789 | H38: =H12 -> 47.789 | I38: =I12 -> 47.789 | J38: =J12 -> 47.789
B39: Diluted WASO | C39: 50.414 | D39: 49.05 | E39: 48.974 | F39: =F13 -> 48.974 | G39: =G13 -> 48.974 | H39: =H13 -> 48.974 | I39: =I13 -> 48.974 | J39: =J13 -> 48.974
B40: Basic earnings per share | C40: =C34/C38 -> 1.6133895 | D40: =D34/D38 -> 2.6974381 | E40: =E34/E38 -> 3.0812739 | F40: =F34/F38 -> 3.6273952 | G40: =G34/G38 -> 4.1134519 | H40: =H34/H38 -> 4.6542807 | I40: =I34/I38 -> 5.1890145 | J40: =J34/J38 -> 5.7037043
A41: * | B41: Diluted earnings per share | C41: =C34/C39 -> 1.5942199 | D41: =D34/D39 -> 2.6575127 | E41: =E34/E39 -> 3.0067179 | F41: =F34/F39 -> 3.5396249 | G41: =G34/G39 -> 4.0139207 | H41: =H34/H39 -> 4.5416634 | I41: =I34/I39 -> 5.0634584 | J41: =J34/J39 -> 5.5656946

Sheet BalSheet
A1: =CoName -> Cheesecake Factory inc. | C1: Hist. | D1: Hist. | E1: Hist. | F1: Proj. | G1: Proj. | H1: Proj. | I1: Proj. | J1: Proj.
A2: Assumptions | C2: 2022 | D2: =C2+1 -> 2023 | E2: =D2+1 -> 2024 | F2: =E2+1 -> 2025 | G2: =F2+1 -> 2026 | H2: =G2+1 -> 2027 | I2: =H2+1 -> 2028 | J2: =I2+1 -> 2029
B4: Operating Cash % of sales | F4: =Assumptions!F38 -> 0.01 | G4: =F4 -> 0.01 | H4: =G4 -> 0.01 | I4: =H4 -> 0.01 | J4: =I4 -> 0.01
B5: Accounts receivable % of sales | F5: =Assumptions!F39 -> 0.031410503 | G5: =Assumptions!G39 -> 0.031410503 | H5: =Assumptions!H39 -> 0.031410503 | I5: =Assumptions!I39 -> 0.031410503 | J5: =Assumptions!J39 -> 0.031410503
B6: Inventories % of COGS | F6: =Assumptions!F40 -> 0.02130274 | G6: =Assumptions!G40 -> 0.02130274 | H6: =Assumptions!H40 -> 0.02130274 | I6: =Assumptions!I40 -> 0.02130274 | J6: =Assumptions!J40 -> 0.02130274
B7: Other current assets % of sales | F7: =Assumptions!F41 -> 0.020132339 | G7: =Assumptions!G41 -> 0.020132339 | H7: =Assumptions!H41 -> 0.020132339 | I7: =Assumptions!I41 -> 0.020132339 | J7: =Assumptions!J41 -> 0.020132339
B9: Other long-term assets % of sales | F9: =Assumptions!F43 -> 0.060176453 | G9: =Assumptions!G43 -> 0.060176453 | H9: =Assumptions!H43 -> 0.060176453 | I9: =Assumptions!I43 -> 0.060176453 | J9: =Assumptions!J43 -> 0.060176453
B11: Accounts payable/Accural % of COGS | F11: =Assumptions!F47 -> 0.020499175 | G11: =Assumptions!G47 -> 0.020499175 | H11: =Assumptions!H47 -> 0.020499175 | I11: =Assumptions!I47 -> 0.020499175 | J11: =Assumptions!J47 -> 0.020499175
B12: Other current liabilities % of sales | F12: =Assumptions!F48 -> 0.18129045 | G12: =Assumptions!G48 -> 0.18129045 | H12: =Assumptions!H48 -> 0.18129045 | I12: =Assumptions!I48 -> 0.18129045 | J12: =Assumptions!J48 -> 0.18129045
B13: Other long-term liabilities % of sales | F13: =Assumptions!F49 -> 0.40059832 | G13: =Assumptions!G49 -> 0.40059832 | H13: =Assumptions!H49 -> 0.40059832 | I13: =Assumptions!I49 -> 0.40059832 | J13: =Assumptions!J49 -> 0.40059832
A15: Balance sheet | C15: =C2 -> 2022 | D15: =D2 -> 2023 | E15: =E2 -> 2024 | F15: =F2 -> 2025 | G15: =G2 -> 2026 | H15: =H2 -> 2027 | I15: =I2 -> 2028 | J15: =J2 -> 2029
B16: Operating Cash | C16: =1%*IncState!C16 -> 33.032 | D16: =1%*IncState!D16 -> 34.395 | E16: =1%*IncState!E16 -> 35.817 | F16: =F4*IncState!F16 -> 37.392948 | G16: =G4*IncState!G16 -> 39.113024 | H16: =H4*IncState!H16 -> 41.068675 | I16: =I4*IncState!I16 -> 42.711422 | J16: =J4*IncState!J16 -> 43.992764
B17: Excess cash | C17: =114.777-C16 -> 81.745 | D17: =56.29-D16 -> 21.895 | E17: =84.176-E16 -> 48.359 | F17: =MAX(CashFlow!F23,0) -> 172.69756 | G17: =MAX(CashFlow!G23,0) -> 312.47906 | H17: =MAX(CashFlow!H23,0) -> 473.70337 | I17: =MAX(CashFlow!I23,0) -> 632.55268 | J17: =MAX(CashFlow!J23,0) -> 787.6522
B18: Accounts receivable | C18: 105.511 | D18: 103.094 | E18: 112.503 | F18: =F5*IncState!F16 -> 117.45313 | G18: =G5*IncState!G16 -> 122.85598 | H18: =H5*IncState!H16 -> 128.99877 | I18: =I5*IncState!I16 -> 134.15873 | J18: =J5*IncState!J16 -> 138.18349
B19: Inventories | C19: 55.559 | D19: 57.654 | E19: 64.526 | F19: =F6*IncState!F17 -> 66.966858 | G19: =G6*IncState!G17 -> 69.630726 | H19: =H6*IncState!H17 -> 72.674825 | I19: =I6*IncState!I17 -> 75.126883 | J19: =J6*IncState!J17 -> 76.912106
B20: Other current assets | C20: =21.522+48.399 -> 69.921 | D20: =20.67+63.09 -> 83.76 | E20: =17.417+54.691 -> 72.108 | F20: =F7*IncState!F16 -> 75.280752 | G20: =G7*IncState!G16 -> 78.743667 | H20: =H7*IncState!H16 -> 82.68085 | I20: =I7*IncState!I16 -> 85.988084 | J20: =J7*IncState!J16 -> 88.567726
B21: Total current assets | C21: =SUM(C16:C20) -> 345.768 | D21: =SUM(D16:D20) -> 300.798 | E21: =SUM(E16:E20) -> 333.313 | F21: =SUM(F16:F20) -> 469.79125 | G21: =SUM(G16:G20) -> 622.82245 | H21: =SUM(H16:H20) -> 799.1265 | I21: =SUM(I16:I20) -> 970.53779 | J21: =SUM(J16:J20) -> 1135.3083
B23: Property, plant & equipment, net | C23: =746.051+1268.986 -> 2015.037 | D23: =791.093+1302.15 -> 2093.243 | E23: =840.773+1400.351 -> 2241.124 | F23: =Calcs!F9 -> 2299.9645 | G23: =Calcs!G9 -> 2363.6563 | H23: =Calcs!H9 -> 2433.0193 | I23: =Calcs!I9 -> 2506.3773 | J23: =Calcs!J9 -> 2581.9182
B24: Intangible assets | C24: 251.524 | D24: =251.727 -> 251.727 | E24: =251.789 -> 251.789 | F24: =E24-IncState!F22 -> 251.789 | G24: =F24-IncState!G22 -> 251.789 | H24: =G24-IncState!H22 -> 251.789 | I24: =H24-IncState!I22 -> 251.789 | J24: =I24-IncState!J22 -> 251.789
B25: Other assets | C25: =162.891 -> 162.891 | D25: =194.615 -> 194.615 | E25: =215.534 -> 215.534 | F25: =F9*IncState!F16 -> 225.0175 | G25: =G9*IncState!G16 -> 235.3683 | H25: =H9*IncState!H16 -> 247.13672 | I25: =I9*IncState!I16 -> 257.02218 | J25: =J9*IncState!J16 -> 264.73285
B26: Total non-current assets | C26: =SUM(C23:C25) -> 2429.452 | D26: =SUM(D23:D25) -> 2539.585 | E26: =SUM(E23:E25) -> 2708.447 | F26: =SUM(F23:F25) -> 2776.771 | G26: =SUM(G23:G25) -> 2850.8136 | H26: =SUM(H23:H25) -> 2931.945 | I26: =SUM(I23:I25) -> 3015.1885 | J26: =SUM(J23:J25) -> 3098.4401
A28: * | B28: TOTAL ASSETS | C28: =SUM(C26,C21) -> 2775.22 | D28: =SUM(D26,D21) -> 2840.383 | E28: =SUM(E26,E21) -> 3041.76 | F28: =SUM(F26,F21) -> 3246.5622 | G28: =SUM(G26,G21) -> 3473.636 | H28: =SUM(H26,H21) -> 3731.0715 | I28: =SUM(I26,I21) -> 3985.7262 | J28: =SUM(J26,J21) -> 4233.7483
B30: Revolver/Short term debt | C30: 0 | D30: 0 | E30: 0 | F30: =MIN(CashFlow!F23,0) -> 0 | G30: =MIN(CashFlow!G23,0) -> 0 | H30: =MIN(CashFlow!H23,0) -> 0 | I30: =MIN(CashFlow!I23,0) -> 0 | J30: =MIN(CashFlow!J23,0) -> 0
B31: Accounts payable/Accurals | C31: 66.638 | D31: 63.152 | E31: 62.092 | F31: =F11*IncState!F17 -> 64.440786 | G31: =G11*IncState!G17 -> 67.00417 | H31: =H11*IncState!H17 -> 69.933441 | I31: =I11*IncState!I17 -> 72.293004 | J31: =J11*IncState!J17 -> 74.010887
B32: Other current liabilities | C32: =219.808+139.099+231.133 -> 590.04 | D32: =222.915+134.905+239.699 -> 597.519 | E32: =157.138+265.38+226.81 -> 649.328 | F32: =F12*IncState!F16 -> 677.89843 | G32: =G12*IncState!G16 -> 709.08176 | H32: =H12*IncState!H16 -> 744.53585 | I32: =I12*IncState!I16 -> 774.31728 | J32: =J12*IncState!J16 -> 797.5468
B33: Total current liabilities | C33: =SUM(C30:C32) -> 656.678 | D33: =SUM(D30:D32) -> 660.671 | E33: =SUM(E30:E32) -> 711.42 | F33: =SUM(F30:F32) -> 742.33922 | G33: =SUM(G30:G32) -> 776.08593 | H33: =SUM(H30:H32) -> 814.46929 | I33: =SUM(I30:I32) -> 846.61029 | J33: =SUM(J30:J32) -> 871.55769
B35: Long-term debt, including current maturities | C35: 468.032 | D35: 470.047 | E35: 452.062 | F35: =Debt!F20 -> 452.062 | G35: =Debt!G20 -> 452.062 | H35: =Debt!H20 -> 452.062 | I35: =Debt!I20 -> 452.062 | J35: =Debt!J20 -> 452.062
B36: Other long-term liabilities | C36: =1233.497+125.01 -> 1358.507 | D36: =1254.955+136.648 -> 1391.603 | E36: =1299.02+135.803 -> 1434.823 | F36: =F13*IncState!F16 -> 1497.9552 | G36: =G13*IncState!G16 -> 1566.8612 | H36: =H13*IncState!H16 -> 1645.2042 | I36: =I13*IncState!I16 -> 1711.0124 | J36: =J13*IncState!J16 -> 1762.3427
B37: Total non-current liabilities | C37: =SUM(C35:C36) -> 1826.539 | D37: =SUM(D35:D36) -> 1861.65 | E37: =SUM(E35:E36) -> 1886.885 | F37: =SUM(F35:F36) -> 1950.0172 | G37: =SUM(G35:G36) -> 2018.9232 | H37: =SUM(H35:H36) -> 2097.2662 | I37: =SUM(I35:I36) -> 2163.0744 | J37: =SUM(J35:J36) -> 2214.4047
B39: Equity | C39: 292.003 | D39: 318.062 | E39: 443.455 | F39: =Calcs!F17 -> 554.20579 | G39: =Calcs!G17 -> 678.62694 | H39: =Calcs!H17 -> 819.33597 | I39: =Calcs!I17 -> 976.04158 | J39: =Calcs!J17 -> 1147.7859
A40: * | B40: TOTAL LIABILITIES & EQUITY | C40: =SUM(C39,C37,C33) -> 2775.22 | D40: =SUM(D39,D37,D33) -> 2840.383 | E40: =SUM(E39,E37,E33) -> 3041.76 | F40: =SUM(F39,F37,F33) -> 3246.5622 | G40: =SUM(G39,G37,G33) -> 3473.636 | H40: =SUM(H39,H37,H33) -> 3731.0715 | I40: =SUM(I39,I37,I33) -> 3985.7262 | J40: =SUM(J39,J37,J33) -> 4233.7483
A42: * | B42: Balance check | C42: =C40-C28 -> 0 | D42: =D40-D28 -> 0 | E42: =E40-E28 -> 0 | F42: =F40-F28 -> 0 | G42: =G40-G28 -> 0 | H42: =H40-H28 -> 0 | I42: =I40-I28 -> 0 | J42: =J40-J28 -> 0

Sheet CashFlow
A1: =CoName -> Cheesecake Factory inc. | C1: Hist. | D1: Hist. | E1: Hist. | F1: Proj. | G1: Proj. | H1: Proj. | I1: Proj. | J1: Proj.
A2: Cash flow statement | C2: 2022 | D2: =C2+1 -> 2023 | E2: =D2+1 -> 2024 | F2: =E2+1 -> 2025 | G2: =F2+1 -> 2026 | H2: =G2+1 -> 2027 | I2: =H2+1 -> 2028 | J2: =I2+1 -> 2029
B3: Net Income | F3: =IncState!F34 -> 173.34959 | G3: =IncState!G34 -> 196.57775 | H3: =IncState!H34 -> 222.42342 | I3: =IncState!I34 -> 247.97781 | J3: =IncState!J34 -> 272.57433
B4: Depreciation | F4: =IncState!F21 -> 108.61712 | G4: =IncState!G21 -> 111.46885 | H4: =IncState!H21 -> 114.55571 | I4: =IncState!I21 -> 117.91741 | J4: =IncState!J21 -> 121.47275
B5: Amortization | F5: =IncState!F22 -> 0 | G5: =IncState!G22 -> 0 | H5: =IncState!H22 -> 0 | I5: =IncState!I22 -> 0 | J5: =IncState!J22 -> 0
B6: (inc) / dec in OWC | F6: =Calcs!F26 -> 18.779528 | G6: =Calcs!G26 -> 20.497009 | H6: =Calcs!H26 -> 23.303628 | I6: =Calcs!I26 -> 19.579007 | J6: =Calcs!J26 -> 15.276431
B7: (inc) / dec in LT assets | F7: =BalSheet!E25-BalSheet!F25 -> -9.483496 | G7: =BalSheet!F25-BalSheet!G25 -> -10.350805 | H7: =BalSheet!G25-BalSheet!H25 -> -11.768415 | I7: =BalSheet!H25-BalSheet!I25 -> -9.8854686 | J7: =BalSheet!I25-BalSheet!J25 -> -7.7106655
B8: inc / (dec) in LT liabilities | F8: =BalSheet!F36-BalSheet!E36 -> 63.132212 | G8: =BalSheet!G36-BalSheet!F36 -> 68.90594 | H8: =BalSheet!H36-BalSheet!G36 -> 78.343058 | I8: =BalSheet!I36-BalSheet!H36 -> 65.808168 | J8: =BalSheet!J36-BalSheet!I36 -> 51.330371
B9: CFFO | F9: =SUM(F3:F8) -> 354.39496 | G9: =SUM(G3:G8) -> 387.09875 | H9: =SUM(H3:H8) -> 426.8574 | I9: =SUM(I3:I8) -> 441.39694 | J9: =SUM(J3:J8) -> 452.94321
B11: Capex | F11: =-Calcs!F7 -> -167.4576 | G11: =-Calcs!G7 -> -175.16065 | H11: =-Calcs!H7 -> -183.91868 | I11: =-Calcs!I7 -> -191.27543 | J11: =-Calcs!J7 -> -197.01369
B12: CFFI | F12: =SUM(F11) -> -167.4576 | G12: =SUM(G11) -> -175.16065 | H12: =SUM(H11) -> -183.91868 | I12: =SUM(I11) -> -191.27543 | J12: =SUM(J11) -> -197.01369
B14: Dividends | F14: =-IncState!F36 -> -62.5988 | G14: =-IncState!G36 -> -72.1566 | H14: =-IncState!H36 -> -81.7144 | I14: =-IncState!I36 -> -91.2722 | J14: =-IncState!J36 -> -100.83
B15: Debt | F15: =SUM(Debt!F8:F9) -> 0 | G15: =SUM(Debt!G8:G9) -> 0 | H15: =SUM(Debt!H8:H9) -> 0 | I15: =SUM(Debt!I8:I9) -> 0 | J15: =SUM(Debt!J8:J9) -> 0
B16: Shares | F16: =Calcs!F11 -> 0 | G16: =Calcs!G11 -> 0 | H16: =Calcs!H11 -> 0 | I16: =Calcs!I11 -> 0 | J16: =Calcs!J11 -> 0
B17: CFFF | F17: =SUM(F14:F16) -> -62.5988 | G17: =SUM(G14:G16) -> -72.1566 | H17: =SUM(H14:H16) -> -81.7144 | I17: =SUM(I14:I16) -> -91.2722 | J17: =SUM(J14:J16) -> -100.83
B19: Net changes in cash | F19: =SUM(F17,F12,F9) -> 124.33856 | G19: =SUM(G17,G12,G9) -> 139.7815 | H19: =SUM(H17,H12,H9) -> 161.22432 | I19: =SUM(I17,I12,I9) -> 158.84931 | J19: =SUM(J17,J12,J9) -> 155.09952
B21: Beginning cash | F21: =BalSheet!E17 -> 48.359 | G21: =BalSheet!F17 -> 172.69756 | H21: =BalSheet!G17 -> 312.47906 | I21: =BalSheet!H17 -> 473.70337 | J21: =BalSheet!I17 -> 632.55268
B22: =B19 -> Net changes in cash | F22: =F19 -> 124.33856 | G22: =G19 -> 139.7815 | H22: =H19 -> 161.22432 | I22: =I19 -> 158.84931 | J22: =J19 -> 155.09952
B23: Ending Cash | F23: =SUM(F21:F22) -> 172.69756 | G23: =SUM(G21:G22) -> 312.47906 | H23: =SUM(H21:H22) -> 473.70337 | I23: =SUM(I21:I22) -> 632.55268 | J23: =SUM(J21:J22) -> 787.6522

Sheet Free Cash Flow
A1: =CoName -> Cheesecake Factory inc. | C1: Hist. | D1: Hist. | E1: Hist. | F1: Proj. | G1: Proj. | H1: Proj. | I1: Proj. | J1: Proj.
A2: Free Cash Flows | C2: 2022 | D2: =C2+1 -> 2023 | E2: =D2+1 -> 2024 | F2: =E2+1 -> 2025 | G2: =F2+1 -> 2026 | H2: =G2+1 -> 2027 | I2: =H2+1 -> 2028 | J2: =I2+1 -> 2029
A3: * | B3: Sales | F3: =IncState!F16 -> 3739.2948 | G3: =IncState!G16 -> 3911.3024 | H3: =IncState!H16 -> 4106.8675 | I3: =IncState!I16 -> 4271.1422 | J3: =IncState!J16 -> 4399.2764
B4: EBIT | F4: =IncState!F19 -> 222.24307 | G4: =IncState!G19 -> 252.02276 | H4: =IncState!H19 -> 285.15823 | I4: =IncState!I19 -> 317.92027 | J4: =IncState!J19 -> 349.45426
B5: Effective Tax Rate | F5: =Assumptions!F16 -> 0.22 | G5: =Assumptions!G16 -> 0.22 | H5: =Assumptions!H16 -> 0.22 | I5: =Assumptions!I16 -> 0.22 | J5: =Assumptions!J16 -> 0.22
A7: * | B7: NOPAT | F7: =F4*(1-F5) -> 173.34959 | G7: =G4*(1-G5) -> 196.57775 | H7: =H4*(1-H5) -> 222.42342 | I7: =I4*(1-I5) -> 247.97781 | J7: =J4*(1-J5) -> 272.57433
B8: Depreciation | F8: =CashFlow!F4 -> 108.61712 | G8: =CashFlow!G4 -> 111.46885 | H8: =CashFlow!H4 -> 114.55571 | I8: =CashFlow!I4 -> 117.91741 | J8: =CashFlow!J4 -> 121.47275
B9: Amortization | F9: =CashFlow!F5 -> 0 | G9: =CashFlow!G5 -> 0 | H9: =CashFlow!H5 -> 0 | I9: =CashFlow!I5 -> 0 | J9: =CashFlow!J5 -> 0
B10: (inc) / dec in OWC | F10: =CashFlow!F6 -> 18.779528 | G10: =CashFlow!G6 -> 20.497009 | H10: =CashFlow!H6 -> 23.303628 | I10: =CashFlow!I6 -> 19.579007 | J10: =CashFlow!J6 -> 15.276431
B11: (inc) / dec in other long-term assets | F11: =CashFlow!F7 -> -9.483496 | G11: =CashFlow!G7 -> -10.350805 | H11: =CashFlow!H7 -> -11.768415 | I11: =CashFlow!I7 -> -9.8854686 | J11: =CashFlow!J7 -> -7.7106655
B12: inc / (dec) other long-term liabilities | F12: =CashFlow!F8 -> 63.132212 | G12: =CashFlow!G8 -> 68.90594 | H12: =CashFlow!H8 -> 78.343058 | I12: =CashFlow!I8 -> 65.808168 | J12: =CashFlow!J8 -> 51.330371
B13: (Capex) | F13: =CashFlow!F12 -> -167.4576 | G13: =CashFlow!G12 -> -175.16065 | H13: =CashFlow!H12 -> -183.91868 | I13: =CashFlow!I12 -> -191.27543 | J13: =CashFlow!J12 -> -197.01369
A15: * | B15: Free Cash Flow | F15: =SUM(F7:F13) -> 186.93736 | G15: =SUM(G7:G13) -> 211.9381 | H15: =SUM(H7:H13) -> 242.93872 | I15: =SUM(I7:I13) -> 250.12151 | J15: =SUM(J7:J13) -> 255.92952

Sheet WACC
A1: =CoName -> Cheesecake Factory inc.
A3: * | B3: WACC | G3: Comp | H3: Levered beta | I3: Gross debt | J3: Market cap | K3: Debt/Mcap | L3: MTR | M3: Unlevered beta
B4: Tax Rate | E4: =Assumptions!F16 -> 0.22 | L4: =E4 -> 0.22 | M4: =H4/((1+K4*(1-L4))) -> 0
B5: Risk free rate | E5: 0.0415 | L5: =L4 -> 0.22 | M5: =H5/((1+K5*(1-L5))) -> 0
B6: Market risk Premium | E6: 0.05 | L6: =L5 -> 0.22 | M6: =H6/((1+K6*(1-L6))) -> 0
B7: Beta | E7: 0.96 | L7: =L6 -> 0.22 | M7: =H7/((1+K7*(1-L7))) -> 0
B8: Cost of Equity | E8: =E5+E6*E7 -> 0.0895
B9: % Equity | E9: =1-E10 -> 0.73142373 | G9: Industry beta (average) | M9: =AVERAGE(M4:M7) -> 0
B10: % Debt | E10: =MAIN!F8/MAIN!F6 -> 0.26857627
B11: Cost of debt | E11: =Assumptions!F24 -> 0.05 | G11: Re-levered beta | M11: =M9*(1+E10*(1-E4)) -> 0
B12: Post tax cost of debt | E12: =E11*(1-E4) -> 0.039
A13: * | B13: WACC | E13: =WACC!E8*WACC!E9+WACC!E12*WACC!E10 -> 0.075936898
B14: Long Term growth rate | E14: 0.025

Sheet DCF Model
A1: =CoName -> Cheesecake Factory inc. | D1: Proj. | E1: Proj. | F1: Proj. | G1: Proj. | H1: Proj.
A2: Discount Model Year count | D2: 1 | E2: =D2+1 -> 2 | F2: =E2+1 -> 3 | G2: =F2+1 -> 4 | H2: =G2+1 -> 5
B3: Discount Factor | D3: =1/(1+$K$17)^D2 -> 0.92942254 | E3: =1/(1+$K$17)^E2 -> 0.86382625 | F3: =1/(1+$K$17)^F2 -> 0.80285958 | G3: =1/(1+$K$17)^G2 -> 0.74619579 | H3: =1/(1+$K$17)^H2 -> 0.69353118
B4: PV FCF | D4: =D3*'Free Cash Flow'!F15 -> 173.74379 | E4: =E3*'Free Cash Flow'!G15 -> 183.07769 | F4: =F3*'Free Cash Flow'!H15 -> 195.04568 | G4: =G3*'Free Cash Flow'!I15 -> 186.63961 | H4: =H3*'Free Cash Flow'!J15 -> 177.4951 | I4: =(H4*(1+K18))/(K17-K18) -> 3571.7227
A6: Value Calculation | E6: Multiples Calculation | I6: DDM
B7: Total PV of FCFs | C7: =SUM(D4:H4) -> 916.00188 | E7: Total PV of FCFs | G7: =C7 -> 916.00188 | I7: FY dividend | K7: =IncState!J36 -> 100.83
B8: PV of TV | C8: =I4*H3 -> 2477.1011 | E8: Multiple TV | G8: =H3*G10*IncState!J23 -> 4899.0385 | I8: Equity Value | K8: =K7/(K17-K18) -> 1979.508
B9: EV | C9: =SUM(C7:C8) -> 3393.103 | E9: EV | G9: =SUM(G7:G8) -> 5815.0404
E10: Implied EBITDA multiple | G10: 15 | I10: Diluted S/O | K10: =G17 -> 49.8417
I11: Implied Share Price | K11: =K8/K10 -> 39.715901
B12: Cash & Cash Equiv | C12: =MAIN!F7 -> 189.978 | E12: Cash & Cash Equiv | G12: =C12 -> 189.978
B13: Debt & Claims | C13: =MAIN!F8 -> 629.156 | E13: Debt & Claims | G13: =C13 -> 629.156
B14: NCI | C14: 0 | E14: NCI | G14: =C14 -> 0
B15: Equity Value | C15: =C9+C12-SUM(C13:C14) -> 2953.925 | E15: Equity Value | G15: =G9+G12-SUM(G13:G14) -> 5375.8624
B17: Diluted S/O | C17: =MAIN!F5 -> 49.8417 | E17: Diluted S/O | G17: =C17 -> 49.8417 | I17: WACC | K17: =WACC!E13 -> 0.075936898
A18: * | B18: Implied Share Price | C18: =C15/C17 -> 59.266136 | E18: Implied Share Price | G18: =G15/G17 -> 107.85873 | I18: Long Term growth rate | K18: 0.025
A20: Sensitivity analysis
C22: Discount rate variance | E22: 0.005 | H22: Discount rate variance | J22: 0.005
C23: Implied growth rate variance | E23: 0.0025 | H23: TV multiple variance | J23: 1
E25: LTGR | J25: Exit mult.
C26: =C18 -> 59.266136 | D26: =E26-E23 -> 0.0225 | E26: 0.025 | F26: =E26+E23 -> 0.0275 | H26: =G18 -> 107.85873 | I26: =J26-J23 -> 14 | J26: 15 | K26: =J26+J23 -> 16
C27: =C28+$E$22 -> 0.085936898 | D27: 45.354536 | E27: 46.935799 | F27: 48.652358 | H27: =C27 -> 0.085936898 | I27: 96.655478 | J27: 102.91207 | K27: 109.16866
C28: =C29+$E$22 -> 0.080936898 | D28: 50.569524 | E28: 52.518825 | F28: 54.650518 | H28: =C28 -> 0.080936898 | I28: 98.949226 | J28: 105.35187 | K28: 111.7545
C29: 0.075936898 | D29: 56.825446 | E29: 59.266136 | F29: 61.958771 | H29: =C29 -> 0.075936898 | I29: 101.30593 | J29: 107.85873 | K29: 114.41153
C30: =C29-$E$22 -> 0.070936898 | D30: 64.449842 | E30: 67.563383 | F30: 71.035322 | H30: =C30 -> 0.070936898 | I30: 103.72764 | J30: 110.43484 | K30: 117.14204
C31: =C30-$E$22 -> 0.065936898 | D31: 73.921462 | E31: 77.985056 | F31: 82.577256 | H31: =C31 -> 0.065936898 | I31: 106.21649 | J31: 113.08248 | K31: 119.94847
