Workbook
Name Ccy: MAIN!$C$6
Name circ: MAIN!$C$9
Name CoName: MAIN!$C$4
Name g: #REF!
Name IQ_CH: 110000
Name IQ_CQ: 5000
Name IQ_CY: 10000
Name IQ_DAILY: 500000
Name IQ_FH: 100000
Name IQ_FQ: 500
Name IQ_FY: 1000
Name IQ_LTM: 2000
Name IQ_MONTH: 15000
Name IQ_NTM: 6000
Name IQ_WEEK: 50000
Name IQ_YTD: 3000
Name OpCase: [1]DCF!$E$98
Name ScenarioREV: Assumptions!$D$4
Name TTS: #REF!
Name Units: MAIN!$C$7

Sheet MAIN
A1: =CoName -> Cava Group Inc.
A2: Model Details
B4: Company name | C4: Cava Group Inc. | E4: Current Stock Price | F4: 53.34 | H4: Operating Case One | I4: Terminal Mult | J4: Perpetuity | K4: Average
B5: Latest BS date | C5: 247.43 | E5: Diluted s/o | F5: =115986.12 -> 115986.12 | H5: Implied Price | I5: ='DCF Model'!G18 -> 80.849527 | J5: ='DCF Model'!C18 -> 53.758969 | K5: =AVERAGE(I5:J5) -> 67.304248
B6: Currency | C6: USD | E6: Mkt Cap | F6: =F5*F4 -> 6186699.6 | H6: Difference | I6: =I5/$F$4-1 -> 0.51573916 | J6: =J5/$F$4-1 -> 0.0078546911 | K6: =K5/$F$4-1 -> 0.26179692
B7: Units | C7: m | E7: Cash | F7: =284570+103115 -> 387685
B8: Analyst name | C8: Alan Chen | E8: Debt | F8: 0
B9: Circular switch | C9: 0 | E9: EV | F9: =F6-F7+F8 -> 5799014.6

Sheet Quarterly Projections

Sheet Assumptions
A1: =CoName -> Cava Group Inc. | C1: Hist. | D1: Hist. | E1: Hist. | F1: Proj. | G1: Proj. | H1: Proj. | I1: Proj. | J1: Proj. | K1: Proj. | L1: Proj.
A2: * | B2: Income Statement | C2: 2022 | D2: =C2+1 -> 2023 | E2: =D2+1 -> 2024 | F2: =E2+1 -> 2025 | G2: =F2+1 -> 2026 | H2: =G2+1 -> 2027 | I2: =H2+1 -> 2028 | J2: =I2+1 -> 2029 | K2: =J2+1 -> 2030 | L2: =K2+1 -> 2031
B4: Operating Case | D4: 1
D5: Variance
B6: Street Case | D6: 0 | F6: 0.225 | G6: =F6-0.0033 -> 0.2217 | H6: =G6-0.0033 -> 0.2184 | I6: =H6-0.0033 -> 0.2151 | J6: =I6-0.0033 -> 0.2118 | K6: =J6-0.0033 -> 0.2085 | L6: =K6-0.0033 -> 0.2052
B7: Optimistic Case | D7: 0.025 | F7: =F6+$D$7 -> 0.25 | G7: =G6+$D$7 -> 0.2467 | H7: =H6+$D$7 -> 0.2434 | I7: =I6+$D$7 -> 0.2401 | J7: =J6+$D$7 -> 0.2368 | K7: =K6+$D$7 -> 0.2335 | L7: =L6+$D$7 -> 0.2302
B8: Pessimistic Case | D8: -0.025 | F8: =F6+$D$8 -> 0.2 | G8: =G6+$D$8 -> 0.1967 | H8: =H6+$D$8 -> 0.1934 | I8: =I6+$D$8 -> 0.1901 | J8: =J6+$D$8 -> 0.1868 | K8: =K6+$D$8 -> 0.1835 | L8: =L6+$D$8 -> 0.1802
B10: Revenue Growth | D10: =IncState!D15/IncState!C15-1 -> 0.29174873 | E10: =IncState!E15/IncState!D15-1 -> 0.32250995 | F10: =CHOOSE(ScenarioREV,F6,F7,F8) -> 0.225 | G10: =CHOOSE(ScenarioREV,G6,G7,G8) -> 0.2217 | H10: =CHOOSE(ScenarioREV,H6,H7,H8) -> 0.2184 | I10: =CHOOSE(ScenarioREV,I6,I7,I8) -> 0.2151 | J10: =CHOOSE(ScenarioREV,J6,J7,J8) -> 0.2118 | K10: =CHOOSE(ScenarioREV,K6,K7,K8) -> 0.2085 | L10: =CHOOSE(ScenarioREV,L6,L7,L8) -> 0.2052
B11: COGS % of sales | C11: =IncState!C16/IncState!C15 -> 0.31906034 | D11: =IncState!D16/IncState!D15 -> 0.29292988 | E11: =IncState!E16/IncState!E15 -> 0.29546452 | F11: =E11-0.005 -> 0.29046452 | G11: =F11-0.005 -> 0.28546452 | H11: =G11-0.005 -> 0.28046452 | I11: =H11-0.005 -> 0.27546452 | J11: =I11-0.005 -> 0.27046452 | K11: =J11-0.005 -> 0.26546452 | L11: =K11-0.005 -> 0.26046452
B12: SG&A % of sales | C12: =IncState!C17/IncState!C15 -> 0.78688539 | D12: =IncState!D17/IncState!D15 -> 0.70058598 | E12: =IncState!E17/IncState!E15 -> 0.65979394 | F12: =E12-0.015 -> 0.64479394 | G12: =F12-0.015 -> 0.62979394 | H12: =G12-0.015 -> 0.61479394 | I12: =H12-0.015 -> 0.59979394 | J12: =I12-0.015 -> 0.58479394 | K12: =J12-0.015 -> 0.56979394 | L12: =K12-0.015 -> 0.55479394
B13: Amortization $ Amt | C13: =IncState!C21 -> 5638 | D13: =IncState!D21 -> 27 | E13: =IncState!E21 -> 0 | F13: =E13 -> 0 | G13: =F13 -> 0 | H13: =G13 -> 0 | I13: =H13 -> 0 | J13: =I13 -> 0 | K13: =J13 -> 0 | L13: =K13 -> 0
B14: Non recurring income / (expense) | C14: =IncState!C24 -> 0 | D14: =IncState!D24 -> 0 | E14: =IncState!E24 -> 0 | F14: 0 | G14: 0 | H14: 0 | I14: 0 | J14: 0 | K14: 0 | L14: 0
B15: Other Income / (expense) | C15: =IncState!C25 -> -919 | D15: =IncState!D25 -> -471 | E15: =IncState!E25 -> -318 | F15: 0 | G15: 0 | H15: 0 | I15: 0 | J15: 0 | K15: 0 | L15: 0
B16: Effective tax rate | C16: =IncState!C32/IncState!C30 -> -0.0015313179 | D16: =IncState!D32/IncState!D30 -> 0.058599115 | E16: =IncState!E32/IncState!E30 -> -1.1878564 | F16: 0.2 | G16: =F16 -> 0.2 | H16: =G16 -> 0.2 | I16: =H16 -> 0.2 | J16: =I16 -> 0.2 | K16: =J16 -> 0.2 | L16: =K16 -> 0.2
B17: Basic WASO | C17: =IncState!C36 -> 1328 | D17: =IncState!D36 -> 60512 | E17: =IncState!E36 -> 114292 | F17: =E17 -> 114292 | G17: =F17 -> 114292 | H17: =G17 -> 114292 | I17: =H17 -> 114292 | J17: =I17 -> 114292 | K17: =J17 -> 114292 | L17: =K17 -> 114292
B18: Diluted WASO | C18: =IncState!C37 -> 1328 | D18: =IncState!D37 -> 63448 | E18: =IncState!E37 -> 118273 | F18: =E18 -> 118273 | G18: =F18 -> 118273 | H18: =G18 -> 118273 | I18: =H18 -> 118273 | J18: =I18 -> 118273 | K18: =J18 -> 118273 | L18: =K18 -> 118273
A20: * | B20: Debt | C20: =C2 -> 2022 | D20: =D2 -> 2023 | E20: =E2 -> 2024 | F20: =F2 -> 2025 | G20: =G2 -> 2026 | H20: =H2 -> 2027 | I20: =I2 -> 2028 | J20: =J2 -> 2029 | ... L20: =L2 -> 2031
B22: Interest rate on Revolver | E22: 0.05 | F22: =E22 -> 0.05 | G22: =F22 -> 0.05 | H22: =G22 -> 0.05 | I22: =H22 -> 0.05 | J22: =I22 -> 0.05 | K22: =J22 -> 0.05 | L22: =K22 -> 0.05
B23: Interest rate on long-term debt | E23: 0.05 | F23: =E23 -> 0.05 | G23: =F23 -> 0.05 | H23: =G23 -> 0.05 | I23: =H23 -> 0.05 | J23: =I23 -> 0.05 | K23: =J23 -> 0.05 | L23: =K23 -> 0.05
B24: Interest rate on cash | E24: =IncState!E27/SUM(BalSheet!E16:E17) -> 0.044996176 | F24: =E24 -> 0.044996176 | G24: =F24 -> 0.044996176 | H24: =G24 -> 0.044996176 | I24: =H24 -> 0.044996176 | J24: =I24 -> 0.044996176 | K24: =J24 -> 0.044996176 | L24: =K24 -> 0.044996176
B26: Issuance of long-term debt | F26: 0 | G26: 0 | H26: 0 | I26: 0 | J26: 0 | K26: 0 | L26: 0
B27: Repayment of long-term debt | F27: 0 | G27: 0 | H27: 0 | I27: 0 | J27: 0 | K27: 0 | L27: 0
A29: * | B29: Calcs | C29: =C20 -> 2022 | D29: =D20 -> 2023 | E29: =E20 -> 2024 | F29: =F20 -> 2025 | G29: =G20 -> 2026 | H29: =H20 -> 2027 | I29: =I20 -> 2028 | J29: =J20 -> 2029 | ... L29: =L20 -> 2031
B31: CapEx % of Sales | C31: =106161/IncState!E15 -> 0.11015831 | D31: =138806/IncState!D15 -> 0.19048442 | E31: =108131/IncState!E15 -> 0.11220249 | F31: =E31-0.005 -> 0.10720249 | G31: =F31-0.005 -> 0.10220249 | H31: =G31-0.005 -> 0.097202492 | I31: =H31-0.005 -> 0.092202492 | J31: =I31-0.005 -> 0.087202492 | K31: =J31-0.005 -> 0.082202492 | L31: =K31-0.005 -> 0.077202492
B32: Depreciation % of beginning PP&E | D32: =IncState!D20/BalSheet!C23 -> 0.091719405 | E32: =IncState!E20/BalSheet!D23 -> 0.097318364 | F32: =E32 -> 0.097318364 | G32: =F32 -> 0.097318364 | H32: =G32 -> 0.097318364 | I32: =H32 -> 0.097318364 | J32: =I32 -> 0.097318364 | K32: =J32 -> 0.097318364 | L32: =K32 -> 0.097318364
B33: Share issuance / (repurchases) | F33: 0 | G33: 0 | H33: 0 | I33: 0 | J33: 0 | K33: 0 | L33: 0
A35: * | B35: Balance Sheet - Assets | C35: =C29 -> 2022 | D35: =D29 -> 2023 | E35: =E29 -> 2024 | F35: =F29 -> 2025 | G35: =G29 -> 2026 | H35: =H29 -> 2027 | I35: =I29 -> 2028 | J35: =J29 -> 2029 | ... L35: =L29 -> 2031
B37: Operating Cash % of sales | C37: =BalSheet!C16/IncState!C15 -> 0.02 | D37: =BalSheet!D16/IncState!D15 -> 0.02 | E37: =BalSheet!E16/IncState!E15 -> 0.02 | F37: =E37 -> 0.02 | G37: =F37 -> 0.02 | H37: =G37 -> 0.02 | I37: =H37 -> 0.02 | J37: =I37 -> 0.02 | K37: =J37 -> 0.02 | L37: =K37 -> 0.02
B38: Accounts receivable % of sales | C38: =BalSheet!C18/IncState!C15 -> 0.013711646 | D38: =BalSheet!D18/IncState!D15 -> 0.016309867 | E38: =BalSheet!E18/IncState!E15 -> 0.013485343 | F38: =E38 -> 0.013485343 | G38: =F38 -> 0.013485343 | H38: =G38 -> 0.013485343 | I38: =H38 -> 0.013485343 | J38: =I38 -> 0.013485343 | K38: =J38 -> 0.013485343 | L38: =K38 -> 0.013485343
B39: Inventories % of COGS | C39: =BalSheet!C19/IncState!C16 -> 0.028551903 | D39: =BalSheet!D19/IncState!D16 -> 0.026408005 | E39: =BalSheet!E19/IncState!E16 -> 0.026690735 | F39: =E39 -> 0.026690735 | G39: =F39 -> 0.026690735 | H39: =G39 -> 0.026690735 | I39: =H39 -> 0.026690735 | J39: =I39 -> 0.026690735 | K39: =J39 -> 0.026690735 | L39: =K39 -> 0.026690735
B40: Other current assets % of sales | C40: =BalSheet!C20/IncState!C15 -> 0.010903728 | D40: =BalSheet!D20/IncState!D15 -> 0.0068093866 | E40: =BalSheet!E20/IncState!E15 -> 0.0077180654 | F40: =E40 -> 0.0077180654 | G40: =F40 -> 0.0077180654 | H40: =G40 -> 0.0077180654 | I40: =H40 -> 0.0077180654 | J40: =I40 -> 0.0077180654 | K40: =J40 -> 0.0077180654 | L40: =K40 -> 0.0077180654
B42: Other long-term assets % of sales | C42: =BalSheet!C25/IncState!C15 -> 0.0098348044 | D42: =BalSheet!D25/IncState!D15 -> 0.0073624262 | E42: =BalSheet!E25/IncState!E15 -> 0.080399455 | F42: 0.01 | G42: =F42 -> 0.01 | H42: =G42 -> 0.01 | I42: =H42 -> 0.01 | J42: =I42 -> 0.01 | K42: =J42 -> 0.01 | L42: =K42 -> 0.01
A44: * | B44: Balance Sheet - Liabilities | C44: =C35 -> 2022 | D44: =D35 -> 2023 | E44: =E35 -> 2024 | F44: =F35 -> 2025 | G44: =G35 -> 2026 | H44: =H35 -> 2027 | I44: =I35 -> 2028 | J44: =J35 -> 2029 | ... L44: =L35 -> 2031
B46: Accounts payable % of COGS | C46: =BalSheet!C31/IncState!C16 -> 0.30434807 | D46: =BalSheet!D31/IncState!D16 -> 0.35816414 | E46: =BalSheet!E31/IncState!E16 -> 0.33502141 | F46: =E46 -> 0.33502141 | G46: =F46 -> 0.33502141 | H46: =G46 -> 0.33502141 | I46: =H46 -> 0.33502141 | J46: =I46 -> 0.33502141 | K46: =J46 -> 0.33502141 | L46: =K46 -> 0.33502141
B47: Other current liabilities % of sales | C47: =BalSheet!C32/IncState!C15 -> 0.052363065 | D47: =BalSheet!D32/IncState!D15 -> 0.044713874 | E47: =BalSheet!E32/IncState!E15 -> 0.038643248 | F47: =E47 -> 0.038643248 | G47: =F47 -> 0.038643248 | H47: =G47 -> 0.038643248 | I47: =H47 -> 0.038643248 | J47: =I47 -> 0.038643248 | K47: =J47 -> 0.038643248 | L47: =K47 -> 0.038643248
B48: Other long-term liabilities % of sales | C48: =BalSheet!C36/IncState!C15 -> 0.50655979 | D48: =BalSheet!D36/IncState!D15 -> 0.41707012 | E48: =BalSheet!E36/IncState!E15 -> 0.35432437 | F48: =E48 -> 0.35432437 | G48: =F48 -> 0.35432437 | H48: =G48 -> 0.35432437 | I48: =H48 -> 0.35432437 | J48: =I48 -> 0.35432437 | K48: =J48 -> 0.35432437 | L48: =K48 -> 0.35432437

Sheet Calcs
A1: =CoName -> Cava Group Inc. | C1: Hist. | D1: Hist. | E1: Hist. | F1: Proj. | G1: Proj. | H1: Proj. | I1: Proj. | J1: Proj. | K1: Proj. | L1: Proj.
A2: Net PP&E | C2: 2022 | D2: =C2+1 -> 2023 | E2: =D2+1 -> 2024 | F2: =E2+1 -> 2025 | G2: =F2+1 -> 2026 | H2: =G2+1 -> 2027 | I2: =H2+1 -> 2028 | J2: =I2+1 -> 2029 | K2: =J2+1 -> 2030 | L2: =K2+1 -> 2031
B3: Capital expenditure % of sales | F3: =Assumptions!F31 -> 0.10720249 | G3: =Assumptions!G31 -> 0.10220249 | H3: =Assumptions!H31 -> 0.097202492 | I3: =Assumptions!I31 -> 0.092202492 | J3: =Assumptions!J31 -> 0.087202492 | K3: =Assumptions!K31 -> 0.082202492 | L3: =Assumptions!L31 -> 0.077202492
B4: Depreciation % of PP&E | F4: =Assumptions!F32 -> 0.097318364 | G4: =F4 -> 0.097318364 | H4: =G4 -> 0.097318364 | I4: =H4 -> 0.097318364 | J4: =I4 -> 0.097318364 | K4: =J4 -> 0.097318364 | L4: =K4 -> 0.097318364
B6: Beginning PP&E | F6: =E9 -> 694734 | G6: =F9 -> 753681.36 | H6: =G9 -> 827738.52 | I6: =H9 -> 917995.3 | J6: =I9 -> 1025533.6 | K6: =J9 -> 1151367.2 | L6: =K9 -> 1296365.3
B7: Capex | F7: =F3*IncState!F15 -> 126557.73 | G7: =G3*IncState!G15 -> 147404.2 | H7: =H3*IncState!H15 -> 170810.93 | I7: =I3*IncState!I15 -> 196876.08 | J7: =J3*IncState!J15 -> 225636.91 | K7: =K3*IncState!K15 -> 257047.2 | L7: =L3*IncState!L15 -> 290949.98
B8: Depreciation | F8: =F4*F6 -> 67610.376 | G8: =G4*G6 -> 73347.036 | H8: =H4*H6 -> 80554.158 | I8: =I4*I6 -> 89337.8 | J8: =J4*J6 -> 99803.249 | K8: =K4*K6 -> 112049.17 | L8: =L4*L6 -> 126160.15
B9: Ending PP&E | E9: =BalSheet!E23 -> 694734 | F9: =F6+F7-F8 -> 753681.36 | G9: =G6+G7-G8 -> 827738.52 | H9: =H6+H7-H8 -> 917995.3 | I9: =I6+I7-I8 -> 1025533.6 | J9: =J6+J7-J8 -> 1151367.2 | K9: =K6+K7-K8 -> 1296365.3 | L9: =L6+L7-L8 -> 1461155.1
A10: Equity | C10: =C2 -> 2022 | D10: =D2 -> 2023 | E10: =E2 -> 2024 | F10: =F2 -> 2025 | G10: =G2 -> 2026 | H10: =H2 -> 2027 | I10: =I2 -> 2028 | J10: =J2 -> 2029 | ... L10: =L2 -> 2031
B11: Share issuance/(repurchases) | F11: =Assumptions!F33 -> 0 | G11: =Assumptions!G33 -> 0 | H11: =Assumptions!H33 -> 0 | I11: =Assumptions!I33 -> 0 | J11: =Assumptions!J33 -> 0 | K11: =Assumptions!K33 -> 0 | L11: =Assumptions!L33 -> 0
B13: Beginning balance | F13: =E16 -> 695566 | G13: =F16 -> 700710.41 | H13: =G16 -> 798486.96 | I13: =H16 -> 945734.21 | J13: =I16 -> 1158818.5 | K13: =J16 -> 1458434.1 | L13: =K16 -> 1870551.5
B14: Net income | F14: =IncState!F33 -> 5144.4148 | G14: =IncState!G33 -> 97776.548 | H14: =IncState!H33 -> 147247.25 | I14: =IncState!I33 -> 213084.26 | J14: =IncState!J33 -> 299615.59 | K14: =IncState!K33 -> 412117.44 | L14: =IncState!L33 -> 556982.51
B15: Share issuance / (repurchase) | F15: =F11 -> 0 | G15: =G11 -> 0 | H15: =H11 -> 0 | I15: =I11 -> 0 | J15: =J11 -> 0 | K15: =K11 -> 0 | L15: =L11 -> 0
B16: Ending balance | E16: =BalSheet!E39 -> 695566 | F16: =SUM(F13:F15) -> 700710.41 | G16: =SUM(G13:G15) -> 798486.96 | H16: =SUM(H13:H15) -> 945734.21 | I16: =SUM(I13:I15) -> 1158818.5 | J16: =SUM(J13:J15) -> 1458434.1 | K16: =SUM(K13:K15) -> 1870551.5 | L16: =SUM(L13:L15) -> 2427534
A17: OWC | C17: =C10 -> 2022 | D17: =D10 -> 2023 | E17: =E10 -> 2024 | F17: =F10 -> 2025 | G17: =G10 -> 2026 | H17: =H10 -> 2027 | I17: =I10 -> 2028 | J17: =J10 -> 2029 | ... L17: =L10 -> 2031
B18: Operating Cash | E18: =BalSheet!E16 -> 19274.26 | F18: =BalSheet!F16 -> 23610.969 | G18: =BalSheet!G16 -> 28845.52 | H18: =BalSheet!H16 -> 35145.382 | I18: =BalSheet!I16 -> 42705.153 | J18: =BalSheet!J16 -> 51750.105 | K18: =BalSheet!K16 -> 62540.002 | L18: =BalSheet!L16 -> 75373.21
B19: =BalSheet!B18 -> Accounts receivable | E19: =BalSheet!E18 -> 12996 | F19: =BalSheet!F18 -> 15920.1 | G19: =BalSheet!G18 -> 19449.586 | H19: =BalSheet!H18 -> 23697.376 | I19: =BalSheet!I18 -> 28794.681 | J19: =BalSheet!J18 -> 34893.395 | K19: =BalSheet!K18 -> 42168.668 | L19: =BalSheet!L18 -> 50821.678
B20: =BalSheet!B19 -> Inventories | E20: =BalSheet!E19 -> 7600 | F20: =BalSheet!F19 -> 9152.4515 | G20: =BalSheet!G19 -> 10989.073 | H20: =BalSheet!H19 -> 13154.572 | I20: =BalSheet!I19 -> 15699.163 | J20: =BalSheet!J19 -> 18678.934 | K20: =BalSheet!K19 -> 22156.182 | L20: =BalSheet!L19 -> 26199.688
B21: Other current assets | E21: =BalSheet!E20 -> 7438 | F21: =BalSheet!F20 -> 9111.55 | G21: =BalSheet!G20 -> 11131.581 | H21: =BalSheet!H20 -> 13562.718 | I21: =BalSheet!I20 -> 16480.058 | J21: =BalSheet!J20 -> 19970.535 | K21: =BalSheet!K20 -> 24134.391 | L21: =BalSheet!L20 -> 29086.768
B22: Accounts payables | E22: =BalSheet!E31 -> 95395 | F22: =BalSheet!F31 -> 114881.33 | G22: =BalSheet!G31 -> 137934.55 | H22: =BalSheet!H31 -> 165115.85 | I22: =BalSheet!I31 -> 197055.48 | J22: =BalSheet!J31 -> 234457.48 | K22: =BalSheet!K31 -> 278103.81 | L22: =BalSheet!L31 -> 328857.8
B23: Other current liabilities | E23: =BalSheet!E32 -> 37241 | F23: =BalSheet!F32 -> 45620.225 | G23: =BalSheet!G32 -> 55734.229 | H23: =BalSheet!H32 -> 67906.584 | I23: =BalSheet!I32 -> 82513.291 | J23: =BalSheet!J32 -> 99989.606 | K23: =BalSheet!K32 -> 120837.44 | L23: =BalSheet!L32 -> 145633.28
A24: * | B24: OWC | E24: =SUM(E18:E21)-SUM(E22:E23) -> -85327.74 | F24: =SUM(F18:F21)-SUM(F22:F23) -> -102706.49 | G24: =SUM(G18:G21)-SUM(G22:G23) -> -123253.02 | H24: =SUM(H18:H21)-SUM(H22:H23) -> -147462.38 | I24: =SUM(I18:I21)-SUM(I22:I23) -> -175889.72 | J24: =SUM(J18:J21)-SUM(J22:J23) -> -209154.12 | K24: =SUM(K18:K21)-SUM(K22:K23) -> -247942 | L24: =SUM(L18:L21)-SUM(L22:L23) -> -293009.74
B25: Change in OWC | F25: =E24-F24 -> 17378.745 | G25: =F24-G24 -> 20546.538 | H25: =G24-H24 -> 24209.36 | I25: =H24-I24 -> 28427.332 | J25: =I24-J24 -> 33264.406 | K25: =J24-K24 -> 38787.884 | L25: =K24-L24 -> 45067.731

Sheet Debt
A1: =CoName -> Cava Group Inc. | C1: Hist. | D1: Hist. | E1: Hist. | F1: Proj. | G1: Proj. | H1: Proj. | I1: Proj. | J1: Proj. | K1: Proj. | L1: Proj.
A2: Assumptions | C2: 2022 | D2: =C2+1 -> 2023 | E2: =D2+1 -> 2024 | F2: =E2+1 -> 2025 | G2: =F2+1 -> 2026 | H2: =G2+1 -> 2027 | I2: =H2+1 -> 2028 | J2: =I2+1 -> 2029 | K2: =J2+1 -> 2030 | L2: =K2+1 -> 2031
B4: Interest rate on revolver | F4: =Assumptions!F22 -> 0.05 | G4: =Assumptions!G22 -> 0.05 | H4: =Assumptions!H22 -> 0.05 | I4: =Assumptions!I22 -> 0.05 | J4: =Assumptions!J22 -> 0.05 | K4: =Assumptions!K22 -> 0.05 | L4: =Assumptions!L22 -> 0.05
B5: Interest rate on long-term debt | F5: =Assumptions!F23 -> 0.05 | G5: =Assumptions!G23 -> 0.05 | H5: =Assumptions!H23 -> 0.05 | I5: =Assumptions!I23 -> 0.05 | J5: =Assumptions!J23 -> 0.05 | K5: =Assumptions!K23 -> 0.05 | L5: =Assumptions!L23 -> 0.05
B6: Interest rate on cash | F6: =Assumptions!F24 -> 0.044996176 | G6: =Assumptions!G24 -> 0.044996176 | H6: =Assumptions!H24 -> 0.044996176 | I6: =Assumptions!I24 -> 0.044996176 | J6: =Assumptions!J24 -> 0.044996176 | K6: =Assumptions!K24 -> 0.044996176 | L6: =Assumptions!L24 -> 0.044996176
B8: Issuance of long-term debt | F8: =Assumptions!F26 -> 0 | G8: =Assumptions!G26 -> 0 | H8: =Assumptions!H26 -> 0 | I8: =Assumptions!I26 -> 0 | J8: =Assumptions!J26 -> 0 | K8: =Assumptions!K26 -> 0 | L8: =Assumptions!L26 -> 0
B9: Repayment of long-term debt | F9: =Assumptions!F27 -> 0 | G9: =Assumptions!G27 -> 0 | H9: =Assumptions!H27 -> 0 | I9: =Assumptions!I27 -> 0 | J9: =Assumptions!J27 -> 0 | K9: =Assumptions!K27 -> 0 | L9: =Assumptions!L27 -> 0
A11: Revolver | C11: =C2 -> 2022 | D11: =D2 -> 2023 | E11: =E2 -> 2024 | F11: =F2 -> 2025 | G11: =G2 -> 2026 | H11: =H2 -> 2027 | I11: =I2 -> 2028 | J11: =J2 -> 2029 | ... L11: =L2 -> 2031
B12: Balance
B13: Interest rate
B14: Interest expense
A16: Long term debt | C16: =C11 -> 2022 | D16: =D11 -> 2023 | E16: =E11 -> 2024 | F16: =F11 -> 2025 | G16: =G11 -> 2026 | H16: =H11 -> 2027 | I16: =I11 -> 2028 | J16: =J11 -> 2029 | ... L16: =L11 -> 2031
B17: Beginning balance
B18: Issuance
B19: Repayment
B20: Ending balance
B21: Interest rate
B22: Interest expense | F22: 0 | G22: 0 | H22: 0 | I22: 0 | J22: 0 | K22: 0 | L22: 0
A24: Debt summary | C24: =C16 -> 2022 | D24: =D16 -> 2023 | E24: =E16 -> 2024 | F24: =F16 -> 2025 | G24: =G16 -> 2026 | H24: =H16 -> 2027 | I24: =I16 -> 2028 | J24: =J16 -> 2029 | ... L24: =L16 -> 2031
B25: Revolver | F25: 0 | G25: 0 | H25: 0 | I25: 0 | J25: 0 | K25: 0 | L25: 0
B26: Total long term debt | F26: 0 | G26: 0 | H26: 0 | I26: 0 | J26: 0 | K26: 0 | L26: 0
B27: Total debt | F27: 0 | G27: 0 | H27: 0 | I27: 0 | J27: 0 | K27: 0 | L27: 0
B28: Total interest expense | F28: 0 | G28: 0 | H28: 0 | I28: 0 | J28: 0 | K28: 0 | L28: 0
A30: Interest income | C30: =C11 -> 2022 | D30: =D11 -> 2023 | E30: =E11 -> 2024 | F30: =F11 -> 2025 | G30: =G11 -> 2026 | H30: =H11 -> 2027 | I30: =I11 -> 2028 | J30: =J11 -> 2029 | ... L30: =L11 -> 2031
B31: Excess Cash | F31: =SUM(BalSheet!F16:F17) -> 476539.1 | G31: =SUM(BalSheet!G16:G17) -> 616158.76 | H31: =SUM(BalSheet!H16:H17) -> 812118.25 | I31: =SUM(BalSheet!I16:I17) -> 1083802 | J31: =SUM(BalSheet!J16:J17) -> 1455613.2 | K31: =SUM(BalSheet!K16:K17) -> 1958071.6 | L31: =SUM(BalSheet!L16:L17) -> 2629104.5
B32: Interest rate | F32: =F6 -> 0.044996176 | G32: =G6 -> 0.044996176 | H32: =H6 -> 0.044996176 | I32: =I6 -> 0.044996176 | J32: =J6 -> 0.044996176 | K32: =K6 -> 0.044996176 | L32: =L6 -> 0.044996176
B33: Interest income | F33: =F31*F32 -> 21442.437 | G33: =G31*G32 -> 27724.788 | H33: =H31*H32 -> 36542.216 | I33: =I31*I32 -> 48766.946 | J33: =J31*J32 -> 65497.026 | K33: =K31*K32 -> 88105.734 | L33: =L31*L32 -> 118299.65

Sheet IncState
A1: =CoName -> Cava Group Inc. | C1: Hist. | D1: Hist. | E1: Hist. | F1: Proj. | G1: Proj. | H1: Proj. | I1: Proj. | J1: Proj. | K1: Proj. | L1: Proj.
A2: Assumptions | C2: 2022 | D2: =C2+1 -> 2023 | E2: =D2+1 -> 2024 | F2: =E2+1 -> 2025 | G2: =F2+1 -> 2026 | H2: =G2+1 -> 2027 | I2: =H2+1 -> 2028 | J2: =I2+1 -> 2029 | K2: =J2+1 -> 2030 | L2: =K2+1 -> 2031
B4: Revenue growth | F4: =Assumptions!F10 -> 0.225 | G4: =Assumptions!G10 -> 0.2217 | H4: =Assumptions!H10 -> 0.2184 | I4: =Assumptions!I10 -> 0.2151 | J4: =Assumptions!J10 -> 0.2118 | K4: =Assumptions!K10 -> 0.2085 | L4: =Assumptions!L10 -> 0.2052
B5: Cost of goods sold as % of sales | F5: =Assumptions!F11 -> 0.29046452 | G5: =Assumptions!G11 -> 0.28546452 | H5: =Assumptions!H11 -> 0.28046452 | I5: =Assumptions!I11 -> 0.27546452 | J5: =Assumptions!J11 -> 0.27046452 | K5: =Assumptions!K11 -> 0.26546452 | L5: =Assumptions!L11 -> 0.26046452
B6: SG&A % of sales | F6: =Assumptions!F12 -> 0.64479394 | G6: =Assumptions!G12 -> 0.62979394 | H6: =Assumptions!H12 -> 0.61479394 | I6: =Assumptions!I12 -> 0.59979394 | J6: =Assumptions!J12 -> 0.58479394 | K6: =Assumptions!K12 -> 0.56979394 | L6: =Assumptions!L12 -> 0.55479394
B7: Amortization amount | F7: =Assumptions!F13 -> 0 | G7: =Assumptions!G13 -> 0 | H7: =Assumptions!H13 -> 0 | I7: =Assumptions!I13 -> 0 | J7: =Assumptions!J13 -> 0 | K7: =Assumptions!K13 -> 0 | L7: =Assumptions!L13 -> 0
B8: Non recurring items, amount | F8: =Assumptions!F14 -> 0 | G8: =Assumptions!G14 -> 0 | H8: =Assumptions!H14 -> 0 | I8: =Assumptions!I14 -> 0 | J8: =Assumptions!J14 -> 0 | K8: =Assumptions!K14 -> 0 | L8: =Assumptions!L14 -> 0
B9: Other income (expense), amt | F9: =Assumptions!F15 -> 0 | G9: =Assumptions!G15 -> 0 | H9: =Assumptions!H15 -> 0 | I9: =Assumptions!I15 -> 0 | J9: =Assumptions!J15 -> 0 | K9: =Assumptions!K15 -> 0 | L9: =Assumptions!L15 -> 0
B10: Effective tax rate | F10: =Assumptions!F16 -> 0.2 | G10: =Assumptions!G16 -> 0.2 | H10: =Assumptions!H16 -> 0.2 | I10: =Assumptions!I16 -> 0.2 | J10: =Assumptions!J16 -> 0.2 | K10: =Assumptions!K16 -> 0.2 | L10: =Assumptions!L16 -> 0.2
B11: Basic WASO | F11: =Assumptions!F17 -> 114292 | G11: =Assumptions!G17 -> 114292 | H11: =Assumptions!H17 -> 114292 | I11: =Assumptions!I17 -> 114292 | J11: =Assumptions!J17 -> 114292 | K11: =Assumptions!K17 -> 114292 | L11: =Assumptions!L17 -> 114292
B12: Diluted WASO | F12: =Assumptions!F18 -> 118273 | G12: =Assumptions!G18 -> 118273 | H12: =Assumptions!H18 -> 118273 | I12: =Assumptions!I18 -> 118273 | J12: =Assumptions!J18 -> 118273 | K12: =Assumptions!K18 -> 118273 | L12: =Assumptions!L18 -> 118273
A14: Income statement | C14: 2022 | D14: =C14+1 -> 2023 | E14: =D14+1 -> 2024 | F14: =E14+1 -> 2025 | G14: =F14+1 -> 2026 | H14: =G14+1 -> 2027 | I14: =H14+1 -> 2028 | J14: =I14+1 -> 2029 | K14: =J14+1 -> 2030 | L14: =K14+1 -> 2031
B15: Revenue | C15: 564119 | D15: 728700 | E15: 963713 | F15: =E15*(1+F4) -> 1180548.4 | G15: =F15*(1+G4) -> 1442276 | H15: =G15*(1+H4) -> 1757269.1 | I15: =H15*(1+I4) -> 2135257.7 | J15: =I15*(1+J4) -> 2587505.2 | K15: =J15*(1+K4) -> 3127000.1 | L15: =K15*(1+L4) -> 3768660.5
B16: COGS | C16: 179988 | D16: 213458 | E16: 284743 | F16: =F15*F5 -> 342907.43 | G16: =G15*G5 -> 411718.63 | H16: =H15*H5 -> 492851.63 | I16: =I15*I5 -> 588187.73 | J16: =J15*J5 -> 699828.37 | K16: =K15*K5 -> 830107.58 | L16: =L15*L5 -> 981602.36
B17: SG&A | C17: =623885-C16 -> 443897 | D17: =723975-D16 -> 510517 | E17: =920595-E16 -> 635852 | F17: =F6*F15 -> 761210.47 | G17: =G6*G15 -> 908336.7 | H17: =H6*H15 -> 1080358.4 | I17: =I6*I15 -> 1280714.6 | J17: =J6*J15 -> 1513157.4 | K17: =K6*K15 -> 1781745.7 | L17: =L6*L15 -> 2090830
A18: * | B18: EBIT | C18: =C15-SUM(C16:C17) -> -59766 | D18: =D15-SUM(D16:D17) -> 4725 | E18: =E15-SUM(E16:E17) -> 43118 | F18: =F15-SUM(F16:F17) -> 76430.519 | G18: =G15-SUM(G16:G17) -> 122220.68 | H18: =H15-SUM(H16:H17) -> 184059.06 | I18: =I15-SUM(I16:I17) -> 266355.32 | J18: =J15-SUM(J16:J17) -> 374519.48 | ... L18: =L15-SUM(L16:L17) -> 696228.13
B20: Depreciation | C20: 37086 | D20: 47406 | E20: 60355 | F20: =Calcs!F8 -> 67610.376 | G20: =Calcs!G8 -> 73347.036 | H20: =Calcs!H8 -> 80554.158 | I20: =Calcs!I8 -> 89337.8 | J20: =Calcs!J8 -> 99803.249 | K20: =Calcs!K8 -> 112049.17 | L20: =Calcs!L8 -> 126160.15
B21: Amortization | C21: 5638 | D21: 27 | E21: 0 | F21: =F7 -> 0 | G21: =G7 -> 0 | H21: =H7 -> 0 | I21: =I7 -> 0 | J21: =J7 -> 0 | K21: =K7 -> 0 | L21: =L7 -> 0
A22: * | B22: EBITDA | C22: =SUM(C18,C20:C21) -> -17042 | D22: =SUM(D18,D20:D21) -> 52158 | E22: =SUM(E18,E20:E21) -> 103473 | F22: =SUM(F18,F20:F21) -> 144040.89 | G22: =SUM(G18,G20:G21) -> 195567.72 | H22: =SUM(H18,H20:H21) -> 264613.22 | I22: =SUM(I18,I20:I21) -> 355693.12 | J22: =SUM(J18,J20:J21) -> 474322.73 | ... L22: =SUM(L18,L20:L21) -> 822388.28
B24: Non-recurring items | C24: 0 | D24: 0 | E24: 0 | F24: =F8 -> 0 | G24: =G8 -> 0 | H24: =H8 -> 0 | I24: =I8 -> 0 | J24: =J8 -> 0 | K24: =K8 -> 0 | L24: =L8 -> 0
B25: Other income (expense) | C25: -919 | D25: -471 | E25: -318 | F25: -70000 | G25: =G9 -> 0 | H25: =H9 -> 0 | I25: =I9 -> 0 | J25: =J9 -> 0 | K25: =K9 -> 0 | L25: =L9 -> 0
B27: Interest income | C27: 0 | D27: 8852 | E27: 16474 | F27: =IF(circ=1,Debt!F33,0) -> 0 | G27: =IF(circ=1,Debt!G33,0) -> 0 | H27: =IF(circ=1,Debt!H33,0) -> 0 | I27: =IF(circ=1,Debt!I33,0) -> 0 | J27: =IF(circ=1,Debt!J33,0) -> 0 | K27: =IF(circ=1,Debt!K33,0) -> 0 | L27: =IF(circ=1,Debt!L33,0) -> 0
B28: Interest expense | C28: -47 | D28: 0 | E28: 0 | F28: =IF(circ=1,-Debt!F28,0) -> 0 | G28: =IF(circ=1,-Debt!G28,0) -> 0 | H28: =IF(circ=1,-Debt!H28,0) -> 0 | I28: =IF(circ=1,-Debt!I28,0) -> 0 | J28: =IF(circ=1,-Debt!J28,0) -> 0 | K28: =IF(circ=1,-Debt!K28,0) -> 0 | L28: =IF(circ=1,-Debt!L28,0) -> 0
A30: * | B30: Pretax Income | C30: =C18+SUM(C25:C28) -> -60732 | D30: =D18+SUM(D25:D28) -> 13106 | E30: =E18+SUM(E24:E28) -> 59274 | F30: =F18+SUM(F24:F28) -> 6430.5185 | G30: =G18+SUM(G24:G28) -> 122220.68 | H30: =H18+SUM(H24:H28) -> 184059.06 | I30: =I18+SUM(I24:I28) -> 266355.32 | J30: =J18+SUM(J24:J28) -> 374519.48 | K30: =K18+SUM(K24:K28) -> 515146.8 | L30: =L18+SUM(L24:L28) -> 696228.13
B32: Tax expense | C32: 93 | D32: 768 | E32: -70409 | F32: =F30*F10 -> 1286.1037 | G32: =G30*G10 -> 24444.137 | H32: =H30*H10 -> 36811.813 | I32: =I30*I10 -> 53271.064 | J32: =J30*J10 -> 74903.897 | K32: =K30*K10 -> 103029.36 | L32: =L30*L10 -> 139245.63
A33: * | B33: Net income | C33: =C30-C32 -> -60825 | D33: =D30-D32 -> 12338 | E33: =E30-E32 -> 129683 | F33: =F30-F32 -> 5144.4148 | G33: =G30-G32 -> 97776.548 | H33: =H30-H32 -> 147247.25 | I33: =I30-I32 -> 213084.26 | J33: =J30-J32 -> 299615.59 | ... L33: =L30-L32 -> 556982.51
A35: Shareholder information | C35: 2022 | D35: =C35+1 -> 2023 | E35: =D35+1 -> 2024 | F35: =E35+1 -> 2025 | G35: =F35+1 -> 2026 | H35: =G35+1 -> 2027 | I35: =H35+1 -> 2028 | J35: =I35+1 -> 2029 | K35: =J35+1 -> 2030 | L35: =K35+1 -> 2031
B36: Basic WASO | C36: 1328 | D36: 60512 | E36: 114292 | F36: =F11 -> 114292 | G36: =G11 -> 114292 | H36: =H11 -> 114292 | I36: =I11 -> 114292 | J36: =J11 -> 114292 | K36: =K11 -> 114292 | L36: =L11 -> 114292
B37: Diluted WASO | C37: 1328 | D37: 63448 | E37: 118273 | F37: =F12 -> 118273 | G37: =G12 -> 118273 | H37: =H12 -> 118273 | I37: =I12 -> 118273 | J37: =J12 -> 118273 | K37: =K12 -> 118273 | L37: =L12 -> 118273
B38: Basic earnings per share | C38: =C33/C36 -> -45.801958 | D38: =D33/D36 -> 0.20389344 | E38: =E33/E36 -> 1.1346638 | F38: =F33/F36 -> 0.045011154 | G38: =G33/G36 -> 0.85549774 | H38: =H33/H36 -> 1.2883426 | I38: =I33/I36 -> 1.8643847 | J38: =J33/J36 -> 2.6214922 | ... L38: =L33/L36 -> 4.8733289
A39: * | B39: Diluted earnings per share | C39: =C33/C37 -> -45.801958 | D39: =D33/D37 -> 0.19445845 | E39: =E33/E37 -> 1.0964717 | F39: =F33/F37 -> 0.043496105 | G39: =G33/G37 -> 0.82670219 | H39: =H33/H37 -> 1.2449777 | I39: =I33/I37 -> 1.8016306 | J39: =J33/J37 -> 2.5332543 | ... L39: =L33/L37 -> 4.7092955

Sheet BalSheet
A1: =CoName -> Cava Group Inc. | C1: Hist. | D1: Hist. | E1: Hist. | F1: Proj. | G1: Proj. | H1: Proj. | I1: Proj. | J1: Proj. | K1: Proj. | L1: Proj.
A2: Assumptions | C2: 2022 | D2: =C2+1 -> 2023 | E2: =D2+1 -> 2024 | F2: =E2+1 -> 2025 | G2: =F2+1 -> 2026 | H2: =G2+1 -> 2027 | I2: =H2+1 -> 2028 | J2: =I2+1 -> 2029 | K2: =J2+1 -> 2030 | L2: =K2+1 -> 2031
B4: Operating Cash % of sales | F4: =Assumptions!F37 -> 0.02 | G4: =F4 -> 0.02 | H4: =G4 -> 0.02 | I4: =H4 -> 0.02 | J4: =I4 -> 0.02 | K4: =J4 -> 0.02 | L4: =K4 -> 0.02
B5: Accounts receivable % of sales | F5: =Assumptions!F38 -> 0.013485343 | G5: =Assumptions!G38 -> 0.013485343 | H5: =Assumptions!H38 -> 0.013485343 | I5: =Assumptions!I38 -> 0.013485343 | J5: =Assumptions!J38 -> 0.013485343 | K5: =Assumptions!K38 -> 0.013485343 | L5: =Assumptions!L38 -> 0.013485343
B6: Inventories % of COGS | F6: =Assumptions!F39 -> 0.026690735 | G6: =Assumptions!G39 -> 0.026690735 | H6: =Assumptions!H39 -> 0.026690735 | I6: =Assumptions!I39 -> 0.026690735 | J6: =Assumptions!J39 -> 0.026690735 | K6: =Assumptions!K39 -> 0.026690735 | L6: =Assumptions!L39 -> 0.026690735
B7: Other current assets % of sales | F7: =Assumptions!F40 -> 0.0077180654 | G7: =Assumptions!G40 -> 0.0077180654 | H7: =Assumptions!H40 -> 0.0077180654 | I7: =Assumptions!I40 -> 0.0077180654 | J7: =Assumptions!J40 -> 0.0077180654 | K7: =Assumptions!K40 -> 0.0077180654 | L7: =Assumptions!L40 -> 0.0077180654
B9: Other long-term assets % of sales | F9: =Assumptions!F42 -> 0.01 | G9: =Assumptions!G42 -> 0.01 | H9: =Assumptions!H42 -> 0.01 | I9: =Assumptions!I42 -> 0.01 | J9: =Assumptions!J42 -> 0.01 | K9: =Assumptions!K42 -> 0.01 | L9: =Assumptions!L42 -> 0.01
B11: Accounts payable/Accural % of COGS | F11: =Assumptions!F46 -> 0.33502141 | G11: =Assumptions!G46 -> 0.33502141 | H11: =Assumptions!H46 -> 0.33502141 | I11: =Assumptions!I46 -> 0.33502141 | J11: =Assumptions!J46 -> 0.33502141 | K11: =Assumptions!K46 -> 0.33502141 | L11: =Assumptions!L46 -> 0.33502141
B12: Other current liabilities % of sales | F12: =Assumptions!F47 -> 0.038643248 | G12: =Assumptions!G47 -> 0.038643248 | H12: =Assumptions!H47 -> 0.038643248 | I12: =Assumptions!I47 -> 0.038643248 | J12: =Assumptions!J47 -> 0.038643248 | K12: =Assumptions!K47 -> 0.038643248 | L12: =Assumptions!L47 -> 0.038643248
B13: Other long-term liabilities % of sales | F13: =Assumptions!F48 -> 0.35432437 | G13: =Assumptions!G48 -> 0.35432437 | H13: =Assumptions!H48 -> 0.35432437 | I13: =Assumptions!I48 -> 0.35432437 | J13: =Assumptions!J48 -> 0.35432437 | K13: =Assumptions!K48 -> 0.35432437 | L13: =Assumptions!L48 -> 0.35432437
A15: Balance sheet | C15: =C2 -> 2022 | D15: =D2 -> 2023 | E15: =E2 -> 2024 | F15: =F2 -> 2025 | G15: =G2 -> 2026 | H15: =H2 -> 2027 | I15: =I2 -> 2028 | J15: =J2 -> 2029 | ... L15: =L2 -> 2031
B16: Operating Cash | C16: =2%*IncState!C15 -> 11282.38 | D16: =2%*IncState!D15 -> 14574 | E16: =2%*IncState!E15 -> 19274.26 | F16: =F4*IncState!F15 -> 23610.969 | G16: =G4*IncState!G15 -> 28845.52 | H16: =H4*IncState!H15 -> 35145.382 | I16: =I4*IncState!I15 -> 42705.153 | J16: =J4*IncState!J15 -> 51750.105 | K16: =K4*IncState!K15 -> 62540.002 | L16: =L4*IncState!L15 -> 75373.21
B17: Excess cash | C17: =39125-C16 -> 27842.62 | D17: =332428-D16 -> 317854 | E17: =366120-E16 -> 346845.74 | F17: =MAX(CashFlow!F23,0) -> 452928.13 | G17: =MAX(CashFlow!G23,0) -> 587313.24 | H17: =MAX(CashFlow!H23,0) -> 776972.87 | I17: =MAX(CashFlow!I23,0) -> 1041096.9 | J17: =MAX(CashFlow!J23,0) -> 1403863.1 | K17: =MAX(CashFlow!K23,0) -> 1895531.6 | L17: =MAX(CashFlow!L23,0) -> 2553731.3
B18: Accounts receivable | C18: =2827+4908 -> 7735 | D18: =3662+8223 -> 11885 | E18: =4799+8197 -> 12996 | F18: =F5*IncState!F15 -> 15920.1 | G18: =G5*IncState!G15 -> 19449.586 | H18: =H5*IncState!H15 -> 23697.376 | I18: =I5*IncState!I15 -> 28794.681 | J18: =J5*IncState!J15 -> 34893.395 | K18: =K5*IncState!K15 -> 42168.668 | L18: =L5*IncState!L15 -> 50821.678
B19: Inventories | C19: 5139 | D19: 5637 | E19: 7600 | F19: =F6*IncState!F16 -> 9152.4515 | G19: =G6*IncState!G16 -> 10989.073 | H19: =H6*IncState!H16 -> 13154.572 | I19: =I6*IncState!I16 -> 15699.163 | J19: =J6*IncState!J16 -> 18678.934 | K19: =K6*IncState!K16 -> 22156.182 | L19: =L6*IncState!L16 -> 26199.688
B20: Other current assets | C20: 6151 | D20: 4962 | E20: 7438 | F20: =F7*IncState!F15 -> 9111.55 | G20: =G7*IncState!G15 -> 11131.581 | H20: =H7*IncState!H15 -> 13562.718 | I20: =I7*IncState!I15 -> 16480.058 | J20: =J7*IncState!J15 -> 19970.535 | K20: =K7*IncState!K15 -> 24134.391 | L20: =L7*IncState!L15 -> 29086.768
B21: Total current assets | C21: =SUM(C16:C20) -> 58150 | D21: =SUM(D16:D20) -> 354912 | E21: =SUM(E16:E20) -> 394154 | F21: =SUM(F16:F20) -> 510723.2 | G21: =SUM(G16:G20) -> 657729 | H21: =SUM(H16:H20) -> 862532.92 | I21: =SUM(I16:I20) -> 1144775.9 | J21: =SUM(J16:J20) -> 1529156 | ... L21: =SUM(L16:L20) -> 2735212.6
B23: Property, plant & equipment, net | C23: =242983+273876 -> 516859 | D23: =330730+289451 -> 620181 | E23: =372902+321832 -> 694734 | F23: =Calcs!F9 -> 753681.36 | G23: =Calcs!G9 -> 827738.52 | H23: =Calcs!H9 -> 917995.3 | I23: =Calcs!I9 -> 1025533.6 | J23: =Calcs!J9 -> 1151367.2 | K23: =Calcs!K9 -> 1296365.3 | L23: =Calcs!L9 -> 1461155.1
B24: Intangible assets | C24: =1944+1382 -> 3326 | D24: =1944+1355 -> 3299 | E24: =1944+1355 -> 3299 | F24: =E24-IncState!F21 -> 3299 | G24: =F24-IncState!G21 -> 3299 | H24: =G24-IncState!H21 -> 3299 | I24: =H24-IncState!I21 -> 3299 | J24: =I24-IncState!J21 -> 3299 | K24: =J24-IncState!K21 -> 3299 | L24: =K24-IncState!L21 -> 3299
B25: Other assets | C25: 5548 | D25: 5365 | E25: =71537+5945 -> 77482 | F25: =F9*IncState!F15 -> 11805.484 | G25: =G9*IncState!G15 -> 14422.76 | H25: =H9*IncState!H15 -> 17572.691 | I25: =I9*IncState!I15 -> 21352.577 | J25: =J9*IncState!J15 -> 25875.052 | K25: =K9*IncState!K15 -> 31270.001 | L25: =L9*IncState!L15 -> 37686.605
B26: Total non-current assets | C26: =SUM(C23:C25) -> 525733 | D26: =SUM(D23:D25) -> 628845 | E26: =SUM(E23:E25) -> 775515 | F26: =SUM(F23:F25) -> 768785.84 | G26: =SUM(G23:G25) -> 845460.28 | H26: =SUM(H23:H25) -> 938866.99 | I26: =SUM(I23:I25) -> 1050185.2 | J26: =SUM(J23:J25) -> 1180541.3 | ... L26: =SUM(L23:L25) -> 1502140.7
A28: * | B28: TOTAL ASSETS | C28: =SUM(C26,C21) -> 583883 | D28: =SUM(D26,D21) -> 983757 | E28: =SUM(E26,E21) -> 1169669 | F28: =SUM(F26,F21) -> 1279509 | G28: =SUM(G26,G21) -> 1503189.3 | H28: =SUM(H26,H21) -> 1801399.9 | I28: =SUM(I26,I21) -> 2194961.1 | J28: =SUM(J26,J21) -> 2709697.3 | ... L28: =SUM(L26,L21) -> 4237353.3
B30: Revolver/Short term debt | C30: 0 | D30: 0 | E30: 0 | F30: =MIN(CashFlow!F23,0) -> 0 | G30: =MIN(CashFlow!G23,0) -> 0 | H30: =MIN(CashFlow!H23,0) -> 0 | I30: =MIN(CashFlow!I23,0) -> 0 | J30: =MIN(CashFlow!J23,0) -> 0 | K30: =MIN(CashFlow!K23,0) -> 0 | L30: =MIN(CashFlow!L23,0) -> 0
B31: Accounts payable/Accurals | C31: =14311+40468 -> 54779 | D31: =17234+59219 -> 76453 | E31: =25573+69822 -> 95395 | F31: =F11*IncState!F16 -> 114881.33 | G31: =G11*IncState!G16 -> 137934.55 | H31: =H11*IncState!H16 -> 165115.85 | I31: =I11*IncState!I16 -> 197055.48 | J31: =J11*IncState!J16 -> 234457.48 | K31: =K11*IncState!K16 -> 278103.81 | L31: =L11*IncState!L16 -> 328857.8
B32: Other current liabilities | C32: 29539 | D32: 32583 | E32: 37241 | F32: =F12*IncState!F15 -> 45620.225 | G32: =G12*IncState!G15 -> 55734.229 | H32: =H12*IncState!H15 -> 67906.584 | I32: =I12*IncState!I15 -> 82513.291 | J32: =J12*IncState!J15 -> 99989.606 | K32: =K12*IncState!K15 -> 120837.44 | L32: =L12*IncState!L15 -> 145633.28
B33: Total current liabilities | C33: =SUM(C30:C32) -> 84318 | D33: =SUM(D30:D32) -> 109036 | E33: =SUM(E30:E32) -> 132636 | F33: =SUM(F30:F32) -> 160501.56 | G33: =SUM(G30:G32) -> 193668.78 | H33: =SUM(H30:H32) -> 233022.43 | I33: =SUM(I30:I32) -> 279568.77 | J33: =SUM(J30:J32) -> 334447.09 | ... L33: =SUM(L30:L32) -> 474491.08
B35: Long-term debt, including current maturities | C35: 0 | D35: 0 | E35: 0 | F35: 0 | G35: 0 | H35: 0 | I35: 0 | J35: 0 | K35: 0 | L35: 0
B36: Other long-term liabilities | C36: =28+538+285194 -> 285760 | D36: =79+303615+225 -> 303919 | E36: =341467 -> 341467 | F36: =BalSheet!F13*IncState!F15 -> 418297.08 | G36: =BalSheet!G13*IncState!G15 -> 511033.54 | H36: =BalSheet!H13*IncState!H15 -> 622643.26 | I36: =BalSheet!I13*IncState!I15 -> 756573.83 | J36: =BalSheet!J13*IncState!J15 -> 916816.16 | K36: =BalSheet!K13*IncState!K15 -> 1107972.3 | L36: =BalSheet!L13*IncState!L15 -> 1335328.3
B37: Total non-current liabilities | C37: =SUM(C35:C36) -> 285760 | D37: =SUM(D35:D36) -> 303919 | E37: =SUM(E35:E36) -> 341467 | F37: =SUM(F35:F36) -> 418297.08 | G37: =SUM(G35:G36) -> 511033.54 | H37: =SUM(H35:H36) -> 622643.26 | I37: =SUM(I35:I36) -> 756573.83 | J37: =SUM(J35:J36) -> 916816.16 | ... L37: =SUM(L35:L36) -> 1335328.3
B39: Equity | C39: 213805 | D39: 570802 | E39: 695566 | F39: =Calcs!F16 -> 700710.41 | G39: =Calcs!G16 -> 798486.96 | H39: =Calcs!H16 -> 945734.21 | I39: =Calcs!I16 -> 1158818.5 | J39: =Calcs!J16 -> 1458434.1 | K39: =Calcs!K16 -> 1870551.5 | L39: =Calcs!L16 -> 2427534
A40: * | B40: TOTAL LIABILITIES & EQUITY | C40: =SUM(C39,C37,C33) -> 583883 | D40: =SUM(D39,D37,D33) -> 983757 | E40: =SUM(E39,E37,E33) -> 1169669 | F40: =SUM(F39,F37,F33) -> 1279509 | G40: =SUM(G39,G37,G33) -> 1503189.3 | H40: =SUM(H39,H37,H33) -> 1801399.9 | I40: =SUM(I39,I37,I33) -> 2194961.1 | J40: =SUM(J39,J37,J33) -> 2709697.3 | ... L40: =SUM(L39,L37,L33) -> 4237353.3
A42: * | B42: Balance check | C42: =C40-C28 -> 0 | D42: =D40-D28 -> 0 | E42: =E40-E28 -> 0 | F42: =F40-F28 -> 0 | G42: =G40-G28 -> 0 | H42: =H40-H28 -> 0 | I42: =I40-I28 -> 0 | J42: =J40-J28 -> 0 | ... L42: =L40-L28 -> 0

Sheet CashFlow
A1: =CoName -> Cava Group Inc. | C1: Hist. | D1: Hist. | E1: Hist. | F1: Proj. | G1: Proj. | H1: Proj. | I1: Proj. | J1: Proj. | K1: Proj. | L1: Proj.
A2: Cash flow statement | C2: 2022 | D2: =C2+1 -> 2023 | E2: =D2+1 -> 2024 | F2: =E2+1 -> 2025 | G2: =F2+1 -> 2026 | H2: =G2+1 -> 2027 | I2: =H2+1 -> 2028 | J2: =I2+1 -> 2029 | K2: =J2+1 -> 2030 | L2: =K2+1 -> 2031
B3: Net Income | F3: =IncState!F33 -> 5144.4148 | G3: =IncState!G33 -> 97776.548 | H3: =IncState!H33 -> 147247.25 | I3: =IncState!I33 -> 213084.26 | J3: =IncState!J33 -> 299615.59 | K3: =IncState!K33 -> 412117.44 | L3: =IncState!L33 -> 556982.51
B4: Depreciation | F4: =IncState!F20 -> 67610.376 | G4: =IncState!G20 -> 73347.036 | H4: =IncState!H20 -> 80554.158 | I4: =IncState!I20 -> 89337.8 | J4: =IncState!J20 -> 99803.249 | K4: =IncState!K20 -> 112049.17 | L4: =IncState!L20 -> 126160.15
B5: Amortization | F5: =IncState!F21 -> 0 | G5: =IncState!G21 -> 0 | H5: =IncState!H21 -> 0 | I5: =IncState!I21 -> 0 | J5: =IncState!J21 -> 0 | K5: =IncState!K21 -> 0 | L5: =IncState!L21 -> 0
B6: (inc) / dec in OWC | F6: =Calcs!F25 -> 17378.745 | G6: =Calcs!G25 -> 20546.538 | H6: =Calcs!H25 -> 24209.36 | I6: =Calcs!I25 -> 28427.332 | J6: =Calcs!J25 -> 33264.406 | K6: =Calcs!K25 -> 38787.884 | L6: =Calcs!L25 -> 45067.731
B7: (inc) / dec in LT assets | F7: =BalSheet!E25-BalSheet!F25 -> 65676.516 | G7: =BalSheet!F25-BalSheet!G25 -> -2617.2759 | H7: =BalSheet!G25-BalSheet!H25 -> -3149.9308 | I7: =BalSheet!H25-BalSheet!I25 -> -3779.8858 | J7: =BalSheet!I25-BalSheet!J25 -> -4522.4758 | K7: =BalSheet!J25-BalSheet!K25 -> -5394.9484 | L7: =BalSheet!K25-BalSheet!L25 -> -6416.6042
B8: inc / (dec) in LT liabilities | F8: =BalSheet!F36-BalSheet!E36 -> 76830.075 | G8: =BalSheet!G36-BalSheet!F36 -> 92736.462 | H8: =BalSheet!H36-BalSheet!G36 -> 111609.72 | I8: =BalSheet!I36-BalSheet!H36 -> 133930.57 | J8: =BalSheet!J36-BalSheet!I36 -> 160242.34 | K8: =BalSheet!K36-BalSheet!J36 -> 191156.17 | L8: =BalSheet!L36-BalSheet!K36 -> 227355.92
B9: CFFO | F9: =SUM(F3:F8) -> 232640.13 | G9: =SUM(G3:G8) -> 281789.31 | H9: =SUM(H3:H8) -> 360470.56 | I9: =SUM(I3:I8) -> 461000.07 | J9: =SUM(J3:J8) -> 588403.1 | K9: =SUM(K3:K8) -> 748715.72 | L9: =SUM(L3:L8) -> 949149.7
B11: Capex | F11: =-Calcs!F7 -> -126557.73 | G11: =-Calcs!G7 -> -147404.2 | H11: =-Calcs!H7 -> -170810.93 | I11: =-Calcs!I7 -> -196876.08 | J11: =-Calcs!J7 -> -225636.91 | K11: =-Calcs!K7 -> -257047.2 | L11: =-Calcs!L7 -> -290949.98
B12: CFFI | F12: =F11 -> -126557.73 | G12: =G11 -> -147404.2 | H12: =H11 -> -170810.93 | I12: =I11 -> -196876.08 | J12: =J11 -> -225636.91 | K12: =K11 -> -257047.2 | L12: =L11 -> -290949.98
B14: Div payments | F14: 0 | G14: 0 | H14: 0 | I14: 0 | J14: 0 | K14: 0 | L14: 0
B15: Share activity | F15: 0 | G15: 0 | H15: 0 | I15: 0 | J15: 0 | K15: 0 | L15: 0
B16: Debt issuance | F16: 0 | G16: 0 | H16: 0 | I16: 0 | J16: 0 | K16: 0 | L16: 0
B17: CFFF | F17: =SUM(F14:F16) -> 0 | G17: =SUM(G14:G16) -> 0 | H17: =SUM(H14:H16) -> 0 | I17: =SUM(I14:I16) -> 0 | J17: =SUM(J14:J16) -> 0 | K17: =SUM(K14:K16) -> 0 | L17: =SUM(L14:L16) -> 0
B19: Net changes in Cash | F19: =SUM(F17,F12,F9) -> 106082.39 | G19: =SUM(G17,G12,G9) -> 134385.11 | H19: =SUM(H17,H12,H9) -> 189659.63 | I19: =SUM(I17,I12,I9) -> 264123.99 | J19: =SUM(J17,J12,J9) -> 362766.2 | K19: =SUM(K17,K12,K9) -> 491668.52 | L19: =SUM(L17,L12,L9) -> 658199.72
B21: Beginning balance | F21: =BalSheet!E17 -> 346845.74 | G21: =BalSheet!F17 -> 452928.13 | H21: =BalSheet!G17 -> 587313.24 | I21: =BalSheet!H17 -> 776972.87 | J21: =BalSheet!I17 -> 1041096.9 | K21: =BalSheet!J17 -> 1403863.1 | L21: =BalSheet!K17 -> 1895531.6
B22: =B19 -> Net changes in Cash | F22: =F19 -> 106082.39 | G22: =G19 -> 134385.11 | H22: =H19 -> 189659.63 | I22: =I19 -> 264123.99 | J22: =J19 -> 362766.2 | K22: =K19 -> 491668.52 | L22: =L19 -> 658199.72
B23: Ending cash | F23: =SUM(F21:F22) -> 452928.13 | G23: =SUM(G21:G22) -> 587313.24 | H23: =SUM(H21:H22) -> 776972.87 | I23: =SUM(I21:I22) -> 1041096.9 | J23: =SUM(J21:J22) -> 1403863.1 | K23: =SUM(K21:K22) -> 1895531.6 | L23: =SUM(L21:L22) -> 2553731.3

Sheet Free Cash Flow
A1: =CoName -> Cava Group Inc. | C1: Hist. | D1: Hist. | E1: Hist. | F1: Proj. | G1: Proj. | H1: Proj. | I1: Proj. | J1: Proj. | K1: Proj. | L1: Proj.
A2: Free Cash Flows | C2: 2022 | D2: =C2+1 -> 2023 | E2: =D2+1 -> 2024 | F2: =E2+1 -> 2025 | G2: =F2+1 -> 2026 | H2: =G2+1 -> 2027 | I2: =H2+1 -> 2028 | J2: =I2+1 -> 2029 | K2: =J2+1 -> 2030 | L2: =K2+1 -> 2031
A3: * | B3: Sales | F3: =IncState!F15 -> 1180548.4 | G3: =IncState!G15 -> 1442276 | H3: =IncState!H15 -> 1757269.1 | I3: =IncState!I15 -> 2135257.7 | J3: =IncState!J15 -> 2587505.2 | K3: =IncState!K15 -> 3127000.1 | L3: =IncState!L15 -> 3768660.5
B4: EBIT | F4: =IncState!F18 -> 76430.519 | G4: =IncState!G18 -> 122220.68 | H4: =IncState!H18 -> 184059.06 | I4: =IncState!I18 -> 266355.32 | J4: =IncState!J18 -> 374519.48 | K4: =IncState!K18 -> 515146.8 | L4: =IncState!L18 -> 696228.13
B5: Effective Tax Rate | F5: =Assumptions!F16 -> 0.2 | G5: =Assumptions!G16 -> 0.2 | H5: =Assumptions!H16 -> 0.2 | I5: =Assumptions!I16 -> 0.2 | J5: =Assumptions!J16 -> 0.2 | K5: =Assumptions!K16 -> 0.2 | L5: =Assumptions!L16 -> 0.2
A7: * | B7: NOPAT | F7: =F4*(1-F5) -> 61144.415 | G7: =G4*(1-G5) -> 97776.548 | H7: =H4*(1-H5) -> 147247.25 | I7: =I4*(1-I5) -> 213084.26 | J7: =J4*(1-J5) -> 299615.59 | K7: =K4*(1-K5) -> 412117.44 | L7: =L4*(1-L5) -> 556982.51
B8: Depreciation | F8: =CashFlow!F4 -> 67610.376 | G8: =CashFlow!G4 -> 73347.036 | H8: =CashFlow!H4 -> 80554.158 | I8: =CashFlow!I4 -> 89337.8 | J8: =CashFlow!J4 -> 99803.249 | K8: =CashFlow!K4 -> 112049.17 | L8: =CashFlow!L4 -> 126160.15
B9: Amortization | F9: =CashFlow!F5 -> 0 | G9: =CashFlow!G5 -> 0 | H9: =CashFlow!H5 -> 0 | I9: =CashFlow!I5 -> 0 | J9: =CashFlow!J5 -> 0 | K9: =CashFlow!K5 -> 0 | L9: =CashFlow!L5 -> 0
B10: (inc) / dec in OWC | F10: =CashFlow!F6 -> 17378.745 | G10: =CashFlow!G6 -> 20546.538 | H10: =CashFlow!H6 -> 24209.36 | I10: =CashFlow!I6 -> 28427.332 | J10: =CashFlow!J6 -> 33264.406 | K10: =CashFlow!K6 -> 38787.884 | L10: =CashFlow!L6 -> 45067.731
B11: (inc) / dec in other long-term assets | F11: =CashFlow!F7 -> 65676.516 | G11: =CashFlow!G7 -> -2617.2759 | H11: =CashFlow!H7 -> -3149.9308 | I11: =CashFlow!I7 -> -3779.8858 | J11: =CashFlow!J7 -> -4522.4758 | K11: =CashFlow!K7 -> -5394.9484 | L11: =CashFlow!L7 -> -6416.6042
B12: inc / (dec) other long-term liabilities | F12: =CashFlow!F8 -> 76830.075 | G12: =CashFlow!G8 -> 92736.462 | H12: =CashFlow!H8 -> 111609.72 | I12: =CashFlow!I8 -> 133930.57 | J12: =CashFlow!J8 -> 160242.34 | K12: =CashFlow!K8 -> 191156.17 | L12: =CashFlow!L8 -> 227355.92
B13: (Capex) | F13: =CashFlow!F11 -> -126557.73 | G13: =CashFlow!G11 -> -147404.2 | H13: =CashFlow!H11 -> -170810.93 | I13: =CashFlow!I11 -> -196876.08 | J13: =CashFlow!J11 -> -225636.91 | K13: =CashFlow!K11 -> -257047.2 | L13: =CashFlow!L11 -> -290949.98
A15: * | B15: Free Cash Flow | F15: =SUM(F7:F13) -> 162082.39 | G15: =SUM(G7:G13) -> 134385.11 | H15: =SUM(H7:H13) -> 189659.63 | I15: =SUM(I7:I13) -> 264123.99 | J15: =SUM(J7:J13) -> 362766.2 | K15: =SUM(K7:K13) -> 491668.52 | L15: =SUM(L7:L13) -> 658199.72

Sheet WACC
A1: =CoName -> Cava Group Inc.
A3: * | B3: WACC | G3: Comp | H3: Levered beta | I3: Gross debt | J3: Market cap | K3: Debt/Mcap | L3: MTR | M3: Unlevered beta
B4: Tax Rate | E4: =Assumptions!F16 -> 0.2 | L4: =E4 -> 0.2 | M4: =H4/((1+K4*(1-L4))) -> 0
B5: Risk free rate | E5: 0.041 | L5: =L4 -> 0.2 | M5: =H5/((1+K5*(1-L5))) -> 0
B6: Market risk Premium | E6: 0.05 | L6: =L5 -> 0.2 | M6: =H6/((1+K6*(1-L6))) -> 0
B7: Beta | E7: 0.82 | L7: =L6 -> 0.2 | M7: =H7/((1+K7*(1-L7))) -> 0
B8: Cost of Equity | E8: =E5+E6*E7 -> 0.082
B9: % Equity | E9: 1 | G9: Industry beta (average) | M9: =AVERAGE(M4:M7) -> 0
B10: % Debt | E10: =MAIN!F8/MAIN!F6 -> 0
B11: Cost of debt | E11: =Assumptions!F23 -> 0.05 | G11: Re-levered beta | M11: =M9*(1+E10*(1-E4)) -> 0
B12: Post tax cost of debt | E12: =E11*(1-E4) -> 0.04
A13: * | B13: WACC | E13: =WACC!E8*WACC!E9+WACC!E12*WACC!E10 -> 0.082
B14: Long Term growth rate | E14: 0.025

Sheet DCF Model
A1: =CoName -> Cava Group Inc. | D1: Proj. | E1: Proj. | F1: Proj. | G1: Proj. | H1: Proj. | I1: Proj. | J1: Proj.
A2: Discount Model Year count | D2: 0.5 | E2: =D2+1 -> 1.5 | F2: =E2+1 -> 2.5 | G2: =F2+1 -> 3.5 | H2: =G2+1 -> 4.5 | I2: =H2+1 -> 5.5 | J2: =I2+1 -> 6.5
B3: Discount Factor | D3: =1/(1+$K$17)^D2 -> 0.96136071 | E3: =1/(1+$K$17)^E2 -> 0.88850343 | F3: =1/(1+$K$17)^F2 -> 0.82116768 | G3: =1/(1+$K$17)^G2 -> 0.75893501 | H3: =1/(1+$K$17)^H2 -> 0.70141868 | I3: =1/(1+$K$17)^I2 -> 0.64826126 | J3: =1/(1+$K$17)^J2 -> 0.5991324
B4: PV FCF | D4: =D3*'Free Cash Flow'!F15 -> 155819.65 | E4: =E3*'Free Cash Flow'!G15 -> 119401.63 | F4: =F3*'Free Cash Flow'!H15 -> 155742.36 | G4: =G3*'Free Cash Flow'!I15 -> 200452.94 | H4: =H3*'Free Cash Flow'!J15 -> 254450.99 | I4: =I3*'Free Cash Flow'!K15 -> 318729.65 | J4: =J3*'Free Cash Flow'!L15 -> 394348.78 | K4: =(J4*(1+K18))/(K17-K18) -> 7091359.6
A6: Value Calculation | E6: Multiples Calculation
B7: Total PV of FCFs | C7: =SUM(D4:J4) -> 1598946 | E7: Total PV of FCFs | G7: =C7 -> 1598946
B8: PV of TV | C8: =K4*J3 -> 4248663.3 | E8: Multiple TV | G8: =G10*J3*IncState!L22 -> 7390791.9
B9: EV | C9: =SUM(C7:C8) -> 5847609.3 | E9: EV | G9: =SUM(G7:G8) -> 8989737.9
E10: Implied EBITDA multiple | G10: 15
B12: Cash & Cash Equiv | C12: =MAIN!F7 -> 387685 | E12: Cash & Cash Equiv | G12: =C12 -> 387685
B13: Debt & Claims | C13: =MAIN!F8 -> 0 | E13: Debt & Claims | G13: =C13 -> 0
B14: NCI | C14: 0 | E14: NCI | G14: 0
B15: Equity Value | C15: =C9+C12-SUM(C13:C14) -> 6235294.3 | E15: Equity Value | G15: =G9+G12-SUM(G13:G14) -> 9377422.9
B17: Diluted S/O | C17: =MAIN!F5 -> 115986.12 | E17: Diluted S/O | G17: =C17 -> 115986.12 | I17: WACC | K17: =WACC!E13 -> 0.082
A18: * | B18: Implied Share Price | C18: =C15/C17 -> 53.758969 | E18: Implied Share Price | G18: =G15/G17 -> 80.849527 | I18: Long Term growth rate | K18: 0.025
A20: Sensitivity analysis
C22: Discount rate variance | E22: 0.005 | H22: Discount rate variance | J22: 0.005
C23: Implied growth rate variance | E23: 0.0025 | H23: TV multiple variance | J23: 2
E25: LTGR | J25: Exit Mult.
C26: =C18 -> 53.758969 | D26: =E26-E23 -> 0.0225 | E26: 0.025 | F26: =E26+E23 -> 0.0275 | H26: =G18 -> 80.849527 | I26: =J26-J23 -> 13 | J26: 15 | K26: =J26+J23 -> 17
C27: =C28+$E$22 -> 0.0845 | D27: 49.595105 | E27: 51.047981 | F27: 52.628301 | H27: =C27 -> 0.0845 | I27: 71.396403 | J27: 79.766082 | K27: 88.13576
C28: =C29+$E$22 -> 0.0795 | D28: 54.921798 | E28: 56.745477 | F28: 58.744511 | H28: =C28 -> 0.0795 | I28: 73.326597 | J28: 81.951489 | K28: 90.576382
C29: 0.0745 | D29: 61.389788 | E29: 63.71684 | F29: 66.291451 | H29: =C29 -> 0.0745 | I29: 75.323301 | J29: 84.212429 | K29: 93.101557
C30: =C29-$E$22 -> 0.0695 | D30: 69.373955 | E30: 72.402712 | F30: 75.792035 | H30: =C30 -> 0.0695 | I30: 77.389154 | J30: 86.551902 | K30: 95.714651
C31: =C30-$E$22 -> 0.0645 | D31: 79.428683 | E31: 83.467901 | F31: 88.052959 | H31: =C31 -> 0.0645 | I31: 79.526915 | J31: 88.973048 | K31: 98.419181
