Workbook
Name Ccy: MAIN!$C$6
Name circ: MAIN!$C$9
Name CoName: MAIN!$C$4
Name g: #REF!
Name IQ_CH: 110000
Name IQ_CQ: 5000
Name IQ_CY: 10000
Name IQ_DAILY: 500000
Name IQ_FH: 100000
Name IQ_FQ: 500
Name IQ_FY: 1000
Name IQ_LTM: 2000
Name IQ_MONTH: 15000
Name IQ_NTM: 6000
Name IQ_WEEK: 50000
Name IQ_YTD: 3000
Name OpCase: [1]DCF!$E$98
Name ScenarioREV: Assumptions!$D$4
Name TTS: #REF!
Name Units: MAIN!$C$7

Sheet MAIN
A1: =CoName -> Chipotle Mexican Grill Inc.
A2: Model Details
B4: Company name | C4: Chipotle Mexican Grill Inc. | E4: Current Stock Price | F4: 34
B5: Latest BS date | C5: 247.43 | E5: Diluted s/o | F5: 1322278
B6: Currency | C6: USD | E6: Mkt Cap | F6: =F5*F4 -> 44957452
B7: Units | C7: t | E7: Cash | F7: =698743+722531 -> 1421274
B8: Analyst name | C8: Alan Chen | E8: Debt | F8: 0
B9: Circular switch | C9: 0 | E9: EV | F9: =F6-F7+F8 -> 43536178
E11: DCF | F11: Terminal Mult
D12: Implied | E12: ='DCF Model'!C18 -> 33.727535 | F12: ='DCF Model'!G18 -> 38.924937
D13: Difference | E13: =E12/$F$4-1 -> -0.0080136883 | F13: =F12/$F$4-1 -> 0.14485108

Sheet Assumptions
A1: =CoName -> Chipotle Mexican Grill Inc. | C1: Hist. | D1: Hist. | E1: Hist. | F1: Proj. | G1: Proj. | H1: Proj. | I1: Proj. | J1: Proj.
A2: * | B2: Income Statement | C2: 44926 | D2: 45291 | E2: 45657 | F2: 46022 | G2: 46387 | H2: 46752 | I2: 47118 | J2: 47483
B4: Operating Case | D4: 1
D5: Variance
B6: Street Case | D6: 0 | F6: =Revenue!O8 -> 0.050618085 | G6: =Revenue!P8 -> 0.074382494 | H6: =Revenue!Q8 -> 0.09934478 | I6: =Revenue!R8 -> 0.099433791 | J6: =Revenue!S8 -> 0.099510749
B7: Optimistic Case | D7: 0.025 | F7: =F6+$D$7 -> 0.075618085 | G7: =G6+$D$7 -> 0.099382494 | H7: =H6+$D$7 -> 0.12434478 | I7: =I6+$D$7 -> 0.12443379 | J7: =J6+$D$7 -> 0.12451075
B8: Pessimistic Case | D8: -0.025 | F8: =F6+$D$8 -> 0.025618085 | G8: =G6+$D$8 -> 0.049382494 | H8: =H6+$D$8 -> 0.07434478 | I8: =I6+$D$8 -> 0.074433791 | J8: =J6+$D$8 -> 0.074510749
B10: Revenue Growth | C10: =Revenue!D8 -> 0.14410789 | D10: =Revenue!E8 -> 0.14325962 | E10: =Revenue!J8 -> 0.12562065 | F10: =CHOOSE(ScenarioREV,F6,F7,F8) -> 0.050618085 | G10: =CHOOSE(ScenarioREV,G6,G7,G8) -> 0.074382494 | H10: =CHOOSE(ScenarioREV,H6,H7,H8) -> 0.09934478 | I10: =CHOOSE(ScenarioREV,I6,I7,I8) -> 0.099433791 | J10: =CHOOSE(ScenarioREV,J6,J7,J8) -> 0.099510749
B11: COGS % of sales | C11: =IncState!C16/IncState!C15 -> 0.80027058 | D11: =IncState!D16/IncState!D15 -> 0.77801105 | E11: =IncState!E16/IncState!E15 -> 0.76897207 | F11: =E11-0.005 -> 0.76397207 | G11: =F11-0.005 -> 0.75897207 | H11: =G11-0.005 -> 0.75397207 | I11: =H11-0.005 -> 0.74897207 | J11: =I11-0.005 -> 0.74397207
B12: SG&A % of sales | C12: =IncState!C17/IncState!C15 -> 0.065340329 | D12: =IncState!D17/IncState!D15 -> 0.064182185 | E12: =IncState!E17/IncState!E15 -> 0.061648582 | F12: =E12-0.001 -> 0.060648582 | G12: =F12-0.001 -> 0.059648582 | H12: =G12-0.001 -> 0.058648582 | I12: =H12-0.001 -> 0.057648582 | J12: =I12-0.001 -> 0.056648582
B13: Amortization $ Amt | C13: 0 | D13: 0 | E13: 0 | F13: =E13 -> 0 | G13: =F13 -> 0 | H13: =G13 -> 0 | I13: =H13 -> 0 | J13: =I13 -> 0
B14: Non recurring income / (expense) | C14: 0 | D14: 0 | E14: 0 | F14: 0 | G14: 0 | H14: 0 | I14: 0 | J14: 0
B15: Other Income / (expense) | C15: 0 | D15: 0 | E15: 0 | F15: 0 | G15: 0 | H15: 0 | I15: 0 | J15: 0
B16: Effective tax rate | C16: =IncState!C33/IncState!C31 -> 0.23903732 | D16: =IncState!D33/IncState!D31 -> 0.2417572 | E16: =IncState!E33/IncState!E31 -> 0.23684852 | F16: 0.26 | G16: =F16-0.01 -> 0.25 | H16: =G16-0.01 -> 0.24 | I16: =H16 -> 0.24 | J16: =I16 -> 0.24
B17: Basic WASO | C17: =IncState!C37 -> 1392543 | D17: =IncState!D37 -> 1377768 | E17: =IncState!E37 -> 1368343 | F17: =E17-(F33/-MAIN!$F$4) -> 1357754.8 | G17: =F17-(G33/-MAIN!$F$4) -> 1347166.5 | H17: =G17-(H33/-MAIN!$F$4) -> 1336578.3 | I17: =H17-(I33/-MAIN!$F$4) -> 1325990.1 | J17: =I17-(J33/-MAIN!$F$4) -> 1315401.8
B18: Diluted WASO | C18: =IncState!C38 -> 1403077 | D18: =IncState!D38 -> 1385500 | E18: =IncState!E38 -> 1376555 | F18: =E18 -> 1376555 | G18: =F18 -> 1376555 | H18: =G18 -> 1376555 | I18: =H18 -> 1376555 | J18: =I18 -> 1376555
A20: * | B20: Debt | C20: 44926 | D20: 45291 | E20: 45657 | F20: 46022 | G20: 46387 | H20: 46752 | I20: 47118 | J20: 47483
B22: Interest rate on Revolver | D22: NO REVOLVER | F22: =E22 -> 0 | G22: =F22 -> 0 | H22: =G22 -> 0 | I22: =H22 -> 0 | J22: =I22 -> 0
B23: Interest rate on long-term debt | D23: NO DEBT | F23: =E23 -> 0 | G23: =F23 -> 0 | H23: =G23 -> 0 | I23: =H23 -> 0 | J23: =I23 -> 0
B24: Interest rate on cash | C24: =IncState!C28/BalSheet!C18 -> 0.027452644 | D24: =IncState!D28/BalSheet!D18 -> 0.054640505 | E24: =IncState!E28/BalSheet!E18 -> 0.074925359 | F24: =AVERAGE(C24:E24) -> 0.052339503 | G24: =F24 -> 0.052339503 | H24: =G24 -> 0.052339503 | I24: =H24 -> 0.052339503 | J24: =I24 -> 0.052339503
B26: Issuance of long-term debt | D26: NO DEBT | F26: 0 | G26: 0 | H26: 0 | I26: 0 | J26: 0
B27: Repayment of long-term debt | D27: NO DEBT | F27: 0 | G27: 0 | H27: 0 | I27: 0 | J27: 0
A29: * | B29: Calcs | C29: 44926 | D29: 45291 | E29: 45657 | F29: 46022 | G29: 46387 | H29: 46752 | I29: 47118 | J29: 47483
B31: CapEx % of Sales | C31: =442475/IncState!C15 -> 0.051244103 | D31: =479164/IncState!D15 -> 0.048539408 | E31: =560731/IncState!E15 -> 0.049561454 | F31: =E31 -> 0.049561454 | G31: =F31 -> 0.049561454 | H31: =G31 -> 0.049561454 | I31: =H31 -> 0.049561454 | J31: =I31 -> 0.049561454
B32: Depreciation % of beginning PP&E | D32: =IncState!D21/BalSheet!C24 -> 0.060795854 | E32: =IncState!E21/BalSheet!D24 -> 0.058280419 | F32: =E32 -> 0.058280419 | G32: =F32 -> 0.058280419 | H32: =G32 -> 0.058280419 | I32: =H32 -> 0.058280419 | J32: =I32 -> 0.058280419
B33: Share issuance / (repurchases) | C33: =-1713.277*62.31 -> -106754.29 | D33: =-2348.512*59.14 -> -138891 | E33: =-1474.582*58.05 -> -85599.485 | F33: =-1800000/5 -> -360000 | G33: =F33 -> -360000 | H33: =G33 -> -360000 | I33: =H33 -> -360000 | J33: =I33 -> -360000
A35: * | B35: Shareholder information | C35: 44926 | D35: 45291 | E35: 45657 | F35: 46022 | G35: 46387 | H35: 46752 | I35: 47118 | J35: 47483
B37: Basic WASO | C37: =C17 -> 1392543 | D37: =D17 -> 1377768 | E37: =E17 -> 1368343 | F37: =F17 -> 1357754.8 | G37: =G17 -> 1347166.5 | H37: =H17 -> 1336578.3 | I37: =I17 -> 1325990.1 | J37: =J17 -> 1315401.8
B38: Diluted WASO | C38: =C18 -> 1403077 | D38: =D18 -> 1385500 | E38: =E18 -> 1376555 | F38: =F18 -> 1376555 | G38: =G18 -> 1376555 | H38: =H18 -> 1376555 | I38: =I18 -> 1376555 | J38: =J18 -> 1376555
A40: * | B40: Balance Sheet - Assets | C40: 44926 | D40: 45291 | E40: 45657 | F40: 46022 | G40: 46387 | H40: 46752 | I40: 47118 | J40: 47483
B42: Operating Cash % of sales | C42: =BalSheet!C17/IncState!C15 -> 0.015 | D42: =BalSheet!D17/IncState!D15 -> 0.015 | E42: =BalSheet!E17/IncState!E15 -> 0.015 | F42: =E42 -> 0.015 | G42: =F42 -> 0.015 | H42: =G42 -> 0.015 | I42: =H42 -> 0.015 | J42: =I42 -> 0.015
B43: Accounts receivable % of sales | C43: =BalSheet!C19/IncState!C15 -> 0.012378032 | D43: =BalSheet!D19/IncState!D15 -> 0.011703718 | E43: =BalSheet!E19/IncState!E15 -> 0.012724489 | F43: =E43 -> 0.012724489 | G43: =F43 -> 0.012724489 | H43: =G43 -> 0.012724489 | I43: =H43 -> 0.012724489 | J43: =I43 -> 0.012724489
B44: Inventories % of COGS | C44: =BalSheet!C20/IncState!C16 -> 0.0051617512 | D44: =BalSheet!D20/IncState!D16 -> 0.0051181914 | E44: =BalSheet!E20/IncState!E16 -> 0.0056254933 | F44: =E44 -> 0.0056254933 | G44: =F44 -> 0.0056254933 | H44: =G44 -> 0.0056254933 | I44: =H44 -> 0.0056254933 | J44: =I44 -> 0.0056254933
B45: Other current assets % of sales | C45: =BalSheet!C21/IncState!C15 -> 0.015536584 | D45: =BalSheet!D21/IncState!D15 -> 0.017263782 | E45: =BalSheet!E21/IncState!E15 -> 0.014563297 | F45: =E45 -> 0.014563297 | G45: =F45 -> 0.014563297 | H45: =G45 -> 0.014563297 | I45: =H45 -> 0.014563297 | J45: =I45 -> 0.014563297
B47: Investments in unconsolidated entities | C47: =BalSheet!C26 -> 388055 | D47: =BalSheet!D26 -> 564488 | E47: =BalSheet!E26 -> 868025 | F47: =E47 -> 868025 | G47: =F47 -> 868025 | H47: =G47 -> 868025 | I47: =H47 -> 868025 | J47: =I47 -> 868025
B48: Other long-term assets % of sales | C48: =BalSheet!C27/IncState!C15 -> 0.010205854 | D48: =BalSheet!D27/IncState!D15 -> 0.0089788444 | E48: =BalSheet!E27/IncState!E15 -> 0.012689753 | F48: =E48 -> 0.012689753 | G48: =F48 -> 0.012689753 | H48: =G48 -> 0.012689753 | I48: =H48 -> 0.012689753 | J48: =I48 -> 0.012689753
A50: * | B50: Balance Sheet - Liabilities | C50: 44926 | D50: 45291 | E50: 45657 | F50: 46022 | G50: 46387 | H50: 46752 | I50: 47118 | J50: 47483
B52: Accounts payable % of COGS | C52: =BalSheet!C33/IncState!C16 -> 0.072728912 | D52: =BalSheet!D33/IncState!D16 -> 0.074590131 | E52: =BalSheet!E33/IncState!E16 -> 0.074983014 | F52: =E52 -> 0.074983014 | G52: =F52 -> 0.074983014 | H52: =G52 -> 0.074983014 | I52: =H52 -> 0.074983014 | J52: =I52 -> 0.074983014
B53: Other current liabilities % of sales | C53: =BalSheet!C34/IncState!C15 -> 0.048562351 | D53: =BalSheet!D34/IncState!D15 -> 0.046370571 | E53: =BalSheet!E34/IncState!E15 -> 0.045644309 | F53: =E53 -> 0.045644309 | G53: =F53 -> 0.045644309 | H53: =G53 -> 0.045644309 | I53: =H53 -> 0.045644309 | J53: =I53 -> 0.045644309
B54: Other long-term liabilities % of sales | C54: =BalSheet!C38/IncState!C15 -> 0.4212794 | D54: =BalSheet!D38/IncState!D15 -> 0.40029077 | E54: =BalSheet!E38/IncState!E15 -> 0.38714132 | F54: =E54 -> 0.38714132 | G54: =F54 -> 0.38714132 | H54: =G54 -> 0.38714132 | I54: =H54 -> 0.38714132 | J54: =I54 -> 0.38714132

Sheet Revenue
A1: =CoName -> Chipotle Mexican Grill Inc.
A2: Revenues | C2: 2021 | D2: 2022 | E2: 2023 | F2: Q124 | G2: Q224 | H2: Q324 | I2: Q424 | J2: 2024 | K2: Q125 | L2: Q225 | M2: Q325 | N2: Q425 | O2: 2025 | P2: =O2+1 -> 2026 | Q2: =P2+1 -> 2027 | R2: =Q2+1 -> 2028 | S2: =R2+1 -> 2029 | T2: =S2+1 -> 2030
A3: * | B3: U.S. food and beverage revenue | C3: 7457169 | D3: 8558001 | E3: 9804124 | F3: 2640397 | G3: 2902839 | H3: 2725898 | I3: =J3-SUM(F3:H3) -> 2776316 | J3: 11045450 | K3: 2807074 | L3: 2984846 | M3: 2923260 | N3: =M3*(1+N4) -> 2901335.6 | O3: =SUM(K3:N3) -> 11616516 | P3: =O3*(1+P4) -> 12487754 | Q3: =P3*(1+Q4) -> 13736530 | R3: =Q3*(1+R4) -> 15110183 | S3: =R3*(1+S4) -> 16621201 | T3: =S3*(1+T4) -> 18283321
B4: y/y | D4: =D3/C3-1 -> 0.14762063 | E4: =E3/D3-1 -> 0.14560912 | J4: =J3/E3-1 -> 0.12661264 | K4: =K3/F3-1 -> 0.063125735 | L4: =L3/G3-1 -> 0.028250619 | M4: =M3/H3-1 -> 0.072402562 | N4: -0.0075 | O4: =O3/J3-1 -> 0.051701429 | P4: 0.075 | Q4: 0.1 | R4: =Q4 -> 0.1 | S4: =R4 -> 0.1 | T4: =S4 -> 0.1
B5: U.S delivery service revenue | C5: 89892 | D5: 76651 | E5: 67525 | F5: 17359 | G5: 18153 | H5: 15497 | I5: =J5-SUM(F5:H5) -> 15273 | J5: 66282 | K5: 15370 | L5: 15584 | M5: 14136 | N5: =M5*(1+N6) -> 12581.04 | O5: =SUM(K5:N5) -> 57671.04 | P5: =O5*(1+P6) -> 54787.488 | Q5: =P5*(1+Q6) -> 52048.114 | R5: =Q5*(1+R6) -> 49445.708 | S5: =R5*(1+S6) -> 46973.423 | T5: =S5*(1+T6) -> 44624.751
B6: y/y | D6: =D5/C5-1 -> -0.14729898 | E6: =E5/D5-1 -> -0.11905911 | J6: =J5/E5-1 -> -0.018407997 | K6: =K5/F5-1 -> -0.11458033 | L6: =L5/G5-1 -> -0.14151931 | M6: =M5/H5-1 -> -0.08782345 | N6: -0.11 | O6: =O5/J5-1 -> -0.129914 | P6: -0.05 | Q6: =P6 -> -0.05 | R6: =Q6 -> -0.05 | S6: =R6 -> -0.05 | T6: =S6 -> -0.05
A7: * | B7: TOTAL REVENUES | C7: =SUM(C5,C3) -> 7547061 | D7: =SUM(D5,D3) -> 8634652 | E7: =SUM(E5,E3) -> 9871649 | F7: =SUM(F5,F3) -> 2657756 | G7: =SUM(G5,G3) -> 2920992 | H7: =SUM(H5,H3) -> 2741395 | I7: =SUM(I5,I3) -> 2791589 | J7: =SUM(J5,J3) -> 11111732 | ... T7: =SUM(T5,T3) -> 18327946
B8: y/y | D8: =D7/C7-1 -> 0.14410789 | E8: =E7/D7-1 -> 0.14325962 | J8: =J7/E7-1 -> 0.12562065 | K8: =K7/F7-1 -> 0.061965056 | L8: =L7/G7-1 -> 0.027195555 | M8: =M7/H7-1 -> 0.071496811 | N8: =N7/I7-1 -> 0.043820057 | O8: =O7/J7-1 -> 0.050618085 | P8: =P7/O7-1 -> 0.074382494 | Q8: =Q7/P7-1 -> 0.09934478 | R8: =R7/Q7-1 -> 0.099433791 | S8: =S7/R7-1 -> 0.099510749 | T8: =T7/S7-1 -> 0.099577277

Sheet Calcs
A1: =CoName -> Chipotle Mexican Grill Inc. | C1: Hist. | D1: Hist. | E1: Hist. | F1: Proj. | G1: Proj. | H1: Proj. | I1: Proj. | J1: Proj.
A2: Net PP&E | C2: 2022 | D2: =C2+1 -> 2023 | E2: =D2+1 -> 2024 | F2: =E2+1 -> 2025 | G2: =F2+1 -> 2026 | H2: =G2+1 -> 2027 | I2: =H2+1 -> 2028 | J2: =I2+1 -> 2029
B3: Capital expenditure % of sales | F3: =Assumptions!F31 -> 0.049561454 | G3: =Assumptions!G31 -> 0.049561454 | H3: =Assumptions!H31 -> 0.049561454 | I3: =Assumptions!I31 -> 0.049561454 | J3: =Assumptions!J31 -> 0.049561454
B4: Depreciation % of PP&E | F4: =Assumptions!F32 -> 0.058280419 | G4: =F4 -> 0.058280419 | H4: =G4 -> 0.058280419 | I4: =H4 -> 0.058280419 | J4: =I4 -> 0.058280419
B6: Beginning PP&E | F6: =E9 -> 6390253 | G6: =F9 -> 6606940.5 | H6: =G9 -> 6854819.2 | I6: =H9 -> 7151130 | J6: =I9 -> 7499359
B7: Capex | F7: =F3*IncState!F15 -> 589114.13 | G7: =G3*IncState!G15 -> 632933.91 | H7: =H3*IncState!H15 -> 695812.59 | I7: =I3*IncState!I15 -> 764999.87 | J7: =J3*IncState!J15 -> 841125.58
B8: Depreciation | F8: =F6*F4 -> 372426.62 | G8: =G6*G4 -> 385055.26 | H8: =H6*H4 -> 399501.73 | I8: =I6*I4 -> 416770.85 | J8: =J6*J4 -> 437065.79
B9: Ending PP&E | E9: =BalSheet!E24 -> 6390253 | F9: =F6+F7-F8 -> 6606940.5 | G9: =G6+G7-G8 -> 6854819.2 | H9: =H6+H7-H8 -> 7151130 | I9: =I6+I7-I8 -> 7499359 | J9: =J6+J7-J8 -> 7903418.8
A10: Equity | C10: =C2 -> 2022 | D10: =D2 -> 2023 | E10: =E2 -> 2024 | F10: =F2 -> 2025 | G10: =G2 -> 2026 | H10: =H2 -> 2027 | I10: =I2 -> 2028 | J10: =J2 -> 2029
B11: Share issuance/(repurchases) | F11: =Assumptions!F33 -> -360000 | G11: =Assumptions!G33 -> -360000 | H11: =Assumptions!H33 -> -360000 | I11: =Assumptions!I33 -> -360000 | J11: =Assumptions!J33 -> -360000
B13: Beginning balance | F13: =E16 -> 3655546 | G13: =F16 -> 4838189.5 | H13: =G16 -> 6215443.9 | I13: =H16 -> 7854769.6 | J13: =I16 -> 9763281.2
B14: Net income | F14: =IncState!F34 -> 1542643.5 | G14: =IncState!G34 -> 1737254.4 | H14: =IncState!H34 -> 1999325.7 | I14: =IncState!I34 -> 2268511.6 | J14: =IncState!J34 -> 2571642.3
B15: Share issuance / (repurchase) | F15: =F11 -> -360000 | G15: =G11 -> -360000 | H15: =H11 -> -360000 | I15: =I11 -> -360000 | J15: =J11 -> -360000
B16: Ending balance | E16: =BalSheet!E41 -> 3655546 | F16: =SUM(F13:F15) -> 4838189.5 | G16: =SUM(G13:G15) -> 6215443.9 | H16: =SUM(H13:H15) -> 7854769.6 | I16: =SUM(I13:I15) -> 9763281.2 | J16: =SUM(J13:J15) -> 11974923
A17: OWC | C17: =C10 -> 2022 | D17: =D10 -> 2023 | E17: =E10 -> 2024 | F17: =F10 -> 2025 | G17: =G10 -> 2026 | H17: =H10 -> 2027 | I17: =I10 -> 2028 | J17: =J10 -> 2029
B18: Operating Cash | E18: =BalSheet!E17 -> 169707.79 | F18: =BalSheet!F17 -> 178298.08 | G18: =BalSheet!G17 -> 191560.33 | H18: =BalSheet!H17 -> 210590.85 | I18: =BalSheet!I17 -> 231530.7 | J18: =BalSheet!J17 -> 254570.49
B19: =BalSheet!B20 -> Inventories | E19: =BalSheet!E20 -> 48942 | F19: =BalSheet!F20 -> 51085.012 | G19: =BalSheet!G20 -> 54525.636 | H19: =BalSheet!H20 -> 59547.58 | I19: =BalSheet!I20 -> 65034.464 | J19: =BalSheet!J20 -> 71028.731
B20: =BalSheet!B19 -> Accounts receivable | E20: =BalSheet!E19 -> 143963 | F20: =BalSheet!F19 -> 151250.13 | G20: =BalSheet!G19 -> 162500.49 | H20: =BalSheet!H19 -> 178644.07 | I20: =BalSheet!I19 -> 196407.33 | J20: =BalSheet!J19 -> 215951.97
B21: Other current assets | E21: =BalSheet!E21 -> 164767 | F21: =BalSheet!F21 -> 173107.19 | G21: =BalSheet!G21 -> 185983.33 | H21: =BalSheet!H21 -> 204459.81 | I21: =BalSheet!I21 -> 224790.02 | J21: =BalSheet!J21 -> 247159.05
B22: Accounts payables | E22: =BalSheet!E33 -> 652355 | F22: =BalSheet!F33 -> 680919.52 | G22: =BalSheet!G33 -> 726780.09 | H22: =BalSheet!H33 -> 793718.32 | I22: =BalSheet!I33 -> 866853.78 | J22: =BalSheet!J33 -> 946752.23
B23: Other current liabilities | E23: =BalSheet!E34 -> 516413 | F23: =BalSheet!F34 -> 542552.84 | G23: =BalSheet!G34 -> 582909.27 | H23: =BalSheet!H34 -> 640818.26 | I23: =BalSheet!I34 -> 704537.25 | J23: =BalSheet!J34 -> 774646.28
A24: * | B24: OWC | E24: =SUM(E18:E21)-SUM(E22:E23) -> -641388.21 | F24: =SUM(F18:F21)-SUM(F22:F23) -> -669731.94 | G24: =SUM(G18:G21)-SUM(G22:G23) -> -715119.56 | H24: =SUM(H18:H21)-SUM(H22:H23) -> -781294.27 | I24: =SUM(I18:I21)-SUM(I22:I23) -> -853628.52 | J24: =SUM(J18:J21)-SUM(J22:J23) -> -932688.27
B25: Change in OWC | F25: =E24-F24 -> 28343.738 | G25: =F24-G24 -> 45387.616 | H25: =G24-H24 -> 66174.709 | I25: =H24-I24 -> 72334.252 | J25: =I24-J24 -> 79059.754

Sheet Debt
A1: =CoName -> Chipotle Mexican Grill Inc. | C1: Hist. | D1: Hist. | E1: Hist. | F1: Proj. | G1: Proj. | H1: Proj. | I1: Proj. | J1: Proj.
A2: Assumptions | C2: 44926 | D2: 45291 | E2: 45657 | F2: 46022 | G2: 46387 | H2: 46752 | I2: 47118 | J2: 47483
B4: Interest rate on revolver | F4: =Assumptions!F22 -> 0 | G4: =Assumptions!G22 -> 0 | H4: =Assumptions!H22 -> 0 | I4: =Assumptions!I22 -> 0 | J4: =Assumptions!J22 -> 0
B5: Interest rate on long-term debt | F5: =Assumptions!F23 -> 0 | G5: =Assumptions!G23 -> 0 | H5: =Assumptions!H23 -> 0 | I5: =Assumptions!I23 -> 0 | J5: =Assumptions!J23 -> 0
B6: Interest rate on cash | F6: =Assumptions!F24 -> 0.052339503 | G6: =Assumptions!G24 -> 0.052339503 | H6: =Assumptions!H24 -> 0.052339503 | I6: =Assumptions!I24 -> 0.052339503 | J6: =Assumptions!J24 -> 0.052339503
B8: Issuance of long-term debt | F8: =Assumptions!F26 -> 0 | G8: =Assumptions!G26 -> 0 | H8: =Assumptions!H26 -> 0 | I8: =Assumptions!I26 -> 0 | J8: =Assumptions!J26 -> 0
B9: Repayment of long-term debt | F9: =Assumptions!F27 -> 0 | G9: =Assumptions!G27 -> 0 | H9: =Assumptions!H27 -> 0 | I9: =Assumptions!I27 -> 0 | J9: =Assumptions!J27 -> 0
A11: Revolver | C11: =C2 -> 44926 | D11: =D2 -> 45291 | E11: =E2 -> 45657 | F11: =F2 -> 46022 | G11: =G2 -> 46387 | H11: =H2 -> 46752 | I11: =I2 -> 47118 | J11: =J2 -> 47483
B12: Balance | F12: NO REVOLVER
B13: Interest rate
B14: Interest expense
A16: Long term debt | C16: =C11 -> 44926 | D16: =D11 -> 45291 | E16: =E11 -> 45657 | F16: =F11 -> 46022 | G16: =G11 -> 46387 | H16: =H11 -> 46752 | I16: =I11 -> 47118 | J16: =J11 -> 47483
B17: Beginning balance | F17: NO DEBT
B18: Issuance
B19: Repayment
B20: Ending balance
B21: Interest rate
B22: Interest expense
A24: Debt summary | C24: =C16 -> 44926 | D24: =D16 -> 45291 | E24: =E16 -> 45657 | F24: =F16 -> 46022 | G24: =G16 -> 46387 | H24: =H16 -> 46752 | I24: =I16 -> 47118 | J24: =J16 -> 47483
B25: Revolver | F25: NO DEBT
B26: Total long term debt
B27: Total debt
B28: Total interest expense
A30: Interest income | C30: =C11 -> 44926 | D30: =D11 -> 45291 | E30: =E11 -> 45657 | F30: =F11 -> 46022 | G30: =G11 -> 46387 | H30: =H11 -> 46752 | I30: =I11 -> 47118 | J30: =J11 -> 47483
B31: Excess Cash | F31: =BalSheet!F18 -> 2461949.9 | G31: =BalSheet!G18 -> 3967784.8 | H31: =BalSheet!H18 -> 5852041.5 | I31: =BalSheet!I18 -> 8007388.9 | J31: =BalSheet!J18 -> 10469184
B32: Interest rate | F32: =F6 -> 0.052339503 | G32: =G6 -> 0.052339503 | H32: =H6 -> 0.052339503 | I32: =I6 -> 0.052339503 | J32: =J6 -> 0.052339503
B33: Interest income | F33: =F31*F32 -> 128857.23 | G33: =G31*G32 -> 207671.88 | H33: =H31*H32 -> 306292.94 | I33: =I31*I32 -> 419102.75 | J33: =J31*J32 -> 547951.86

Sheet IncState
A1: =CoName -> Chipotle Mexican Grill Inc. | C1: Hist. | D1: Hist. | E1: Hist. | F1: Proj. | G1: Proj. | H1: Proj. | I1: Proj. | J1: Proj.
A2: Assumptions | C2: 44926 | D2: 45291 | E2: 45657 | F2: 46022 | G2: 46387 | H2: 46752 | I2: 47118 | J2: 47483
B4: Revenue growth | F4: =Assumptions!F10 -> 0.050618085 | G4: =Assumptions!G10 -> 0.074382494 | H4: =Assumptions!H10 -> 0.09934478 | I4: =Assumptions!I10 -> 0.099433791 | J4: =Assumptions!J10 -> 0.099510749
B5: Cost of goods sold as % of sales | F5: =Assumptions!F11 -> 0.76397207 | G5: =Assumptions!G11 -> 0.75897207 | H5: =Assumptions!H11 -> 0.75397207 | I5: =Assumptions!I11 -> 0.74897207 | J5: =Assumptions!J11 -> 0.74397207
B6: SG&A % of sales | F6: =Assumptions!F12 -> 0.060648582 | G6: =Assumptions!G12 -> 0.059648582 | H6: =Assumptions!H12 -> 0.058648582 | I6: =Assumptions!I12 -> 0.057648582 | J6: =Assumptions!J12 -> 0.056648582
B7: Amortization amount | F7: =Assumptions!F13 -> 0 | G7: =Assumptions!G13 -> 0 | H7: =Assumptions!H13 -> 0 | I7: =Assumptions!I13 -> 0 | J7: =Assumptions!J13 -> 0
B8: Non recurring items, amount | F8: =Assumptions!F14 -> 0 | G8: =Assumptions!G14 -> 0 | H8: =Assumptions!H14 -> 0 | I8: =Assumptions!I14 -> 0 | J8: =Assumptions!J14 -> 0
B9: Other income (expense), amt | F9: =Assumptions!F15 -> 0 | G9: =Assumptions!G15 -> 0 | H9: =Assumptions!H15 -> 0 | I9: =Assumptions!I15 -> 0 | J9: =Assumptions!J15 -> 0
B10: Effective tax rate | F10: =Assumptions!F16 -> 0.26 | G10: =Assumptions!G16 -> 0.25 | H10: =Assumptions!H16 -> 0.24 | I10: =Assumptions!I16 -> 0.24 | J10: =Assumptions!J16 -> 0.24
B11: Basic WASO | F11: =Assumptions!F17 -> 1357754.8 | G11: =Assumptions!G17 -> 1347166.5 | H11: =Assumptions!H17 -> 1336578.3 | I11: =Assumptions!I17 -> 1325990.1 | J11: =Assumptions!J17 -> 1315401.8
B12: Diluted WASO | F12: =Assumptions!F18 -> 1376555 | G12: =Assumptions!G18 -> 1376555 | H12: =Assumptions!H18 -> 1376555 | I12: =Assumptions!I18 -> 1376555 | J12: =Assumptions!J18 -> 1376555
A14: Income statement | C14: =C36 -> 44926 | D14: =D36 -> 45291 | E14: =E36 -> 45657 | F14: =F36 -> 46022 | G14: =G36 -> 46022 | H14: =H36 -> 46022 | I14: =I36 -> 46022 | J14: =J36 -> 46022
B15: Revenue | C15: 8634652 | D15: 9871649 | E15: 11313853 | F15: =E15*(1+F4) -> 11886539 | G15: =F15*(1+G4) -> 12770689 | H15: =G15*(1+H4) -> 14039390 | I15: =H15*(1+I4) -> 15435380 | J15: =I15*(1+J4) -> 16971366
B16: COGS | C16: =7474249-C17 -> 6910058 | D16: =8313836-D17 -> 7680252 | E16: =3374516+2789789+563374+1568482+335030+41897+26949 -> 8700037 | F16: =F15*F5 -> 9080983.5 | G16: =G15*G5 -> 9692596.3 | H16: =H15*H5 -> 10585308 | I16: =I15*I5 -> 11560669 | J16: =J15*J5 -> 12626223
B17: SG&A | C17: 564191 | D17: 633584 | E17: =9397520-E16 -> 697483 | F17: =F15*F6 -> 720901.71 | G17: =G15*G6 -> 761753.49 | H17: =H15*H6 -> 823390.34 | I17: =I15*I6 -> 889827.78 | J17: =J15*J6 -> 961403.84
A18: * | B18: EBIT | C18: =C15-SUM(C16:C17) -> 1160403 | D18: =D15-SUM(D16:D17) -> 1557813 | E18: =E15-SUM(E16:E17) -> 1916333 | F18: =F15-SUM(F16:F17) -> 2084653.3 | G18: =G15-SUM(G16:G17) -> 2316339.2 | H18: =H15-SUM(H16:H17) -> 2630691.7 | I18: =I15-SUM(I16:I17) -> 2984883.7 | J18: =J15-SUM(J16:J17) -> 3383739.9
B19: EBIT margin | C19: =C18/C15 -> 0.13438909 | D19: =D18/D15 -> 0.15780677 | E19: =E18/E15 -> 0.16937934 | F19: =F18/F15 -> 0.17537934 | G19: =G18/G15 -> 0.18137934 | H19: =H18/H15 -> 0.18737934 | I19: =I18/I15 -> 0.19337934 | J19: =J18/J15 -> 0.19937934
B21: Depreciation | C21: 286826 | D21: 319394 | E21: 335030 | F21: =Calcs!F8 -> 372426.62 | G21: =Calcs!G8 -> 385055.26 | H21: =Calcs!H8 -> 399501.73 | I21: =Calcs!I8 -> 416770.85 | J21: =Calcs!J8 -> 437065.79
B22: Amortization | C22: 0 | D22: 0 | E22: 0 | F22: =F7 -> 0 | G22: =G7 -> 0 | H22: =H7 -> 0 | I22: =I7 -> 0 | J22: =J7 -> 0
A23: * | B23: EBITDA | C23: =C18+C21 -> 1447229 | D23: =D18+D21 -> 1877207 | E23: =E18+E21 -> 2251363 | F23: =F18+F21 -> 2457080 | G23: =G18+G21 -> 2701394.4 | H23: =H18+H21 -> 3030193.5 | I23: =I18+I21 -> 3401654.5 | J23: =J18+J21 -> 3820805.7
B25: Non-recurring items | C25: 0 | D25: 0 | E25: 0 | F25: =F8 -> 0 | G25: =G8 -> 0 | H25: =H8 -> 0 | I25: =I8 -> 0 | J25: =J8 -> 0
B26: Other income (expense) | C26: 0 | D26: 0 | E26: 0 | F26: =F9 -> 0 | G26: =G9 -> 0 | H26: =H9 -> 0 | I26: =I9 -> 0 | J26: =J9 -> 0
B28: Interest income | C28: 21128 | D28: 62693 | E28: 93897 | F28: =IF(circ=1,Debt!F33,0) -> 0 | G28: =IF(circ=1,Debt!G33,0) -> 0 | H28: =IF(circ=1,Debt!H33,0) -> 0 | I28: =IF(circ=1,Debt!I33,0) -> 0 | J28: =IF(circ=1,Debt!J33,0) -> 0
B29: Interest expense | C29: 0 | D29: 0 | E29: 0 | F29: =IF(circ=1,Debt!F28,0) -> 0 | G29: =IF(circ=1,Debt!G28,0) -> 0 | H29: =IF(circ=1,Debt!H28,0) -> 0 | I29: =IF(circ=1,Debt!I28,0) -> 0 | J29: =IF(circ=1,Debt!J28,0) -> 0
A31: * | B31: Pretax Income | C31: =SUM(C18,C25:C26,C28)-C29 -> 1181531 | D31: =SUM(D18,D25:D26,D28)-D29 -> 1620506 | E31: =SUM(E18,E25:E26,E28)-E29 -> 2010230 | F31: =SUM(F18,F25:F26,F28)-F29 -> 2084653.3 | G31: =SUM(G18,G25:G26,G28)-G29 -> 2316339.2 | H31: =SUM(H18,H25:H26,H28)-H29 -> 2630691.7 | I31: =SUM(I18,I25:I26,I28)-I29 -> 2984883.7 | J31: =SUM(J18,J25:J26,J28)-J29 -> 3383739.9
B33: Tax expense | C33: 282430 | D33: 391769 | E33: 476120 | F33: =F31*F10 -> 542009.87 | G33: =G31*G10 -> 579084.8 | H33: =H31*H10 -> 631366.02 | I33: =I31*I10 -> 716372.08 | J33: =J31*J10 -> 812097.57
A34: * | B34: Net income | C34: =C31-C33 -> 899101 | D34: =D31-D33 -> 1228737 | E34: =E31-E33 -> 1534110 | F34: =F31-F33 -> 1542643.5 | G34: =G31-G33 -> 1737254.4 | H34: =H31-H33 -> 1999325.7 | I34: =I31-I33 -> 2268511.6 | J34: =J31-J33 -> 2571642.3
A36: Shareholder information | C36: 44926 | D36: 45291 | E36: 45657 | F36: 46022 | G36: 46022 | H36: 46022 | I36: 46022 | J36: 46022
B37: Basic WASO | C37: 1392543 | D37: 1377768 | E37: 1368343 | F37: =F11 -> 1357754.8 | G37: =G11 -> 1347166.5 | H37: =H11 -> 1336578.3 | I37: =I11 -> 1325990.1 | J37: =J11 -> 1315401.8
B38: Diluted WASO | C38: 1403077 | D38: 1385500 | E38: 1376555 | F38: =F12 -> 1376555 | G38: =G12 -> 1376555 | H38: =H12 -> 1376555 | I38: =I12 -> 1376555 | J38: =J12 -> 1376555
B39: Basic earnings per share | C39: =C34/C37 -> 0.64565403 | D39: =D34/D37 -> 0.89183157 | E39: =E34/E37 -> 1.1211443 | F39: =F34/F37 -> 1.1361724 | G39: =G34/G37 -> 1.2895617 | H39: =H34/H37 -> 1.4958538 | I39: =I34/I37 -> 1.7108059 | J39: =J34/J37 -> 1.9550241
A40: * | B40: Diluted earnings per share | C40: =C34/C38 -> 0.6408066 | D40: =D34/D38 -> 0.88685457 | E40: =E34/E38 -> 1.114456 | F40: =F34/F38 -> 1.1206552 | G40: =G34/G38 -> 1.2620305 | H40: =H34/H38 -> 1.4524125 | I40: =I34/I38 -> 1.6479629 | J40: =J34/J38 -> 1.8681726

Sheet BalSheet
A1: =CoName -> Chipotle Mexican Grill Inc. | C1: Hist. | D1: Hist. | E1: Hist. | F1: Proj. | G1: Proj. | H1: Proj. | I1: Proj. | J1: Proj.
A2: Assumptions | C2: 44926 | D2: 45291 | E2: 45657 | F2: 46022 | G2: 46387 | H2: 46752 | I2: 47118 | J2: 47483
B4: Operating Cash % of sales | F4: =Assumptions!F42 -> 0.015 | G4: =F4 -> 0.015 | H4: =G4 -> 0.015 | I4: =H4 -> 0.015 | J4: =I4 -> 0.015
B5: Accounts receivable % of sales | F5: =Assumptions!F43 -> 0.012724489 | G5: =Assumptions!G43 -> 0.012724489 | H5: =Assumptions!H43 -> 0.012724489 | I5: =Assumptions!I43 -> 0.012724489 | J5: =Assumptions!J43 -> 0.012724489
B6: Inventories % of COGS | F6: =Assumptions!F44 -> 0.0056254933 | G6: =Assumptions!G44 -> 0.0056254933 | H6: =Assumptions!H44 -> 0.0056254933 | I6: =Assumptions!I44 -> 0.0056254933 | J6: =Assumptions!J44 -> 0.0056254933
B7: Other current assets % of sales | F7: =Assumptions!F45 -> 0.014563297 | G7: =Assumptions!G45 -> 0.014563297 | H7: =Assumptions!H45 -> 0.014563297 | I7: =Assumptions!I45 -> 0.014563297 | J7: =Assumptions!J45 -> 0.014563297
B9: Other long-term assets % of sales | F9: =Assumptions!F48 -> 0.012689753 | G9: =Assumptions!G48 -> 0.012689753 | H9: =Assumptions!H48 -> 0.012689753 | I9: =Assumptions!I48 -> 0.012689753 | J9: =Assumptions!J48 -> 0.012689753
B10: Investment in unconsolidated entities $ balance | F10: =Assumptions!F47 -> 868025 | G10: =Assumptions!G47 -> 868025 | H10: =Assumptions!H47 -> 868025 | I10: =Assumptions!I47 -> 868025 | J10: =Assumptions!J47 -> 868025
B12: Accounts payable/Accural % of COGS | F12: =Assumptions!F52 -> 0.074983014 | G12: =Assumptions!G52 -> 0.074983014 | H12: =Assumptions!H52 -> 0.074983014 | I12: =Assumptions!I52 -> 0.074983014 | J12: =Assumptions!J52 -> 0.074983014
B13: Other current liabilities % of sales | F13: =Assumptions!F53 -> 0.045644309 | G13: =Assumptions!G53 -> 0.045644309 | H13: =Assumptions!H53 -> 0.045644309 | I13: =Assumptions!I53 -> 0.045644309 | J13: =Assumptions!J53 -> 0.045644309
B14: Other long-term liabilities % of sales | F14: =Assumptions!F54 -> 0.38714132 | G14: =Assumptions!G54 -> 0.38714132 | H14: =Assumptions!H54 -> 0.38714132 | I14: =Assumptions!I54 -> 0.38714132 | J14: =Assumptions!J54 -> 0.38714132
A16: Balance sheet | C16: =C2 -> 44926 | D16: =D2 -> 45291 | E16: =E2 -> 45657 | F16: =F2 -> 46022 | G16: =G2 -> 46387 | H16: =H2 -> 46752 | I16: =I2 -> 47118 | J16: =J2 -> 47483
B17: Operating Cash | C17: =1.5%*IncState!C15 -> 129519.78 | D17: =1.5%*IncState!D15 -> 148074.73 | E17: =1.5%*IncState!E15 -> 169707.79 | F17: =F4*IncState!F15 -> 178298.08 | G17: =G4*IncState!G15 -> 191560.33 | H17: =H4*IncState!H15 -> 210590.85 | I17: =I4*IncState!I15 -> 231530.7 | J17: =J4*IncState!J15 -> 254570.49
B18: Excess cash | C18: =384000+515136-C17 -> 769616.22 | D18: =560609+734838-D17 -> 1147372.3 | E18: =748537+674378-E17 -> 1253207.2 | F18: =MAX(CashFlow!F21,0) -> 2461949.9 | G18: =MAX(CashFlow!G21,0) -> 3967784.8 | H18: =MAX(CashFlow!H21,0) -> 5852041.5 | I18: =MAX(CashFlow!I21,0) -> 8007388.9 | J18: =MAX(CashFlow!J21,0) -> 10469184
B19: Accounts receivable | C19: =106880 -> 106880 | D19: 115535 | E19: 143963 | F19: =F5*IncState!F15 -> 151250.13 | G19: =G5*IncState!G15 -> 162500.49 | H19: =H5*IncState!H15 -> 178644.07 | I19: =I5*IncState!I15 -> 196407.33 | J19: =J5*IncState!J15 -> 215951.97
B20: Inventories | C20: 35668 | D20: 39309 | E20: 48942 | F20: =F6*IncState!F16 -> 51085.012 | G20: =G6*IncState!G16 -> 54525.636 | H20: =H6*IncState!H16 -> 59547.58 | I20: =I6*IncState!I16 -> 65034.464 | J20: =J6*IncState!J16 -> 71028.731
B21: Other current assets | C21: =1175837-SUM(C17:C20) -> 134153 | D21: =117462+52960 -> 170422 | E21: =97538+67229 -> 164767 | F21: =F7*IncState!F15 -> 173107.19 | G21: =G7*IncState!G15 -> 185983.33 | H21: =H7*IncState!H15 -> 204459.81 | I21: =I7*IncState!I15 -> 224790.02 | J21: =J7*IncState!J15 -> 247159.05
B22: Total current assets | C22: =SUM(C17:C21) -> 1175837 | D22: =SUM(D17:D21) -> 1620713 | E22: =SUM(E17:E21) -> 1780587 | F22: =SUM(F17:F21) -> 3015690.3 | G22: =SUM(G17:G21) -> 4562354.6 | H22: =SUM(H17:H21) -> 6505283.8 | I22: =SUM(I17:I21) -> 8725151.4 | J22: =SUM(J17:J21) -> 11257894
B24: Property, plant & equipment, net | C24: =1951147+3302402 -> 5253549 | D24: =2170038+3578548 -> 5748586 | E24: =2390126+4000127 -> 6390253 | F24: =Calcs!F9 -> 6606940.5 | G24: =Calcs!G9 -> 6854819.2 | H24: =Calcs!H9 -> 7151130 | I24: =Calcs!I9 -> 7499359 | J24: =Calcs!J9 -> 7903418.8
B25: Intangible assets | C25: 21939 | D25: 21939 | E25: =21939 -> 21939 | F25: =E25-IncState!F22 -> 21939 | G25: =F25-IncState!G22 -> 21939 | H25: =G25-IncState!H22 -> 21939 | I25: =H25-IncState!I22 -> 21939 | J25: =I25-IncState!J22 -> 21939
B26: Investment in unconsolidated entities | C26: 388055 | D26: 564488 | E26: 868025 | F26: =F10 -> 868025 | G26: =G10 -> 868025 | H26: =H10 -> 868025 | I26: =I10 -> 868025 | J26: =J10 -> 868025
B27: Other assets | C27: =63158+24966 -> 88124 | D27: =63082+25554 -> 88636 | E27: =29842+113728 -> 143570 | F27: =F9*IncState!F15 -> 150837.24 | G27: =G9*IncState!G15 -> 162056.89 | H27: =H9*IncState!H15 -> 178156.39 | I27: =I9*IncState!I15 -> 195871.16 | J27: =J9*IncState!J15 -> 215362.45
B28: Total non-current assets | C28: =SUM(C24:C27) -> 5751667 | D28: =SUM(D24:D27) -> 6423649 | E28: =SUM(E24:E27) -> 7423787 | F28: =SUM(F24:F27) -> 7647741.7 | G28: =SUM(G24:G27) -> 7906840 | H28: =SUM(H24:H27) -> 8219250.4 | I28: =SUM(I24:I27) -> 8585194.2 | J28: =SUM(J24:J27) -> 9008745.3
A30: * | B30: TOTAL ASSETS | C30: =SUM(C28,C22) -> 6927504 | D30: =SUM(D28,D22) -> 8044362 | E30: =SUM(E28,E22) -> 9204374 | F30: =SUM(F28,F22) -> 10663432 | G30: =SUM(G28,G22) -> 12469195 | H30: =SUM(H28,H22) -> 14724534 | I30: =SUM(I28,I22) -> 17310346 | J30: =SUM(J28,J22) -> 20266639
B32: Revolver/Short term debt | C32: 0 | D32: 0 | E32: 0 | F32: =MIN(CashFlow!F21,0) -> 0 | G32: =MIN(CashFlow!G21,0) -> 0 | H32: =MIN(CashFlow!H21,0) -> 0 | I32: =MIN(CashFlow!I21,0) -> 0 | J32: =MIN(CashFlow!J21,0) -> 0
B33: Accounts payable/Accurals | C33: =184566+170456+147539 -> 502561 | D33: =197646+227537+147688 -> 572871 | E33: =210695+261913+179747 -> 652355 | F33: =F12*IncState!F16 -> 680919.52 | G33: =G12*IncState!G16 -> 726780.09 | H33: =H12*IncState!H16 -> 793718.32 | I33: =I12*IncState!I16 -> 866853.78 | J33: =J12*IncState!J16 -> 946752.23
B34: Other current liabilities | C34: =921880-C33 -> 419319 | D34: =209680+248074 -> 457754 | E34: =238577+277836 -> 516413 | F34: =F13*IncState!F15 -> 542552.84 | G34: =G13*IncState!G15 -> 582909.27 | H34: =H13*IncState!H15 -> 640818.26 | I34: =I13*IncState!I15 -> 704537.25 | J34: =J13*IncState!J15 -> 774646.28
B35: Total current liabilities | C35: =SUM(C32:C34) -> 921880 | D35: =SUM(D32:D34) -> 1030625 | E35: =SUM(E32:E34) -> 1168768 | F35: =SUM(F32:F34) -> 1223472.4 | G35: =SUM(G32:G34) -> 1309689.4 | H35: =SUM(H32:H34) -> 1434536.6 | I35: =SUM(I32:I34) -> 1571391 | J35: =SUM(J32:J34) -> 1721398.5
B37: Long-term debt, including current maturities | C37: 0 | D37: 0 | E37: 0 | F37: =E37+SUM(Debt!F8:F9) -> 0 | G37: =F37+SUM(Debt!G8:G9) -> 0 | H37: =G37+SUM(Debt!H8:H9) -> 0 | I37: =H37+SUM(Debt!I8:I9) -> 0 | J37: =I37+SUM(Debt!J8:J9) -> 0
B38: Other long-term liabilities | C38: =4559481-C35 -> 3637601 | D38: =4982155-D35 -> 3951530 | E38: =5548828-E35 -> 4380060 | F38: =F14*IncState!F15 -> 4601770.2 | G38: =G14*IncState!G15 -> 4944061.4 | H38: =H14*IncState!H15 -> 5435228.1 | I38: =I14*IncState!I15 -> 5975673.4 | J38: =J14*IncState!J15 -> 6570317.2
B39: Total non-current liabilities | C39: =SUM(C37:C38) -> 3637601 | D39: =SUM(D37:D38) -> 3951530 | E39: =SUM(E37:E38) -> 4380060 | F39: =SUM(F37:F38) -> 4601770.2 | G39: =SUM(G37:G38) -> 4944061.4 | H39: =SUM(H37:H38) -> 5435228.1 | I39: =SUM(I37:I38) -> 5975673.4 | J39: =SUM(J37:J38) -> 6570317.2
B41: Equity | C41: 2368023 | D41: 3062207 | E41: 3655546 | F41: =Calcs!F16 -> 4838189.5 | G41: =Calcs!G16 -> 6215443.9 | H41: =Calcs!H16 -> 7854769.6 | I41: =Calcs!I16 -> 9763281.2 | J41: =Calcs!J16 -> 11974923
A42: * | B42: TOTAL LIABILITIES & EQUITY | C42: =SUM(C41,C39,C35) -> 6927504 | D42: =SUM(D41,D39,D35) -> 8044362 | E42: =SUM(E41,E39,E35) -> 9204374 | F42: =SUM(F41,F39,F35) -> 10663432 | G42: =SUM(G41,G39,G35) -> 12469195 | H42: =SUM(H41,H39,H35) -> 14724534 | I42: =SUM(I41,I39,I35) -> 17310346 | J42: =SUM(J41,J39,J35) -> 20266639
A44: * | B44: Balance check | C44: =C42-C30 -> 0 | D44: =D42-D30 -> 0 | E44: =E42-E30 -> 0 | F44: =F42-F30 -> 0 | G44: =G42-G30 -> 0 | H44: =H42-H30 -> 0 | I44: =I42-I30 -> 0 | J44: =J42-J30 -> 0

Sheet CashFlow
A1: =CoName -> Chipotle Mexican Grill Inc. | C1: Hist. | D1: Hist. | E1: Hist. | F1: Proj. | G1: Proj. | H1: Proj. | I1: Proj. | J1: Proj.
A2: Cash flow statement | C2: 2022 | D2: =C2+1 -> 2023 | E2: =D2+1 -> 2024 | F2: =E2+1 -> 2025 | G2: =F2+1 -> 2026 | H2: =G2+1 -> 2027 | I2: =H2+1 -> 2028 | J2: =I2+1 -> 2029
B3: Net Income | F3: =IncState!F34 -> 1542643.5 | G3: =IncState!G34 -> 1737254.4 | H3: =IncState!H34 -> 1999325.7 | I3: =IncState!I34 -> 2268511.6 | J3: =IncState!J34 -> 2571642.3
B4: Depreciation | F4: =Calcs!F8 -> 372426.62 | G4: =Calcs!G8 -> 385055.26 | H4: =Calcs!H8 -> 399501.73 | I4: =Calcs!I8 -> 416770.85 | J4: =Calcs!J8 -> 437065.79
B5: Amortization | F5: =IncState!F22 -> 0 | G5: =IncState!G22 -> 0 | H5: =IncState!H22 -> 0 | I5: =IncState!I22 -> 0 | J5: =IncState!J22 -> 0
B6: (inc) / dec in OWC | F6: =Calcs!F25 -> 28343.738 | G6: =Calcs!G25 -> 45387.616 | H6: =Calcs!H25 -> 66174.709 | I6: =Calcs!I25 -> 72334.252 | J6: =Calcs!J25 -> 79059.754
B7: (inc) / dec in LT assets | F7: =BalSheet!E27-BalSheet!F27 -> -7267.2384 | G7: =BalSheet!F27-BalSheet!G27 -> -11219.65 | H7: =BalSheet!G27-BalSheet!H27 -> -16099.506 | I7: =BalSheet!H27-BalSheet!I27 -> -17714.766 | J7: =BalSheet!I27-BalSheet!J27 -> -19491.286
B8: inc / (dec) in LT liabilities | F8: =BalSheet!F38-BalSheet!E38 -> 221710.25 | G8: =BalSheet!G38-BalSheet!F38 -> 342291.15 | H8: =BalSheet!H38-BalSheet!G38 -> 491166.69 | I8: =BalSheet!I38-BalSheet!H38 -> 540445.33 | J8: =BalSheet!J38-BalSheet!I38 -> 594643.74
B9: Cash Flow From Operations | F9: =SUM(F3:F8) -> 2157856.8 | G9: =SUM(G3:G8) -> 2498768.8 | H9: =SUM(H3:H8) -> 2940069.3 | I9: =SUM(I3:I8) -> 3280347.3 | J9: =SUM(J3:J8) -> 3662920.3
B11: Capex | F11: =Calcs!F7 -> 589114.13 | G11: =Calcs!G7 -> 632933.91 | H11: =Calcs!H7 -> 695812.59 | I11: =Calcs!I7 -> 764999.87 | J11: =Calcs!J7 -> 841125.58
B12: Cash Flow From Investing | F12: =-F11 -> -589114.13 | G12: =-G11 -> -632933.91 | H12: =-H11 -> -695812.59 | I12: =-I11 -> -764999.87 | J12: =-J11 -> -841125.58
B14: Share Issuance / (repayments) | F14: =Calcs!F11 -> -360000 | G14: =Calcs!G11 -> -360000 | H14: =Calcs!H11 -> -360000 | I14: =Calcs!I11 -> -360000 | J14: =Calcs!J11 -> -360000
B15: Cash Flow From Financing | F15: =F14 -> -360000 | G15: =G14 -> -360000 | H15: =H14 -> -360000 | I15: =I14 -> -360000 | J15: =J14 -> -360000
B17: Net changes in cash | F17: =SUM(F15,F12,F9) -> 1208742.7 | G17: =SUM(G15,G12,G9) -> 1505834.9 | H17: =SUM(H15,H12,H9) -> 1884256.8 | I17: =SUM(I15,I12,I9) -> 2155347.4 | J17: =SUM(J15,J12,J9) -> 2461794.7
B19: Beginning Cash | F19: =BalSheet!E18 -> 1253207.2 | G19: =BalSheet!F18 -> 2461949.9 | H19: =BalSheet!G18 -> 3967784.8 | I19: =BalSheet!H18 -> 5852041.5 | J19: =BalSheet!I18 -> 8007388.9
B20: Changes | F20: =F17 -> 1208742.7 | G20: =G17 -> 1505834.9 | H20: =H17 -> 1884256.8 | I20: =I17 -> 2155347.4 | J20: =J17 -> 2461794.7
B21: Ending Cash | F21: =SUM(F19:F20) -> 2461949.9 | G21: =SUM(G19:G20) -> 3967784.8 | H21: =SUM(H19:H20) -> 5852041.5 | I21: =SUM(I19:I20) -> 8007388.9 | J21: =SUM(J19:J20) -> 10469184

Sheet Free Cash Flow
A1: =CoName -> Chipotle Mexican Grill Inc. | C1: Hist. | D1: Hist. | E1: Hist. | F1: Proj. | G1: Proj. | H1: Proj. | I1: Proj. | J1: Proj.
A2: Free Cash Flows | C2: 2022 | D2: =C2+1 -> 2023 | E2: =D2+1 -> 2024 | F2: =E2+1 -> 2025 | G2: =F2+1 -> 2026 | H2: =G2+1 -> 2027 | I2: =H2+1 -> 2028 | J2: =I2+1 -> 2029
A3: * | B3: Sales | F3: =IncState!F15 -> 11886539 | G3: =IncState!G15 -> 12770689 | H3: =IncState!H15 -> 14039390 | I3: =IncState!I15 -> 15435380 | J3: =IncState!J15 -> 16971366
B4: EBIT | F4: =IncState!F18 -> 2084653.3 | G4: =IncState!G18 -> 2316339.2 | H4: =IncState!H18 -> 2630691.7 | I4: =IncState!I18 -> 2984883.7 | J4: =IncState!J18 -> 3383739.9
B5: Effective Tax Rate | F5: =IncState!F10 -> 0.26 | G5: =IncState!G10 -> 0.25 | H5: =IncState!H10 -> 0.24 | I5: =IncState!I10 -> 0.24 | J5: =IncState!J10 -> 0.24
A7: * | B7: NOPAT | F7: =F4*(1-F5) -> 1542643.5 | G7: =G4*(1-G5) -> 1737254.4 | H7: =H4*(1-H5) -> 1999325.7 | I7: =I4*(1-I5) -> 2268511.6 | J7: =J4*(1-J5) -> 2571642.3
B8: Depreciation | F8: =CashFlow!F4 -> 372426.62 | G8: =CashFlow!G4 -> 385055.26 | H8: =CashFlow!H4 -> 399501.73 | I8: =CashFlow!I4 -> 416770.85 | J8: =CashFlow!J4 -> 437065.79
B9: Amortization | F9: =CashFlow!F5 -> 0 | G9: =CashFlow!G5 -> 0 | H9: =CashFlow!H5 -> 0 | I9: =CashFlow!I5 -> 0 | J9: =CashFlow!J5 -> 0
B10: (inc) / dec in OWC | F10: =CashFlow!F6 -> 28343.738 | G10: =CashFlow!G6 -> 45387.616 | H10: =CashFlow!H6 -> 66174.709 | I10: =CashFlow!I6 -> 72334.252 | J10: =CashFlow!J6 -> 79059.754
B11: (inc) / dec in other long-term assets | F11: =CashFlow!F7 -> -7267.2384 | G11: =CashFlow!G7 -> -11219.65 | H11: =CashFlow!H7 -> -16099.506 | I11: =CashFlow!I7 -> -17714.766 | J11: =CashFlow!J7 -> -19491.286
B12: inc / (dec) other long-term liabilities | F12: =CashFlow!F8 -> 221710.25 | G12: =CashFlow!G8 -> 342291.15 | H12: =CashFlow!H8 -> 491166.69 | I12: =CashFlow!I8 -> 540445.33 | J12: =CashFlow!J8 -> 594643.74
B13: (Capex) | F13: =CashFlow!F12 -> -589114.13 | G13: =CashFlow!G12 -> -632933.91 | H13: =CashFlow!H12 -> -695812.59 | I13: =CashFlow!I12 -> -764999.87 | J13: =CashFlow!J12 -> -841125.58
A15: * | B15: Free Cash Flow | F15: =SUM(F7:F13) -> 1568742.7 | G15: =SUM(G7:G13) -> 1865834.9 | H15: =SUM(H7:H13) -> 2244256.8 | I15: =SUM(I7:I13) -> 2515347.4 | J15: =SUM(J7:J13) -> 2821794.7

Sheet WACC
A1: =CoName -> Chipotle Mexican Grill Inc.
A3: * | B3: WACC | G3: Comp | H3: Levered beta | I3: Gross debt | J3: Market cap | K3: Debt/Mcap | L3: MTR | M3: Unlevered beta
B4: Tax Rate | E4: 0.24 | G4: DRI | H4: 0.66 | I4: =142+2135 -> 2277 | J4: =116.3*180.1 -> 20945.63 | K4: =I4/J4 -> 0.10871003 | L4: =E4 -> 0.24 | M4: =H4/((1+K4*(1-L4))) -> 0.6096324
B5: Risk free rate | E5: 0.041 | G5: SBUX | H5: 1 | I5: =14570+2748.2 -> 17318.2 | J5: =1100*83 -> 91300 | K5: =I5/J5 -> 0.18968456 | L5: =L4 -> 0.24 | M5: =H5/((1+K5*(1-L5))) -> 0.87400344
B6: Market risk Premium | E6: 0.055 | G6: MCD | H6: 0.5 | I6: =40801+602 -> 41403 | J6: =305.79*713.6 -> 218211.74 | K6: =I6/J6 -> 0.18973773 | L6: =L5 -> 0.24 | M6: =H6/((1+K6*(1-L6))) -> 0.43698628
B7: Beta | E7: 0.5 | G7: YUM | H7: 0.68 | I7: =971+10418 -> 11389 | J7: =149.4*277.5 -> 41458.5 | K7: =I7/J7 -> 0.27470844 | L7: =L6 -> 0.24 | M7: =H7/((1+K7*(1-L7))) -> 0.56255141
B8: Cost of Equity | E8: =E5+E6*E7 -> 0.0685
B9: % Equity | E9: 1 | G9: Industry beta (average) | M9: =AVERAGE(M4:M7) -> 0.62079338
B10: % Debt | E10: 0
B11: Cost of debt | E11: 0 | G11: Re-levered beta | M11: =M9*(1+E10*(1-E4)) -> 0.62079338
B12: Post tax cost of debt | E12: =E11*(1-E4) -> 0
A13: * | B13: WACC | E13: =WACC!E8*WACC!E9+WACC!E12*WACC!E10 -> 0.0685
B14: Long Term growth rate | E14: 0.025

Sheet DCF Model
A1: =CoName -> Chipotle Mexican Grill Inc. | D1: Proj. | E1: Proj. | F1: Proj. | G1: Proj. | H1: Proj.
A2: Discount Model Year count | D2: 1 | E2: =D2+1 -> 2 | F2: =E2+1 -> 3 | G2: =F2+1 -> 4 | H2: =G2+1 -> 5
B3: Discount Factor | D3: =1/(1+$M$3)^D2 -> 0.93589144 | E3: =1/(1+$M$3)^E2 -> 0.87589278 | F3: =1/(1+$M$3)^F2 -> 0.81974055 | G3: =1/(1+$M$3)^G2 -> 0.76718816 | H3: =1/(1+$M$3)^H2 -> 0.71800483 | J3: WACC | M3: =WACC!E13 -> 0.0685
B4: PV FCF | D4: =D3*'Free Cash Flow'!F15 -> 1468172.9 | E4: =E3*'Free Cash Flow'!G15 -> 1634271.3 | F4: =F3*'Free Cash Flow'!H15 -> 1839708.3 | G4: =G3*'Free Cash Flow'!I15 -> 1929744.7 | H4: =H3*'Free Cash Flow'!J15 -> 2026062.2 | J4: Long Term growth rate | M4: 0.025
H5: =((H4*(1+M4)))/(M3-M4) -> 47740547
A6: Value Calculation | E6: Multiples Calculation
B7: Total PV of FCFs | C7: =SUM(D4:H4) -> 8897959.4 | E7: Total PV of FCFs | G7: =C7 -> 8897959.4 | K7: LTGR | P7: Terminal mult
B8: PV of TV | C8: =H5*H3 -> 34277944 | E8: Multiple TV | G8: =G10*H3*IncState!J23 -> 41150354 | I8: =C18 -> 33.727535 | J8: =K8-E23 -> 0.0225 | K8: 0.025 | L8: =K8+E23 -> 0.0275 | N8: =G18 -> 38.924937 | O8: =P8-L23 -> 15.5 | P8: 17.5 | Q8: =P8+L23 -> 19.5
B9: EV | C9: =SUM(C7:C8) -> 43175903 | E9: EV | G9: =SUM(G7:G8) -> 50048313 | I9: =I10+$E$22 -> 0.072086182 | J9: 29.671933 | K9: 30.893229 | L9: 32.251485 | N9: =I9 -> 0.072086182 | O9: 39.35726 | P9: 43.437762 | Q9: 47.518265
E10: Implied EBITDA multiple | G10: 15 | I10: =I11+$E$22 -> 0.067086182 | J10: 33.398814 | K10: 34.983734 | L10: 36.76884 | N10: =I10 -> 0.067086182 | O10: 40.204113 | P10: 44.381115 | Q10: 48.558117
I11: 0.062086182 | J11: 38.113955 | K11: 40.227196 | L11: 42.645941 | N11: =I11 -> 0.062086182 | O11: 41.07453 | P11: 45.350783 | Q11: 49.627036
B12: Cash & Cash Equiv | C12: =MAIN!F7 -> 1421274 | E12: Cash & Cash Equiv | G12: =C12 -> 1421274 | I12: =I11-$E$22 -> 0.057086182 | J12: 44.249673 | K12: 47.166619 | L12: 50.576523 | N12: =I12 -> 0.057086182 | O12: 41.96929 | P12: 46.347637 | Q12: 50.725985
B13: Debt & Claims | C13: =MAIN!F8 -> 0 | E13: Debt & Claims | G13: =C13 -> 0 | I13: =I12-$E$22 -> 0.052086182 | J13: 52.530828 | K13: 56.746279 | L13: 61.819012 | N13: =I13 -> 0.052086182 | O13: 42.8892 | P13: 47.37258 | Q13: 51.855961
B14: NCI | C14: 0 | E14: NCI | G14: =C14 -> 0
B15: Equity Value | C15: =C9+C12-C13-C14 -> 44597177 | E15: Equity Value | G15: =G9+G12-G13-G14 -> 51469587 | K15: Weighted avg | P15: =K15 -> Weighted avg
K16: =AVERAGE(J9:L13) -> 42.136271 | P16: =AVERAGE(O9:Q13) -> 45.377976
B17: Diluted S/O | C17: =MAIN!F5 -> 1322278 | E17: Diluted S/O | G17: =C17 -> 1322278
A18: * | B18: Implied Share Price | C18: =C15/C17 -> 33.727535 | E18: Implied Share Price | G18: =G15/G17 -> 38.924937
A20: Sensitivity analysis
C22: Discount rate variance | E22: 0.005 | J22: Discount rate variance | L22: 0.005
C23: Implied growth rate variance | E23: 0.0025 | J23: TV multiple variance | L23: 2
A25: DCF tables
