Workbook
Name Ccy: MAIN!$C$6
Name circ: MAIN!$C$9
Name CoName: MAIN!$C$4
Name g: #REF!
Name IQ_CH: 110000
Name IQ_CQ: 5000
Name IQ_CY: 10000
Name IQ_DAILY: 500000
Name IQ_FH: 100000
Name IQ_FQ: 500
Name IQ_FY: 1000
Name IQ_LTM: 2000
Name IQ_MONTH: 15000
Name IQ_NTM: 6000
Name IQ_WEEK: 50000
Name IQ_YTD: 3000
Name OpCase: [1]DCF!$E$98
Name ScenarioREV: Assumptions!$D$4
Name TTS: #REF!
Name Units: MAIN!$C$7

Sheet MAIN
A1: =CoName -> Domino's Pizza Inc
A2: Model Details
B4: Company name | C4: Domino's Pizza Inc | E4: Current Stock Price | F4: 432 | H4: Operating Case One | I4: Perpetuity | J4: Terminal Mult | K4: Average
B5: Latest BS date | C5: 247.43 | E5: Diluted s/o | F5: 33786 | H5: Implied Price | I5: ='DCF Model'!C18 -> 338.86878 | J5: ='DCF Model'!G18 -> 413.94929 | K5: =AVERAGE(I5:J5) -> 376.40904
B6: Currency | C6: USD | E6: Mkt Cap | F6: =F5*F4 -> 14595552 | H6: Difference | I6: =I5/$F$4-1 -> -0.21558152 | J6: =J5/$F$4-1 -> -0.041784062 | K6: =K5/$F$4-1 -> -0.12868279
B7: Units | C7: m | E7: Cash | F7: =139728+202501 -> 342229
B8: Analyst name | C8: Alan Chen | E8: Debt | F8: =5521+46163+4810274+190757 -> 5052715
B9: Circular switch | C9: 0 | E9: EV | F9: =F6-F7+F8 -> 19306038

Sheet Quarterly Projections

Sheet Assumptions
A1: =CoName -> Domino's Pizza Inc | C1: Hist. | D1: Hist. | E1: Hist. | F1: Proj. | G1: Proj. | H1: Proj. | I1: Proj. | J1: Proj.
A2: * | B2: Income Statement | C2: 2022 | D2: =C2+1 -> 2023 | E2: =D2+1 -> 2024 | F2: =E2+1 -> 2025 | G2: =F2+1 -> 2026 | H2: =G2+1 -> 2027 | I2: =H2+1 -> 2028 | J2: =I2+1 -> 2029
B4: Operating Case | D4: 1
D5: Variance
B6: Street Case | D6: 0 | F6: 0.05 | G6: 0.065 | H6: 0.06 | I6: 0.055 | J6: 0.05
B7: Optimistic Case | D7: 0.025 | F7: =F6+$D$7 -> 0.075 | G7: =G6+$D$7 -> 0.09 | H7: =H6+$D$7 -> 0.085 | I7: =I6+$D$7 -> 0.08 | J7: =J6+$D$7 -> 0.075
B8: Pessimistic Case | D8: -0.025 | F8: =F6+$D$8 -> 0.025 | G8: =G6+$D$8 -> 0.04 | H8: =H6+$D$8 -> 0.035 | I8: =I6+$D$8 -> 0.03 | J8: =J6+$D$8 -> 0.025
B10: Revenue Growth | D10: =IncState!D16/IncState!C16-1 -> -0.012739252 | E10: =IncState!E16/IncState!D16-1 -> 0.050689853 | F10: =CHOOSE(ScenarioREV,F6,F7,F8) -> 0.05 | G10: =CHOOSE(ScenarioREV,G6,G7,G8) -> 0.065 | H10: =CHOOSE(ScenarioREV,H6,H7,H8) -> 0.06 | I10: =CHOOSE(ScenarioREV,I6,I7,I8) -> 0.055 | J10: =CHOOSE(ScenarioREV,J6,J7,J8) -> 0.05
B11: COGS % of sales | C11: =IncState!C17/IncState!C16 -> 0.63664347 | D11: =IncState!D17/IncState!D16 -> 0.61436058 | E11: =IncState!E17/IncState!E16 -> 0.60723786 | F11: =E11-0.002 -> 0.60523786 | G11: =F11-0.002 -> 0.60323786 | H11: =G11-0.002 -> 0.60123786 | I11: =H11-0.002 -> 0.59923786 | J11: =I11-0.002 -> 0.59723786
B12: SG&A % of sales | C12: =IncState!C18/IncState!C16 -> 0.19410411 | D12: =IncState!D18/IncState!D16 -> 0.20268485 | E12: =IncState!E18/IncState!E16 -> 0.20599603 | F12: =AVERAGE(C12:E12) -> 0.20092833 | G12: =F12 -> 0.20092833 | H12: =G12 -> 0.20092833 | I12: =H12 -> 0.20092833 | J12: =I12 -> 0.20092833
B13: Amortization $ Amt | C13: =IncState!C22 -> 0 | D13: =IncState!D22 -> 0 | E13: =IncState!E22 -> 0 | F13: =E13 -> 0 | G13: =F13 -> 0 | H13: =G13 -> 0 | I13: =H13 -> 0 | J13: =I13 -> 0
B14: Non recurring income / (expense) | C14: =IncState!C25 -> 0 | D14: =IncState!D25 -> 0 | E14: =IncState!E25 -> 0 | F14: 0 | G14: 0 | H14: 0 | I14: 0 | J14: 0
B15: Other Income / (expense) | C15: =IncState!C26 -> 0 | D15: =IncState!D26 -> 17713 | E15: =IncState!E26 -> 22064 | F15: 0 | G15: 0 | H15: 0 | I15: 0 | J15: 0
B16: Effective tax rate | C16: =IncState!C33/IncState!C31 -> 0.21048019 | D16: =IncState!D33/IncState!D31 -> 0.20434369 | E16: =IncState!E33/IncState!E31 -> 0.19114114 | F16: 0.21 | G16: =F16 -> 0.21 | H16: =G16 -> 0.21 | I16: =H16 -> 0.21 | J16: =I16 -> 0.21
B17: Dividend Payout Rate | C17: =IncState!C35 -> 4.4096963 | D17: =IncState!D35 -> 4.840182 | E17: =IncState!E35 -> 6.0485378 | F17: =E17+0.4 -> 6.4485378 | G17: =F17+0.4 -> 6.8485378 | H17: =G17+0.4 -> 7.2485378 | I17: =H17+0.4 -> 7.6485378 | J17: =I17+0.4 -> 8.0485378
B18: Basic WASO | C18: =IncState!C38 -> 35723.776 | D18: =IncState!D38 -> 35075.541 | E18: =IncState!E38 -> 34710.042 | F18: =E18 -> 34710.042 | G18: =F18 -> 34710.042 | H18: =G18 -> 34710.042 | I18: =H18 -> 34710.042 | J18: =I18 -> 34710.042
B19: Diluted WASO | C19: =IncState!C39 -> 36094.413 | D19: =IncState!D39 -> 35410.505 | E19: =IncState!E39 -> 35001.198 | F19: =E19 -> 35001.198 | G19: =F19 -> 35001.198 | H19: =G19 -> 35001.198 | I19: =H19 -> 35001.198 | J19: =I19 -> 35001.198
A21: * | B21: Debt | C21: =C2 -> 2022 | D21: =D2 -> 2023 | E21: =E2 -> 2024 | F21: =F2 -> 2025 | G21: =G2 -> 2026 | H21: =H2 -> 2027 | I21: =I2 -> 2028 | J21: =J2 -> 2029
B23: Interest rate on Revolver | E23: =E24+1% -> 0.04936818 | F23: =E23 -> 0.04936818 | G23: =F23 -> 0.04936818 | H23: =G23 -> 0.04936818 | I23: =H23 -> 0.04936818 | J23: =I23 -> 0.04936818
B24: Interest rate on long-term debt | E24: =IncState!E29/-BalSheet!E37 -> 0.03936818 | F24: =E24 -> 0.03936818 | G24: =F24 -> 0.03936818 | H24: =G24 -> 0.03936818 | I24: =H24 -> 0.03936818 | J24: =I24 -> 0.03936818
B25: Interest rate on cash | C25: =IncState!C28/SUM(BalSheet!C17:C18) -> 0.052389158 | D25: =IncState!D28/SUM(BalSheet!D17:D18) -> 0.10239443 | E25: =IncState!E28/SUM(BalSheet!E17:E18) -> 0.091454176 | F25: =E25 -> 0.091454176 | G25: =F25 -> 0.091454176 | H25: =G25 -> 0.091454176 | I25: =H25 -> 0.091454176 | J25: =I25 -> 0.091454176
B27: Issuance of long-term debt | F27: 0 | G27: 0 | H27: 0 | I27: 0 | J27: 0
B28: Repayment of long-term debt | F28: 0 | G28: 0 | H28: 0 | I28: 0 | J28: 0
A30: * | B30: Calcs | C30: =C21 -> 2022 | D30: =D21 -> 2023 | E30: =E21 -> 2024 | F30: =F21 -> 2025 | G30: =G21 -> 2026 | H30: =H21 -> 2027 | I30: =I21 -> 2028 | J30: =J21 -> 2029
B32: CapEx % of Sales | C32: =87234/IncState!C16 -> 0.019226573 | D32: =105396/IncState!D16 -> 0.023529265 | E32: =112885/IncState!E16 -> 0.023985343 | F32: =E32 -> 0.023985343 | G32: =F32 -> 0.023985343 | H32: =G32 -> 0.023985343 | I32: =H32 -> 0.023985343 | J32: =I32 -> 0.023985343
B33: Depreciation % of beginning PP&E | D33: =IncState!D21/BalSheet!C24 -> 0.15464955 | E33: =IncState!E21/BalSheet!D24 -> 0.17145604 | F33: =E33 -> 0.17145604 | G33: =F33 -> 0.17145604 | H33: =G33 -> 0.17145604 | I33: =H33 -> 0.17145604 | J33: =I33 -> 0.17145604
B34: Share issuance / (repurchases) | F34: 0 | G34: 0 | H34: 0 | I34: 0 | J34: 0
A36: * | B36: Balance Sheet - Assets | C36: =C30 -> 2022 | D36: =D30 -> 2023 | E36: =E30 -> 2024 | F36: =F30 -> 2025 | G36: =G30 -> 2026 | H36: =H30 -> 2027 | I36: =I30 -> 2028 | J36: =J30 -> 2029
B38: Operating Cash % of sales | C38: =BalSheet!C17/IncState!C16 -> 0.01 | D38: =BalSheet!D17/IncState!D16 -> 0.01 | E38: =BalSheet!E17/IncState!E16 -> 0.01 | F38: =E38 -> 0.01 | G38: =F38 -> 0.01 | H38: =G38 -> 0.01 | I38: =H38 -> 0.01 | J38: =I38 -> 0.01
B39: Accounts receivable % of sales | C39: =BalSheet!C19/IncState!C16 -> 0.056751826 | D39: =BalSheet!D19/IncState!D16 -> 0.063136057 | E39: =BalSheet!E19/IncState!E16 -> 0.065677152 | F39: =E39 -> 0.065677152 | G39: =F39 -> 0.065677152 | H39: =G39 -> 0.065677152 | I39: =H39 -> 0.065677152 | J39: =I39 -> 0.065677152
B40: Inventories % of COGS | C40: =BalSheet!C20/IncState!C17 -> 0.028239062 | D40: =BalSheet!D20/IncState!D17 -> 0.030147449 | E40: =BalSheet!E20/IncState!E17 -> 0.024814952 | F40: =E40 -> 0.024814952 | G40: =F40 -> 0.024814952 | H40: =G40 -> 0.024814952 | I40: =H40 -> 0.024814952 | J40: =I40 -> 0.024814952
B41: Other current assets % of sales | C41: =BalSheet!C21/IncState!C16 -> 0.086229309 | D41: =BalSheet!D21/IncState!D16 -> 0.075327759 | E41: =BalSheet!E21/IncState!E16 -> 0.072056741 | F41: =E41 -> 0.072056741 | G41: =F41 -> 0.072056741 | H41: =G41 -> 0.072056741 | I41: =H41 -> 0.072056741 | J41: =I41 -> 0.072056741
B43: Investments in unconsolidated entities | C43: =BalSheet!C26 -> 13395 | D43: =BalSheet!D26 -> 16720 | E43: =BalSheet!E26 -> 20638 | F43: =E43 -> 20638 | G43: =F43 -> 20638 | H43: =G43 -> 20638 | I43: =H43 -> 20638 | J43: =I43 -> 20638
B44: Other long-term assets % of sales | C44: =BalSheet!C27/IncState!C16 -> 0.034518965 | D44: =BalSheet!D27/IncState!D16 -> 0.04094493 | E44: =BalSheet!E27/IncState!E16 -> 0.028262058 | F44: =E44 -> 0.028262058 | G44: =F44 -> 0.028262058 | H44: =G44 -> 0.028262058 | I44: =H44 -> 0.028262058 | J44: =I44 -> 0.028262058
A46: * | B46: Balance Sheet - Liabilities | C46: =C36 -> 2022 | D46: =D36 -> 2023 | E46: =E36 -> 2024 | F46: =F36 -> 2025 | G46: =G36 -> 2026 | H46: =H36 -> 2027 | I46: =I36 -> 2028 | J46: =J36 -> 2029
B48: Accounts payable % of COGS | C48: =BalSheet!C33/IncState!C17 -> 0.056993954 | D48: =BalSheet!D33/IncState!D17 -> 0.070613069 | E48: =BalSheet!E33/IncState!E17 -> 0.061892695 | F48: =E48 -> 0.061892695 | G48: =F48 -> 0.061892695 | H48: =G48 -> 0.061892695 | I48: =H48 -> 0.061892695 | J48: =I48 -> 0.061892695
B49: Other current liabilities % of sales | C49: =BalSheet!C34/IncState!C16 -> 0.069906757 | D49: =BalSheet!D34/IncState!D16 -> 0.066228464 | E49: =BalSheet!E34/IncState!E16 -> 0.060746649 | F49: =E49 -> 0.060746649 | G49: =F49 -> 0.060746649 | H49: =G49 -> 0.060746649 | I49: =H49 -> 0.060746649 | J49: =I49 -> 0.060746649
B50: Other long-term liabilities % of sales | C50: =BalSheet!C38/IncState!C16 -> 0.063309455 | D50: =BalSheet!D38/IncState!D16 -> 0.058904423 | E50: =BalSheet!E38/IncState!E16 -> 0.055495094 | F50: =E50 -> 0.055495094 | G50: =F50 -> 0.055495094 | H50: =G50 -> 0.055495094 | I50: =H50 -> 0.055495094 | J50: =I50 -> 0.055495094

Sheet Calcs
A1: =CoName -> Domino's Pizza Inc | C1: Hist. | D1: Hist. | E1: Hist. | F1: Proj. | G1: Proj. | H1: Proj. | I1: Proj. | J1: Proj.
A2: Net PP&E | C2: 2022 | D2: =C2+1 -> 2023 | E2: =D2+1 -> 2024 | F2: =E2+1 -> 2025 | G2: =F2+1 -> 2026 | H2: =G2+1 -> 2027 | I2: =H2+1 -> 2028 | J2: =I2+1 -> 2029
B3: Capital expenditure % of sales | F3: =Assumptions!F32 -> 0.023985343 | G3: =Assumptions!G32 -> 0.023985343 | H3: =Assumptions!H32 -> 0.023985343 | I3: =Assumptions!I32 -> 0.023985343 | J3: =Assumptions!J32 -> 0.023985343
B4: Depreciation % of PP&E | F4: =Assumptions!F33 -> 0.17145604 | G4: =F4 -> 0.17145604 | H4: =G4 -> 0.17145604 | I4: =H4 -> 0.17145604 | J4: =I4 -> 0.17145604
B6: Beginning PP&E | F6: =E9 -> 511481 | G6: =F9 -> 542313.74 | H6: =G9 -> 575564.42 | I6: =H9 -> 610688.1 | J6: =I9 -> 647149.02
B7: Capex | F7: =F3*IncState!F16 -> 118529.25 | G7: =G3*IncState!G16 -> 126233.65 | H7: =H3*IncState!H16 -> 133807.67 | I7: =I3*IncState!I16 -> 141167.09 | J7: =J3*IncState!J16 -> 148225.45
B8: Depreciation | F8: =F4*F6 -> 87696.509 | G8: =G4*G6 -> 92982.968 | H8: =H4*H6 -> 98683.999 | I8: =I4*I6 -> 104706.16 | J8: =J4*J6 -> 110957.61
B9: Ending PP&E | E9: =BalSheet!E24 -> 511481 | F9: =F6+F7-F8 -> 542313.74 | G9: =G6+G7-G8 -> 575564.42 | H9: =H6+H7-H8 -> 610688.1 | I9: =I6+I7-I8 -> 647149.02 | J9: =J6+J7-J8 -> 684416.86
A10: Equity | C10: =C2 -> 2022 | D10: =D2 -> 2023 | E10: =E2 -> 2024 | F10: =F2 -> 2025 | G10: =G2 -> 2026 | H10: =H2 -> 2027 | I10: =I2 -> 2028 | J10: =J2 -> 2029
B11: Share issuance/(repurchases) | F11: =Assumptions!F34 -> 0 | G11: =Assumptions!G34 -> 0 | H11: =Assumptions!H34 -> 0 | I11: =Assumptions!I34 -> 0 | J11: =Assumptions!J34 -> 0
B13: Beginning balance | F13: =E17 -> -3962291 | G13: =F17 -> -3429398.2 | H13: =G17 -> -2852887.1 | I13: =H17 -> -2232592.2 | J13: =I17 -> -1568928
B14: Net income | F14: =IncState!F34 -> 756721.77 | G14: =IncState!G34 -> 814224.15 | H14: =IncState!H34 -> 871891.99 | I14: =IncState!I34 -> 929145.22 | J14: =IncState!J34 -> 985366.62
B15: Dividends paid | F15: =-IncState!F36 -> -223829.02 | G15: =-IncState!G36 -> -237713.03 | H15: =-IncState!H36 -> -251597.05 | I15: =-IncState!I36 -> -265481.07 | J15: =-IncState!J36 -> -279365.08
B16: Share issuance / (repurchase) | F16: =F11 -> 0 | G16: =G11 -> 0 | H16: =H11 -> 0 | I16: =I11 -> 0 | J16: =J11 -> 0
B17: Ending balance | E17: =BalSheet!E41 -> -3962291 | F17: =SUM(F13:F16) -> -3429398.2 | G17: =SUM(G13:G16) -> -2852887.1 | H17: =SUM(H13:H16) -> -2232592.2 | I17: =SUM(I13:I16) -> -1568928 | J17: =SUM(J13:J16) -> -862926.49
A18: OWC | C18: =C10 -> 2022 | D18: =D10 -> 2023 | E18: =E10 -> 2024 | F18: =F10 -> 2025 | G18: =G10 -> 2026 | H18: =H10 -> 2027 | I18: =I10 -> 2028 | J18: =J10 -> 2029
B19: Operating Cash | E19: =BalSheet!E17 -> 47064.16 | F19: =BalSheet!F17 -> 49417.368 | G19: =BalSheet!G17 -> 52629.497 | H19: =BalSheet!H17 -> 55787.267 | I19: =BalSheet!I17 -> 58855.566 | J19: =BalSheet!J17 -> 61798.345
B20: =BalSheet!B19 -> Accounts receivable | E20: =BalSheet!E19 -> 309104 | F20: =BalSheet!F19 -> 324559.2 | G20: =BalSheet!G19 -> 345655.55 | H20: =BalSheet!H19 -> 366394.88 | I20: =BalSheet!I19 -> 386546.6 | J20: =BalSheet!J19 -> 405873.93
B21: =BalSheet!B20 -> Inventories | E21: =BalSheet!E20 -> 70919 | F21: =BalSheet!F20 -> 74219.692 | G21: =BalSheet!G20 -> 78782.772 | H21: =BalSheet!H20 -> 83232.867 | I21: =BalSheet!I20 -> 87518.575 | J21: =BalSheet!J20 -> 91587.799
B22: Other current assets | E22: =BalSheet!E21 -> 339129 | F22: =BalSheet!F21 -> 356085.45 | G22: =BalSheet!G21 -> 379231 | H22: =BalSheet!H21 -> 401984.86 | I22: =BalSheet!I21 -> 424094.03 | J22: =BalSheet!J21 -> 445298.73
B23: Accounts payables | E23: =BalSheet!E33 -> 176884 | F23: =BalSheet!F33 -> 185116.49 | G23: =BalSheet!G33 -> 196497.58 | H23: =BalSheet!H33 -> 207596.87 | I23: =BalSheet!I33 -> 218286.15 | J23: =BalSheet!J33 -> 228435.49
B24: Other current liabilities | E24: =BalSheet!E34 -> 285899 | F24: =BalSheet!F34 -> 300193.95 | G24: =BalSheet!G34 -> 319706.56 | H24: =BalSheet!H34 -> 338888.95 | I24: =BalSheet!I34 -> 357527.84 | J24: =BalSheet!J34 -> 375404.23
A25: * | B25: OWC | E25: =SUM(E19:E22)-SUM(E23:E24) -> 303433.16 | F25: =SUM(F19:F22)-SUM(F23:F24) -> 318971.27 | G25: =SUM(G19:G22)-SUM(G23:G24) -> 340094.68 | H25: =SUM(H19:H22)-SUM(H23:H24) -> 360914.06 | I25: =SUM(I19:I22)-SUM(I23:I24) -> 381200.78 | J25: =SUM(J19:J22)-SUM(J23:J24) -> 400719.09
B26: Change in OWC | F26: =E25-F25 -> -15538.115 | G26: =F25-G25 -> -21123.409 | H26: =G25-H25 -> -20819.374 | I26: =H25-I25 -> -20286.72 | J26: =I25-J25 -> -19518.308

Sheet Debt
A1: =CoName -> Domino's Pizza Inc | C1: Hist. | D1: Hist. | E1: Hist. | F1: Proj. | G1: Proj. | H1: Proj. | I1: Proj. | J1: Proj.
A2: Assumptions | C2: 2022 | D2: =C2+1 -> 2023 | E2: =D2+1 -> 2024 | F2: =E2+1 -> 2025 | G2: =F2+1 -> 2026 | H2: =G2+1 -> 2027 | I2: =H2+1 -> 2028 | J2: =I2+1 -> 2029
B4: Interest rate on revolver | F4: =Assumptions!F23 -> 0.04936818 | G4: =Assumptions!G23 -> 0.04936818 | H4: =Assumptions!H23 -> 0.04936818 | I4: =Assumptions!I23 -> 0.04936818 | J4: =Assumptions!J23 -> 0.04936818
B5: Interest rate on long-term debt | F5: =Assumptions!F24 -> 0.03936818 | G5: =Assumptions!G24 -> 0.03936818 | H5: =Assumptions!H24 -> 0.03936818 | I5: =Assumptions!I24 -> 0.03936818 | J5: =Assumptions!J24 -> 0.03936818
B6: Interest rate on cash | F6: =Assumptions!F25 -> 0.091454176 | G6: =Assumptions!G25 -> 0.091454176 | H6: =Assumptions!H25 -> 0.091454176 | I6: =Assumptions!I25 -> 0.091454176 | J6: =Assumptions!J25 -> 0.091454176
B8: Issuance of long-term debt | F8: =Assumptions!F27 -> 0 | G8: =Assumptions!G27 -> 0 | H8: =Assumptions!H27 -> 0 | I8: =Assumptions!I27 -> 0 | J8: =Assumptions!J27 -> 0
B9: Repayment of long-term debt | F9: -1149679 | G9: =Assumptions!G28 -> 0 | H9: =Assumptions!H28 -> 0 | I9: =Assumptions!I28 -> 0 | J9: =Assumptions!J28 -> 0
A11: Revolver | C11: =C2 -> 2022 | D11: =D2 -> 2023 | E11: =E2 -> 2024 | F11: =F2 -> 2025 | G11: =G2 -> 2026 | H11: =H2 -> 2027 | I11: =I2 -> 2028 | J11: =J2 -> 2029
B12: Balance | F12: =BalSheet!F32 -> 517686.76 | G12: =BalSheet!G32 -> 0 | H12: =BalSheet!H32 -> 0 | I12: =BalSheet!I32 -> 0 | J12: =BalSheet!J32 -> 0
B13: Interest rate | F13: =F4 -> 0.04936818 | G13: =G4 -> 0.04936818 | H13: =H4 -> 0.04936818 | I13: =I4 -> 0.04936818 | J13: =J4 -> 0.04936818
B14: Interest expense | F14: =-F12*F13 -> -25557.253 | G14: =-G12*G13 -> 0 | H14: =-H12*H13 -> 0 | I14: =-I12*I13 -> 0 | J14: =-J12*J13 -> 0
A16: Long term debt | C16: =C11 -> 2022 | D16: =D11 -> 2023 | E16: =E11 -> 2024 | F16: =F11 -> 2025 | G16: =G11 -> 2026 | H16: =H11 -> 2027 | I16: =I11 -> 2028 | J16: =J11 -> 2029
B17: Beginning balance | F17: =E20 -> 4975338 | G17: =F20 -> 3825659 | H17: =G20 -> 3825659 | I17: =H20 -> 3825659 | J17: =I20 -> 3825659
B18: Issuance | F18: =F8 -> 0 | G18: =G8 -> 0 | H18: =H8 -> 0 | I18: =I8 -> 0 | J18: =J8 -> 0
B19: Repayment | F19: =F9 -> -1149679 | G19: =G9 -> 0 | H19: =H9 -> 0 | I19: =I9 -> 0 | J19: =J9 -> 0
B20: Ending balance | E20: =BalSheet!E37 -> 4975338 | F20: =SUM(F17:F19) -> 3825659 | G20: =SUM(G17:G19) -> 3825659 | H20: =SUM(H17:H19) -> 3825659 | I20: =SUM(I17:I19) -> 3825659 | J20: =SUM(J17:J19) -> 3825659
B21: Interest rate | F21: =F5 -> 0.03936818 | G21: =G5 -> 0.03936818 | H21: =H5 -> 0.03936818 | I21: =I5 -> 0.03936818 | J21: =J5 -> 0.03936818
B22: Interest expense | F22: =F20*-F21 -> -150609.23 | G22: =G20*-G21 -> -150609.23 | H22: =H20*-H21 -> -150609.23 | I22: =I20*-I21 -> -150609.23 | J22: =J20*-J21 -> -150609.23
A24: Debt summary | C24: =C16 -> 2022 | D24: =D16 -> 2023 | E24: =E16 -> 2024 | F24: =F16 -> 2025 | G24: =G16 -> 2026 | H24: =H16 -> 2027 | I24: =I16 -> 2028 | J24: =J16 -> 2029
B25: Revolver | F25: =F12 -> 517686.76 | G25: =G12 -> 0 | H25: =H12 -> 0 | I25: =I12 -> 0 | J25: =J12 -> 0
B26: Total long term debt | F26: =F20 -> 3825659 | G26: =G20 -> 3825659 | H26: =H20 -> 3825659 | I26: =I20 -> 3825659 | J26: =J20 -> 3825659
B27: Total debt | F27: =SUM(F25:F26) -> 4343345.8 | G27: =SUM(G25:G26) -> 3825659 | H27: =SUM(H25:H26) -> 3825659 | I27: =SUM(I25:I26) -> 3825659 | J27: =SUM(J25:J26) -> 3825659
B28: Total interest expense | F28: =SUM(F22,F14) -> -176166.48 | G28: =SUM(G22,G14) -> -150609.23 | H28: =SUM(H22,H14) -> -150609.23 | I28: =SUM(I22,I14) -> -150609.23 | J28: =SUM(J22,J14) -> -150609.23
A30: Interest income | C30: =C11 -> 2022 | D30: =D11 -> 2023 | E30: =E11 -> 2024 | F30: =F11 -> 2025 | G30: =G11 -> 2026 | H30: =H11 -> 2027 | I30: =I11 -> 2028 | J30: =J11 -> 2029
B31: Excess Cash | F31: =BalSheet!F18 -> 0 | G31: =BalSheet!G18 -> 13197.866 | H31: =BalSheet!H18 -> 586149.32 | I31: =BalSheet!I18 -> 1201421.7 | J31: =BalSheet!J18 -> 1858651.2
B32: Interest rate | F32: =F6 -> 0.091454176 | G32: =G6 -> 0.091454176 | H32: =H6 -> 0.091454176 | I32: =I6 -> 0.091454176 | J32: =J6 -> 0.091454176
B33: Interest income | F33: =F31*F32 -> 0 | G33: =G31*G32 -> 1207 | H33: =H31*H32 -> 53605.803 | I33: =I31*I32 -> 109875.04 | J33: =J31*J32 -> 169981.42

Sheet IncState
A1: =CoName -> Domino's Pizza Inc | C1: Hist. | D1: Hist. | E1: Hist. | F1: Proj. | G1: Proj. | H1: Proj. | I1: Proj. | J1: Proj.
A2: Assumptions | C2: 2022 | D2: =C2+1 -> 2023 | E2: =D2+1 -> 2024 | F2: =E2+1 -> 2025 | G2: =F2+1 -> 2026 | H2: =G2+1 -> 2027 | I2: =H2+1 -> 2028 | J2: =I2+1 -> 2029
B4: Revenue growth | F4: =Assumptions!F10 -> 0.05 | G4: =Assumptions!G10 -> 0.065 | H4: =Assumptions!H10 -> 0.06 | I4: =Assumptions!I10 -> 0.055 | J4: =Assumptions!J10 -> 0.05
B5: Cost of goods sold as % of sales | F5: =Assumptions!F11 -> 0.60523786 | G5: =Assumptions!G11 -> 0.60323786 | H5: =Assumptions!H11 -> 0.60123786 | I5: =Assumptions!I11 -> 0.59923786 | J5: =Assumptions!J11 -> 0.59723786
B6: SG&A % of sales | F6: =Assumptions!F12 -> 0.20092833 | G6: =Assumptions!G12 -> 0.20092833 | H6: =Assumptions!H12 -> 0.20092833 | I6: =Assumptions!I12 -> 0.20092833 | J6: =Assumptions!J12 -> 0.20092833
B7: Amortization amount | F7: =Assumptions!F13 -> 0 | G7: =Assumptions!G13 -> 0 | H7: =Assumptions!H13 -> 0 | I7: =Assumptions!I13 -> 0 | J7: =Assumptions!J13 -> 0
B8: Non recurring items, amount | F8: =Assumptions!F14 -> 0 | G8: =Assumptions!G14 -> 0 | H8: =Assumptions!H14 -> 0 | I8: =Assumptions!I14 -> 0 | J8: =Assumptions!J14 -> 0
B9: Other income (expense), amt | F9: =Assumptions!F15 -> 0 | G9: =Assumptions!G15 -> 0 | H9: =Assumptions!H15 -> 0 | I9: =Assumptions!I15 -> 0 | J9: =Assumptions!J15 -> 0
B10: Effective tax rate | F10: =Assumptions!F16 -> 0.21 | G10: =Assumptions!G16 -> 0.21 | H10: =Assumptions!H16 -> 0.21 | I10: =Assumptions!I16 -> 0.21 | J10: =Assumptions!J16 -> 0.21
B11: Dividend Payout Rate | F11: =Assumptions!F17 -> 6.4485378 | G11: =Assumptions!G17 -> 6.8485378 | H11: =Assumptions!H17 -> 7.2485378 | I11: =Assumptions!I17 -> 7.6485378 | J11: =Assumptions!J17 -> 8.0485378
B12: Basic WASO | F12: =Assumptions!F18 -> 34710.042 | G12: =Assumptions!G18 -> 34710.042 | H12: =Assumptions!H18 -> 34710.042 | I12: =Assumptions!I18 -> 34710.042 | J12: =Assumptions!J18 -> 34710.042
B13: Diluted WASO | F13: =Assumptions!F19 -> 35001.198 | G13: =Assumptions!G19 -> 35001.198 | H13: =Assumptions!H19 -> 35001.198 | I13: =Assumptions!I19 -> 35001.198 | J13: =Assumptions!J19 -> 35001.198
A15: Income statement | C15: =C37 -> 44926 | D15: =D37 -> 45291 | E15: =E37 -> 45657 | F15: =F37 -> 46022 | G15: =G37 -> 46022 | H15: =H37 -> 46022 | I15: =I37 -> 46022 | J15: =J37 -> 46022
B16: Revenue | C16: 4537158 | D16: 4479358 | E16: 4706416 | F16: =E16*(1+F4) -> 4941736.8 | G16: =F16*(1+G4) -> 5262949.7 | H16: =G16*(1+H4) -> 5578726.7 | I16: =H16*(1+I4) -> 5885556.6 | J16: =I16*(1+J4) -> 6179834.5
B17: COGS | C17: 2888552 | D17: 2751941 | E17: 2857914 | F17: =F16*F5 -> 2990926.2 | G17: =G16*G5 -> 3174810.5 | H17: =H16*H5 -> 3354141.7 | I17: =I16*I5 -> 3526848.4 | J17: =J16*J5 -> 3690831.1
B18: SG&A | C18: =416524+485330-21173 -> 880681 | D18: =434554+473195+149 -> 907898 | E18: =459492+509853+158 -> 969503 | F18: =F16*F6 -> 992934.91 | G18: =G16*G6 -> 1057475.7 | H18: =H16*H6 -> 1120924.2 | I18: =I16*I6 -> 1182575.1 | J18: =J16*J6 -> 1241703.8
A19: * | B19: EBIT | C19: =C16-SUM(C17:C18) -> 767925 | D19: =D16-SUM(D17:D18) -> 819519 | E19: =E16-SUM(E17:E18) -> 878999 | F19: =F16-SUM(F17:F18) -> 957875.66 | G19: =G16-SUM(G17:G18) -> 1030663.5 | H19: =H16-SUM(H17:H18) -> 1103660.7 | I19: =I16-SUM(I17:I18) -> 1176133.2 | J19: =J16-SUM(J17:J18) -> 1247299.5
B21: Depreciation | C21: 80251 | D21: 80640 | E21: 87732 | F21: =Calcs!F8 -> 87696.509 | G21: =Calcs!G8 -> 92982.968 | H21: =Calcs!H8 -> 98683.999 | I21: =Calcs!I8 -> 104706.16 | J21: =Calcs!J8 -> 110957.61
B22: Amortization | C22: 0 | D22: 0 | E22: 0 | F22: =F7 -> 0 | G22: =G7 -> 0 | H22: =H7 -> 0 | I22: =I7 -> 0 | J22: =J7 -> 0
A23: * | B23: EBITDA | C23: =SUM(C19,C21:C22) -> 848176 | D23: =SUM(D19,D21:D22) -> 900159 | E23: =SUM(E19,E21:E22) -> 966731 | F23: =SUM(F19,F21:F22) -> 1045572.2 | G23: =SUM(G19,G21:G22) -> 1123646.4 | H23: =SUM(H19,H21:H22) -> 1202344.7 | I23: =SUM(I19,I21:I22) -> 1280839.4 | J23: =SUM(J19,J21:J22) -> 1358257.1
B25: Non-recurring items | C25: 0 | D25: 0 | E25: 0 | F25: =F8 -> 0 | G25: =G8 -> 0 | H25: =H8 -> 0 | I25: =I8 -> 0 | J25: =J8 -> 0
B26: Other income (expense) | C26: 0 | D26: 17713 | E26: 22064 | F26: =F9 -> 0 | G26: =G9 -> 0 | H26: =H9 -> 0 | I26: =I9 -> 0 | J26: =J9 -> 0
B28: Interest income | C28: 3162 | D28: 11683 | E28: 17022 | F28: =IF(circ=1,Debt!F33,0) -> 0 | G28: =IF(circ=1,Debt!G33,0) -> 0 | H28: =IF(circ=1,Debt!H33,0) -> 0 | I28: =IF(circ=1,Debt!I33,0) -> 0 | J28: =IF(circ=1,Debt!J33,0) -> 0
B29: Interest expense | C29: -198254 | D29: -196475 | E29: -195870 | F29: =IF(circ=1,Debt!F28,0) -> 0 | G29: =IF(circ=1,Debt!G28,0) -> 0 | H29: =IF(circ=1,Debt!H28,0) -> 0 | I29: =IF(circ=1,Debt!I28,0) -> 0 | J29: =IF(circ=1,Debt!J28,0) -> 0
A31: * | B31: Pretax Income | C31: =C19+SUM(C26:C29) -> 572833 | D31: =D19+SUM(D26:D29) -> 652440 | E31: =E19+SUM(E25:E29) -> 722215 | F31: =F19+SUM(F25:F29) -> 957875.66 | G31: =G19+SUM(G25:G29) -> 1030663.5 | H31: =H19+SUM(H25:H29) -> 1103660.7 | I31: =I19+SUM(I25:I29) -> 1176133.2 | J31: =J19+SUM(J25:J29) -> 1247299.5
B33: Tax expense | C33: 120570 | D33: 133322 | E33: 138045 | F33: =F31*F10 -> 201153.89 | G33: =G31*G10 -> 216439.33 | H33: =H31*H10 -> 231768.76 | I33: =I31*I10 -> 246987.97 | J33: =J31*J10 -> 261932.9
A34: * | B34: Net income | C34: =C31-C33 -> 452263 | D34: =D31-D33 -> 519118 | E34: =E31-E33 -> 584170 | F34: =F31-F33 -> 756721.77 | G34: =G31-G33 -> 814224.15 | H34: =H31-H33 -> 871891.99 | I34: =I31-I33 -> 929145.22 | J34: =J31-J33 -> 985366.62
B35: Dividend payout rate | C35: =C36/C38 -> 4.4096963 | D35: =D36/D38 -> 4.840182 | E35: =E36/E38 -> 6.0485378 | F35: =F11 -> 6.4485378 | G35: =G11 -> 6.8485378 | H35: =H11 -> 7.2485378 | I35: =I11 -> 7.6485378 | J35: =J11 -> 8.0485378
B36: Dividends | C36: 157531 | D36: 169772 | E36: 209945 | F36: =F35*F38 -> 223829.02 | G36: =G35*G38 -> 237713.03 | H36: =H35*H38 -> 251597.05 | I36: =I35*I38 -> 265481.07 | J36: =J35*J38 -> 279365.08
A37: Shareholder information | C37: 44926 | D37: 45291 | E37: 45657 | F37: 46022 | G37: 46022 | H37: 46022 | I37: 46022 | J37: 46022
B38: Basic WASO | C38: =C34/C40 -> 35723.776 | D38: =D34/D40 -> 35075.541 | E38: =E34/E40 -> 34710.042 | F38: =F12 -> 34710.042 | G38: =G12 -> 34710.042 | H38: =H12 -> 34710.042 | I38: =I12 -> 34710.042 | J38: =J12 -> 34710.042
B39: Diluted WASO | C39: =C34/C41 -> 36094.413 | D39: =D34/D41 -> 35410.505 | E39: =E34/E41 -> 35001.198 | F39: =F13 -> 35001.198 | G39: =G13 -> 35001.198 | H39: =H13 -> 35001.198 | I39: =I13 -> 35001.198 | J39: =J13 -> 35001.198
B40: Basic earnings per share | C40: 12.66 | D40: 14.8 | E40: 16.83 | F40: =F34/F38 -> 21.801235 | G40: =G34/G38 -> 23.457885 | H40: =H34/H38 -> 25.119301 | I40: =I34/I38 -> 26.768773 | J40: =J34/J38 -> 28.388518
A41: * | B41: Diluted earnings per share | C41: 12.53 | D41: 14.66 | E41: 16.69 | F41: =F34/F39 -> 21.619882 | G41: =G34/G39 -> 23.262751 | H41: =H34/H39 -> 24.910347 | I41: =I34/I39 -> 26.546098 | J41: =J34/J39 -> 28.152368

Sheet BalSheet
A1: =CoName -> Domino's Pizza Inc | C1: Hist. | D1: Hist. | E1: Hist. | F1: Proj. | G1: Proj. | H1: Proj. | I1: Proj. | J1: Proj.
A2: Assumptions | C2: 2022 | D2: =C2+1 -> 2023 | E2: =D2+1 -> 2024 | F2: =E2+1 -> 2025 | G2: =F2+1 -> 2026 | H2: =G2+1 -> 2027 | I2: =H2+1 -> 2028 | J2: =I2+1 -> 2029
B4: Operating Cash % of sales | F4: =Assumptions!F38 -> 0.01 | G4: =F4 -> 0.01 | H4: =G4 -> 0.01 | I4: =H4 -> 0.01 | J4: =I4 -> 0.01
B5: Accounts receivable % of sales | F5: =Assumptions!F39 -> 0.065677152 | G5: =Assumptions!G39 -> 0.065677152 | H5: =Assumptions!H39 -> 0.065677152 | I5: =Assumptions!I39 -> 0.065677152 | J5: =Assumptions!J39 -> 0.065677152
B6: Inventories % of COGS | F6: =Assumptions!F40 -> 0.024814952 | G6: =Assumptions!G40 -> 0.024814952 | H6: =Assumptions!H40 -> 0.024814952 | I6: =Assumptions!I40 -> 0.024814952 | J6: =Assumptions!J40 -> 0.024814952
B7: Other current assets % of sales | F7: =Assumptions!F41 -> 0.072056741 | G7: =Assumptions!G41 -> 0.072056741 | H7: =Assumptions!H41 -> 0.072056741 | I7: =Assumptions!I41 -> 0.072056741 | J7: =Assumptions!J41 -> 0.072056741
B9: Other long-term assets % of sales | F9: =Assumptions!F44 -> 0.028262058 | G9: =Assumptions!G44 -> 0.028262058 | H9: =Assumptions!H44 -> 0.028262058 | I9: =Assumptions!I44 -> 0.028262058 | J9: =Assumptions!J44 -> 0.028262058
B10: Investment in unconsolidated entities $ balance | F10: =Assumptions!F43 -> 20638 | G10: =Assumptions!G43 -> 20638 | H10: =Assumptions!H43 -> 20638 | I10: =Assumptions!I43 -> 20638 | J10: =Assumptions!J43 -> 20638
B12: Accounts payable/Accural % of COGS | F12: =Assumptions!F48 -> 0.061892695 | G12: =Assumptions!G48 -> 0.061892695 | H12: =Assumptions!H48 -> 0.061892695 | I12: =Assumptions!I48 -> 0.061892695 | J12: =Assumptions!J48 -> 0.061892695
B13: Other current liabilities % of sales | F13: =Assumptions!F49 -> 0.060746649 | G13: =Assumptions!G49 -> 0.060746649 | H13: =Assumptions!H49 -> 0.060746649 | I13: =Assumptions!I49 -> 0.060746649 | J13: =Assumptions!J49 -> 0.060746649
B14: Other long-term liabilities % of sales | F14: =Assumptions!F50 -> 0.055495094 | G14: =Assumptions!G50 -> 0.055495094 | H14: =Assumptions!H50 -> 0.055495094 | I14: =Assumptions!I50 -> 0.055495094 | J14: =Assumptions!J50 -> 0.055495094
A16: Balance sheet | C16: =C2 -> 2022 | D16: =D2 -> 2023 | E16: =E2 -> 2024 | F16: =F2 -> 2025 | G16: =G2 -> 2026 | H16: =H2 -> 2027 | I16: =I2 -> 2028 | J16: =J2 -> 2029
B17: Operating Cash | C17: =1%*IncState!C16 -> 45371.58 | D17: =1%*IncState!D16 -> 44793.58 | E17: =1%*IncState!E16 -> 47064.16 | F17: =F4*IncState!F16 -> 49417.368 | G17: =G4*IncState!G16 -> 52629.497 | H17: =H4*IncState!H16 -> 55787.267 | I17: =I4*IncState!I16 -> 58855.566 | J17: =J4*IncState!J16 -> 61798.345
B18: Excess cash | C18: =60356-C17 -> 14984.42 | D18: =114098-D17 -> 69304.42 | E18: =186126-E17 -> 139061.84 | F18: =MAX(CashFlow!F23,0) -> 0 | G18: =MAX(CashFlow!G23,0) -> 13197.866 | H18: =MAX(CashFlow!H23,0) -> 586149.32 | I18: =MAX(CashFlow!I23,0) -> 1201421.7 | J18: =MAX(CashFlow!J23,0) -> 1858651.2
B19: Accounts receivable | C19: 257492 | D19: 282809 | E19: 309104 | F19: =F5*IncState!F16 -> 324559.2 | G19: =G5*IncState!G16 -> 345655.55 | H19: =H5*IncState!H16 -> 366394.88 | I19: =I5*IncState!I16 -> 386546.6 | J19: =J5*IncState!J16 -> 405873.93
B20: Inventories | C20: 81570 | D20: 82964 | E20: 70919 | F20: =F6*IncState!F17 -> 74219.692 | G20: =G6*IncState!G17 -> 78782.772 | H20: =H6*IncState!H17 -> 83232.867 | I20: =I6*IncState!I17 -> 87518.575 | J20: =J6*IncState!J17 -> 91587.799
B21: Other current assets | C21: =37287+162660+191289 -> 391236 | D21: =30215+106335+200870 -> 337420 | E21: =40363+103396+195370 -> 339129 | F21: =F7*IncState!F16 -> 356085.45 | G21: =G7*IncState!G16 -> 379231 | H21: =H7*IncState!H16 -> 401984.86 | I21: =I7*IncState!I16 -> 424094.03 | J21: =J7*IncState!J16 -> 445298.73
B22: Total current assets | C22: =SUM(C17:C21) -> 790654 | D22: =SUM(D17:D21) -> 817291 | E22: =SUM(E17:E21) -> 905278 | F22: =SUM(F17:F21) -> 804281.71 | G22: =SUM(G17:G21) -> 869496.69 | H22: =SUM(H17:H21) -> 1493549.2 | I22: =SUM(I17:I21) -> 2158436.5 | J22: =SUM(J17:J21) -> 2863210
B24: Property, plant & equipment, net | C24: =302235+219202 -> 521437 | D24: =304365+207323 -> 511688 | E24: =301179+210302 -> 511481 | F24: =Calcs!F9 -> 542313.74 | G24: =Calcs!G9 -> 575564.42 | H24: =Calcs!H9 -> 610688.1 | I24: =Calcs!I9 -> 647149.02 | J24: =Calcs!J9 -> 684416.86
B25: Intangible assets | C25: =11763+108354 -> 120117 | D25: =11688+134105 -> 145793 | E25: =11578+155025 -> 166603 | F25: =E25-IncState!F22 -> 166603 | G25: =F25-IncState!G22 -> 166603 | H25: =G25-IncState!H22 -> 166603 | I25: =H25-IncState!I22 -> 166603 | J25: =I25-IncState!J22 -> 166603
B26: Investment in unconsolidated entities | C26: 13395 | D26: 16720 | E26: =20638 -> 20638 | F26: =F10 -> 20638 | G26: =G10 -> 20638 | H26: =H10 -> 20638 | I26: =I10 -> 20638 | J26: =J10 -> 20638
B27: Other assets | C27: =125840+28852+1926 -> 156618 | D27: =143553+26174+13680 -> 183407 | E27: =82699+26882+23432 -> 133013 | F27: =F9*IncState!F16 -> 139663.65 | G27: =G9*IncState!G16 -> 148741.79 | H27: =H9*IncState!H16 -> 157666.29 | I27: =I9*IncState!I16 -> 166337.94 | J27: =J9*IncState!J16 -> 174654.84
B28: Total non-current assets | C28: =SUM(C24:C27) -> 811567 | D28: =SUM(D24:D27) -> 857608 | E28: =SUM(E24:E27) -> 831735 | F28: =SUM(F24:F27) -> 869218.39 | G28: =SUM(G24:G27) -> 911547.21 | H28: =SUM(H24:H27) -> 955595.39 | I28: =SUM(I24:I27) -> 1000728 | J28: =SUM(J24:J27) -> 1046312.7
A30: * | B30: TOTAL ASSETS | C30: =SUM(C28,C22) -> 1602221 | D30: =SUM(D28,D22) -> 1674899 | E30: =SUM(E28,E22) -> 1737013 | F30: =SUM(F28,F22) -> 1673500.1 | G30: =SUM(G28,G22) -> 1781043.9 | H30: =SUM(H28,H22) -> 2449144.6 | I30: =SUM(I28,I22) -> 3159164.5 | J30: =SUM(J28,J22) -> 3909522.7
B32: Revolver/Short term debt | C32: 0 | D32: 0 | E32: 0 | F32: =-MIN(CashFlow!F23,0) -> 517686.76 | G32: =-MIN(CashFlow!G23,0) -> 0 | H32: =-MIN(CashFlow!H23,0) -> 0 | I32: =-MIN(CashFlow!I23,0) -> 0 | J32: =-MIN(CashFlow!J23,0) -> 0
B33: Accounts payable/Accurals | C33: =89715+40442+34473 -> 164630 | D33: =106267+54689+33367 -> 194323 | E33: =85898+58203+32783 -> 176884 | F33: =F12*IncState!F17 -> 185116.49 | G33: =G12*IncState!G17 -> 196497.58 | H33: =H12*IncState!H17 -> 207596.87 | I33: =I12*IncState!I17 -> 218286.15 | J33: =J12*IncState!J17 -> 228435.49
B34: Other current liabilities | C34: =34877+31435+157909+92957 -> 317178 | D34: =39330+28135+104246+124950 -> 296661 | E34: =39920+25658+101567+118754 -> 285899 | F34: =F13*IncState!F16 -> 300193.95 | G34: =G13*IncState!G16 -> 319706.56 | H34: =H13*IncState!H16 -> 338888.95 | I34: =I13*IncState!I16 -> 357527.84 | J34: =J13*IncState!J16 -> 375404.23
B35: Total current liabilities | C35: =SUM(C32:C34) -> 481808 | D35: =SUM(D32:D34) -> 490984 | E35: =SUM(E32:E34) -> 462783 | F35: =SUM(F32:F34) -> 1002997.2 | G35: =SUM(G32:G34) -> 516204.14 | H35: =SUM(H32:H34) -> 546485.82 | I35: =SUM(I32:I34) -> 575813.99 | J35: =SUM(J32:J34) -> 603839.72
B37: Long-term debt, including current maturities | C37: =4967420+54813 -> 5022233 | D37: =56366+4934062 -> 4990428 | E37: =1149679+3825659 -> 4975338 | F37: =Debt!F20 -> 3825659 | G37: =Debt!G20 -> 3825659 | H37: =Debt!H20 -> 3825659 | I37: =Debt!I20 -> 3825659 | J37: =Debt!J20 -> 3825659
B38: Other long-term liabilities | C38: =195244+40179+7761+44061 -> 287245 | D38: =179548+38559+45747 -> 263854 | E38: =181983+33229+45971 -> 261183 | F38: =F14*IncState!F16 -> 274242.15 | G38: =G14*IncState!G16 -> 292067.89 | H38: =H14*IncState!H16 -> 309591.96 | I38: =I14*IncState!I16 -> 326619.52 | J38: =J14*IncState!J16 -> 342950.5
B39: Total non-current liabilities | C39: =SUM(C37:C38) -> 5309478 | D39: =SUM(D37:D38) -> 5254282 | E39: =SUM(E37:E38) -> 5236521 | F39: =SUM(F37:F38) -> 4099901.1 | G39: =SUM(G37:G38) -> 4117726.9 | H39: =SUM(H37:H38) -> 4135251 | I39: =SUM(I37:I38) -> 4152278.5 | J39: =SUM(J37:J38) -> 4168609.5
B41: Equity | C41: -4189065 | D41: -4070367 | E41: -3962291 | F41: =Calcs!F17 -> -3429398.2 | G41: =Calcs!G17 -> -2852887.1 | H41: =Calcs!H17 -> -2232592.2 | I41: =Calcs!I17 -> -1568928 | J41: =Calcs!J17 -> -862926.49
A42: * | B42: TOTAL LIABILITIES & EQUITY | C42: =SUM(C41,C39,C35) -> 1602221 | D42: =SUM(D41,D39,D35) -> 1674899 | E42: =SUM(E41,E39,E35) -> 1737013 | F42: =SUM(F41,F39,F35) -> 1673500.1 | G42: =SUM(G41,G39,G35) -> 1781043.9 | H42: =SUM(H41,H39,H35) -> 2449144.6 | I42: =SUM(I41,I39,I35) -> 3159164.5 | J42: =SUM(J41,J39,J35) -> 3909522.7
A44: * | B44: Balance check | C44: =C42-C30 -> 0 | D44: =D42-D30 -> 0 | E44: =E42-E30 -> 0 | F44: =F42-F30 -> 0 | G44: =G42-G30 -> 0 | H44: =H42-H30 -> 0 | I44: =I42-I30 -> 0 | J44: =J42-J30 -> 0

Sheet CashFlow
A1: =CoName -> Domino's Pizza Inc | C1: Hist. | D1: Hist. | E1: Hist. | F1: Proj. | G1: Proj. | H1: Proj. | I1: Proj. | J1: Proj.
A2: Cash flow statement | C2: 2022 | D2: =C2+1 -> 2023 | E2: =D2+1 -> 2024 | F2: =E2+1 -> 2025 | G2: =F2+1 -> 2026 | H2: =G2+1 -> 2027 | I2: =H2+1 -> 2028 | J2: =I2+1 -> 2029
B3: Net Income | F3: =IncState!F34 -> 756721.77 | G3: =IncState!G34 -> 814224.15 | H3: =IncState!H34 -> 871891.99 | I3: =IncState!I34 -> 929145.22 | J3: =IncState!J34 -> 985366.62
B4: Depreciation | F4: =IncState!F21 -> 87696.509 | G4: =IncState!G21 -> 92982.968 | H4: =IncState!H21 -> 98683.999 | I4: =IncState!I21 -> 104706.16 | J4: =IncState!J21 -> 110957.61
B5: Amortization | F5: =IncState!F22 -> 0 | G5: =IncState!G22 -> 0 | H5: =IncState!H22 -> 0 | I5: =IncState!I22 -> 0 | J5: =IncState!J22 -> 0
B6: (inc) / dec in OWC | F6: =Calcs!F26 -> -15538.115 | G6: =Calcs!G26 -> -21123.409 | H6: =Calcs!H26 -> -20819.374 | I6: =Calcs!I26 -> -20286.72 | J6: =Calcs!J26 -> -19518.308
B7: (inc) / dec in LT assets | F7: =BalSheet!E27-BalSheet!F27 -> -6650.65 | G7: =BalSheet!F27-BalSheet!G27 -> -9078.1372 | H7: =BalSheet!G27-BalSheet!H27 -> -8924.5072 | I7: =BalSheet!H27-BalSheet!I27 -> -8671.6462 | J7: =BalSheet!I27-BalSheet!J27 -> -8316.897
B8: inc / (dec) in LT liabilities | F8: =BalSheet!F38-BalSheet!E38 -> 13059.15 | G8: =BalSheet!G38-BalSheet!F38 -> 17825.74 | H8: =BalSheet!H38-BalSheet!G38 -> 17524.073 | I8: =BalSheet!I38-BalSheet!H38 -> 17027.558 | J8: =BalSheet!J38-BalSheet!I38 -> 16330.976
B9: CFFO | F9: =SUM(F3:F8) -> 835288.67 | G9: =SUM(G3:G8) -> 894831.31 | H9: =SUM(H3:H8) -> 958356.18 | I9: =SUM(I3:I8) -> 1021920.6 | J9: =SUM(J3:J8) -> 1084820
B11: Capex | F11: =-Calcs!F7 -> -118529.25 | G11: =-Calcs!G7 -> -126233.65 | H11: =-Calcs!H7 -> -133807.67 | I11: =-Calcs!I7 -> -141167.09 | J11: =-Calcs!J7 -> -148225.45
B12: CFFI | F12: =SUM(F11) -> -118529.25 | G12: =SUM(G11) -> -126233.65 | H12: =SUM(H11) -> -133807.67 | I12: =SUM(I11) -> -141167.09 | J12: =SUM(J11) -> -148225.45
B14: Dividends paid | F14: =-IncState!F36 -> -223829.02 | G14: =-IncState!G36 -> -237713.03 | H14: =-IncState!H36 -> -251597.05 | I14: =-IncState!I36 -> -265481.07 | J14: =-IncState!J36 -> -279365.08
B15: Debt issuance / (repayments) | F15: =SUM(Debt!F8:F9) -> -1149679 | G15: =SUM(Debt!G8:G9) -> 0 | H15: =SUM(Debt!H8:H9) -> 0 | I15: =SUM(Debt!I8:I9) -> 0 | J15: =SUM(Debt!J8:J9) -> 0
B16: Share issuance / (repurchases) | F16: =Calcs!F11 -> 0 | G16: =Calcs!G11 -> 0 | H16: =Calcs!H11 -> 0 | I16: =Calcs!I11 -> 0 | J16: =Calcs!J11 -> 0
B17: CFFF | F17: =SUM(F14:F16) -> -1373508 | G17: =SUM(G14:G16) -> -237713.03 | H17: =SUM(H14:H16) -> -251597.05 | I17: =SUM(I14:I16) -> -265481.07 | J17: =SUM(J14:J16) -> -279365.08
B19: Net changes In cash | F19: =SUM(F17,F12,F9) -> -656748.6 | G19: =SUM(G17,G12,G9) -> 530884.63 | H19: =SUM(H17,H12,H9) -> 572951.46 | I19: =SUM(I17,I12,I9) -> 615272.42 | J19: =SUM(J17,J12,J9) -> 657229.48
B21: Beginning cash | F21: =BalSheet!E18 -> 139061.84 | G21: =F23 -> -517686.76 | H21: =G23 -> 13197.866 | I21: =H23 -> 586149.32 | J21: =I23 -> 1201421.7
B22: =B19 -> Net changes In cash | F22: =F19 -> -656748.6 | G22: =G19 -> 530884.63 | H22: =H19 -> 572951.46 | I22: =I19 -> 615272.42 | J22: =J19 -> 657229.48
B23: Ending Cash | F23: =SUM(F21:F22) -> -517686.76 | G23: =SUM(G21:G22) -> 13197.866 | H23: =SUM(H21:H22) -> 586149.32 | I23: =SUM(I21:I22) -> 1201421.7 | J23: =SUM(J21:J22) -> 1858651.2

Sheet Free Cash Flow
A1: =CoName -> Domino's Pizza Inc | C1: Hist. | D1: Hist. | E1: Hist. | F1: Proj. | G1: Proj. | H1: Proj. | I1: Proj. | J1: Proj.
A2: Free Cash Flows | C2: 2022 | D2: =C2+1 -> 2023 | E2: =D2+1 -> 2024 | F2: =E2+1 -> 2025 | G2: =F2+1 -> 2026 | H2: =G2+1 -> 2027 | I2: =H2+1 -> 2028 | J2: =I2+1 -> 2029
A3: * | B3: Sales | F3: =IncState!F16 -> 4941736.8 | G3: =IncState!G16 -> 5262949.7 | H3: =IncState!H16 -> 5578726.7 | I3: =IncState!I16 -> 5885556.6 | J3: =IncState!J16 -> 6179834.5
B4: EBIT | F4: =IncState!F19 -> 957875.66 | G4: =IncState!G19 -> 1030663.5 | H4: =IncState!H19 -> 1103660.7 | I4: =IncState!I19 -> 1176133.2 | J4: =IncState!J19 -> 1247299.5
B5: Effective Tax Rate | F5: =Assumptions!F16 -> 0.21 | G5: =Assumptions!G16 -> 0.21 | H5: =Assumptions!H16 -> 0.21 | I5: =Assumptions!I16 -> 0.21 | J5: =Assumptions!J16 -> 0.21
A7: * | B7: NOPAT | F7: =F4*(1-F5) -> 756721.77 | G7: =G4*(1-G5) -> 814224.15 | H7: =H4*(1-H5) -> 871891.99 | I7: =I4*(1-I5) -> 929145.22 | J7: =J4*(1-J5) -> 985366.62
B8: Depreciation | F8: =CashFlow!F4 -> 87696.509 | G8: =CashFlow!G4 -> 92982.968 | H8: =CashFlow!H4 -> 98683.999 | I8: =CashFlow!I4 -> 104706.16 | J8: =CashFlow!J4 -> 110957.61
B9: Amortization | F9: =CashFlow!F5 -> 0 | G9: =CashFlow!G5 -> 0 | H9: =CashFlow!H5 -> 0 | I9: =CashFlow!I5 -> 0 | J9: =CashFlow!J5 -> 0
B10: (inc) / dec in OWC | F10: =CashFlow!F6 -> -15538.115 | G10: =CashFlow!G6 -> -21123.409 | H10: =CashFlow!H6 -> -20819.374 | I10: =CashFlow!I6 -> -20286.72 | J10: =CashFlow!J6 -> -19518.308
B11: (inc) / dec in other long-term assets | F11: =CashFlow!F7 -> -6650.65 | G11: =CashFlow!G7 -> -9078.1372 | H11: =CashFlow!H7 -> -8924.5072 | I11: =CashFlow!I7 -> -8671.6462 | J11: =CashFlow!J7 -> -8316.897
B12: inc / (dec) other long-term liabilities | F12: =CashFlow!F8 -> 13059.15 | G12: =CashFlow!G8 -> 17825.74 | H12: =CashFlow!H8 -> 17524.073 | I12: =CashFlow!I8 -> 17027.558 | J12: =CashFlow!J8 -> 16330.976
B13: (Capex) | F13: =CashFlow!F11 -> -118529.25 | G13: =CashFlow!G11 -> -126233.65 | H13: =CashFlow!H11 -> -133807.67 | I13: =CashFlow!I11 -> -141167.09 | J13: =CashFlow!J11 -> -148225.45
A15: * | B15: Free Cash Flow | F15: =SUM(F7:F13) -> 716759.42 | G15: =SUM(G7:G13) -> 768597.66 | H15: =SUM(H7:H13) -> 824548.51 | I15: =SUM(I7:I13) -> 880753.49 | J15: =SUM(J7:J13) -> 936594.56

Sheet WACC
A1: =CoName -> Domino's Pizza Inc
A3: * | B3: WACC | G3: Comp | H3: Levered beta | I3: Gross debt | J3: Market cap | K3: Debt/Mcap | L3: MTR | M3: Unlevered beta
B4: Tax Rate | E4: =Assumptions!F16 -> 0.21 | L4: =E4 -> 0.21 | M4: =H4/((1+K4*(1-L4))) -> 0
B5: Risk free rate | E5: 0.0415 | L5: =L4 -> 0.21 | M5: =H5/((1+K5*(1-L5))) -> 0
B6: Market risk Premium | E6: 0.05 | L6: =L5 -> 0.21 | M6: =H6/((1+K6*(1-L6))) -> 0
B7: Beta | E7: 0.82 | L7: =L6 -> 0.21 | M7: =H7/((1+K7*(1-L7))) -> 0
B8: Cost of Equity | E8: =E5+E6*E7 -> 0.0825
B9: % Equity | E9: =1-E10 -> 0.7024199 | G9: Industry beta (average) | M9: =AVERAGE(M4:M7) -> 0
B10: % Debt | E10: =SUM(BalSheet!F32,BalSheet!F37)/MAIN!F6 -> 0.2975801
B11: Cost of debt | E11: =Assumptions!F24 -> 0.03936818 | G11: Re-levered beta | M11: =M9*(1+E10*(1-E4)) -> 0
B12: Post tax cost of debt | E12: =E11*(1-E4) -> 0.031100862
A13: * | B13: WACC | E13: =WACC!E8*WACC!E9+WACC!E12*WACC!E10 -> 0.06720464
B14: Long Term growth rate | E14: 0.025

Sheet DCF Model
A1: =CoName -> Domino's Pizza Inc | D1: Proj. | E1: Proj. | F1: Proj. | G1: Proj. | H1: Proj.
A2: Discount Model Year count | D2: 0.5 | E2: =D2+1 -> 1.5 | F2: =E2+1 -> 2.5 | G2: =F2+1 -> 3.5 | H2: =G2+1 -> 4.5
B3: Discount Factor | D3: =1/(1+$K$17)^D2 -> 0.96800176 | E3: =1/(1+$K$17)^E2 -> 0.90704418 | F3: =1/(1+$K$17)^F2 -> 0.84992526 | G3: =1/(1+$K$17)^G2 -> 0.79640327 | H3: =1/(1+$K$17)^H2 -> 0.74625169
B4: PV FCF | D4: =D3*'Free Cash Flow'!F15 -> 693824.38 | E4: =E3*'Free Cash Flow'!G15 -> 697152.04 | F4: =F3*'Free Cash Flow'!H15 -> 700804.61 | G4: =G3*'Free Cash Flow'!I15 -> 701434.96 | H4: =H3*'Free Cash Flow'!J15 -> 698935.28
H5: =(H4*(1+K18))/(K17-K18) -> 16974642
A6: Value Calculation | E6: Multiples Calculation | I6: Dividend Discount
B7: Total PV of FCFs | C7: =SUM(D4:H4) -> 3492151.3 | E7: Total PV of FCFs | G7: =C7 -> 3492151.3 | I7: FY dividends | K7: =IncState!J36 -> 279365.08
B8: PV of TV | C8: =H5*H3 -> 12667356 | E8: Multiple TV | G8: =G10*H3*IncState!J23 -> 15204025 | I8: Equity Value | K8: =K7/(K17-K18) -> 6619297.9
B9: EV | C9: =SUM(C7:C8) -> 16159507 | E9: EV | G9: =SUM(G7:G8) -> 18696177
E10: Implied EBITDA multiple | G10: 15 | I10: Diluted S/O | K10: =G17 -> 33786
I11: Implied Share Price | K11: =K8/K10 -> 195.91837
B12: Cash & Cash Equiv | C12: =MAIN!F7 -> 342229 | E12: Cash & Cash Equiv | G12: =C12 -> 342229
B13: Debt & Claims | C13: =MAIN!F8 -> 5052715 | E13: Debt & Claims | G13: =C13 -> 5052715
B14: NCI | C14: 0 | E14: NCI | G14: =C14 -> 0
B15: Equity Value | C15: =C9+C12-SUM(C13:C14) -> 11449021 | E15: Equity Value | G15: =G9+G12-SUM(G13:G14) -> 13985691
B17: Diluted S/O | C17: =MAIN!F5 -> 33786 | E17: Diluted S/O | G17: =C17 -> 33786 | I17: WACC | K17: =WACC!E13 -> 0.06720464
A18: * | B18: Implied Share Price | C18: =C15/C17 -> 338.86878 | E18: Implied Share Price | G18: =G15/G17 -> 413.94929 | I18: Long Term growth rate | K18: 0.025
A20: Sensitivity analysis
C22: Discount rate variance | E22: 0.005 | J22: Discount rate variance | L22: 0.005
C23: Implied growth rate variance | E23: 0.0025 | J23: TV multiple variance | L23: 1
