Workbook
Name Ccy: MAIN!$C$6
Name circ: MAIN!$C$9
Name CoName: MAIN!$C$4
Name g: #REF!
Name IQ_CH: 110000
Name IQ_CQ: 5000
Name IQ_CY: 10000
Name IQ_DAILY: 500000
Name IQ_FH: 100000
Name IQ_FQ: 500
Name IQ_FY: 1000
Name IQ_LTM: 2000
Name IQ_MONTH: 15000
Name IQ_NTM: 6000
Name IQ_WEEK: 50000
Name IQ_YTD: 3000
Name OpCase: [1]DCF!$E$98
Name ScenarioREV: Assumptions!$D$4
Name TTS: #REF!
Name Units: MAIN!$C$7

Sheet MAIN
A1: =CoName -> Jack In the Box Inc.
A2: Model Details
B4: Company name | C4: Jack In the Box Inc. | E4: Current Stock Price | F4: 21 | H4: Operating Case One | I4: Perpetuity
B5: Latest BS date | C5: 247.43 | E5: Diluted s/o | F5: 18882 | H5: Implied Price | I5: ='DCF Model'!C18 -> 19.379611
B6: Currency | C6: USD | E6: Mkt Cap | F6: =F5*F4 -> 396522 | H6: Difference | I6: =I5/$F$4-1 -> -0.07716138
B7: Units | C7: m | E7: Cash | F7: =38014+30097 -> 68111
B8: Analyst name | C8: Alan Chen | E8: Debt | F8: =1680812+1260670 -> 2941482
B9: Circular switch | C9: 1 | E9: EV | F9: =F6-F7+F8 -> 3269893

Sheet Quarterly Projections

Sheet Assumptions
A1: =CoName -> Jack In the Box Inc. | C1: Hist. | D1: Hist. | E1: Hist. | F1: Proj. | G1: Proj. | H1: Proj. | I1: Proj. | J1: Proj.
A2: * | B2: Income Statement | C2: 2022 | D2: =C2+1 -> 2023 | E2: =D2+1 -> 2024 | F2: =E2+1 -> 2025 | G2: =F2+1 -> 2026 | H2: =G2+1 -> 2027 | I2: =H2+1 -> 2028 | J2: =I2+1 -> 2029
B4: Operating Case | D4: 1
D5: Variance
B6: Street Case | D6: 0 | F6: -0.16 | G6: -0.015 | H6: 0.01 | I6: 0.01 | J6: 0.01
B7: Optimistic Case | D7: 0.025 | F7: =F6+$D$7 -> -0.135 | G7: =G6+$D$7 -> 0.01 | H7: =H6+$D$7 -> 0.035 | I7: =I6+$D$7 -> 0.035 | J7: =J6+$D$7 -> 0.035
B8: Pessimistic Case | D8: -0.025 | F8: =F6+$D$8 -> -0.185 | G8: =G6+$D$8 -> -0.04 | H8: =H6+$D$8 -> -0.015 | I8: =I6+$D$8 -> -0.015 | J8: =J6+$D$8 -> -0.015
B10: Revenue Growth | D10: =IncState!D15/IncState!C15-1 -> 0.15273183 | E10: =IncState!E15/IncState!D15-1 -> -0.071500072 | F10: =CHOOSE(ScenarioREV,F6,F7,F8) -> -0.16 | G10: =CHOOSE(ScenarioREV,G6,G7,G8) -> -0.015 | H10: =CHOOSE(ScenarioREV,H6,H7,H8) -> 0.01 | I10: =CHOOSE(ScenarioREV,I6,I7,I8) -> 0.01 | J10: =CHOOSE(ScenarioREV,J6,J7,J8) -> 0.01
B11: COGS % of sales | C11: =IncState!C16/IncState!C15 -> 0.70484366 | D11: =IncState!D16/IncState!D15 -> 0.69973752 | E11: =IncState!E16/IncState!E15 -> 0.69904525 | F11: =E11 -> 0.69904525 | G11: =F11 -> 0.69904525 | H11: =G11 -> 0.69904525 | I11: =H11 -> 0.69904525 | J11: =I11 -> 0.69904525
B12: SG&A % of sales | C12: =IncState!C17/IncState!C15 -> 0.12604464 | D12: =IncState!D17/IncState!D15 -> 0.13554464 | E12: =IncState!E17/IncState!E15 -> 0.14493167 | F12: =E12 -> 0.14493167 | G12: =F12 -> 0.14493167 | H12: =G12 -> 0.14493167 | I12: =H12 -> 0.14493167 | J12: =I12 -> 0.14493167
B13: Amortization $ Amt | C13: =IncState!C21 -> 0 | D13: =IncState!D21 -> 0 | E13: =IncState!E21 -> 0 | F13: =E13 -> 0 | G13: =F13 -> 0 | H13: =G13 -> 0 | I13: =H13 -> 0 | J13: =I13 -> 0
B14: Non recurring income / (expense) | C14: =IncState!C24 -> 0 | D14: =IncState!D24 -> 0 | E14: =IncState!E24 -> -162624 | F14: 0 | G14: 0 | H14: 0 | I14: 0 | J14: 0
B15: Other Income / (expense) | C15: =IncState!C25 -> -303 | D15: =IncState!D25 -> -6967 | E15: =IncState!E25 -> -6843 | F15: 0 | G15: 0 | H15: 0 | I15: 0 | J15: 0
B16: Effective tax rate | C16: =IncState!C32/IncState!C30 -> 0.28482569 | D16: =IncState!D32/IncState!D30 -> 0.30904194 | E16: =IncState!E32/IncState!E30 -> -7.4883183 | F16: 0.23 | G16: =F16 -> 0.23 | H16: =G16 -> 0.23 | I16: =H16 -> 0.23 | J16: =I16 -> 0.23
B17: Basic WASO | C17: =IncState!C35 -> 21205.311 | D17: =IncState!D35 -> 20602.52 | E17: =IncState!E35 -> 19622.995 | F17: =E17 -> 19622.995 | G17: =F17 -> 19622.995 | H17: =G17 -> 19622.995 | I17: =H17 -> 19622.995 | J17: =I17 -> 19622.995
B18: Diluted WASO | C18: =IncState!C36 -> 21244.22 | D18: =IncState!D36 -> 20766.032 | E18: =IncState!E36 -> 19622.995 | F18: =E18 -> 19622.995 | G18: =F18 -> 19622.995 | H18: =G18 -> 19622.995 | I18: =H18 -> 19622.995 | J18: =I18 -> 19622.995
A20: * | B20: Debt | C20: =C2 -> 2022 | D20: =D2 -> 2023 | E20: =E2 -> 2024 | F20: =F2 -> 2025 | G20: =G2 -> 2026 | H20: =H2 -> 2027 | I20: =I2 -> 2028 | J20: =J2 -> 2029
B22: Interest rate on Revolver | E22: =E23+0.01 -> 0.05197 | F22: =E22 -> 0.05197 | G22: =F22 -> 0.05197 | H22: =G22 -> 0.05197 | I22: =H22 -> 0.05197 | J22: =I22 -> 0.05197
B23: Interest rate on long-term debt | E23: 0.04197 | F23: =E23 -> 0.04197 | G23: =F23 -> 0.04197 | H23: =G23 -> 0.04197 | I23: =H23 -> 0.04197 | J23: =I23 -> 0.04197
B24: Interest rate on cash | E24: 0.04 | F24: =E24 -> 0.04 | G24: =F24 -> 0.04 | H24: =G24 -> 0.04 | I24: =H24 -> 0.04 | J24: =I24 -> 0.04
B26: Issuance of long-term debt | F26: 0 | G26: 0 | H26: 0 | I26: 0 | J26: 0
B27: Repayment of long-term debt | D27: -30169 | E27: -29964 | F27: -35880 | G27: =F27-(-F27+E27) -> -41796 | H27: =G27-(-G27+F27) -> -47712 | I27: =H27-(-H27+G27) -> -53628 | J27: =I27-(-I27+H27) -> -59544
A29: * | B29: Calcs | C29: =C20 -> 2022 | D29: =D20 -> 2023 | E29: =E20 -> 2024 | F29: =F20 -> 2025 | G29: =G20 -> 2026 | H29: =H20 -> 2027 | I29: =I20 -> 2028 | J29: =J20 -> 2029
B31: CapEx % of Sales | C31: =46475/IncState!C15 -> 0.031656929 | D31: =74954/IncState!D15 -> 0.044291044 | E31: =115474/IncState!E15 -> 0.073489187 | F31: =E31 -> 0.073489187 | G31: =F31-0.005 -> 0.068489187 | H31: =G31-0.005 -> 0.063489187 | I31: =H31-0.005 -> 0.058489187 | J31: =I31-0.005 -> 0.053489187
B32: Depreciation % of beginning PP&E | D32: =IncState!D20/BalSheet!C23 -> 0.035586491 | E32: =IncState!E20/BalSheet!D23 -> 0.033032988 | F32: =E32 -> 0.033032988 | G32: =F32 -> 0.033032988 | H32: =G32 -> 0.033032988 | I32: =H32 -> 0.033032988 | J32: =I32 -> 0.033032988
B33: Share issuance / (repurchases) | F33: 0 | G33: 0 | H33: 0 | I33: 0 | J33: 0
A35: * | B35: Balance Sheet - Assets | C35: =C29 -> 2022 | D35: =D29 -> 2023 | E35: =E29 -> 2024 | F35: =F29 -> 2025 | G35: =G29 -> 2026 | H35: =H29 -> 2027 | I35: =I29 -> 2028 | J35: =J29 -> 2029
B37: Operating Cash % of sales | C37: =BalSheet!C16/IncState!C15 -> 0.01 | D37: =BalSheet!D16/IncState!D15 -> 0.01 | E37: =BalSheet!E16/IncState!E15 -> 0.01 | F37: =E37 -> 0.01 | G37: =F37 -> 0.01 | H37: =G37 -> 0.01 | I37: =H37 -> 0.01 | J37: =I37 -> 0.01
B38: Accounts receivable % of sales | C38: =BalSheet!C18/IncState!C15 -> 0.070706493 | D38: =BalSheet!D18/IncState!D15 -> 0.058900695 | E38: =BalSheet!E18/IncState!E15 -> 0.053183148 | F38: =E38 -> 0.053183148 | G38: =F38 -> 0.053183148 | H38: =G38 -> 0.053183148 | I38: =H38 -> 0.053183148 | J38: =I38 -> 0.053183148
B39: Inventories % of COGS | C39: =BalSheet!C19/IncState!C16 -> 0.0050871257 | D39: =BalSheet!D19/IncState!D16 -> 0.0032900681 | E39: =BalSheet!E19/IncState!E16 -> 0.0035706027 | F39: =E39 -> 0.0035706027 | G39: =F39 -> 0.0035706027 | H39: =G39 -> 0.0035706027 | I39: =H39 -> 0.0035706027 | J39: =I39 -> 0.0035706027
B40: Other current assets % of sales | C40: =BalSheet!C20/IncState!C15 -> 0.044299948 | D40: =BalSheet!D20/IncState!D15 -> 0.038265538 | E40: =BalSheet!E20/IncState!E15 -> 0.043939882 | F40: =E40 -> 0.043939882 | G40: =F40 -> 0.043939882 | H40: =G40 -> 0.043939882 | I40: =H40 -> 0.043939882 | J40: =I40 -> 0.043939882
B42: Other long-term assets % of sales | C42: =BalSheet!C25/IncState!C15 -> 0.15432983 | D42: =BalSheet!D25/IncState!D15 -> 0.1422361 | E42: =BalSheet!E25/IncState!E15 -> 0.16483486 | F42: =E42 -> 0.16483486 | G42: =F42 -> 0.16483486 | H42: =G42 -> 0.16483486 | I42: =H42 -> 0.16483486 | J42: =I42 -> 0.16483486
A44: * | B44: Balance Sheet - Liabilities | C44: =C35 -> 2022 | D44: =D35 -> 2023 | E44: =E35 -> 2024 | F44: =F35 -> 2025 | G44: =G35 -> 2026 | H44: =H35 -> 2027 | I44: =I35 -> 2028 | J44: =J35 -> 2029
B46: Accounts payable % of COGS | C46: =BalSheet!C31/IncState!C16 -> 0.30944394 | D46: =BalSheet!D31/IncState!D16 -> 0.32692772 | E46: =BalSheet!E31/IncState!E16 -> 0.2151848 | F46: =E46 -> 0.2151848 | G46: =F46 -> 0.2151848 | H46: =G46 -> 0.2151848 | I46: =H46 -> 0.2151848 | J46: =I46 -> 0.2151848
B47: Other current liabilities % of sales | C47: =BalSheet!C32/IncState!C15 -> 0.11669027 | D47: =BalSheet!D32/IncState!D15 -> 0.084215266 | E47: =BalSheet!E32/IncState!E15 -> 0.10310977 | F47: =E47 -> 0.10310977 | G47: =F47 -> 0.10310977 | H47: =G47 -> 0.10310977 | I47: =H47 -> 0.10310977 | J47: =I47 -> 0.10310977
B48: Other long-term liabilities % of sales | C48: =BalSheet!C36/IncState!C15 -> 0.91103432 | D48: =BalSheet!D36/IncState!D15 -> 0.84787621 | E48: =BalSheet!E36/IncState!E15 -> 0.92517625 | F48: =E48 -> 0.92517625 | G48: =F48 -> 0.92517625 | H48: =G48 -> 0.92517625 | I48: =H48 -> 0.92517625 | J48: =I48 -> 0.92517625

Sheet Calcs
A1: =CoName -> Jack In the Box Inc. | C1: Hist. | D1: Hist. | E1: Hist. | F1: Proj. | G1: Proj. | H1: Proj. | I1: Proj. | J1: Proj.
A2: Net PP&E | C2: 2022 | D2: =C2+1 -> 2023 | E2: =D2+1 -> 2024 | F2: =E2+1 -> 2025 | G2: =F2+1 -> 2026 | H2: =G2+1 -> 2027 | I2: =H2+1 -> 2028 | J2: =I2+1 -> 2029
B3: Capital expenditure % of sales | F3: =Assumptions!F31 -> 0.073489187 | G3: =Assumptions!G31 -> 0.068489187 | H3: =Assumptions!H31 -> 0.063489187 | I3: =Assumptions!I31 -> 0.058489187 | J3: =Assumptions!J31 -> 0.053489187
B4: Depreciation % of PP&E | F4: =Assumptions!F32 -> 0.033032988 | G4: =F4 -> 0.033032988 | H4: =G4 -> 0.033032988 | I4: =H4 -> 0.033032988 | J4: =I4 -> 0.033032988
B6: Beginning PP&E | F6: =E9 -> 1840122 | G6: =F9 -> 1876335.4 | H6: =G9 -> 1903397.2 | I6: =H9 -> 1923889.9 | J6: =I9 -> 1937908.2
B7: Capex | F7: =F3*IncState!F15 -> 96998.16 | G7: =G3*IncState!G15 -> 89042.695 | H7: =H3*IncState!H15 -> 83367.624 | I7: =I3*IncState!I15 -> 77570.147 | J7: =J3*IncState!J15 -> 71648.384
B8: Depreciation | F8: =F6*F4 -> 60784.728 | G8: =G6*G4 -> 61980.966 | H8: =H6*H4 -> 62874.896 | I8: =I6*I4 -> 63551.832 | J8: =J6*J4 -> 64014.899
B9: Ending PP&E | E9: =BalSheet!E23 -> 1840122 | F9: =F6+F7-F8 -> 1876335.4 | G9: =G6+G7-G8 -> 1903397.2 | H9: =H6+H7-H8 -> 1923889.9 | I9: =I6+I7-I8 -> 1937908.2 | J9: =J6+J7-J8 -> 1945541.7
A10: Equity | C10: =C2 -> 2022 | D10: =D2 -> 2023 | E10: =E2 -> 2024 | F10: =F2 -> 2025 | G10: =G2 -> 2026 | H10: =H2 -> 2027 | I10: =I2 -> 2028 | J10: =J2 -> 2029
B11: Share issuance/(repurchases) | F11: =Assumptions!F33 -> 0 | G11: =Assumptions!G33 -> 0 | H11: =Assumptions!H33 -> 0 | I11: =Assumptions!I33 -> 0 | J11: =Assumptions!J33 -> 0
B13: Beginning balance | F13: =E16 -> -851798 | G13: =F16 -> -740963.29 | H13: =G16 -> -632043.16 | I13: =H16 -> -522157.6 | J13: =I16 -> -411170.92
B14: Net income | F14: =IncState!F33 -> 110834.71 | G14: =IncState!G33 -> 108920.13 | H14: =IncState!H33 -> 109885.56 | I14: =IncState!I33 -> 110986.68 | J14: =IncState!J33 -> 112827.02
B15: Share issuance / (repurchase) | F15: =F11 -> 0 | G15: =G11 -> 0 | H15: =H11 -> 0 | I15: =I11 -> 0 | J15: =J11 -> 0
B16: Ending balance | E16: =BalSheet!E39 -> -851798 | F16: =SUM(F13:F15) -> -740963.29 | G16: =SUM(G13:G15) -> -632043.16 | H16: =SUM(H13:H15) -> -522157.6 | I16: =SUM(I13:I15) -> -411170.92 | J16: =SUM(J13:J15) -> -298343.91
A17: OWC | C17: =C10 -> 2022 | D17: =D10 -> 2023 | E17: =E10 -> 2024 | F17: =F10 -> 2025 | G17: =G10 -> 2026 | H17: =H10 -> 2027 | I17: =I10 -> 2028 | J17: =J10 -> 2029
B18: Operating Cash | E18: =BalSheet!E16 -> 15713.06 | F18: =BalSheet!F16 -> 13198.97 | G18: =BalSheet!G16 -> 13000.986 | H18: =BalSheet!H16 -> 13130.996 | I18: =BalSheet!I16 -> 13262.306 | J18: =BalSheet!J16 -> 13394.929
B19: =BalSheet!B18 -> Accounts receivable | E19: =BalSheet!E18 -> 83567 | F19: =BalSheet!F18 -> 70196.28 | G19: =BalSheet!G18 -> 69143.336 | H19: =BalSheet!H18 -> 69834.769 | I19: =BalSheet!I18 -> 70533.117 | J19: =BalSheet!J18 -> 71238.448
B20: =BalSheet!B19 -> Inventories | E20: =BalSheet!E19 -> 3922 | F20: =BalSheet!F19 -> 3294.48 | G20: =BalSheet!G19 -> 3245.0628 | H20: =BalSheet!H19 -> 3277.5134 | I20: =BalSheet!I19 -> 3310.2886 | J20: =BalSheet!J19 -> 3343.3914
B21: Other current assets | E21: =BalSheet!E20 -> 69043 | F21: =BalSheet!F20 -> 57996.12 | G21: =BalSheet!G20 -> 57126.178 | H21: =BalSheet!H20 -> 57697.44 | I21: =BalSheet!I20 -> 58274.414 | J21: =BalSheet!J20 -> 58857.159
B22: Accounts payables | E22: =BalSheet!E31 -> 236362 | F22: =BalSheet!F31 -> 198544.08 | G22: =BalSheet!G31 -> 195565.92 | H22: =BalSheet!H31 -> 197521.58 | I22: =BalSheet!I31 -> 199496.79 | J22: =BalSheet!J31 -> 201491.76
B23: Other current liabilities | E23: =BalSheet!E32 -> 162017 | F23: =BalSheet!F32 -> 136094.28 | G23: =BalSheet!G32 -> 134052.87 | H23: =BalSheet!H32 -> 135393.39 | I23: =BalSheet!I32 -> 136747.33 | J23: =BalSheet!J32 -> 138114.8
A24: * | B24: OWC | E24: =SUM(E18:E21)-SUM(E22:E23) -> -226133.94 | F24: =SUM(F18:F21)-SUM(F22:F23) -> -189952.51 | G24: =SUM(G18:G21)-SUM(G22:G23) -> -187103.22 | H24: =SUM(H18:H21)-SUM(H22:H23) -> -188974.25 | I24: =SUM(I18:I21)-SUM(I22:I23) -> -190864 | J24: =SUM(J18:J21)-SUM(J22:J23) -> -192772.64
B25: Change in OWC | F25: =E24-F24 -> -36181.43 | G25: =F24-G24 -> -2849.2876 | H25: =G24-H24 -> 1871.0322 | I25: =H24-I24 -> 1889.7425 | J25: =I24-J24 -> 1908.64

Sheet Debt
A1: =CoName -> Jack In the Box Inc. | C1: Hist. | D1: Hist. | E1: Hist. | F1: Proj. | G1: Proj. | H1: Proj. | I1: Proj. | J1: Proj.
A2: Assumptions | C2: 2022 | D2: =C2+1 -> 2023 | E2: =D2+1 -> 2024 | F2: =E2+1 -> 2025 | G2: =F2+1 -> 2026 | H2: =G2+1 -> 2027 | I2: =H2+1 -> 2028 | J2: =I2+1 -> 2029
B4: Interest rate on revolver | F4: =Assumptions!F22 -> 0.05197 | G4: =Assumptions!G22 -> 0.05197 | H4: =Assumptions!H22 -> 0.05197 | I4: =Assumptions!I22 -> 0.05197 | J4: =Assumptions!J22 -> 0.05197
B5: Interest rate on long-term debt | F5: =Assumptions!F23 -> 0.04197 | G5: =Assumptions!G23 -> 0.04197 | H5: =Assumptions!H23 -> 0.04197 | I5: =Assumptions!I23 -> 0.04197 | J5: =Assumptions!J23 -> 0.04197
B6: Interest rate on cash | F6: =Assumptions!F24 -> 0.04 | G6: =Assumptions!G24 -> 0.04 | H6: =Assumptions!H24 -> 0.04 | I6: =Assumptions!I24 -> 0.04 | J6: =Assumptions!J24 -> 0.04
B8: Issuance of long-term debt | F8: =Assumptions!F26 -> 0 | G8: =Assumptions!G26 -> 0 | H8: =Assumptions!H26 -> 0 | I8: =Assumptions!I26 -> 0 | J8: =Assumptions!J26 -> 0
B9: Repayment of long-term debt | F9: =Assumptions!F27 -> -35880 | G9: =Assumptions!G27 -> -41796 | H9: =Assumptions!H27 -> -47712 | I9: =Assumptions!I27 -> -53628 | J9: =Assumptions!J27 -> -59544
A11: Revolver | C11: =C2 -> 2022 | D11: =D2 -> 2023 | E11: =E2 -> 2024 | F11: =F2 -> 2025 | G11: =G2 -> 2026 | H11: =H2 -> 2027 | I11: =I2 -> 2028 | J11: =J2 -> 2029
B12: Balance | F12: =BalSheet!F30 -> 179564.85 | G12: =BalSheet!G30 -> 157405.32 | H12: =BalSheet!H30 -> 103968.27 | I12: =BalSheet!I30 -> 48754.128 | J12: =BalSheet!J30 -> 0
B13: Interest rate | F13: =F4 -> 0.05197 | G13: =G4 -> 0.05197 | H13: =H4 -> 0.05197 | I13: =I4 -> 0.05197 | J13: =J4 -> 0.05197
B14: Interest expense | F14: =F12*F13 -> 9331.9853 | G14: =G12*G13 -> 8180.3547 | H14: =H12*H13 -> 5403.2312 | I14: =I12*I13 -> 2533.752 | J14: =J12*J13 -> 0
A16: Long term debt | C16: =C11 -> 2022 | D16: =D11 -> 2023 | E16: =E11 -> 2024 | F16: =F11 -> 2025 | G16: =G11 -> 2026 | H16: =H11 -> 2027 | I16: =I11 -> 2028 | J16: =J11 -> 2029
B17: Beginning balance | F17: =E20 -> 1735313 | G17: =F20 -> 1699433 | H17: =G20 -> 1657637 | I17: =H20 -> 1609925 | J17: =I20 -> 1556297
B18: Issuance | F18: =F8 -> 0 | G18: =G8 -> 0 | H18: =H8 -> 0 | I18: =I8 -> 0 | J18: =J8 -> 0
B19: Repayment | F19: =F9 -> -35880 | G19: =G9 -> -41796 | H19: =H9 -> -47712 | I19: =I9 -> -53628 | J19: =J9 -> -59544
B20: Ending balance | E20: =BalSheet!E35 -> 1735313 | F20: =SUM(F17:F19) -> 1699433 | G20: =SUM(G17:G19) -> 1657637 | H20: =SUM(H17:H19) -> 1609925 | I20: =SUM(I17:I19) -> 1556297 | J20: =SUM(J17:J19) -> 1496753
B21: Interest rate | F21: =F5 -> 0.04197 | G21: =G5 -> 0.04197 | H21: =H5 -> 0.04197 | I21: =I5 -> 0.04197 | J21: =J5 -> 0.04197
B22: Interest expense | F22: =F20*-F21 -> -71325.203 | G22: =G20*-G21 -> -69571.025 | H22: =H20*-H21 -> -67568.552 | I22: =I20*-I21 -> -65317.785 | J22: =J20*-J21 -> -62818.723
A24: Debt summary | C24: =C16 -> 2022 | D24: =D16 -> 2023 | E24: =E16 -> 2024 | F24: =F16 -> 2025 | G24: =G16 -> 2026 | H24: =H16 -> 2027 | I24: =I16 -> 2028 | J24: =J16 -> 2029
B25: Revolver | F25: =-F12 -> -179564.85 | G25: =G12 -> 157405.32 | H25: =H12 -> 103968.27 | I25: =I12 -> 48754.128 | J25: =J12 -> 0
B26: Total long term debt | F26: =F20 -> 1699433 | G26: =G20 -> 1657637 | H26: =H20 -> 1609925 | I26: =I20 -> 1556297 | J26: =J20 -> 1496753
B27: Total debt | F27: =SUM(F25:F26) -> 1519868.1 | G27: =SUM(G25:G26) -> 1815042.3 | H27: =SUM(H25:H26) -> 1713893.3 | I27: =SUM(I25:I26) -> 1605051.1 | J27: =SUM(J25:J26) -> 1496753
B28: Total interest expense | F28: =SUM(F22,F14) -> -61993.218 | G28: =SUM(G22,G14) -> -61390.67 | H28: =SUM(H22,H14) -> -62165.321 | I28: =SUM(I22,I14) -> -62784.033 | J28: =SUM(J22,J14) -> -62818.723
A30: Interest income | C30: =C11 -> 2022 | D30: =D11 -> 2023 | E30: =E11 -> 2024 | F30: =F11 -> 2025 | G30: =G11 -> 2026 | H30: =H11 -> 2027 | I30: =I11 -> 2028 | J30: =J11 -> 2029
B31: Excess Cash | F31: =BalSheet!F17 -> 0 | G31: =BalSheet!G17 -> 0 | H31: =BalSheet!H17 -> 0 | I31: =BalSheet!I17 -> 0 | J31: =BalSheet!J17 -> 8887.9249
B32: Interest rate | F32: =F6 -> 0.04 | G32: =G6 -> 0.04 | H32: =H6 -> 0.04 | I32: =I6 -> 0.04 | J32: =J6 -> 0.04
B33: Interest income | F33: =F31*F32 -> 0 | G33: =G31*G32 -> 0 | H33: =H31*H32 -> 0 | I33: =I31*I32 -> 0 | J33: =J31*J32 -> 355.517

Sheet IncState
A1: =CoName -> Jack In the Box Inc. | C1: Hist. | D1: Hist. | E1: Hist. | F1: Proj. | G1: Proj. | H1: Proj. | I1: Proj. | J1: Proj.
A2: Assumptions | C2: 2022 | D2: =C2+1 -> 2023 | E2: =D2+1 -> 2024 | F2: =E2+1 -> 2025 | G2: =F2+1 -> 2026 | H2: =G2+1 -> 2027 | I2: =H2+1 -> 2028 | J2: =I2+1 -> 2029
B4: Revenue growth | F4: =Assumptions!F10 -> -0.16 | G4: =Assumptions!G10 -> -0.015 | H4: =Assumptions!H10 -> 0.01 | I4: =Assumptions!I10 -> 0.01 | J4: =Assumptions!J10 -> 0.01
B5: Cost of goods sold as % of sales | F5: =Assumptions!F11 -> 0.69904525 | G5: =Assumptions!G11 -> 0.69904525 | H5: =Assumptions!H11 -> 0.69904525 | I5: =Assumptions!I11 -> 0.69904525 | J5: =Assumptions!J11 -> 0.69904525
B6: SG&A % of sales | F6: =Assumptions!F12 -> 0.14493167 | G6: =Assumptions!G12 -> 0.14493167 | H6: =Assumptions!H12 -> 0.14493167 | I6: =Assumptions!I12 -> 0.14493167 | J6: =Assumptions!J12 -> 0.14493167
B7: Amortization amount | F7: =Assumptions!F13 -> 0 | G7: =Assumptions!G13 -> 0 | H7: =Assumptions!H13 -> 0 | I7: =Assumptions!I13 -> 0 | J7: =Assumptions!J13 -> 0
B8: Non recurring items, amount | F8: =Assumptions!F14 -> 0 | G8: =Assumptions!G14 -> 0 | H8: =Assumptions!H14 -> 0 | I8: =Assumptions!I14 -> 0 | J8: =Assumptions!J14 -> 0
B9: Other income (expense), amt | F9: =Assumptions!F15 -> 0 | G9: =Assumptions!G15 -> 0 | H9: =Assumptions!H15 -> 0 | I9: =Assumptions!I15 -> 0 | J9: =Assumptions!J15 -> 0
B10: Effective tax rate | F10: =Assumptions!F16 -> 0.23 | G10: =Assumptions!G16 -> 0.23 | H10: =Assumptions!H16 -> 0.23 | I10: =Assumptions!I16 -> 0.23 | J10: =Assumptions!J16 -> 0.23
B11: Basic WASO | F11: =Assumptions!F17 -> 19622.995 | G11: =Assumptions!G17 -> 19622.995 | H11: =Assumptions!H17 -> 19622.995 | I11: =Assumptions!I17 -> 19622.995 | J11: =Assumptions!J17 -> 19622.995
B12: Diluted WASO | F12: =Assumptions!F18 -> 19622.995 | G12: =Assumptions!G18 -> 19622.995 | H12: =Assumptions!H18 -> 19622.995 | I12: =Assumptions!I18 -> 19622.995 | J12: =Assumptions!J18 -> 19622.995
A14: Income statement | C14: =C34 -> 44926 | D14: =D34 -> 45291 | E14: =E34 -> 45657 | F14: =F34 -> 46022 | G14: =G34 -> 46022 | H14: =H34 -> 46022 | I14: =I34 -> 46022 | J14: =J34 -> 46022
B15: Revenue | C15: 1468083 | D15: 1692306 | E15: 1571306 | F15: =E15*(1+F4) -> 1319897 | G15: =F15*(1+G4) -> 1300098.6 | H15: =G15*(1+H4) -> 1313099.6 | I15: =H15*(1+I4) -> 1326230.6 | J15: =I15*(1+J4) -> 1339492.9
B16: COGS | C16: =216345+232250+135803+215609+16490+218272 -> 1034769 | D16: =250836+274598+163273+229602+12328+253533 -> 1184170 | E16: =199271+238047+139305+245379+17281+259131 -> 1098414 | F16: =F15*F5 -> 922667.76 | G16: =G15*G5 -> 908827.74 | H16: =H15*H5 -> 917916.02 | I16: =I15*I5 -> 927095.18 | J16: =J15*J5 -> 936366.13
B17: SG&A | C17: =130823+56100+1110+889-3878 -> 185044 | D17: =172872+62287+1385+10837-17998 -> 229383 | E17: =143233+59776+3182+24796-3255 -> 227732 | F17: =F15*F6 -> 191294.88 | G17: =G15*G6 -> 188425.46 | H17: =H15*H6 -> 190309.71 | I17: =I15*I6 -> 192212.81 | J17: =J15*J6 -> 194134.94
A18: * | B18: EBIT | C18: =C15-SUM(C16:C17) -> 248270 | D18: =D15-SUM(D16:D17) -> 278753 | E18: =E15-SUM(E16:E17) -> 245160 | F18: =F15-SUM(F16:F17) -> 205934.4 | G18: =G15-SUM(G16:G17) -> 202845.38 | H18: =H15-SUM(H16:H17) -> 204873.84 | I18: =I15-SUM(I16:I17) -> 206922.58 | J18: =J15-SUM(J16:J17) -> 208991.8
B20: Depreciation | C20: 56100 | D20: 62287 | E20: 59776 | F20: =Calcs!F8 -> 60784.728 | G20: =Calcs!G8 -> 61980.966 | H20: =Calcs!H8 -> 62874.896 | I20: =Calcs!I8 -> 63551.832 | J20: =Calcs!J8 -> 64014.899
B21: Amortization | C21: 0 | D21: 0 | E21: 0 | F21: =F7 -> 0 | G21: =G7 -> 0 | H21: =H7 -> 0 | I21: =I7 -> 0 | J21: =J7 -> 0
A22: * | B22: EBITDA | C22: =SUM(C18,C20:C21) -> 304370 | D22: =SUM(D18,D20:D21) -> 341040 | E22: =SUM(E18,E20:E21) -> 304936 | F22: =SUM(F18,F20:F21) -> 266719.13 | G22: =SUM(G18,G20:G21) -> 264826.35 | H22: =SUM(H18,H20:H21) -> 267748.73 | I22: =SUM(I18,I20:I21) -> 270474.41 | J22: =SUM(J18,J20:J21) -> 273006.7
B24: Non-recurring items | C24: 0 | D24: 0 | E24: -162624 | F24: =F8 -> 0 | G24: =G8 -> 0 | H24: =H8 -> 0 | I24: =I8 -> 0 | J24: =J8 -> 0
B25: Other income (expense) | C25: -303 | D25: -6967 | E25: -6843 | F25: =F9 -> 0 | G25: =G9 -> 0 | H25: =H9 -> 0 | I25: =I9 -> 0 | J25: =J9 -> 0
B27: Interest income | F27: =IF(circ=1,Debt!F33,0) -> 0 | G27: =IF(circ=1,Debt!G33,0) -> 0 | H27: =IF(circ=1,Debt!H33,0) -> 0 | I27: =IF(circ=1,Debt!I33,0) -> 0 | J27: =IF(circ=1,Debt!J33,0) -> 355.517
B28: Interest expense | C28: -86075 | D28: -82446 | E28: -80016 | F28: =IF(circ=1,Debt!F28,0) -> -61993.218 | G28: =IF(circ=1,Debt!G28,0) -> -61390.67 | H28: =IF(circ=1,Debt!H28,0) -> -62165.321 | I28: =IF(circ=1,Debt!I28,0) -> -62784.033 | J28: =IF(circ=1,Debt!J28,0) -> -62818.723
A30: * | B30: Pretax Income | C30: =C18+SUM(C25:C28) -> 161892 | D30: =D18+SUM(D25:D28) -> 189340 | E30: =E18+SUM(E24:E28) -> -4323 | F30: =F18+SUM(F24:F28) -> 143941.18 | G30: =G18+SUM(G24:G28) -> 141454.71 | H30: =H18+SUM(H24:H28) -> 142708.52 | I30: =I18+SUM(I24:I28) -> 144138.54 | J30: =J18+SUM(J24:J28) -> 146528.6
B32: Tax expense | C32: 46111 | D32: 58514 | E32: 32372 | F32: =F10*F30 -> 33106.472 | G32: =G10*G30 -> 32534.584 | H32: =H10*H30 -> 32822.959 | I32: =I10*I30 -> 33151.865 | J32: =J10*J30 -> 33701.577
A33: * | B33: Net income | C33: =C30-C32 -> 115781 | D33: =D30-D32 -> 130826 | E33: =E30-E32 -> -36695 | F33: =F30-F32 -> 110834.71 | G33: =G30-G32 -> 108920.13 | H33: =H30-H32 -> 109885.56 | I33: =I30-I32 -> 110986.68 | J33: =J30-J32 -> 112827.02
A34: Shareholder information | C34: 44926 | D34: 45291 | E34: 45657 | F34: 46022 | G34: 46022 | H34: 46022 | I34: 46022 | J34: 46022
B35: Basic WASO | C35: =C33/C37 -> 21205.311 | D35: =D33/D37 -> 20602.52 | E35: =E33/E37 -> 19622.995 | F35: =F11 -> 19622.995 | G35: =G11 -> 19622.995 | H35: =H11 -> 19622.995 | I35: =I11 -> 19622.995 | J35: =J11 -> 19622.995
B36: Diluted WASO | C36: =C33/C38 -> 21244.22 | D36: =D33/D38 -> 20766.032 | E36: =E33/E38 -> 19622.995 | F36: =F12 -> 19622.995 | G36: =G12 -> 19622.995 | H36: =H12 -> 19622.995 | I36: =I12 -> 19622.995 | J36: =J12 -> 19622.995
B37: Basic earnings per share | C37: 5.46 | D37: 6.35 | E37: -1.87 | F37: =F33/F35 -> 5.6482057 | G37: =G33/G35 -> 5.5506375 | H37: =H33/H35 -> 5.5998363 | I37: =I33/I35 -> 5.6559501 | J37: =J33/J35 -> 5.749735
A38: * | B38: Diluted earnings per share | C38: 5.45 | D38: 6.3 | E38: -1.87 | F38: =F33/F36 -> 5.6482057 | G38: =G33/G36 -> 5.5506375 | H38: =H33/H36 -> 5.5998363 | I38: =I33/I36 -> 5.6559501 | J38: =J33/J36 -> 5.749735

Sheet BalSheet
A1: =CoName -> Jack In the Box Inc. | C1: Hist. | D1: Hist. | E1: Hist. | F1: Proj. | G1: Proj. | H1: Proj. | I1: Proj. | J1: Proj.
A2: Assumptions | C2: 2022 | D2: =C2+1 -> 2023 | E2: =D2+1 -> 2024 | F2: =E2+1 -> 2025 | G2: =F2+1 -> 2026 | H2: =G2+1 -> 2027 | I2: =H2+1 -> 2028 | J2: =I2+1 -> 2029
B4: Operating Cash % of sales | F4: =Assumptions!F37 -> 0.01 | G4: =F4 -> 0.01 | H4: =G4 -> 0.01 | I4: =H4 -> 0.01 | J4: =I4 -> 0.01
B5: Accounts receivable % of sales | F5: =Assumptions!F38 -> 0.053183148 | G5: =Assumptions!G38 -> 0.053183148 | H5: =Assumptions!H38 -> 0.053183148 | I5: =Assumptions!I38 -> 0.053183148 | J5: =Assumptions!J38 -> 0.053183148
B6: Inventories % of COGS | F6: =Assumptions!F39 -> 0.0035706027 | G6: =Assumptions!G39 -> 0.0035706027 | H6: =Assumptions!H39 -> 0.0035706027 | I6: =Assumptions!I39 -> 0.0035706027 | J6: =Assumptions!J39 -> 0.0035706027
B7: Other current assets % of sales | F7: =Assumptions!F40 -> 0.043939882 | G7: =Assumptions!G40 -> 0.043939882 | H7: =Assumptions!H40 -> 0.043939882 | I7: =Assumptions!I40 -> 0.043939882 | J7: =Assumptions!J40 -> 0.043939882
B9: Other long-term assets % of sales | F9: =Assumptions!F42 -> 0.16483486 | G9: =Assumptions!G42 -> 0.16483486 | H9: =Assumptions!H42 -> 0.16483486 | I9: =Assumptions!I42 -> 0.16483486 | J9: =Assumptions!J42 -> 0.16483486
B11: Accounts payable/Accural % of COGS | F11: =Assumptions!F46 -> 0.2151848 | G11: =Assumptions!G46 -> 0.2151848 | H11: =Assumptions!H46 -> 0.2151848 | I11: =Assumptions!I46 -> 0.2151848 | J11: =Assumptions!J46 -> 0.2151848
B12: Other current liabilities % of sales | F12: =Assumptions!F47 -> 0.10310977 | G12: =Assumptions!G47 -> 0.10310977 | H12: =Assumptions!H47 -> 0.10310977 | I12: =Assumptions!I47 -> 0.10310977 | J12: =Assumptions!J47 -> 0.10310977
B13: Other long-term liabilities % of sales | F13: =Assumptions!F48 -> 0.92517625 | G13: =Assumptions!G48 -> 0.92517625 | H13: =Assumptions!H48 -> 0.92517625 | I13: =Assumptions!I48 -> 0.92517625 | J13: =Assumptions!J48 -> 0.92517625
A15: Balance sheet | C15: =C2 -> 2022 | D15: =D2 -> 2023 | E15: =E2 -> 2024 | F15: =F2 -> 2025 | G15: =G2 -> 2026 | H15: =H2 -> 2027 | I15: =I2 -> 2028 | J15: =J2 -> 2029
B16: Operating Cash | C16: =1%*IncState!C15 -> 14680.83 | D16: =1%*IncState!D15 -> 16923.06 | E16: =1%*IncState!E15 -> 15713.06 | F16: =F4*IncState!F15 -> 13198.97 | G16: =G4*IncState!G15 -> 13000.986 | H16: =H4*IncState!H15 -> 13130.996 | I16: =I4*IncState!I15 -> 13262.306 | J16: =J4*IncState!J15 -> 13394.929
B17: Excess cash | C17: =108890-C16 -> 94209.17 | D17: =157653-D16 -> 140729.94 | E17: =24745-E16 -> 9031.94 | F17: =MAX(CashFlow!F22,0) -> 0 | G17: =MAX(CashFlow!G22,0) -> 0 | H17: =MAX(CashFlow!H22,0) -> 0 | I17: =MAX(CashFlow!I22,0) -> 0 | J17: =MAX(CashFlow!J22,0) -> 8887.9249
B18: Accounts receivable | C18: 103803 | D18: 99678 | E18: 83567 | F18: =F5*IncState!F15 -> 70196.28 | G18: =G5*IncState!G15 -> 69143.336 | H18: =H5*IncState!H15 -> 69834.769 | I18: =I5*IncState!I15 -> 70533.117 | J18: =J5*IncState!J15 -> 71238.448
B19: Inventories | C19: 5264 | D19: 3896 | E19: 3922 | F19: =F6*IncState!F16 -> 3294.48 | G19: =G6*IncState!G16 -> 3245.0628 | H19: =H6*IncState!H16 -> 3277.5134 | I19: =I6*IncState!I16 -> 3310.2886 | J19: =J6*IncState!J16 -> 3343.3914
B20: Other current assets | C20: =16095+17019+4772+27150 -> 65036 | D20: =16911+13925+5667+28254 -> 64757 | E20: =29422+13126+16493+10002 -> 69043 | F20: =F7*IncState!F15 -> 57996.12 | G20: =G7*IncState!G15 -> 57126.178 | H20: =H7*IncState!H15 -> 57697.44 | I20: =I7*IncState!I15 -> 58274.414 | J20: =J7*IncState!J15 -> 58857.159
B21: Total current assets | C21: =SUM(C16:C20) -> 282993 | D21: =SUM(D16:D20) -> 325984 | E21: =SUM(E16:E20) -> 181277 | F21: =SUM(F16:F20) -> 144685.85 | G21: =SUM(G16:G20) -> 142515.56 | H21: =SUM(H16:H20) -> 143940.72 | I21: =SUM(I16:I20) -> 145380.13 | J21: =SUM(J16:J20) -> 155721.85
B23: Property, plant & equipment, net | C23: =418164+1332135 -> 1750299 | D23: =412030+1397555 -> 1809585 | E23: =430039+1410083 -> 1840122 | F23: =Calcs!F9 -> 1876335.4 | G23: =Calcs!G9 -> 1903397.2 | H23: =Calcs!H9 -> 1923889.9 | I23: =Calcs!I9 -> 1937908.2 | J23: =Calcs!J9 -> 1945541.7
B24: Intangible assets | C24: =12324+283500+366821 -> 662645 | D24: =11330+283500+329986 -> 624816 | E24: =10515+283500+161209 -> 455224 | F24: =E24-IncState!F21 -> 455224 | G24: =F24-IncState!G21 -> 455224 | H24: =G24-IncState!H21 -> 455224 | I24: =H24-IncState!I21 -> 455224 | J24: =I24-IncState!J21 -> 455224
B25: Other assets | C25: 226569 | D25: 240707 | E25: 259006 | F25: =F9*IncState!F15 -> 217565.04 | G25: =G9*IncState!G15 -> 214301.56 | H25: =H9*IncState!H15 -> 216444.58 | I25: =I9*IncState!I15 -> 218609.03 | J25: =J9*IncState!J15 -> 220795.12
B26: Total non-current assets | C26: =SUM(C23:C25) -> 2639513 | D26: =SUM(D23:D25) -> 2675108 | E26: =SUM(E23:E25) -> 2554352 | F26: =SUM(F23:F25) -> 2549124.5 | G26: =SUM(G23:G25) -> 2572922.7 | H26: =SUM(H23:H25) -> 2595558.5 | I26: =SUM(I23:I25) -> 2611741.2 | J26: =SUM(J23:J25) -> 2621560.8
A28: * | B28: TOTAL ASSETS | C28: =SUM(C26,C21) -> 2922506 | D28: =SUM(D26,D21) -> 3001092 | E28: =SUM(E26,E21) -> 2735629 | F28: =SUM(F26,F21) -> 2693810.3 | G28: =SUM(G26,G21) -> 2715438.3 | H28: =SUM(H26,H21) -> 2739499.2 | I28: =SUM(I26,I21) -> 2757121.4 | J28: =SUM(J26,J21) -> 2777282.7
B30: Revolver/Short term debt | C30: 0 | D30: 0 | E30: 0 | F30: =-MIN(CashFlow!F22,0) -> 179564.85 | G30: =MIN(CashFlow!G22,0)*-1 -> 157405.32 | H30: =MIN(CashFlow!H22,0)*-1 -> 103968.27 | I30: =MIN(CashFlow!I22,0)*-1 -> 48754.128 | J30: =MIN(CashFlow!J22,0)*-1 -> 0
B31: Accounts payable/Accurals | C31: =66271+253932 -> 320203 | D31: =84960+302178 -> 387138 | E31: =69494+166868 -> 236362 | F31: =F11*IncState!F16 -> 198544.08 | G31: =G11*IncState!G16 -> 195565.92 | H31: =H11*IncState!H16 -> 197521.58 | I31: =I11*IncState!I16 -> 199496.79 | J31: =J11*IncState!J16 -> 201491.76
B32: Other current liabilities | C32: 171311 | D32: =142518 -> 142518 | E32: =162017 -> 162017 | F32: =F12*IncState!F15 -> 136094.28 | G32: =G12*IncState!G15 -> 134052.87 | H32: =H12*IncState!H15 -> 135393.39 | I32: =I12*IncState!I15 -> 136747.33 | J32: =J12*IncState!J15 -> 138114.8
B33: Total current liabilities | C33: =SUM(C30:C32) -> 491514 | D33: =SUM(D30:D32) -> 529656 | E33: =SUM(E30:E32) -> 398379 | F33: =SUM(F30:F32) -> 514203.21 | G33: =SUM(G30:G32) -> 487024.11 | H33: =SUM(H30:H32) -> 436883.25 | I33: =SUM(I30:I32) -> 384998.25 | J33: =SUM(J30:J32) -> 339606.56
B35: Long-term debt, including current maturities | C35: =30169+1799540 -> 1829709 | D35: =1724933+29964 -> 1754897 | E35: =1699433+35880 -> 1735313 | F35: =Debt!F20 -> 1699433 | G35: =Debt!G20 -> 1657637 | H35: =Debt!H20 -> 1609925 | I35: =Debt!I20 -> 1556297 | J35: =Debt!J20 -> 1496753
B36: Other long-term liabilities | C36: =1165097+37683+134694 -> 1337474 | D36: =1265514+26229+143123 -> 1434866 | E36: =1286415+13612+153708 -> 1453735 | F36: =F13*IncState!F15 -> 1221137.4 | G36: =G13*IncState!G15 -> 1202820.3 | H36: =H13*IncState!H15 -> 1214848.5 | I36: =I13*IncState!I15 -> 1226997 | J36: =J13*IncState!J15 -> 1239267
B37: Total non-current liabilities | C37: =SUM(C35:C36) -> 3167183 | D37: =SUM(D35:D36) -> 3189763 | E37: =SUM(E35:E36) -> 3189048 | F37: =SUM(F35:F36) -> 2920570.4 | G37: =SUM(G35:G36) -> 2860457.3 | H37: =SUM(H35:H36) -> 2824773.5 | I37: =SUM(I35:I36) -> 2783294 | J37: =SUM(J35:J36) -> 2736020
B39: Equity | C39: -736191 | D39: -718327 | E39: -851798 | F39: =Calcs!F16 -> -740963.29 | G39: =Calcs!G16 -> -632043.16 | H39: =Calcs!H16 -> -522157.6 | I39: =Calcs!I16 -> -411170.92 | J39: =Calcs!J16 -> -298343.91
A40: * | B40: TOTAL LIABILITIES & EQUITY | C40: =SUM(C39,C37,C33) -> 2922506 | D40: =SUM(D39,D37,D33) -> 3001092 | E40: =SUM(E39,E37,E33) -> 2735629 | F40: =SUM(F39,F37,F33) -> 2693810.3 | G40: =SUM(G39,G37,G33) -> 2715438.3 | H40: =SUM(H39,H37,H33) -> 2739499.2 | I40: =SUM(I39,I37,I33) -> 2757121.4 | J40: =SUM(J39,J37,J33) -> 2777282.7
A42: * | B42: Balance check | C42: =C40-C28 -> 0 | D42: =D40-D28 -> 0 | E42: =E40-E28 -> 0 | F42: =F40-F28 -> 0 | G42: =G40-G28 -> 0 | H42: =H40-H28 -> 0 | I42: =I40-I28 -> 0 | J42: =J40-J28 -> 0

Sheet CashFlow
A1: =CoName -> Jack In the Box Inc. | C1: Hist. | D1: Hist. | E1: Hist. | F1: Proj. | G1: Proj. | H1: Proj. | I1: Proj. | J1: Proj.
A2: Cash flow statement | C2: 2022 | D2: =C2+1 -> 2023 | E2: =D2+1 -> 2024 | F2: =E2+1 -> 2025 | G2: =F2+1 -> 2026 | H2: =G2+1 -> 2027 | I2: =H2+1 -> 2028 | J2: =I2+1 -> 2029
B3: Net Income | F3: =IncState!F33 -> 110834.71 | G3: =IncState!G33 -> 108920.13 | H3: =IncState!H33 -> 109885.56 | I3: =IncState!I33 -> 110986.68 | J3: =IncState!J33 -> 112827.02
B4: Depreciation | F4: =IncState!F20 -> 60784.728 | G4: =IncState!G20 -> 61980.966 | H4: =IncState!H20 -> 62874.896 | I4: =IncState!I20 -> 63551.832 | J4: =IncState!J20 -> 64014.899
B5: Amortization | F5: =IncState!F21 -> 0 | G5: =IncState!G21 -> 0 | H5: =IncState!H21 -> 0 | I5: =IncState!I21 -> 0 | J5: =IncState!J21 -> 0
B6: (inc) / dec in OWC | F6: =Calcs!F25 -> -36181.43 | G6: =Calcs!G25 -> -2849.2876 | H6: =Calcs!H25 -> 1871.0322 | I6: =Calcs!I25 -> 1889.7425 | J6: =Calcs!J25 -> 1908.64
B7: (inc) / dec in LT assets | F7: =BalSheet!E25-BalSheet!F25 -> 41440.96 | G7: =BalSheet!F25-BalSheet!G25 -> 3263.4756 | H7: =BalSheet!G25-BalSheet!H25 -> -2143.0156 | I7: =BalSheet!H25-BalSheet!I25 -> -2164.4458 | J7: =BalSheet!I25-BalSheet!J25 -> -2186.0903
B8: inc / (dec) in LT liabilities | F8: =BalSheet!F36-BalSheet!E36 -> -232597.6 | G8: =BalSheet!G36-BalSheet!F36 -> -18317.061 | H8: =BalSheet!H36-BalSheet!G36 -> 12028.203 | I8: =BalSheet!I36-BalSheet!H36 -> 12148.485 | J8: =BalSheet!J36-BalSheet!I36 -> 12269.97
B9: CFFO | F9: =SUM(F3:F8) -> -55718.632 | G9: =SUM(G3:G8) -> 152998.22 | H9: =SUM(H3:H8) -> 184516.67 | I9: =SUM(I3:I8) -> 186412.29 | J9: =SUM(J3:J8) -> 188834.44
B11: Capex | F11: =-Calcs!F7 -> -96998.16 | G11: =-Calcs!G7 -> -89042.695 | H11: =-Calcs!H7 -> -83367.624 | I11: =-Calcs!I7 -> -77570.147 | J11: =-Calcs!J7 -> -71648.384
B12: CFFI | F12: =SUM(F11) -> -96998.16 | G12: =SUM(G11) -> -89042.695 | H12: =SUM(H11) -> -83367.624 | I12: =SUM(I11) -> -77570.147 | J12: =SUM(J11) -> -71648.384
B14: Debt issuance / (repayments) | F14: =SUM(Debt!F8:F9) -> -35880 | G14: =SUM(Debt!G8:G9) -> -41796 | H14: =SUM(Debt!H8:H9) -> -47712 | I14: =SUM(Debt!I8:I9) -> -53628 | J14: =SUM(Debt!J8:J9) -> -59544
B15: Share issuance / (repurchases) | F15: =Calcs!F11 -> 0 | G15: =Calcs!G11 -> 0 | H15: =Calcs!H11 -> 0 | I15: =Calcs!I11 -> 0 | J15: =Calcs!J11 -> 0
B16: CFFF | F16: =SUM(F14:F15) -> -35880 | G16: =SUM(G14:G15) -> -41796 | H16: =SUM(H14:H15) -> -47712 | I16: =SUM(I14:I15) -> -53628 | J16: =SUM(J14:J15) -> -59544
B18: Net changes in cash | F18: =SUM(F16,F12,F9) -> -188596.79 | G18: =SUM(G16,G12,G9) -> 22159.528 | H18: =SUM(H16,H12,H9) -> 53437.05 | I18: =SUM(I16,I12,I9) -> 55214.145 | J18: =SUM(J16,J12,J9) -> 57642.053
B20: Beginning cash | F20: =BalSheet!E17 -> 9031.94 | G20: =F22 -> -179564.85 | H20: =G22 -> -157405.32 | I20: =H22 -> -103968.27 | J20: =I22 -> -48754.128
B21: =B18 -> Net changes in cash | F21: =F18 -> -188596.79 | G21: =G18 -> 22159.528 | H21: =H18 -> 53437.05 | I21: =I18 -> 55214.145 | J21: =J18 -> 57642.053
B22: Ending cash | F22: =SUM(F20:F21) -> -179564.85 | G22: =SUM(G20:G21) -> -157405.32 | H22: =SUM(H20:H21) -> -103968.27 | I22: =SUM(I20:I21) -> -48754.128 | J22: =SUM(J20:J21) -> 8887.9249

Sheet Free Cash Flow
A1: =CoName -> Jack In the Box Inc. | C1: Hist. | D1: Hist. | E1: Hist. | F1: Proj. | G1: Proj. | H1: Proj. | I1: Proj. | J1: Proj.
A2: Free Cash Flows | C2: 2022 | D2: =C2+1 -> 2023 | E2: =D2+1 -> 2024 | F2: =E2+1 -> 2025 | G2: =F2+1 -> 2026 | H2: =G2+1 -> 2027 | I2: =H2+1 -> 2028 | J2: =I2+1 -> 2029
A3: * | B3: Sales | F3: =IncState!F15 -> 1319897 | G3: =IncState!G15 -> 1300098.6 | H3: =IncState!H15 -> 1313099.6 | I3: =IncState!I15 -> 1326230.6 | J3: =IncState!J15 -> 1339492.9
B4: EBIT | F4: =IncState!F18 -> 205934.4 | G4: =IncState!G18 -> 202845.38 | H4: =IncState!H18 -> 204873.84 | I4: =IncState!I18 -> 206922.58 | J4: =IncState!J18 -> 208991.8
B5: Effective Tax Rate | F5: =Assumptions!F16 -> 0.23 | G5: =Assumptions!G16 -> 0.23 | H5: =Assumptions!H16 -> 0.23 | I5: =Assumptions!I16 -> 0.23 | J5: =Assumptions!J16 -> 0.23
A7: * | B7: NOPAT | F7: =F4*(1-F5) -> 158569.49 | G7: =G4*(1-G5) -> 156190.95 | H7: =H4*(1-H5) -> 157752.86 | I7: =I4*(1-I5) -> 159330.38 | J7: =J4*(1-J5) -> 160923.69
B8: Depreciation | F8: =CashFlow!F4 -> 60784.728 | G8: =CashFlow!G4 -> 61980.966 | H8: =CashFlow!H4 -> 62874.896 | I8: =CashFlow!I4 -> 63551.832 | J8: =CashFlow!J4 -> 64014.899
B9: Amortization | F9: =CashFlow!F5 -> 0 | G9: =CashFlow!G5 -> 0 | H9: =CashFlow!H5 -> 0 | I9: =CashFlow!I5 -> 0 | J9: =CashFlow!J5 -> 0
B10: (inc) / dec in OWC | F10: =CashFlow!F6 -> -36181.43 | G10: =CashFlow!G6 -> -2849.2876 | H10: =CashFlow!H6 -> 1871.0322 | I10: =CashFlow!I6 -> 1889.7425 | J10: =CashFlow!J6 -> 1908.64
B11: (inc) / dec in other long-term assets | F11: =CashFlow!F7 -> 41440.96 | G11: =CashFlow!G7 -> 3263.4756 | H11: =CashFlow!H7 -> -2143.0156 | I11: =CashFlow!I7 -> -2164.4458 | J11: =CashFlow!J7 -> -2186.0903
B12: inc / (dec) other long-term liabilities | F12: =CashFlow!F8 -> -232597.6 | G12: =CashFlow!G8 -> -18317.061 | H12: =CashFlow!H8 -> 12028.203 | I12: =CashFlow!I8 -> 12148.485 | J12: =CashFlow!J8 -> 12269.97
B13: (Capex) | F13: =CashFlow!F11 -> -96998.16 | G13: =CashFlow!G11 -> -89042.695 | H13: =CashFlow!H11 -> -83367.624 | I13: =CashFlow!I11 -> -77570.147 | J13: =CashFlow!J11 -> -71648.384
A15: * | B15: Free Cash Flow | F15: =SUM(F7:F13) -> -104982.01 | G15: =SUM(G7:G13) -> 111226.34 | H15: =SUM(H7:H13) -> 149016.35 | I15: =SUM(I7:I13) -> 157185.85 | J15: =SUM(J7:J13) -> 165282.72

Sheet WACC
A1: =CoName -> Jack In the Box Inc.
A3: * | B3: WACC | G3: Comp | H3: Levered beta | I3: Gross debt | J3: Market cap | K3: Debt/Mcap | L3: MTR | M3: Unlevered beta
B4: Tax Rate | E4: =Assumptions!F16 -> 0.23 | L4: =E4 -> 0.23 | M4: =H4/((1+K4*(1-L4))) -> 0
B5: Risk free rate | E5: 0.0415 | L5: =L4 -> 0.23 | M5: =H5/((1+K5*(1-L5))) -> 0
B6: Market risk Premium | E6: 0.05 | L6: =L5 -> 0.23 | M6: =H6/((1+K6*(1-L6))) -> 0
B7: Beta | E7: 1 | L7: =L6 -> 0.23 | M7: =H7/((1+K7*(1-L7))) -> 0
B8: Cost of Equity | E8: =E5+E6*E7 -> 0.0915
B9: % Equity | E9: =1-E10 -> 0.46930588 | G9: Industry beta (average) | M9: =AVERAGE(M4:M7) -> 0
B10: % Debt | E10: =BalSheet!E35/MAIN!F9 -> 0.53069412
B11: Cost of debt | E11: =Assumptions!F23 -> 0.04197 | G11: Re-levered beta | M11: =M9*(1+E10*(1-E4)) -> 0
B12: Post tax cost of debt | E12: =E11*(1-E4) -> 0.0323169
A13: * | B13: WACC | E13: =WACC!E8*WACC!E9+WACC!E12*WACC!E10 -> 0.060091877
B14: Long Term growth rate | E14: 0.025

Sheet DCF Model
A1: =CoName -> Jack In the Box Inc. | D1: Proj. | E1: Proj. | F1: Proj. | G1: Proj. | H1: Proj.
A2: Discount Model Year count | D2: 0.5 | E2: =D2+1 -> 1.5 | F2: =E2+1 -> 2.5 | G2: =F2+1 -> 3.5 | H2: =G2+1 -> 4.5
B3: Discount Factor | D3: =1/(1+$K$17)^D2 -> 0.97124377 | E3: =1/(1+$K$17)^E2 -> 0.9161883 | F3: =1/(1+$K$17)^F2 -> 0.86425367 | G3: =1/(1+$K$17)^G2 -> 0.81526299 | H3: =1/(1+$K$17)^H2 -> 0.76904937
B4: PV FCF | D4: =D3*'Free Cash Flow'!F15 -> -101963.13 | E4: =E3*'Free Cash Flow'!G15 -> 101904.27 | F4: =F3*'Free Cash Flow'!H15 -> 128787.93 | G4: =G3*'Free Cash Flow'!I15 -> 128147.81 | H4: =H3*'Free Cash Flow'!J15 -> 127110.57 | I4: =(H4*(1+K18))/(K17-K18) -> 3712777.7
A6: Value Calculation | E6: Multiples Calculation
B7: Total PV of FCFs | C7: =SUM(D4:H4) -> 383987.45 | E7: Total PV of FCFs | G7: =C7 -> 383987.45
B8: PV of TV | C8: =I4*H3 -> 2855309.4 | E8: Multiple TV | G8: =IncState!J22*'DCF Model'!H3+'DCF Model'!G10 -> 209970.63
B9: EV | C9: =SUM(C7:C8) -> 3239296.8 | E9: EV | G9: =SUM(G7:G8) -> 593958.08
E10: Implied EBITDA multiple | G10: 15
B12: Cash & Cash Equiv | C12: =MAIN!F7 -> 68111 | E12: Cash & Cash Equiv | G12: =C12 -> 68111
B13: Debt & Claims | C13: =MAIN!F8 -> 2941482 | E13: Debt & Claims | G13: =C13 -> 2941482
B14: NCI | C14: 0 | E14: NCI | G14: 0
B15: Equity Value | C15: =C9+C12-SUM(C13:C14) -> 365925.82 | E15: Equity Value | G15: =G9+G12-SUM(G13:G14) -> -2279412.9
B17: Diluted S/O | C17: =MAIN!F5 -> 18882 | E17: Diluted S/O | G17: =C17 -> 18882 | I17: WACC | K17: =WACC!E13 -> 0.060091877
A18: * | B18: Implied Share Price | C18: =C15/C17 -> 19.379611 | E18: Implied Share Price | G18: =G15/G17 -> -120.71883 | I18: Long Term growth rate | K18: 0.025
A20: Sensitivity analysis
C22: Discount rate variance | E22: 0.005 | J22: Discount rate variance | L22: 0.005
C23: Implied growth rate variance | E23: 0.0025 | J23: TV multiple variance | L23: 1
