Workbook
Name Ccy: MAIN!$C$6
Name circ: MAIN!$C$9
Name CoName: MAIN!$C$4
Name g: #REF!
Name IQ_CH: 110000
Name IQ_CQ: 5000
Name IQ_CY: 10000
Name IQ_DAILY: 500000
Name IQ_FH: 100000
Name IQ_FQ: 500
Name IQ_FY: 1000
Name IQ_LTM: 2000
Name IQ_MONTH: 15000
Name IQ_NTM: 6000
Name IQ_WEEK: 50000
Name IQ_YTD: 3000
Name OpCase: [1]DCF!$E$98
Name ScenarioREV: Assumptions!$D$4
Name TTS: #REF!
Name Units: MAIN!$C$7

Sheet MAIN
A1: =CoName -> Papa John's Inc
A2: Model Details
B4: Company name | C4: Papa John's Inc | E4: Current Stock Price | F4: 42 | H4: Operating Case One | I4: Perpetuity | J4: Terminal Mult | K4: DDM | L4: Average
B5: Latest BS date | C5: =TODAY() -> 46006 | E5: S/O | F5: 32789.416 | H5: Implied Price | I5: ='DCF Model'!C18 -> 44.432451 | J5: ='DCF Model'!G18 -> 68.788549 | K5: ='DCF Model'!K11 -> 30.426409 | L5: =AVERAGE(I5:K5) -> 47.88247
B6: Currency | C6: USD | E6: Mkt Cap | F6: =F5*F4 -> 1377155.5 | H6: Difference | I6: =I5/$F$4-1 -> 0.057915506 | J6: =J5/$F$4-1 -> 0.63782259 | K6: =K5/$F$4-1 -> -0.2755617 | L6: =L5/$F$4-1 -> 0.1400588
B7: Units | C7: m | E7: Cash | F7: 38972
B8: Analyst name | C8: Alan Chen | E8: Debt | F8: =727135 -> 727135
B9: Circular switch | C9: 0 | E9: EV | F9: =F6-F7+F8 -> 2065318.5

Sheet Quarterly Projections

Sheet Assumptions
A1: =CoName -> Papa John's Inc | C1: Hist. | D1: Hist. | E1: Hist. | F1: Proj. | G1: Proj. | H1: Proj. | I1: Proj. | J1: Proj.
A2: * | B2: Income Statement | C2: 2022 | D2: =C2+1 -> 2023 | E2: =D2+1 -> 2024 | F2: =E2+1 -> 2025 | G2: =F2+1 -> 2026 | H2: =G2+1 -> 2027 | I2: =H2+1 -> 2028 | J2: =I2+1 -> 2029
B4: Operating Case | D4: 1
D5: Variance
B6: Street Case | D6: 0 | F6: 0.006 | G6: -0.019 | H6: -0.02 | I6: -0.02 | J6: -0.02
B7: Optimistic Case | D7: 0.025 | F7: =F6+$D$7 -> 0.031 | G7: =G6+$D$7 -> 0.006 | H7: =H6+$D$7 -> 0.005 | I7: =I6+$D$7 -> 0.005 | J7: =J6+$D$7 -> 0.005
B8: Pessimistic Case | D8: -0.025 | F8: =F6+$D$8 -> -0.019 | G8: =G6+$D$8 -> -0.044 | H8: =H6+$D$8 -> -0.045 | I8: =I6+$D$8 -> -0.045 | J8: =J6+$D$8 -> -0.045
B10: Revenue Growth | D10: =IncState!D16/IncState!C16-1 -> 0.01598875 | E10: =IncState!E16/IncState!D16-1 -> -0.035737948 | F10: =CHOOSE(ScenarioREV,F6,F7,F8) -> 0.006 | G10: =CHOOSE(ScenarioREV,G6,G7,G8) -> -0.019 | H10: =CHOOSE(ScenarioREV,H6,H7,H8) -> -0.02 | I10: =CHOOSE(ScenarioREV,I6,I7,I8) -> -0.02 | J10: =CHOOSE(ScenarioREV,J6,J7,J8) -> -0.02
B11: COGS % of sales | C11: =IncState!C17/IncState!C16 -> 0.74103695 | D11: =IncState!D17/IncState!D16 -> 0.72970385 | E11: =IncState!E17/IncState!E16 -> 0.71789615 | F11: =E11 -> 0.71789615 | G11: =F11 -> 0.71789615 | H11: =G11 -> 0.71789615 | I11: =H11 -> 0.71789615 | J11: =I11 -> 0.71789615
B12: SG&A % of sales | C12: =IncState!C18/IncState!C16 -> 0.20148537 | D12: =IncState!D18/IncState!D16 -> 0.20140019 | E12: =IncState!E18/IncState!E16 -> 0.2060113 | F12: =E12 -> 0.2060113 | G12: =F12 -> 0.2060113 | H12: =G12 -> 0.2060113 | I12: =H12 -> 0.2060113 | J12: =I12 -> 0.2060113
B13: Amortization $ Amt | C13: =IncState!C22 -> 0 | D13: =IncState!D22 -> 0 | E13: =IncState!E22 -> 0 | F13: =E13 -> 0 | G13: =F13 -> 0 | H13: =G13 -> 0 | I13: =H13 -> 0 | J13: =I13 -> 0
B14: Non recurring income / (expense) | C14: =IncState!C25 -> -12065 | D14: =IncState!D25 -> 0 | E14: =IncState!E25 -> 0 | F14: 0 | G14: 0 | H14: 0 | I14: 0 | J14: 0
B15: Other Income / (expense) | C15: =IncState!C26 -> 0 | D15: =IncState!D26 -> 0 | E15: =IncState!E26 -> 0 | F15: 0 | G15: 0 | H15: 0 | I15: 0 | J15: 0
B16: Effective tax rate | C16: =IncState!C33/IncState!C31 -> 0.15089522 | D16: =IncState!D33/IncState!D31 -> 0.20134461 | E16: =IncState!E33/IncState!E31 -> 0.26224524 | F16: 0.21 | G16: =F16 -> 0.21 | H16: =G16 -> 0.21 | I16: =H16 -> 0.21 | J16: =I16 -> 0.21
B17: Dividend Payout Rate | C17: =IncState!C35 -> 1.5428628 | D17: =IncState!D35 -> 1.7749537 | E17: =IncState!E35 -> 1.8509949 | F17: =E17+(E17-AVERAGE(C17:D17)) -> 2.0430816 | G17: =F17+(F17-AVERAGE(D17:E17)) -> 2.2731888 | H17: =G17+(G17-AVERAGE(E17:F17)) -> 2.5993394 | I17: =H17+(H17-AVERAGE(F17:G17)) -> 3.0405436 | J17: =I17+(I17-AVERAGE(G17:H17)) -> 3.6448232
B18: Basic WASO | C18: =IncState!C38 -> 35497 | D18: =IncState!D38 -> 32931 | E18: =IncState!E38 -> 32717 | F18: =E18 -> 32717 | G18: =F18 -> 32717 | H18: =G18 -> 32717 | I18: =H18 -> 32717 | J18: =I18 -> 32717
B19: Diluted WASO | C19: =IncState!C39 -> 35717 | D19: =IncState!D39 -> 33159 | E19: =IncState!E39 -> 32819 | F19: =E19 -> 32819 | G19: =F19 -> 32819 | H19: =G19 -> 32819 | I19: =H19 -> 32819 | J19: =I19 -> 32819
A21: * | B21: Debt | C21: =C2 -> 2022 | D21: =D2 -> 2023 | E21: =E2 -> 2024 | F21: =F2 -> 2025 | G21: =G2 -> 2026 | H21: =H2 -> 2027 | I21: =I2 -> 2028 | J21: =J2 -> 2029
B23: Interest rate on Revolver | E23: =E24+1% -> 0.04875 | F23: =E23 -> 0.04875 | G23: =F23 -> 0.04875 | H23: =G23 -> 0.04875 | I23: =H23 -> 0.04875 | J23: =I23 -> 0.04875
B24: Interest rate on long-term debt | E24: 0.03875 | F24: =E24 -> 0.03875 | G24: =F24 -> 0.03875 | H24: =G24 -> 0.03875 | I24: =H24 -> 0.03875 | J24: =I24 -> 0.03875
B25: Interest rate on cash | E25: 0.04 | F25: =E25 -> 0.04 | G25: =F25 -> 0.04 | H25: =G25 -> 0.04 | I25: =H25 -> 0.04 | J25: =I25 -> 0.04
B27: Issuance of long-term debt | F27: 0 | G27: 0 | H27: 0 | I27: 0 | J27: 0
B28: Repayment of long-term debt | F28: 0 | G28: 0 | H28: 0 | I28: 0 | J28: 0
A30: * | B30: Calcs | C30: =C21 -> 2022 | D30: =D21 -> 2023 | E30: =E21 -> 2024 | F30: =F21 -> 2025 | G30: =G21 -> 2026 | H30: =H21 -> 2027 | I30: =I21 -> 2028 | J30: =J21 -> 2029
B32: CapEx % of Sales | C32: =78391/IncState!C16 -> 0.037291703 | D32: =76620/IncState!D16 -> 0.035875607 | E32: =72848/IncState!E16 -> 0.035373633 | F32: =AVERAGE(C32:E32) -> 0.036180314 | G32: =F32 -> 0.036180314 | H32: =G32 -> 0.036180314 | I32: =H32 -> 0.036180314 | J32: =I32 -> 0.036180314
B33: Depreciation % of beginning PP&E | D33: =IncState!D21/BalSheet!C23 -> 0.14332709 | E33: =IncState!E21/BalSheet!D23 -> 0.12618704 | F33: =AVERAGE(D33:E33) -> 0.13475707 | G33: =F33 -> 0.13475707 | H33: =G33 -> 0.13475707 | I33: =H33 -> 0.13475707 | J33: =I33 -> 0.13475707
B34: Share issuance / (repurchases) | F34: 0 | G34: 0 | H34: 0 | I34: 0 | J34: 0
A36: * | B36: Balance Sheet - Assets | C36: =C30 -> 2022 | D36: =D30 -> 2023 | E36: =E30 -> 2024 | F36: =F30 -> 2025 | G36: =G30 -> 2026 | H36: =H30 -> 2027 | I36: =I30 -> 2028 | J36: =J30 -> 2029
B38: Operating Cash % of sales | C38: =BalSheet!C16/IncState!C16 -> 0.01 | D38: =BalSheet!D16/IncState!D16 -> 0.01 | E38: =BalSheet!E16/IncState!E16 -> 0.01 | F38: =E38 -> 0.01 | G38: =F38 -> 0.01 | H38: =G38 -> 0.01 | I38: =H38 -> 0.01 | J38: =I38 -> 0.01
B39: Accounts receivable % of sales | C39: =BalSheet!C18/IncState!C16 -> 0.056210852 | D39: =BalSheet!D18/IncState!D16 -> 0.052450868 | E39: =BalSheet!E18/IncState!E16 -> 0.052840481 | F39: =E39 -> 0.052840481 | G39: =F39 -> 0.052840481 | H39: =G39 -> 0.052840481 | I39: =H39 -> 0.052840481 | J39: =I39 -> 0.052840481
B40: Inventories % of COGS | C40: =BalSheet!C19/IncState!C17 -> 0.026565477 | D40: =BalSheet!D19/IncState!D17 -> 0.023180903 | E40: =BalSheet!E19/IncState!E17 -> 0.023839543 | F40: =E40 -> 0.023839543 | G40: =F40 -> 0.023839543 | H40: =G40 -> 0.023839543 | I40: =H40 -> 0.023839543 | J40: =I40 -> 0.023839543
B41: Other current assets % of sales | C41: =BalSheet!C20/IncState!C16 -> 0.020989932 | D41: =BalSheet!D20/IncState!D16 -> 0.019799009 | E41: =BalSheet!E20/IncState!E16 -> 0.023592457 | F41: =E41 -> 0.023592457 | G41: =F41 -> 0.023592457 | H41: =G41 -> 0.023592457 | I41: =H41 -> 0.023592457 | J41: =I41 -> 0.023592457
B43: Other long-term assets % of sales | C43: =BalSheet!C25/IncState!C16 -> 0.045389308 | D43: =BalSheet!D25/IncState!D16 -> 0.04170551 | E43: =BalSheet!E25/IncState!E16 -> 0.046824128 | F43: =E43 -> 0.046824128 | G43: =F43 -> 0.046824128 | H43: =G43 -> 0.046824128 | I43: =H43 -> 0.046824128 | J43: =I43 -> 0.046824128
A45: * | B45: Balance Sheet - Liabilities | C45: =C36 -> 2022 | D45: =D36 -> 2023 | E45: =E36 -> 2024 | F45: =F36 -> 2025 | G45: =G36 -> 2026 | H45: =H36 -> 2027 | I45: =I36 -> 2028 | J45: =J36 -> 2029
B47: Accounts payable % of COGS | C47: =BalSheet!C31/IncState!C17 -> 0.14034278 | D47: =BalSheet!D31/IncState!D17 -> 0.16109977 | E47: =BalSheet!E31/IncState!E17 -> 0.15517043 | F47: =E47 -> 0.15517043 | G47: =F47 -> 0.15517043 | H47: =G47 -> 0.15517043 | I47: =H47 -> 0.15517043 | J47: =I47 -> 0.15517043
B48: Other current liabilities % of sales | C48: =BalSheet!C32/IncState!C16 -> 0.022139733 | D48: =BalSheet!D32/IncState!D16 -> 0.025065166 | E48: =BalSheet!E32/IncState!E16 -> 0.023577404 | F48: =E48 -> 0.023577404 | G48: =F48 -> 0.023577404 | H48: =G48 -> 0.023577404 | I48: =H48 -> 0.023577404 | J48: =I48 -> 0.023577404
B49: Other long-term liabilities % of sales | C49: =BalSheet!C36/IncState!C16 -> 0.12913164 | D49: =BalSheet!D36/IncState!D16 -> 0.11975017 | E49: =BalSheet!E36/IncState!E16 -> 0.13725055 | F49: =E49 -> 0.13725055 | G49: =F49 -> 0.13725055 | H49: =G49 -> 0.13725055 | I49: =H49 -> 0.13725055 | J49: =I49 -> 0.13725055

Sheet Calcs
A1: =CoName -> Papa John's Inc | C1: Hist. | D1: Hist. | E1: Hist. | F1: Proj. | G1: Proj. | H1: Proj. | I1: Proj. | J1: Proj.
A2: Net PP&E | C2: 2022 | D2: =C2+1 -> 2023 | E2: =D2+1 -> 2024 | F2: =E2+1 -> 2025 | G2: =F2+1 -> 2026 | H2: =G2+1 -> 2027 | I2: =H2+1 -> 2028 | J2: =I2+1 -> 2029
B3: Capital expenditure % of sales | F3: =Assumptions!F32 -> 0.036180314 | G3: =Assumptions!G32 -> 0.036180314 | H3: =Assumptions!H32 -> 0.036180314 | I3: =Assumptions!I32 -> 0.036180314 | J3: =Assumptions!J32 -> 0.036180314
B4: Depreciation % of PP&E | F4: =Assumptions!F33 -> 0.13475707 | G4: =F4 -> 0.13475707 | H4: =G4 -> 0.13475707 | I4: =H4 -> 0.13475707 | J4: =I4 -> 0.13475707
B6: Beginning PP&E | F6: =E9 -> 486458 | G6: =F9 -> 495860.67 | H6: =G9 -> 502572.09 | I6: =H9 -> 506908.46 | J6: =I9 -> 509219.24
B7: Capex | F7: =F3*IncState!F16 -> 74956.324 | G7: =G3*IncState!G16 -> 73532.154 | H7: =H3*IncState!H16 -> 72061.511 | I7: =I3*IncState!I16 -> 70620.281 | J7: =J3*IncState!J16 -> 69207.875
B8: Depreciation | F8: =F6*F4 -> 65553.654 | G8: =G6*G4 -> 66820.731 | H8: =H6*H4 -> 67725.142 | I8: =I6*I4 -> 68309.499 | J8: =J6*J4 -> 68620.893
B9: Ending PP&E | E9: =BalSheet!E23 -> 486458 | F9: =F6+F7-F8 -> 495860.67 | G9: =G6+G7-G8 -> 502572.09 | H9: =H6+H7-H8 -> 506908.46 | I9: =I6+I7-I8 -> 509219.24 | J9: =J6+J7-J8 -> 509806.23
A10: Equity | C10: =C2 -> 2022 | D10: =D2 -> 2023 | E10: =E2 -> 2024 | F10: =F2 -> 2025 | G10: =G2 -> 2026 | H10: =H2 -> 2027 | I10: =I2 -> 2028 | J10: =J2 -> 2029
B11: Share issuance/(repurchases) | F11: =Assumptions!F34 -> 0 | G11: =Assumptions!G34 -> 0 | H11: =Assumptions!H34 -> 0 | I11: =Assumptions!I34 -> 0 | J11: =Assumptions!J34 -> 0
B13: Beginning balance | F13: =E17 -> -413313 | G13: =F17 -> -355617.56 | H13: =G17 -> -307816.78 | I13: =H17 -> -273130.13 | J13: =I17 -> -255272.94
B14: Net income | F14: =IncState!F34 -> 124538.94 | G14: =IncState!G34 -> 122172.7 | H14: =IncState!H34 -> 119729.24 | I14: =IncState!I34 -> 117334.66 | J14: =IncState!J34 -> 114987.97
B15: Dividends paid | F15: =-IncState!F36 -> -66843.499 | G15: =-IncState!G36 -> -74371.919 | H15: =-IncState!H36 -> -85042.588 | I15: =-IncState!I36 -> -99477.466 | J15: =-IncState!J36 -> -119247.68
B16: Share issuance / (repurchase) | F16: =F11 -> 0 | G16: =G11 -> 0 | H16: =H11 -> 0 | I16: =I11 -> 0 | J16: =J11 -> 0
B17: Ending balance | E17: =BalSheet!E39 -> -413313 | F17: =SUM(F13:F16) -> -355617.56 | G17: =SUM(G13:G16) -> -307816.78 | H17: =SUM(H13:H16) -> -273130.13 | I17: =SUM(I13:I16) -> -255272.94 | J17: =SUM(J13:J16) -> -259532.65
A18: OWC | C18: =C10 -> 2022 | D18: =D10 -> 2023 | E18: =E10 -> 2024 | F18: =F10 -> 2025 | G18: =G10 -> 2026 | H18: =H10 -> 2027 | I18: =I10 -> 2028 | J18: =J10 -> 2029
B19: Operating Cash | E19: =BalSheet!E16 -> 20593.87 | F19: =BalSheet!F16 -> 20717.433 | G19: =BalSheet!G16 -> 20323.802 | H19: =BalSheet!H16 -> 19917.326 | I19: =BalSheet!I16 -> 19518.979 | J19: =BalSheet!J16 -> 19128.6
B20: =BalSheet!B18 -> Accounts receivable | E20: =BalSheet!E18 -> 108819 | F20: =BalSheet!F18 -> 109471.91 | G20: =BalSheet!G18 -> 107391.95 | H20: =BalSheet!H18 -> 105244.11 | I20: =BalSheet!I18 -> 103139.23 | J20: =BalSheet!J18 -> 101076.44
B21: =BalSheet!B19 -> Inventories | E21: =BalSheet!E19 -> 35245 | F21: =BalSheet!F19 -> 35456.47 | G21: =BalSheet!G19 -> 34782.797 | H21: =BalSheet!H19 -> 34087.141 | I21: =BalSheet!I19 -> 33405.398 | J21: =BalSheet!J19 -> 32737.29
B22: Other current assets | E22: =BalSheet!E20 -> 48586 | F22: =BalSheet!F20 -> 48877.516 | G22: =BalSheet!G20 -> 47948.843 | H22: =BalSheet!H20 -> 46989.866 | I22: =BalSheet!I20 -> 46050.069 | J22: =BalSheet!J20 -> 45129.068
B23: Accounts payables | E23: =BalSheet!E31 -> 229408 | F23: =BalSheet!F31 -> 230784.45 | G23: =BalSheet!G31 -> 226399.54 | H23: =BalSheet!H31 -> 221871.55 | I23: =BalSheet!I31 -> 217434.12 | J23: =BalSheet!J31 -> 213085.44
B24: Other current liabilities | E24: =BalSheet!E32 -> 48555 | F24: =BalSheet!F32 -> 48846.33 | G24: =BalSheet!G32 -> 47918.25 | H24: =BalSheet!H32 -> 46959.885 | I24: =BalSheet!I32 -> 46020.687 | J24: =BalSheet!J32 -> 45100.273
A25: * | B25: OWC | E25: =SUM(E19:E22)-SUM(E23:E24) -> -64719.13 | F25: =SUM(F19:F22)-SUM(F23:F24) -> -65107.445 | G25: =SUM(G19:G22)-SUM(G23:G24) -> -63870.403 | H25: =SUM(H19:H22)-SUM(H23:H24) -> -62592.995 | I25: =SUM(I19:I22)-SUM(I23:I24) -> -61341.135 | J25: =SUM(J19:J22)-SUM(J23:J24) -> -60114.313
B26: Change in OWC | F26: =E25-F25 -> 388.31478 | G26: =F25-G25 -> -1237.0415 | H26: =G25-H25 -> -1277.4081 | I26: =H25-I25 -> -1251.8599 | J26: =I25-J25 -> -1226.8227

Sheet Debt
A1: =CoName -> Papa John's Inc | C1: Hist. | D1: Hist. | E1: Hist. | F1: Proj. | G1: Proj. | H1: Proj. | I1: Proj. | J1: Proj.
A2: Assumptions | C2: 2022 | D2: =C2+1 -> 2023 | E2: =D2+1 -> 2024 | F2: =E2+1 -> 2025 | G2: =F2+1 -> 2026 | H2: =G2+1 -> 2027 | I2: =H2+1 -> 2028 | J2: =I2+1 -> 2029
B4: Interest rate on revolver | F4: =Assumptions!F23 -> 0.04875 | G4: =Assumptions!G23 -> 0.04875 | H4: =Assumptions!H23 -> 0.04875 | I4: =Assumptions!I23 -> 0.04875 | J4: =Assumptions!J23 -> 0.04875
B5: Interest rate on long-term debt | F5: =Assumptions!F24 -> 0.03875 | G5: =Assumptions!G24 -> 0.03875 | H5: =Assumptions!H24 -> 0.03875 | I5: =Assumptions!I24 -> 0.03875 | J5: =Assumptions!J24 -> 0.03875
B6: Interest rate on cash | F6: =Assumptions!F25 -> 0.04 | G6: =Assumptions!G25 -> 0.04 | H6: =Assumptions!H25 -> 0.04 | I6: =Assumptions!I25 -> 0.04 | J6: =Assumptions!J25 -> 0.04
B8: Issuance of long-term debt | F8: =Assumptions!F27 -> 0 | G8: =Assumptions!G27 -> 0 | H8: =Assumptions!H27 -> 0 | I8: =Assumptions!I27 -> 0 | J8: =Assumptions!J27 -> 0
B9: Repayment of long-term debt | F9: =Assumptions!F28 -> 0 | G9: =Assumptions!G28 -> 0 | H9: =Assumptions!H28 -> 0 | I9: =Assumptions!I28 -> 0 | J9: =Assumptions!J28 -> 0
A11: Revolver | C11: =C2 -> 2022 | D11: =D2 -> 2023 | E11: =E2 -> 2024 | F11: =F2 -> 2025 | G11: =G2 -> 2026 | H11: =H2 -> 2027 | I11: =I2 -> 2028 | J11: =J2 -> 2029
B12: Balance | F12: =BalSheet!F30 -> 0 | G12: =BalSheet!G30 -> 0 | H12: =BalSheet!H30 -> 0 | I12: =BalSheet!I30 -> 0 | J12: =BalSheet!J30 -> 0
B13: Interest rate | F13: =F4 -> 0.04875 | G13: =G4 -> 0.04875 | H13: =H4 -> 0.04875 | I13: =I4 -> 0.04875 | J13: =J4 -> 0.04875
B14: Interest expense | F14: =F12*-F13 -> 0 | G14: =G12*-G13 -> 0 | H14: =H12*-H13 -> 0 | I14: =I12*-I13 -> 0 | J14: =J12*-J13 -> 0
A16: Long term debt | C16: =C11 -> 2022 | D16: =D11 -> 2023 | E16: =E11 -> 2024 | F16: =F11 -> 2025 | G16: =G11 -> 2026 | H16: =H11 -> 2027 | I16: =I11 -> 2028 | J16: =J11 -> 2029
B17: Beginning balance | F17: =E20 -> 741650 | G17: =F20 -> 741650 | H17: =G20 -> 741650 | I17: =H20 -> 741650 | J17: =I20 -> 741650
B18: Issuance | F18: =F8 -> 0 | G18: =G8 -> 0 | H18: =H8 -> 0 | I18: =I8 -> 0 | J18: =J8 -> 0
B19: Repayment | F19: =F9 -> 0 | G19: =G9 -> 0 | H19: =H9 -> 0 | I19: =I9 -> 0 | J19: =J9 -> 0
B20: Ending balance | E20: =BalSheet!E35 -> 741650 | F20: =SUM(F17:F19) -> 741650 | G20: =SUM(G17:G19) -> 741650 | H20: =SUM(H17:H19) -> 741650 | I20: =SUM(I17:I19) -> 741650 | J20: =SUM(J17:J19) -> 741650
B21: Interest rate | F21: =F5 -> 0.03875 | G21: =G5 -> 0.03875 | H21: =H5 -> 0.03875 | I21: =I5 -> 0.03875 | J21: =J5 -> 0.03875
B22: Interest expense | F22: =F20*-F21 -> -28738.938 | G22: =G20*-G21 -> -28738.938 | H22: =H20*-H21 -> -28738.938 | I22: =I20*-I21 -> -28738.938 | J22: =J20*-J21 -> -28738.938
A24: Debt summary | C24: =C16 -> 2022 | D24: =D16 -> 2023 | E24: =E16 -> 2024 | F24: =F16 -> 2025 | G24: =G16 -> 2026 | H24: =H16 -> 2027 | I24: =I16 -> 2028 | J24: =J16 -> 2029
B25: Revolver | F25: =F12 -> 0 | G25: =G12 -> 0 | H25: =H12 -> 0 | I25: =I12 -> 0 | J25: =J12 -> 0
B26: Total long term debt | F26: =F20 -> 741650 | G26: =G20 -> 741650 | H26: =H20 -> 741650 | I26: =I20 -> 741650 | J26: =J20 -> 741650
B27: Total debt | F27: =SUM(F25:F26) -> 741650 | G27: =SUM(G25:G26) -> 741650 | H27: =SUM(H25:H26) -> 741650 | I27: =SUM(I25:I26) -> 741650 | J27: =SUM(J25:J26) -> 741650
B28: Total interest expense | F28: =SUM(F22,F14) -> -28738.938 | G28: =SUM(G22,G14) -> -28738.938 | H28: =SUM(H22,H14) -> -28738.938 | I28: =SUM(I22,I14) -> -28738.938 | J28: =SUM(J22,J14) -> -28738.938
A30: Interest income | C30: =C11 -> 2022 | D30: =D11 -> 2023 | E30: =E11 -> 2024 | F30: =F11 -> 2025 | G30: =G11 -> 2026 | H30: =H11 -> 2027 | I30: =I11 -> 2028 | J30: =J11 -> 2029
B31: Excess Cash | F31: =BalSheet!F17 -> 67159.55 | G31: =BalSheet!G17 -> 103452.4 | H31: =BalSheet!H17 -> 128849.66 | I31: =BalSheet!I17 -> 139542.1 | J31: =BalSheet!J17 -> 129938.52
B32: Interest rate | F32: =F6 -> 0.04 | G32: =G6 -> 0.04 | H32: =H6 -> 0.04 | I32: =I6 -> 0.04 | J32: =J6 -> 0.04
B33: Interest income | F33: =F31*F32 -> 2686.382 | G33: =G31*G32 -> 4138.0959 | H33: =H31*H32 -> 5153.9864 | I33: =I31*I32 -> 5581.6842 | J33: =J31*J32 -> 5197.5409

Sheet IncState
A1: =CoName -> Papa John's Inc | C1: Hist. | D1: Hist. | E1: Hist. | F1: Proj. | G1: Proj. | H1: Proj. | I1: Proj. | J1: Proj.
A2: Assumptions | C2: 2022 | D2: =C2+1 -> 2023 | E2: =D2+1 -> 2024 | F2: =E2+1 -> 2025 | G2: =F2+1 -> 2026 | H2: =G2+1 -> 2027 | I2: =H2+1 -> 2028 | J2: =I2+1 -> 2029
B4: Revenue growth | F4: =Assumptions!F10 -> 0.006 | G4: =Assumptions!G10 -> -0.019 | H4: =Assumptions!H10 -> -0.02 | I4: =Assumptions!I10 -> -0.02 | J4: =Assumptions!J10 -> -0.02
B5: Cost of goods sold as % of sales | F5: =Assumptions!F11 -> 0.71789615 | G5: =Assumptions!G11 -> 0.71789615 | H5: =Assumptions!H11 -> 0.71789615 | I5: =Assumptions!I11 -> 0.71789615 | J5: =Assumptions!J11 -> 0.71789615
B6: SG&A % of sales | F6: =Assumptions!F12 -> 0.2060113 | G6: =Assumptions!G12 -> 0.2060113 | H6: =Assumptions!H12 -> 0.2060113 | I6: =Assumptions!I12 -> 0.2060113 | J6: =Assumptions!J12 -> 0.2060113
B7: Amortization amount | F7: =Assumptions!F13 -> 0 | G7: =Assumptions!G13 -> 0 | H7: =Assumptions!H13 -> 0 | I7: =Assumptions!I13 -> 0 | J7: =Assumptions!J13 -> 0
B8: Non recurring items, amount | F8: =Assumptions!F14 -> 0 | G8: =Assumptions!G14 -> 0 | H8: =Assumptions!H14 -> 0 | I8: =Assumptions!I14 -> 0 | J8: =Assumptions!J14 -> 0
B9: Other income (expense), amt | F9: =Assumptions!F15 -> 0 | G9: =Assumptions!G15 -> 0 | H9: =Assumptions!H15 -> 0 | I9: =Assumptions!I15 -> 0 | J9: =Assumptions!J15 -> 0
B10: Effective tax rate | F10: =Assumptions!F16 -> 0.21 | G10: =Assumptions!G16 -> 0.21 | H10: =Assumptions!H16 -> 0.21 | I10: =Assumptions!I16 -> 0.21 | J10: =Assumptions!J16 -> 0.21
B11: Dividend Payout Rate | F11: =Assumptions!F17 -> 2.0430816 | G11: =Assumptions!G17 -> 2.2731888 | H11: =Assumptions!H17 -> 2.5993394 | I11: =Assumptions!I17 -> 3.0405436 | J11: =Assumptions!J17 -> 3.6448232
B12: Basic WASO | F12: =Assumptions!F18 -> 32717 | G12: =Assumptions!G18 -> 32717 | H12: =Assumptions!H18 -> 32717 | I12: =Assumptions!I18 -> 32717 | J12: =Assumptions!J18 -> 32717
B13: Diluted WASO | F13: =Assumptions!F19 -> 32819 | G13: =Assumptions!G19 -> 32819 | H13: =Assumptions!H19 -> 32819 | I13: =Assumptions!I19 -> 32819 | J13: =Assumptions!J19 -> 32819
A15: Income statement | C15: =C2 -> 2022 | D15: =D2 -> 2023 | E15: =E2 -> 2024 | F15: =F2 -> 2025 | G15: =G2 -> 2026 | H15: =H2 -> 2027 | I15: =I2 -> 2028 | J15: =J2 -> 2029
B16: Revenue | C16: 2102103 | D16: 2135713 | E16: 2059387 | F16: =E16*(1+F4) -> 2071743.3 | G16: =F16*(1+G4) -> 2032380.2 | H16: =G16*(1+H4) -> 1991732.6 | I16: =H16*(1+I4) -> 1951897.9 | J16: =I16*(1+J4) -> 1912860
B17: COGS | C17: 1557736 | D17: 1558438 | E17: 1478426 | F17: =F16*F5 -> 1487296.6 | G17: =G16*G5 -> 1459037.9 | H17: =H16*H5 -> 1429857.2 | I17: =I16*I5 -> 1401260 | J17: =J16*J5 -> 1373234.8
B18: SG&A | C18: =215303+52303+155937 -> 423543 | D18: =64090+208083+157960 -> 430133 | E18: =190515+69407+164335 -> 424257 | F18: =F16*F6 -> 426802.54 | G18: =G16*G6 -> 418693.29 | H18: =H16*H6 -> 410319.43 | I18: =I16*I6 -> 402113.04 | J18: =J16*J6 -> 394070.78
A19: * | B19: EBIT | C19: =C16-SUM(C17:C18) -> 120824 | D19: =D16-SUM(D17:D18) -> 147142 | E19: =E16-SUM(E17:E18) -> 156704 | F19: =F16-SUM(F17:F18) -> 157644.22 | G19: =G16-SUM(G17:G18) -> 154648.98 | H19: =H16-SUM(H17:H18) -> 151556 | I19: =I16-SUM(I17:I18) -> 148524.88 | J19: =J16-SUM(J17:J18) -> 145554.39
B21: Depreciation | C21: 52032 | D21: 64090 | E21: 60407 | F21: =Calcs!F8 -> 65553.654 | G21: =Calcs!G8 -> 66820.731 | H21: =Calcs!H8 -> 67725.142 | I21: =Calcs!I8 -> 68309.499 | J21: =Calcs!J8 -> 68620.893
B22: Amortization | C22: 0 | D22: 0 | E22: 0 | F22: =F7 -> 0 | G22: =G7 -> 0 | H22: =H7 -> 0 | I22: =I7 -> 0 | J22: =J7 -> 0
A23: * | B23: EBITDA | C23: =SUM(C19,C21:C22) -> 172856 | D23: =SUM(D19,D21:D22) -> 211232 | E23: =SUM(E19,E21:E22) -> 217111 | F23: =SUM(F19,F21:F22) -> 223197.88 | G23: =SUM(G19,G21:G22) -> 221469.71 | H23: =SUM(H19,H21:H22) -> 219281.15 | I23: =SUM(I19,I21:I22) -> 216834.38 | J23: =SUM(J19,J21:J22) -> 214175.28
B25: Non-recurring items | C25: -12065 | D25: 0 | E25: 0 | F25: =F8 -> 0 | G25: =G8 -> 0 | H25: =H8 -> 0 | I25: =I8 -> 0 | J25: =J8 -> 0
B26: Other income (expense) | C26: 0 | D26: 0 | E26: 0 | F26: =F9 -> 0 | G26: =G9 -> 0 | H26: =H9 -> 0 | I26: =I9 -> 0 | J26: =J9 -> 0
B28: Interest income | F28: =IF(circ=1,Debt!F33,0) -> 0 | G28: =IF(circ=1,Debt!G33,0) -> 0 | H28: =IF(circ=1,Debt!H33,0) -> 0 | I28: =IF(circ=1,Debt!I33,0) -> 0 | J28: =IF(circ=1,Debt!J33,0) -> 0
B29: Interest expense | C29: -25261 | D29: -43469 | E29: -42578 | F29: =IF(circ=1,Debt!F28,0) -> 0 | G29: =IF(circ=1,Debt!G28,0) -> 0 | H29: =IF(circ=1,Debt!H28,0) -> 0 | I29: =IF(circ=1,Debt!I28,0) -> 0 | J29: =IF(circ=1,Debt!J28,0) -> 0
A31: * | B31: Pretax Income | C31: =C19+SUM(C26:C29) -> 95563 | D31: =D19+SUM(D26:D29) -> 103673 | E31: =E19+SUM(E25:E29) -> 114126 | F31: =F19+SUM(F25:F29) -> 157644.22 | G31: =G19+SUM(G25:G29) -> 154648.98 | H31: =H19+SUM(H25:H29) -> 151556 | I31: =I19+SUM(I25:I29) -> 148524.88 | J31: =J19+SUM(J25:J29) -> 145554.39
B33: Tax expense | C33: 14420 | D33: 20874 | E33: 29929 | F33: =F31*F10 -> 33105.287 | G33: =G31*G10 -> 32476.287 | H33: =H31*H10 -> 31826.761 | I33: =I31*I10 -> 31190.226 | J33: =J31*J10 -> 30566.421
A34: * | B34: Net income | C34: =C31-C33 -> 81143 | D34: =D31-D33 -> 82799 | E34: =E31-E33 -> 84197 | F34: =F31-F33 -> 124538.94 | G34: =G31-G33 -> 122172.7 | H34: =H31-H33 -> 119729.24 | I34: =I31-I33 -> 117334.66 | J34: =J31-J33 -> 114987.97
B35: Dividend payout rate | C35: =C36/C38 -> 1.5428628 | D35: =D36/D38 -> 1.7749537 | E35: =E36/E38 -> 1.8509949 | F35: =F11 -> 2.0430816 | G35: =G11 -> 2.2731888 | H35: =H11 -> 2.5993394 | I35: =I11 -> 3.0405436 | J35: =J11 -> 3.6448232
B36: Dividends | C36: 54767 | D36: 58451 | E36: 60559 | F36: =F35*F38 -> 66843.499 | G36: =G35*G38 -> 74371.919 | H36: =H35*H38 -> 85042.588 | I36: =I35*I38 -> 99477.466 | J36: =J35*J38 -> 119247.68
A37: Shareholder information | C37: =C15 -> 2022 | D37: =D15 -> 2023 | E37: =E15 -> 2024 | F37: =F15 -> 2025 | G37: =G15 -> 2026 | H37: =H15 -> 2027 | I37: =I15 -> 2028 | J37: =J15 -> 2029
B38: Basic WASO | C38: 35497 | D38: 32931 | E38: 32717 | F38: =F12 -> 32717 | G38: =G12 -> 32717 | H38: =H12 -> 32717 | I38: =I12 -> 32717 | J38: =J12 -> 32717
B39: Diluted WASO | C39: 35717 | D39: 33159 | E39: 32819 | F39: =F13 -> 32819 | G39: =G13 -> 32819 | H39: =H13 -> 32819 | I39: =I13 -> 32819 | J39: =J13 -> 32819
B40: Basic earnings per share | C40: =C34/C38 -> 2.2859115 | D40: =D34/D38 -> 2.5143178 | E40: =E34/E38 -> 2.5734939 | F40: =F34/F38 -> 3.8065512 | G40: =G34/G38 -> 3.7342268 | H40: =H34/H38 -> 3.6595422 | I40: =I34/I38 -> 3.5863514 | J40: =J34/J38 -> 3.5146244
A41: * | B41: Diluted earnings per share | C41: =C34/C39 -> 2.2718313 | D41: =D34/D39 -> 2.4970295 | E41: =E34/E39 -> 2.5654956 | F41: =F34/F39 -> 3.7947206 | G41: =G34/G39 -> 3.722621 | H41: =H34/H39 -> 3.6481685 | I41: =I34/I39 -> 3.5752052 | J41: =J34/J39 -> 3.5037011

Sheet BalSheet
A1: =CoName -> Papa John's Inc | C1: Hist. | D1: Hist. | E1: Hist. | F1: Proj. | G1: Proj. | H1: Proj. | I1: Proj. | J1: Proj.
A2: Assumptions | C2: 2022 | D2: =C2+1 -> 2023 | E2: =D2+1 -> 2024 | F2: =E2+1 -> 2025 | G2: =F2+1 -> 2026 | H2: =G2+1 -> 2027 | I2: =H2+1 -> 2028 | J2: =I2+1 -> 2029
B4: Operating Cash % of sales | F4: =Assumptions!F38 -> 0.01 | G4: =F4 -> 0.01 | H4: =G4 -> 0.01 | I4: =H4 -> 0.01 | J4: =I4 -> 0.01
B5: Accounts receivable % of sales | F5: =Assumptions!F39 -> 0.052840481 | G5: =Assumptions!G39 -> 0.052840481 | H5: =Assumptions!H39 -> 0.052840481 | I5: =Assumptions!I39 -> 0.052840481 | J5: =Assumptions!J39 -> 0.052840481
B6: Inventories % of COGS | F6: =Assumptions!F40 -> 0.023839543 | G6: =Assumptions!G40 -> 0.023839543 | H6: =Assumptions!H40 -> 0.023839543 | I6: =Assumptions!I40 -> 0.023839543 | J6: =Assumptions!J40 -> 0.023839543
B7: Other current assets % of sales | F7: =Assumptions!F41 -> 0.023592457 | G7: =Assumptions!G41 -> 0.023592457 | H7: =Assumptions!H41 -> 0.023592457 | I7: =Assumptions!I41 -> 0.023592457 | J7: =Assumptions!J41 -> 0.023592457
B9: Other long-term assets % of sales | F9: =Assumptions!F43 -> 0.046824128 | G9: =Assumptions!G43 -> 0.046824128 | H9: =Assumptions!H43 -> 0.046824128 | I9: =Assumptions!I43 -> 0.046824128 | J9: =Assumptions!J43 -> 0.046824128
B11: Accounts payable/Accural % of COGS | F11: =Assumptions!F47 -> 0.15517043 | G11: =Assumptions!G47 -> 0.15517043 | H11: =Assumptions!H47 -> 0.15517043 | I11: =Assumptions!I47 -> 0.15517043 | J11: =Assumptions!J47 -> 0.15517043
B12: Other current liabilities % of sales | F12: =Assumptions!F48 -> 0.023577404 | G12: =Assumptions!G48 -> 0.023577404 | H12: =Assumptions!H48 -> 0.023577404 | I12: =Assumptions!I48 -> 0.023577404 | J12: =Assumptions!J48 -> 0.023577404
B13: Other long-term liabilities % of sales | F13: =Assumptions!F49 -> 0.13725055 | G13: =Assumptions!G49 -> 0.13725055 | H13: =Assumptions!H49 -> 0.13725055 | I13: =Assumptions!I49 -> 0.13725055 | J13: =Assumptions!J49 -> 0.13725055
A15: Balance sheet | C15: =C2 -> 2022 | D15: =D2 -> 2023 | E15: =E2 -> 2024 | F15: =F2 -> 2025 | G15: =G2 -> 2026 | H15: =H2 -> 2027 | I15: =I2 -> 2028 | J15: =J2 -> 2029
B16: Operating Cash | C16: =1%*IncState!C16 -> 21021.03 | D16: =1%*IncState!D16 -> 21357.13 | E16: =1%*IncState!E16 -> 20593.87 | F16: =F4*IncState!F16 -> 20717.433 | G16: =G4*IncState!G16 -> 20323.802 | H16: =H4*IncState!H16 -> 19917.326 | I16: =I4*IncState!I16 -> 19518.979 | J16: =J4*IncState!J16 -> 19128.6
B17: Excess cash | C17: =47373-C16 -> 26351.97 | D17: =40587-D16 -> 19229.87 | E17: =37955-E16 -> 17361.13 | F17: =MAX(CashFlow!F23,0) -> 67159.55 | G17: =MAX(CashFlow!G23,0) -> 103452.4 | H17: =MAX(CashFlow!H23,0) -> 128849.66 | I17: =MAX(CashFlow!I23,0) -> 139542.1 | J17: =MAX(CashFlow!J23,0) -> 129938.52
B18: Accounts receivable | C18: =102533+6848+8780 -> 118161 | D18: =104244+5199+2577 -> 112020 | E18: =101677+4928+2214 -> 108819 | F18: =F5*IncState!F16 -> 109471.91 | G18: =G5*IncState!G16 -> 107391.95 | H18: =H5*IncState!H16 -> 105244.11 | I18: =I5*IncState!I16 -> 103139.23 | J18: =J5*IncState!J16 -> 101076.44
B19: Inventories | C19: 41382 | D19: 36126 | E19: 35245 | F19: =F6*IncState!F17 -> 35456.47 | G19: =G6*IncState!G17 -> 34782.797 | H19: =H6*IncState!H17 -> 34087.141 | I19: =I6*IncState!I17 -> 33405.398 | J19: =J6*IncState!J17 -> 32737.29
B20: Other current assets | C20: 44123 | D20: 42285 | E20: 48586 | F20: =F7*IncState!F16 -> 48877.516 | G20: =G7*IncState!G16 -> 47948.843 | H20: =H7*IncState!H16 -> 46989.866 | I20: =I7*IncState!I16 -> 46050.069 | J20: =J7*IncState!J16 -> 45129.068
B21: Total current assets | C21: =SUM(C16:C20) -> 251039 | D21: =SUM(D16:D20) -> 231018 | E21: =SUM(E16:E20) -> 230605 | F21: =SUM(F16:F20) -> 281682.88 | G21: =SUM(G16:G20) -> 313899.79 | H21: =SUM(H16:H20) -> 335088.1 | I21: =SUM(I16:I20) -> 341655.78 | J21: =SUM(J16:J20) -> 328009.92
B23: Property, plant & equipment, net | C23: =249793+24941+172425 -> 447159 | D23: =282812+31740+164158 -> 478710 | E23: =273272+28761+184425 -> 486458 | F23: =Calcs!F9 -> 495860.67 | G23: =Calcs!G9 -> 502572.09 | H23: =Calcs!H9 -> 506908.46 | I23: =Calcs!I9 -> 509219.24 | J23: =Calcs!J9 -> 509806.23
B24: Intangible assets | C24: 70616 | D24: 76206 | E24: 75460 | F24: =E24-IncState!F22 -> 75460 | G24: =F24-IncState!G22 -> 75460 | H24: =G24-IncState!H22 -> 75460 | I24: =H24-IncState!I22 -> 75460 | J24: =I24-IncState!J22 -> 75460
B25: Other assets | C25: =21248+74165 -> 95413 | D25: =76725+12346 -> 89071 | E25: =8867+87562 -> 96429 | F25: =F9*IncState!F16 -> 97007.574 | G25: =G9*IncState!G16 -> 95164.43 | H25: =H9*IncState!H16 -> 93261.141 | I25: =I9*IncState!I16 -> 91395.919 | J25: =J9*IncState!J16 -> 89568
B26: Total non-current assets | C26: =SUM(C23:C25) -> 613188 | D26: =SUM(D23:D25) -> 643987 | E26: =SUM(E23:E25) -> 658347 | F26: =SUM(F23:F25) -> 668328.24 | G26: =SUM(G23:G25) -> 673196.52 | H26: =SUM(H23:H25) -> 675629.6 | I26: =SUM(I23:I25) -> 676075.16 | J26: =SUM(J23:J25) -> 674834.23
A28: * | B28: TOTAL ASSETS | C28: =SUM(C26,C21) -> 864227 | D28: =SUM(D26,D21) -> 875005 | E28: =SUM(E26,E21) -> 888952 | F28: =SUM(F26,F21) -> 950011.13 | G28: =SUM(G26,G21) -> 987096.31 | H28: =SUM(H26,H21) -> 1010717.7 | I28: =SUM(I26,I21) -> 1017730.9 | J28: =SUM(J26,J21) -> 1002844.1
B30: Revolver/Short term debt | C30: 0 | D30: 0 | E30: 0 | F30: =-MIN(CashFlow!F23,0) -> 0 | G30: =-MIN(CashFlow!G23,0) -> 0 | H30: =-MIN(CashFlow!H23,0) -> 0 | I30: =-MIN(CashFlow!I23,0) -> 0 | J30: =-MIN(CashFlow!J23,0) -> 0
B31: Accounts payable/Accurals | C31: =67316+8766+142535 -> 218617 | D31: =74949+17948+158167 -> 251064 | E31: =61842+11987+155579 -> 229408 | F31: =BalSheet!F11*IncState!F17 -> 230784.45 | G31: =BalSheet!G11*IncState!G17 -> 226399.54 | H31: =BalSheet!H11*IncState!H17 -> 221871.55 | I31: =BalSheet!I11*IncState!I17 -> 217434.12 | J31: =BalSheet!J11*IncState!J17 -> 213085.44
B32: Other current liabilities | C32: =265157-C31 -> 46540 | D32: =304596-D31 -> 53532 | E32: =277963-E31 -> 48555 | F32: =F12*IncState!F16 -> 48846.33 | G32: =G12*IncState!G16 -> 47918.25 | H32: =H12*IncState!H16 -> 46959.885 | I32: =I12*IncState!I16 -> 46020.687 | J32: =J12*IncState!J16 -> 45100.273
B33: Total current liabilities | C33: =SUM(C30:C32) -> 265157 | D33: =SUM(D30:D32) -> 304596 | E33: =SUM(E30:E32) -> 277963 | F33: =SUM(F30:F32) -> 279630.78 | G33: =SUM(G30:G32) -> 274317.79 | H33: =SUM(H30:H32) -> 268831.44 | I33: =SUM(I30:I32) -> 263454.81 | J33: =SUM(J30:J32) -> 258185.71
B35: Long-term debt, including current maturities | C35: 597069 | D35: 757422 | E35: 741650 | F35: =Debt!F20 -> 741650 | G35: =Debt!G20 -> 741650 | H35: =Debt!H20 -> 741650 | I35: =Debt!I20 -> 741650 | J35: =Debt!J20 -> 741650
B36: Other long-term liabilities | C36: =1133674-C35-C33 -> 271448 | D36: =1317770-D35-D33 -> 255752 | E36: =1302265-E35-E33 -> 282652 | F36: =F13*IncState!F16 -> 284347.91 | G36: =G13*IncState!G16 -> 278945.3 | H36: =H13*IncState!H16 -> 273366.4 | I36: =I13*IncState!I16 -> 267899.07 | J36: =J13*IncState!J16 -> 262541.09
B37: Total non-current liabilities | C37: =SUM(C35:C36) -> 868517 | D37: =SUM(D35:D36) -> 1013174 | E37: =SUM(E35:E36) -> 1024302 | F37: =SUM(F35:F36) -> 1025997.9 | G37: =SUM(G35:G36) -> 1020595.3 | H37: =SUM(H35:H36) -> 1015016.4 | I37: =SUM(I35:I36) -> 1009549.1 | J37: =SUM(J35:J36) -> 1004191.1
B39: Equity | C39: -269447 | D39: -442765 | E39: -413313 | F39: =Calcs!F17 -> -355617.56 | G39: =Calcs!G17 -> -307816.78 | H39: =Calcs!H17 -> -273130.13 | I39: =Calcs!I17 -> -255272.94 | J39: =Calcs!J17 -> -259532.65
A40: * | B40: TOTAL LIABILITIES & EQUITY | C40: =SUM(C39,C37,C33) -> 864227 | D40: =SUM(D39,D37,D33) -> 875005 | E40: =SUM(E39,E37,E33) -> 888952 | F40: =SUM(F39,F37,F33) -> 950011.13 | G40: =SUM(G39,G37,G33) -> 987096.31 | H40: =SUM(H39,H37,H33) -> 1010717.7 | I40: =SUM(I39,I37,I33) -> 1017730.9 | J40: =SUM(J39,J37,J33) -> 1002844.1
A42: * | B42: Balance check | C42: =C40-C28 -> 0 | D42: =D40-D28 -> 0 | E42: =E40-E28 -> 0 | F42: =F40-F28 -> 0 | G42: =G40-G28 -> 0 | H42: =H40-H28 -> 0 | I42: =I40-I28 -> 0 | J42: =J40-J28 -> 0

Sheet CashFlow
A1: =CoName -> Papa John's Inc | C1: Hist. | D1: Hist. | E1: Hist. | F1: Proj. | G1: Proj. | H1: Proj. | I1: Proj. | J1: Proj.
A2: Cash flow statement | C2: 2022 | D2: =C2+1 -> 2023 | E2: =D2+1 -> 2024 | F2: =E2+1 -> 2025 | G2: =F2+1 -> 2026 | H2: =G2+1 -> 2027 | I2: =H2+1 -> 2028 | J2: =I2+1 -> 2029
B3: Net Income | F3: =IncState!F34 -> 124538.94 | G3: =IncState!G34 -> 122172.7 | H3: =IncState!H34 -> 119729.24 | I3: =IncState!I34 -> 117334.66 | J3: =IncState!J34 -> 114987.97
B4: Depreciation | F4: =IncState!F21 -> 65553.654 | G4: =IncState!G21 -> 66820.731 | H4: =IncState!H21 -> 67725.142 | I4: =IncState!I21 -> 68309.499 | J4: =IncState!J21 -> 68620.893
B5: Amortization | F5: =IncState!F22 -> 0 | G5: =IncState!G22 -> 0 | H5: =IncState!H22 -> 0 | I5: =IncState!I22 -> 0 | J5: =IncState!J22 -> 0
B6: (inc) / dec In OWC | F6: =Calcs!F26 -> 388.31478 | G6: =Calcs!G26 -> -1237.0415 | H6: =Calcs!H26 -> -1277.4081 | I6: =Calcs!I26 -> -1251.8599 | J6: =Calcs!J26 -> -1226.8227
B7: (inc) / dec in LT assets | F7: =BalSheet!E25-BalSheet!F25 -> -578.574 | G7: =BalSheet!F25-BalSheet!G25 -> 1843.1439 | H7: =BalSheet!G25-BalSheet!H25 -> 1903.2886 | I7: =BalSheet!H25-BalSheet!I25 -> 1865.2228 | J7: =BalSheet!I25-BalSheet!J25 -> 1827.9184
B8: inc / (dec) in LT liabilities | F8: =BalSheet!F36-BalSheet!E36 -> 1695.912 | G8: =BalSheet!G36-BalSheet!F36 -> -5402.6103 | H8: =BalSheet!H36-BalSheet!G36 -> -5578.906 | I8: =BalSheet!I36-BalSheet!H36 -> -5467.3279 | J8: =BalSheet!J36-BalSheet!I36 -> -5357.9814
B9: CFFO | F9: =SUM(F3:F8) -> 191598.24 | G9: =SUM(G3:G8) -> 184196.92 | H9: =SUM(H3:H8) -> 182501.36 | I9: =SUM(I3:I8) -> 180790.19 | J9: =SUM(J3:J8) -> 178851.97
B11: Capex | F11: =-Calcs!F7 -> -74956.324 | G11: =-Calcs!G7 -> -73532.154 | H11: =-Calcs!H7 -> -72061.511 | I11: =-Calcs!I7 -> -70620.281 | J11: =-Calcs!J7 -> -69207.875
B12: CFFI | F12: =SUM(F11) -> -74956.324 | G12: =SUM(G11) -> -73532.154 | H12: =SUM(H11) -> -72061.511 | I12: =SUM(I11) -> -70620.281 | J12: =SUM(J11) -> -69207.875
B14: Dividends Paid | F14: =-IncState!F36 -> -66843.499 | G14: =-IncState!G36 -> -74371.919 | H14: =-IncState!H36 -> -85042.588 | I14: =-IncState!I36 -> -99477.466 | J14: =-IncState!J36 -> -119247.68
B15: Debt issuance | F15: =SUM(Debt!F8:F9) -> 0 | G15: =SUM(Debt!G8:G9) -> 0 | H15: =SUM(Debt!H8:H9) -> 0 | I15: =SUM(Debt!I8:I9) -> 0 | J15: =SUM(Debt!J8:J9) -> 0
B16: Share issuance | F16: =Calcs!F11 -> 0 | G16: =Calcs!G11 -> 0 | H16: =Calcs!H11 -> 0 | I16: =Calcs!I11 -> 0 | J16: =Calcs!J11 -> 0
B17: CFFF | F17: =SUM(F14:F16) -> -66843.499 | G17: =SUM(G14:G16) -> -74371.919 | H17: =SUM(H14:H16) -> -85042.588 | I17: =SUM(I14:I16) -> -99477.466 | J17: =SUM(J14:J16) -> -119247.68
B19: Net changes in cash | F19: =SUM(F17,F12,F9) -> 49798.42 | G19: =SUM(G17,G12,G9) -> 36292.847 | H19: =SUM(H17,H12,H9) -> 25397.261 | I19: =SUM(I17,I12,I9) -> 10692.445 | J19: =SUM(J17,J12,J9) -> -9603.5823
B21: Beginning cash | F21: =E23 -> 17361.13 | G21: =F23 -> 67159.55 | H21: =G23 -> 103452.4 | I21: =H23 -> 128849.66 | J21: =I23 -> 139542.1
B22: =B19 -> Net changes in cash | F22: =F19 -> 49798.42 | G22: =G19 -> 36292.847 | H22: =H19 -> 25397.261 | I22: =I19 -> 10692.445 | J22: =J19 -> -9603.5823
B23: Ending cash | E23: =BalSheet!E17 -> 17361.13 | F23: =SUM(F21:F22) -> 67159.55 | G23: =SUM(G21:G22) -> 103452.4 | H23: =SUM(H21:H22) -> 128849.66 | I23: =SUM(I21:I22) -> 139542.1 | J23: =SUM(J21:J22) -> 129938.52

Sheet Free Cash Flow
A1: =CoName -> Papa John's Inc | C1: Hist. | D1: Hist. | E1: Hist. | F1: Proj. | G1: Proj. | H1: Proj. | I1: Proj. | J1: Proj.
A2: Free Cash Flows | C2: 2022 | D2: =C2+1 -> 2023 | E2: =D2+1 -> 2024 | F2: =E2+1 -> 2025 | G2: =F2+1 -> 2026 | H2: =G2+1 -> 2027 | I2: =H2+1 -> 2028 | J2: =I2+1 -> 2029
A3: * | B3: Sales | F3: =IncState!F16 -> 2071743.3 | G3: =IncState!G16 -> 2032380.2 | H3: =IncState!H16 -> 1991732.6 | I3: =IncState!I16 -> 1951897.9 | J3: =IncState!J16 -> 1912860
B4: EBIT | F4: =IncState!F19 -> 157644.22 | G4: =IncState!G19 -> 154648.98 | H4: =IncState!H19 -> 151556 | I4: =IncState!I19 -> 148524.88 | J4: =IncState!J19 -> 145554.39
B5: Effective Tax Rate | F5: =Assumptions!F16 -> 0.21 | G5: =Assumptions!G16 -> 0.21 | H5: =Assumptions!H16 -> 0.21 | I5: =Assumptions!I16 -> 0.21 | J5: =Assumptions!J16 -> 0.21
A7: * | B7: NOPAT | F7: =F4*(1-F5) -> 124538.94 | G7: =G4*(1-G5) -> 122172.7 | H7: =H4*(1-H5) -> 119729.24 | I7: =I4*(1-I5) -> 117334.66 | J7: =J4*(1-J5) -> 114987.97
B8: Depreciation | F8: =CashFlow!F4 -> 65553.654 | G8: =CashFlow!G4 -> 66820.731 | H8: =CashFlow!H4 -> 67725.142 | I8: =CashFlow!I4 -> 68309.499 | J8: =CashFlow!J4 -> 68620.893
B9: Amortization | F9: =CashFlow!F5 -> 0 | G9: =CashFlow!G5 -> 0 | H9: =CashFlow!H5 -> 0 | I9: =CashFlow!I5 -> 0 | J9: =CashFlow!J5 -> 0
B10: (inc) / dec in OWC | F10: =CashFlow!F6 -> 388.31478 | G10: =CashFlow!G6 -> -1237.0415 | H10: =CashFlow!H6 -> -1277.4081 | I10: =CashFlow!I6 -> -1251.8599 | J10: =CashFlow!J6 -> -1226.8227
B11: (inc) / dec in other long-term assets | F11: =CashFlow!F7 -> -578.574 | G11: =CashFlow!G7 -> 1843.1439 | H11: =CashFlow!H7 -> 1903.2886 | I11: =CashFlow!I7 -> 1865.2228 | J11: =CashFlow!J7 -> 1827.9184
B12: inc / (dec) other long-term liabilities | F12: =CashFlow!F8 -> 1695.912 | G12: =CashFlow!G8 -> -5402.6103 | H12: =CashFlow!H8 -> -5578.906 | I12: =CashFlow!I8 -> -5467.3279 | J12: =CashFlow!J8 -> -5357.9814
B13: (Capex) | F13: =CashFlow!F11 -> -74956.324 | G13: =CashFlow!G11 -> -73532.154 | H13: =CashFlow!H11 -> -72061.511 | I13: =CashFlow!I11 -> -70620.281 | J13: =CashFlow!J11 -> -69207.875
A15: * | B15: Free Cash Flow | F15: =SUM(F7:F13) -> 116641.92 | G15: =SUM(G7:G13) -> 110664.77 | H15: =SUM(H7:H13) -> 110439.85 | I15: =SUM(I7:I13) -> 110169.91 | J15: =SUM(J7:J13) -> 109644.1

Sheet WACC
A1: =CoName -> Papa John's Inc
A3: * | B3: WACC | G3: Comp | H3: Levered beta | I3: Gross debt | J3: Market cap | K3: Debt/Mcap | L3: MTR | M3: Unlevered beta
B4: Tax Rate | E4: =Assumptions!F16 -> 0.21 | L4: =E4 -> 0.21 | M4: =H4/((1+K4*(1-L4))) -> 0
B5: Risk free rate | E5: 0.041 | L5: =L4 -> 0.21 | M5: =H5/((1+K5*(1-L5))) -> 0
B6: Market risk Premium | E6: 0.05 | L6: =L5 -> 0.21 | M6: =H6/((1+K6*(1-L6))) -> 0
B7: Beta | E7: 0.82 | L7: =L6 -> 0.21 | M7: =H7/((1+K7*(1-L7))) -> 0
B8: Cost of Equity | E8: =E5+E6*E7 -> 0.082
B9: % Equity | E9: =1-E10 -> 0.4614624 | G9: Industry beta (average) | M9: =AVERAGE(M4:M7) -> 0
B10: % Debt | E10: =BalSheet!E35/MAIN!F6 -> 0.5385376
B11: Cost of debt | E11: =Assumptions!F24 -> 0.03875 | G11: Re-levered beta | M11: =M9*(1+E10*(1-E4)) -> 0
B12: Post tax cost of debt | E12: =E11*(1-E4) -> 0.0306125
A13: * | B13: WACC | E13: =WACC!E8*WACC!E9+WACC!E12*WACC!E10 -> 0.054325899
B14: Long Term growth rate | E14: 0.025

Sheet DCF Model
A1: =CoName -> Papa John's Inc | D1: Proj. | E1: Proj. | F1: Proj. | G1: Proj. | H1: Proj.
A2: Discount Model Year count | D2: 1 | E2: =D2+1 -> 2 | F2: =E2+1 -> 3 | G2: =F2+1 -> 4 | H2: =G2+1 -> 5
B3: Discount Factor | D3: =1/(1+$K$17)^D2 -> 0.94847333 | E3: =1/(1+$K$17)^E2 -> 0.89960166 | F3: =1/(1+$K$17)^F2 -> 0.85324819 | G3: =1/(1+$K$17)^G2 -> 0.80928315 | H3: =1/(1+$K$17)^H2 -> 0.76758349
B4: PV FCF | D4: =D3*'Free Cash Flow'!F15 -> 110631.75 | E4: =E3*'Free Cash Flow'!G15 -> 99554.207 | F4: =F3*'Free Cash Flow'!H15 -> 94232.601 | G4: =G3*'Free Cash Flow'!I15 -> 89158.653 | H4: =H3*'Free Cash Flow'!J15 -> 84160.999
H5: =(H4*(1+$K$18))/($K$17-$K$18) -> 2172192.3
A6: Value Calculation | E6: Multiples Calculation | I6: Dividend Discount Model
B7: Total PV of FCFs | C7: =SUM(D4:H4) -> 477738.21 | E7: Total PV of FCFs | G7: =C7 -> 477738.21 | I7: FY Dividend | K7: =IncState!F36 -> 66843.499
B8: PV of TV | C8: =H5*H3 -> 1667338.9 | E8: Multiple TV | G8: =H3*G10*IncState!J23 -> 2465961.1 | I8: Equity Value | K8: =K7/(WACC!E8-'DCF Model'!K18) -> 997664.17
B9: EV | C9: =C7+C8 -> 2145077.1 | E9: EV | G9: =G7+G8 -> 2943699.3
E10: Implied EBITDA multiple | G10: 15 | I10: Diluted S/O | K10: =G17 -> 32789.416
I11: Implied Share Price | K11: =K8/K10 -> 30.426409
B12: Cash & Cash Equiv | C12: =MAIN!F7 -> 38972 | E12: Cash & Cash Equiv | G12: =C12 -> 38972
B13: Debt & Claims | C13: =MAIN!F8 -> 727135 | E13: Debt & Claims | G13: =C13 -> 727135
B14: NCI | C14: 0 | E14: NCI | G14: =C14 -> 0
B15: Equity Value | C15: =C9+C12-SUM(C13:C14) -> 1456914.1 | E15: Equity Value | G15: =G9+G12-SUM(G13:G14) -> 2255536.3
B17: Diluted S/O | C17: =MAIN!F5 -> 32789.416 | E17: Diluted S/O | G17: =C17 -> 32789.416 | I17: WACC | K17: =WACC!E13 -> 0.054325899
A18: * | B18: Implied Share Price | C18: =C15/C17 -> 44.432451 | E18: Implied Share Price | G18: =G15/G17 -> 68.788549 | I18: Long Term growth rate | K18: 0.015
A20: Sensitivity analysis
C22: Discount rate variance | E22: 0.005 | H22: Discount rate variance | J22: 0.005
C23: Implied growth rate variance | E23: 0.0025 | H23: TV multiple variance | J23: 2
E25: LTGR | J25: Exit Multiple
C26: =C18 -> 44.432451 | D26: =E26-E23 -> 0.0125 | E26: 0.015 | F26: =E26+E23 -> 0.0175 | H26: =G18 -> 68.788549 | I26: =J26-J23 -> 13 | J26: 15 | K26: =J26+J23 -> 17
C27: =C28+$E$22 -> 0.064325899 | D27: 28.21772 | E27: 30.083662 | F27: 32.148846 | H27: =C27 -> 0.064325899 | I27: 55.368289 | J27: 64.933455 | K27: 74.498621
C28: =C29+$E$22 -> 0.059325899 | D28: 34.0182 | E28: 36.415826 | F28: 39.100073 | H28: =C28 -> 0.059325899 | I28: 57.041324 | J28: 66.834368 | K28: 76.627412
C29: 0.054325899 | D29: 41.275312 | E29: 44.432451 | F29: 48.018248 | H29: =C29 -> 0.054325899 | I29: 58.761081 | J29: 68.788549 | K29: 78.816017
C30: =C29-$E$22 -> 0.049325899 | D30: 50.588193 | E30: 54.875877 | F30: 59.837177 | H30: =C30 -> 0.049325899 | I30: 60.52911 | J30: 70.797768 | K30: 81.066426
C31: =C30-$E$22 -> 0.044325899 | D31: 62.932963 | E31: 68.995231 | F31: 76.187427 | H31: =C31 -> 0.044325899 | I31: 62.347023 | J31: 72.863867 | K31: 83.38071
