Workbook
Name Ccy: MAIN!$C$6
Name circ: MAIN!$C$9
Name CoName: MAIN!$C$4
Name g: #REF!
Name IQ_CH: 110000
Name IQ_CQ: 5000
Name IQ_CY: 10000
Name IQ_DAILY: 500000
Name IQ_FH: 100000
Name IQ_FQ: 500
Name IQ_FY: 1000
Name IQ_LTM: 2000
Name IQ_MONTH: 15000
Name IQ_NTM: 6000
Name IQ_WEEK: 50000
Name IQ_YTD: 3000
Name OpCase: [1]DCF!$E$98
Name ScenarioREV: Assumptions!$D$4
Name TTS: #REF!
Name Units: MAIN!$C$7

Sheet MAIN
A1: =CoName -> Resturant Brands International Inc
A2: Model Details
B4: Company name | C4: Resturant Brands International Inc | E4: Current Stock Price | F4: 73.44 | H4: Operating Case One | I4: Terminal Mult | J4: Perpetuity | K4: DDM | L4: Average
B5: Latest BS date | C5: 247.43 | E5: Diluted s/o | F5: =327.812+126.983 -> 454.795 | H5: Implied Price | I5: ='DCF Model'!G18 -> 85.255726 | J5: ='DCF Model'!C18 -> 76.391724 | K5: ='DCF Model'!K11 -> 68.039399 | L5: =AVERAGE(I5:K5) -> 76.562283
B6: Currency | C6: USD | E6: Mkt Cap | F6: =F4*F5 -> 33400.145 | H6: Difference | I6: =I5/$F$4-1 -> 0.16088951 | J6: =J5/$F$4-1 -> 0.040192316 | K6: =K5/$F$4-1 -> -0.073537594 | L6: =L5/$F$4-1 -> 0.042514744
B7: Units | C7: m | E7: Cash | F7: =1206 -> 1206
B8: Analyst name | C8: Alan Chen | E8: Debt | F8: =116+13415 -> 13531
B9: Circular switch | C9: 0 | E9: EV | F9: =F6-F7+F8 -> 45725.145

Sheet Quarterly Projections
A1: =CoName -> Resturant Brands International Inc
A2: Individual Resturants | C2: Q123 | D2: Q223 | E2: Q323 | F2: Q423 | G2: 2023 | H2: Q124 | I2: Q224 | J2: Q324 | K2: Q424 | L2: 2024 | M2: Q125 | N2: Q225 | O2: Q325 | P2: Q425E | Q2: 2025E | R2: Q126E | S2: Q226E | T2: Q326E | U2: Q426E | V2: 2026E | W2: 2027E | X2: 2028E | Y2: 2029E
B3: Supply chain sales | C3: 729 | D3: 676 | E3: 706 | F3: 690 | G3: =SUM(C3:F3) -> 2801 | H3: 627 | I3: 682 | J3: 699 | K3: 700 | L3: =SUM(H3:K3) -> 2708 | M3: 611 | N3: 732 | O3: 769 | P3: =K3*(1+P4) -> 734.51898 | Q3: =SUM(M3:P3) -> 2846.519 | R3: =M3*(1+R4) -> 641.55 | S3: =N3*(1+S4) -> 768.6 | T3: =O3*(1+T4) -> 807.45 | U3: =P3*(1+U4) -> 771.24493 | V3: =SUM(R3:U3) -> 2988.8449 | W3: =V3*(1+W4) -> 3128.424 | X3: =W3*(1+X4) -> 3264.1976 | Y3: =X3*(1+Y4) -> 3395.0919
C4: n/a | D4: n/a | E4: n/a | F4: n/a | G4: n/a | H4: =H3/C3-1 -> -0.1399177 | I4: =I3/D3-1 -> 0.0088757396 | J4: =J3/E3-1 -> -0.0099150142 | K4: =K3/F3-1 -> 0.014492754 | L4: =L3/G3-1 -> -0.033202428 | M4: =M3/H3-1 -> -0.025518341 | N4: =N3/I3-1 -> 0.073313783 | O4: =O3/J3-1 -> 0.10014306 | P4: =AVERAGE(M4:O4) -> 0.049312834 | Q4: =Q3/L3-1 -> 0.051151767 | R4: 0.05 | S4: =R4 -> 0.05 | T4: =S4 -> 0.05 | U4: =T4 -> 0.05 | V4: =V3/Q3-1 -> 0.05 | W4: =V4-0.0033 -> 0.0467 | X4: =W4-0.0033 -> 0.0434 | Y4: =X4-0.0033 -> 0.0401
B5: Company resturant sales | C5: 0 | D5: 68 | E5: 65 | F5: 77 | G5: =SUM(C5:F5) -> 210 | H5: 102 | I5: 347 | J5: 567 | K5: 576 | L5: =SUM(H5:K5) -> 1592 | M5: 558 | N5: 600 | O5: 588 | P5: =K5*(1+P6) -> 633.6 | Q5: =SUM(M5:P5) -> 2379.6 | R5: =M5*(1+R6) -> 591.48 | S5: =N5*(1+S6) -> 636 | T5: =O5*(1+T6) -> 623.28 | U5: =P5*(1+U6) -> 671.616 | V5: =SUM(R5:U5) -> 2522.376 | W5: =V5*(1+W6) -> 2665.3947 | X5: =W5*(1+X6) -> 2807.7268 | Y5: =X5*(1+Y6) -> 2948.3939
C6: n/a | D6: n/a | E6: n/a | F6: n/a | G6: n/a | I6: =I5/D5-1 -> 4.1029412 | J6: =J5/E5-1 -> 7.7230769 | K6: =K5/F5-1 -> 6.4805195 | L6: =L5/G5-1 -> 6.5809524 | M6: =M5/H5-1 -> 4.4705882 | N6: =N5/I5-1 -> 0.72910663 | O6: =O5/J5-1 -> 0.037037037 | P6: 0.1 | Q6: =Q5/L5-1 -> 0.49472362 | R6: 0.06 | S6: =R6 -> 0.06 | T6: =S6 -> 0.06 | U6: =T6 -> 0.06 | V6: =V5/Q5-1 -> 0.06 | W6: =V6-0.0033 -> 0.0567 | X6: =W6-0.0033 -> 0.0534 | Y6: =X6-0.0033 -> 0.0501
B7: Franchise and property revenues | C7: 712 | D7: 742 | E7: 753 | F7: 740 | G7: =SUM(C7:F7) -> 2947 | H7: 712 | I7: 747 | J7: 735 | K7: 725 | L7: =SUM(H7:K7) -> 2919 | M7: 663 | N7: 760 | O7: 778 | P7: =K7*(1+P8) -> 761.25 | Q7: =SUM(M7:P7) -> 2962.25 | R7: =M7*(1+R8) -> 696.15 | S7: =N7*(1+S8) -> 798 | T7: =O7*(1+T8) -> 816.9 | U7: =P7*(1+U8) -> 799.3125 | V7: =SUM(R7:U7) -> 3110.3625 | W7: =V7*(1+W8) -> 3255.6164 | X7: =W7*(1+X8) -> 3396.9102 | Y7: =X7*(1+Y8) -> 3533.1263
C8: n/a | D8: n/a | E8: n/a | F8: n/a | G8: n/a | I8: =I7/D7-1 -> 0.0067385445 | J8: =J7/E7-1 -> -0.023904382 | K8: =K7/F7-1 -> -0.02027027 | L8: =L7/G7-1 -> -0.0095011876 | M8: =M7/H7-1 -> -0.068820225 | N8: =N7/I7-1 -> 0.017402945 | O8: =O7/J7-1 -> 0.058503401 | P8: 0.05 | Q8: =Q7/L7-1 -> 0.014816718 | R8: 0.05 | S8: =R8 -> 0.05 | T8: =S8 -> 0.05 | U8: =T8 -> 0.05 | V8: =V7/Q7-1 -> 0.05 | W8: =V8-0.0033 -> 0.0467 | X8: =W8-0.0033 -> 0.0434 | Y8: =X8-0.0033 -> 0.0401
B9: Advertising revenues & other | C9: 298 | D9: 289 | E9: 313 | F9: 313 | G9: =SUM(C9:F9) -> 1213 | H9: 298 | I9: 304 | J9: 290 | K9: 295 | L9: =SUM(H9:K9) -> 1187 | M9: 277 | N9: 318 | O9: 314 | P9: =K9*(1+P10) -> 300.73691 | Q9: =SUM(M9:P9) -> 1209.7369 | R9: =M9*(1+R10) -> 285.31 | S9: =N9*(1+S10) -> 327.54 | T9: =O9*(1+T10) -> 323.42 | U9: =P9*(1+U10) -> 309.75902 | V9: =SUM(R9:U9) -> 1246.029 | W9: =V9*(1+W10) -> 1279.298 | X9: =W9*(1+X10) -> 1309.2336 | Y9: =X9*(1+Y10) -> 1335.5492
C10: n/a | D10: n/a | E10: n/a | F10: n/a | G10: n/a | I10: =I9/D9-1 -> 0.051903114 | J10: =J9/E9-1 -> -0.073482428 | K10: =K9/F9-1 -> -0.057507987 | L10: =L9/G9-1 -> -0.02143446 | M10: =M9/H9-1 -> -0.070469799 | N10: =N9/I9-1 -> 0.046052632 | O10: =O9/J9-1 -> 0.082758621 | P10: =AVERAGE(M10:O10) -> 0.019447151 | Q10: =Q9/L9-1 -> 0.019154936 | R10: 0.03 | S10: =R10 -> 0.03 | T10: =S10 -> 0.03 | U10: =T10 -> 0.03 | V10: =V9/Q9-1 -> 0.03 | W10: =V10-0.0033 -> 0.0267 | X10: =W10-0.0033 -> 0.0234 | Y10: =X10-0.0033 -> 0.0201
A11: Revenues | C11: =SUM(C3:C9) -> 1739 | D11: =SUM(D3:D9) -> 1775 | E11: =SUM(E3:E9) -> 1837 | F11: =SUM(F3:F9) -> 1820 | G11: =SUM(G3:G9) -> 7171 | H11: =SUM(H3:H9) -> 1738.8601 | I11: =SUM(I3:I9) -> 2084.1186 | J11: =SUM(J3:J9) -> 2298.6893 | ... Y11: =SUM(Y3:Y9) -> 11212.292
H12: =H11/C11-1 -> -8.0458709e-05 | I12: =I11/D11-1 -> 0.1741513 | J12: =J11/E11-1 -> 0.25132785 | K12: =K11/F11-1 -> 0.26509601 | L12: =L11/G11-1 -> 0.17313321 | M12: =M11/H11-1 -> 0.21538028 | N12: =N11/I11-1 -> 0.15675753 | O12: =O11/J11-1 -> 0.06547489 | ... V12: =V11/Q11-1 -> 0.049911959 | W12: =W11/V11-1 -> 0.046728964 | X12: =X11/W11-1 -> 0.043501809 | Y12: =Y11/X11-1 -> 0.040274155
B14: COGS | C14: 606 | D14: 551 | E14: 572 | F14: 573 | G14: =SUM(C14:F14) -> 2302 | H14: 517 | I14: 540 | J14: 559 | K14: 564 | L14: =SUM(H14:K14) -> 2180 | M14: 496 | N14: 589 | O14: 619 | Q14: =SUM(M14:P14) -> 1704
B15: Margin % | C15: =C14/C11 -> 0.34847614 | D15: =D14/D11 -> 0.31042254 | E15: =E14/E11 -> 0.31137725 | F15: =F14/F11 -> 0.31483516 | G15: =G14/G11 -> 0.3210152 | H15: =H14/H11 -> 0.29732122 | I15: =I14/I11 -> 0.25910234 | J15: =J14/J11 -> 0.24318206 | ... O15: =O14/O11 -> 0.25273603
B16: Company resturant expenses | C16: 126 | D16: 61 | E16: 58 | F16: 70 | G16: =SUM(C16:F16) -> 315 | H16: 89 | I16: 286 | J16: 473 | K16: 480 | L16: =SUM(H16:K16) -> 1328 | M16: 468 | N16: 498 | O16: 498 | Q16: =SUM(M16:P16) -> 1464
B17: Margin % | C17: =C16/C11 -> 0.072455434 | D17: =D16/D11 -> 0.034366197 | E17: =E16/E11 -> 0.031573217 | F17: =F16/F11 -> 0.038461538 | G17: =G16/G11 -> 0.043926928 | H17: =H16/H11 -> 0.051182957 | I17: =I16/I11 -> 0.13722828 | J17: =J16/J11 -> 0.20576944 | ... O17: =O16/O11 -> 0.20333206
B18: Franchise and property expenses | C18: 311 | D18: 130 | E18: 119 | F18: 140 | G18: =SUM(C18:F18) -> 700 | H18: 126 | I18: 134 | J18: 134 | K18: 150 | L18: =SUM(H18:K18) -> 544 | M18: 130 | N18: 144 | O18: 147 | Q18: =SUM(M18:P18) -> 421
B19: Margin % | C19: =C18/C11 -> 0.17883841 | D19: =D18/D11 -> 0.073239437 | E19: =E18/E11 -> 0.064779532 | F19: =F18/F11 -> 0.076923077 | G19: =G18/G11 -> 0.097615395 | H19: =H18/H11 -> 0.072461264 | I19: =I18/I11 -> 0.064295766 | J19: =J18/J11 -> 0.058294091 | ... O19: =O18/O11 -> 0.060019704
B20: Advertising expenses | C20: 173 | D20: 312 | E20: 326 | F20: 364 | G20: =SUM(C20:F20) -> 1175 | H20: 311 | I20: 334 | J20: 327 | K20: 358 | L20: =SUM(H20:K20) -> 1330 | M20: 311 | N20: 364 | O20: 342 | Q20: =SUM(M20:P20) -> 1017
B21: Margin % | C21: =C20/C11 -> 0.099482461 | D21: =D20/D11 -> 0.17577465 | E21: =E20/E11 -> 0.17746326 | F21: =F20/F11 -> 0.2 | G21: =G20/G11 -> 0.16385441 | H21: =H20/H11 -> 0.1788528 | I21: =I20/I11 -> 0.1602596 | J21: =J20/J11 -> 0.14225498 | ... O21: =O20/O11 -> 0.13963768
B22: SG&A | C22: 0 | D22: 163 | E22: 169 | F22: 197 | G22: =SUM(C22:F22) -> 529 | H22: 173 | I22: 185 | J22: 176 | K22: 199 | L22: =SUM(H22:K22) -> 733 | M22: 191 | N22: 188 | O22: 170 | Q22: =SUM(M22:P22) -> 549
B23: Margin % | C23: =C22/C11 -> 0 | D23: =D22/D11 -> 0.091830986 | E23: =E22/E11 -> 0.091997823 | F23: =F22/F11 -> 0.10824176 | G23: =G22/G11 -> 0.073769349 | H23: =H22/H11 -> 0.099490466 | I23: =I22/I11 -> 0.088766543 | J23: =J22/J11 -> 0.076565373 | ... O23: =O22/O11 -> 0.069410542
A24: Operating Income | C24: =C11-SUM(C14:C22) -> 522.30075 | D24: =D11-SUM(D14:D22) -> 557.4062 | E24: =E11-SUM(E14:E22) -> 592.41481 | F24: =F11-SUM(F14:F22) -> 475.36978 | G24: =G11-SUM(G14:G22) -> 2149.3736 | H24: =H11-SUM(H14:H22) -> 522.26026 | I24: =I11-SUM(I14:I22) -> 604.49767 | J24: =J11-SUM(J14:J22) -> 629.03976 | ... O24: =O11-SUM(O14:O22) -> 672.53996 | P24: =P25*P11 -> 675.6778 | Q24: =SUM(M24:P24) -> 2492.0874 | R24: =R25*R11 -> 615.72095 | S24: =S25*S11 -> 703.47853 | T24: =T25*T11 -> 714.8524 | U24: =U25*U11 -> 709.53731 | V24: =SUM(R24:U24) -> 2743.5892 | W24: =W25*W11 -> 2923.4387 | X24: =X25*X11 -> 3104.5046 | Y24: =Y25*Y11 -> 3285.5974
B25: Margin % | D25: =D24/D11 -> 0.31403166 | E25: =E24/E11 -> 0.32249037 | F25: =F24/F11 -> 0.26119219 | G25: =G24/G11 -> 0.29973136 | H25: =H24/H11 -> 0.30034634 | I25: =I24/I11 -> 0.29004956 | J25: =J24/J11 -> 0.2736515 | K25: =K24/K11 -> 0.23922116 | ... O25: =O24/O11 -> 0.27459625 | P25: =AVERAGE(M25:O25,H25:K25,D25:F25) -> 0.27802179 | Q25: =Q24/Q11 -> 0.2651533 | R25: =P25 -> 0.27802179 | S25: =R25 -> 0.27802179 | T25: =S25 -> 0.27802179 | U25: =T25 -> 0.27802179 | V25: =V24/V11 -> 0.27803531 | W25: =V25+0.005 -> 0.28303531 | X25: =W25+0.005 -> 0.28803531 | Y25: =X25+0.005 -> 0.29303531
A26: Comparable Sales Analysis | C26: Q123 | D26: Q223 | E26: Q323 | F26: Q423 | G26: 2023 | H26: Q124 | I26: Q224 | J26: Q324 | K26: Q424 | L26: 2024 | M26: Q125 | N26: Q225 | O26: Q325 | P26: Q425E | Q26: 2025E | R26: Q126E | S26: Q226E | T26: Q326E | U26: Q426E | V26: 2026E | W26: 2027E | X26: 2028E | Y26: 2029E
B27: Comps margins | H27: 0.046 | I27: 0.019 | J27: 0.003 | K27: 0.058 | L27: =L36/L11 -> 0.026720829 | M27: 0.001 | N27: 0.019 | O27: 0.04 | P27: 0.025 | Q27: =Q36/Q11 -> 0.020305705 | R27: 0.025 | S27: =R27-0.001 -> 0.024 | T27: =S27-0.001 -> 0.023 | U27: =T27-0.001 -> 0.022 | V27: =V36/V11 -> 0.023028326 | W27: =V27-0.0033 -> 0.019728326 | X27: =W27-0.0033 -> 0.016428326 | Y27: =X27-0.0033 -> 0.013128326
B29: y/y Beginning resturant | H29: 29956 | I29: 30125 | J29: 30375 | K29: 31070 | L29: =H31 -> 31113 | M29: 31113 | N29: 31324 | O29: 31525 | P29: =K31 -> 32125 | Q29: =M31 -> 32149 | R29: =M31 -> 32149 | S29: =N31 -> 32229 | T29: =O31 -> 32423 | U29: =P31 -> 33071.333 | V29: =R31 -> 33071.222 | W29: =V31 -> 33997.156 | X29: =W31 -> 34922.979 | Y29: =X31 -> 35848.802
B30: Net Additions | H30: =H31-H29 -> 1157 | I30: =I31-I29 -> 1199 | J30: =J31-J29 -> 1150 | K30: =K31-K29 -> 1055 | L30: =L31-L29 -> 1012 | M30: =M31-M29 -> 1036 | N30: =N31-N29 -> 905 | O30: =O31-O29 -> 898 | P30: =AVERAGE(M30:O30) -> 946.33333 | Q30: =Q31-Q29 -> 922.33333 | R30: =AVERAGE(O30:Q30) -> 922.22222 | S30: =AVERAGE(P30:R30) -> 930.2963 | T30: =AVERAGE(Q30:S30) -> 924.95062 | U30: =AVERAGE(R30:T30) -> 925.82305 | V30: =V31-V29 -> 925.93416 | W30: =AVERAGE(R30:U30) -> 925.82305 | X30: =W30 -> 925.82305 | Y30: =X30 -> 925.82305
B31: y/y Ending resturant | H31: 31113 | I31: 31324 | J31: 31525 | K31: 32125 | L31: =K31 -> 32125 | M31: 32149 | N31: 32229 | O31: 32423 | P31: =P29+P30 -> 33071.333 | Q31: =P31 -> 33071.333 | R31: =R29+R30 -> 33071.222 | S31: =S29+S30 -> 33159.296 | T31: =T29+T30 -> 33347.951 | U31: =U29+U30 -> 33997.156 | V31: =U31 -> 33997.156 | W31: =W29+W30 -> 34922.979 | X31: =X29+X30 -> 35848.802 | Y31: =Y29+Y30 -> 36774.626
B33: Prior year revenue | H33: =C11 -> 1739 | I33: =D11 -> 1775 | J33: =E11 -> 1837 | K33: =F11 -> 1820 | L33: =SUM(H33:K33) -> 7171 | M33: =H11 -> 1738.8601 | N33: =I11 -> 2084.1186 | O33: =J11 -> 2298.6893 | P33: =K38 -> 2302.4747 | Q33: =SUM(M33:P33) -> 8424.1426 | R33: =M38 -> 2113.3762 | S33: =N38 -> 2410.8198 | T33: =O38 -> 2541.1433 | U33: =P38 -> 2640.8136 | V33: =SUM(R33:U33) -> 9706.153 | W33: =V38 -> 10175.259 | X33: =W38 -> 10845.049 | Y33: =X38 -> 11492.265
B34: New additions Impact | H34: =H11-C11 -> -0.1399177 | I34: =I11-D11 -> 309.11856 | J34: =J11-E11 -> 461.68926 | K34: =K11-F11 -> 482.47474 | L34: =L11-G11 -> 1241.5382 | M34: =M11-H11 -> 374.51617 | N34: =N11-I11 -> 326.70127 | O34: =O11-J11 -> 150.50643 | P34: =P35*P30 -> 280.77703 | Q34: =Q11-L11 -> 986.12834 | R34: =R35*R30 -> 471.39964 | S34: =S35*S30 -> 582.06256 | T34: =T35*T30 -> 680.14628 | U34: =U35*U30 -> 577.76393 | V34: =V11-Q11 -> 469.10586 | W34: =W30*W35 -> 469.04957 | X34: =X30*X35 -> 469.04957 | Y34: =Y30*Y35 -> 469.04957
B35: Margin% | H35: =H34/H30 -> -0.00012093146 | I35: =I34/I30 -> 0.25781364 | J35: =J34/J30 -> 0.40146892 | K35: =K34/K30 -> 0.45732203 | L35: =L34/L30 -> 1.2268165 | M35: =M34/M30 -> 0.36150209 | N35: =N34/N30 -> 0.36099588 | O35: =O34/O30 -> 0.16760181 | P35: =AVERAGE(M35:O35) -> 0.29669993 | Q35: =Q34/Q30 -> 1.069167 | R35: =AVERAGE(O35:Q35) -> 0.51115624 | S35: =AVERAGE(P35:R35) -> 0.62567438 | T35: =AVERAGE(Q35:S35) -> 0.73533253 | U35: =AVERAGE(R35:T35) -> 0.62405438 | V35: =V34/V30 -> 0.50662983 | W35: =V35 -> 0.50662983 | X35: =W35 -> 0.50662983 | Y35: =X35 -> 0.50662983
B36: Comp impact | H36: =H33*H37 -> 79.994 | I36: =I33*I37 -> 33.725 | J36: =J33*J37 -> 5.511 | K36: =K33*K37 -> 105.56 | L36: =SUM(H36:K36) -> 224.79 | M36: =M33*M37 -> 1.7388601 | N36: =N33*N37 -> 39.598253 | O36: =O33*O37 -> 91.94757 | P36: =P33*P37 -> 57.561869 | Q36: =SUM(M36:P36) -> 190.84655 | R36: =R33*R37 -> 52.834406 | S36: =S33*S37 -> 57.859676 | T36: =T33*T37 -> 58.446295 | U36: =U33*U37 -> 58.0979 | V36: =SUM(R36:U36) -> 227.23828 | W36: =W37*W33 -> 200.74082 | X36: =X37*X33 -> 178.166 | Y36: =Y37*Y33 -> 150.87419
B37: =B27 -> Comps margins | H37: =H27 -> 0.046 | I37: =I27 -> 0.019 | J37: =J27 -> 0.003 | K37: =K27 -> 0.058 | L37: =L27 -> 0.026720829 | M37: =M27 -> 0.001 | N37: =N27 -> 0.019 | O37: =O27 -> 0.04 | ... Y37: =Y27 -> 0.013128326
B38: Implied ending revenue | H38: =H33+H34 -> 1738.8601 | I38: =I33+I34 -> 2084.1186 | J38: =J33+J34 -> 2298.6893 | K38: =K33+K34 -> 2302.4747 | L38: =L33+L34 -> 8412.5382 | M38: =M33+M34 -> 2113.3762 | N38: =N33+N34 -> 2410.8198 | O38: =SUM(O33,O34,O36) -> 2541.1433 | P38: =P33+P34+P36 -> 2640.8136 | Q38: =Q33+Q34 -> 9410.271 | R38: =R33+R34+R36 -> 2637.6103 | S38: =S33+S34+S36 -> 3050.7421 | T38: =T33+T34+T36 -> 3279.7358 | U38: =U33+U34+U36 -> 3276.6755 | V38: =V33+V34 -> 10175.259 | W38: =W33+W34+W36 -> 10845.049 | X38: =X33+X34+X36 -> 11492.265 | Y38: =Y33+Y34+Y36 -> 12112.189
M39: =M38/H38-1 -> 0.21538028 | N39: =N38/I38-1 -> 0.15675753 | O39: =O38/J38-1 -> 0.10547489 | P39: =P38/K38-1 -> 0.14694576 | Q39: =Q38/L38-1 -> 0.11860068 | R39: =R38/M38-1 -> 0.24805524 | S39: =S38/N38-1 -> 0.2654376 | T39: =T38/O38-1 -> 0.29065365 | ... V39: =V38/Q38-1 -> 0.081292862 | W39: =W38/V38-1 -> 0.065825391 | X39: =X38/W38-1 -> 0.059678436 | Y39: =Y38/X38-1 -> 0.053942698

Sheet Assumptions
A1: =CoName -> Resturant Brands International Inc | C1: Hist. | D1: Hist. | E1: Hist. | F1: Proj. | G1: Proj. | H1: Proj. | I1: Proj. | J1: Proj.
A2: * | B2: Income Statement | C2: 2022 | D2: =C2+1 -> 2023 | E2: =D2+1 -> 2024 | F2: =E2+1 -> 2025 | G2: =F2+1 -> 2026 | H2: =G2+1 -> 2027 | I2: =H2+1 -> 2028 | J2: =I2+1 -> 2029
B4: Operating Case | D4: 1
B6: Revenue Model | F6: ='Quarterly Projections'!Q12 -> 0.11722126 | G6: ='Quarterly Projections'!V12 -> 0.049911959 | H6: ='Quarterly Projections'!W12 -> 0.046728964 | I6: ='Quarterly Projections'!X12 -> 0.043501809 | J6: ='Quarterly Projections'!Y12 -> 0.040274155
B7: Comps Model | F7: ='Quarterly Projections'!Q39 -> 0.11860068 | G7: ='Quarterly Projections'!V39 -> 0.081292862 | H7: ='Quarterly Projections'!W39 -> 0.065825391 | I7: ='Quarterly Projections'!X39 -> 0.059678436 | J7: ='Quarterly Projections'!Y39 -> 0.053942698
B8: Pessimistic Case | F8: 0.03 | G8: =F8 -> 0.03 | H8: =G8 -> 0.03 | I8: =H8 -> 0.03 | J8: =I8 -> 0.03
B10: Revenue Growth | D10: =IncState!D16/IncState!C16-1 -> 0.079477325 | E10: =IncState!E16/IncState!D16-1 -> 0.19709484 | F10: =CHOOSE(ScenarioREV,F6,F7,F8) -> 0.11722126 | G10: =CHOOSE(ScenarioREV,G6,G7,G8) -> 0.049911959 | H10: =CHOOSE(ScenarioREV,H6,H7,H8) -> 0.046728964 | I10: =CHOOSE(ScenarioREV,I6,I7,I8) -> 0.043501809 | J10: =CHOOSE(ScenarioREV,J6,J7,J8) -> 0.040274155
B11: COGS % of sales | C11: =IncState!C17/IncState!C16 -> 0.33712529 | D11: =IncState!D17/IncState!D16 -> 0.18911991 | E11: =IncState!E17/IncState!E16 -> 0.25933857 | F11: =E11-0.001 -> 0.25833857 | G11: =F11-0.001 -> 0.25733857 | H11: =G11-0.001 -> 0.25633857 | I11: =H11-0.001 -> 0.25533857 | J11: =I11-0.001 -> 0.25433857
B12: SG&A % of sales | C12: =IncState!C18/IncState!C16 -> 0.37109915 | D12: =IncState!D18/IncState!D16 -> 0.51879806 | E12: =IncState!E18/IncState!E16 -> 0.45289079 | F12: =E12-0.001 -> 0.45189079 | G12: =F12-0.001 -> 0.45089079 | H12: =G12-0.001 -> 0.44989079 | I12: =H12-0.001 -> 0.44889079 | J12: =I12-0.001 -> 0.44789079
B13: Amortization $ Amt | C13: =IncState!C22 -> 0 | D13: =IncState!D22 -> 0 | E13: =IncState!E22 -> 0 | F13: =E13 -> 0 | G13: =F13 -> 0 | H13: =G13 -> 0 | I13: =H13 -> 0 | J13: =I13 -> 0
B14: Non recurring income / (expense) | C14: =IncState!C25 -> 0 | D14: =IncState!D25 -> 0 | E14: =IncState!E25 -> 0 | F14: 0 | G14: 0 | H14: 0 | I14: 0 | J14: 0
B15: Other Income / (expense) | C15: =IncState!C26 -> 0 | D15: =IncState!D26 -> 0 | E15: =IncState!E26 -> 0 | F15: 0 | G15: 0 | H15: 0 | I15: 0 | J15: 0
B16: Effective tax rate | C16: =IncState!C33/IncState!C31 -> -0.085714286 | D16: =IncState!D33/IncState!D31 -> -0.18039483 | E16: =IncState!E33/IncState!E31 -> 0.19761129 | F16: =E16 -> 0.19761129 | G16: =F16 -> 0.19761129 | H16: =G16 -> 0.19761129 | I16: =H16 -> 0.19761129 | J16: =I16 -> 0.19761129
B17: Dividend Payout Rate | C17: =IncState!C35 -> 3.1628664 | D17: =IncState!D35 -> 3.1730769 | E17: =IncState!E35 -> 3.2257053 | F17: =E17+0.1 -> 3.3257053 | G17: =F17+0.1 -> 3.4257053 | H17: =G17+0.1 -> 3.5257053 | I17: =H17+0.1 -> 3.6257053 | J17: =I17+0.1 -> 3.7257053
B18: Basic WASO | C18: =IncState!C38 -> 307 | D18: =IncState!D38 -> 312 | E18: =IncState!E38 -> 319 | F18: =E18 -> 319 | G18: =F18 -> 319 | H18: =G18 -> 319 | I18: =H18 -> 319 | J18: =I18 -> 319
B19: Diluted WASO | C19: =IncState!C39 -> 455 | D19: =IncState!D39 -> 456 | E19: =IncState!E39 -> 454 | F19: =E19 -> 454 | G19: =F19 -> 454 | H19: =G19 -> 454 | I19: =H19 -> 454 | J19: =I19 -> 454
A21: * | B21: Debt | C21: =C2 -> 2022 | D21: =D2 -> 2023 | E21: =E2 -> 2024 | F21: =F2 -> 2025 | G21: =G2 -> 2026 | H21: =H2 -> 2027 | I21: =I2 -> 2028 | J21: =J2 -> 2029
B23: Interest rate on Revolver | E23: 0.0695 | F23: =E23 -> 0.0695 | G23: =F23 -> 0.0695 | H23: =G23 -> 0.0695 | I23: =H23 -> 0.0695 | J23: =I23 -> 0.0695
B24: Interest rate on long-term debt | E24: 0.045 | F24: =E24 -> 0.045 | G24: =F24 -> 0.045 | H24: =G24 -> 0.045 | I24: =H24 -> 0.045 | J24: =I24 -> 0.045
B25: Interest rate on cash | E25: =IncState!E28/SUM(BalSheet!E15:E16) -> 0.029235382 | F25: =E25 -> 0.029235382 | G25: =F25 -> 0.029235382 | H25: =G25 -> 0.029235382 | I25: =H25 -> 0.029235382 | J25: =I25 -> 0.029235382
B27: Issuance of long-term debt | F27: 0 | G27: 0 | H27: 0 | I27: 0 | J27: 0
B28: Repayment of long-term debt | F28: -222 | G28: 0 | H28: 0 | I28: 0 | J28: 0
A30: * | B30: Calcs | C30: =C21 -> 2022 | D30: =D21 -> 2023 | E30: =E21 -> 2024 | F30: =F21 -> 2025 | G30: =G21 -> 2026 | H30: =H21 -> 2027 | I30: =I21 -> 2028 | J30: =J21 -> 2029
B32: CapEx % of Sales | C32: =100/IncState!C16 -> 0.01537279 | D32: =120/IncState!D16 -> 0.017089148 | E32: =201/IncState!E16 -> 0.023911492 | F32: =E32+(E32-D32) -> 0.030733835 | G32: =F32+(F32-E32) -> 0.037556179 | H32: =G32+(G32-F32) -> 0.044378522 | I32: =H32+(H32-G32) -> 0.051200865 | J32: =I32+(I32-H32) -> 0.058023209
B33: Depreciation % of beginning PP&E | D33: =IncState!D21/BalSheet!C22 -> 0.062994723 | E33: =IncState!E21/BalSheet!D22 -> 0.085881588 | F33: =E33 -> 0.085881588 | G33: =F33 -> 0.085881588 | H33: =G33 -> 0.085881588 | I33: =H33 -> 0.085881588 | J33: =I33 -> 0.085881588
B34: Share issuance / (repurchases) | F34: 0 | G34: 0 | H34: 0 | I34: 0 | J34: 0
A36: * | B36: Shareholder information | C36: =C30 -> 2022 | D36: =D30 -> 2023 | E36: =E30 -> 2024 | F36: =F30 -> 2025 | G36: =G30 -> 2026 | H36: =H30 -> 2027 | I36: =I30 -> 2028 | J36: =J30 -> 2029
B38: =B17 -> Dividend Payout Rate | C38: =C17 -> 3.1628664 | D38: =D17 -> 3.1730769 | E38: =E17 -> 3.2257053 | F38: =F17 -> 3.3257053 | G38: =G17 -> 3.4257053 | H38: =H17 -> 3.5257053 | I38: =I17 -> 3.6257053 | J38: =J17 -> 3.7257053
B39: Basic WASO | C39: =C18 -> 307 | D39: =D18 -> 312 | E39: =E18 -> 319 | F39: =F18 -> 319 | G39: =G18 -> 319 | H39: =H18 -> 319 | I39: =I18 -> 319 | J39: =J18 -> 319
B40: Diluted WASO | C40: =C19 -> 455 | D40: =D19 -> 456 | E40: =E19 -> 454 | F40: =F19 -> 454 | G40: =G19 -> 454 | H40: =H19 -> 454 | I40: =I19 -> 454 | J40: =J19 -> 454
A42: * | B42: Balance Sheet - Assets | C42: =C36 -> 2022 | D42: =D36 -> 2023 | E42: =E36 -> 2024 | F42: =F36 -> 2025 | G42: =G36 -> 2026 | H42: =H36 -> 2027 | I42: =I36 -> 2028 | J42: =J36 -> 2029
B44: Operating Cash % of sales | C44: =BalSheet!C15/IncState!C16 -> 0.02 | D44: =BalSheet!D15/IncState!D16 -> 0.02 | E44: =BalSheet!E15/IncState!E16 -> 0.02 | F44: =E44 -> 0.02 | G44: =F44 -> 0.02 | H44: =G44 -> 0.02 | I44: =H44 -> 0.02 | J44: =I44 -> 0.02
B45: Accounts receivable % of sales | C45: =BalSheet!C17/IncState!C16 -> 0.094388932 | D45: =BalSheet!D17/IncState!D16 -> 0.10666477 | E45: =BalSheet!E17/IncState!E16 -> 0.083035927 | F45: =E45 -> 0.083035927 | G45: =F45 -> 0.083035927 | H45: =G45 -> 0.083035927 | I45: =H45 -> 0.083035927 | J45: =I45 -> 0.083035927
B46: Inventories % of COGS | C46: =BalSheet!C18/IncState!C17 -> 0.060647515 | D46: =BalSheet!D18/IncState!D17 -> 0.125 | E46: =BalSheet!E18/IncState!E17 -> 0.065137615 | F46: =E46 -> 0.065137615 | G46: =F46 -> 0.065137615 | H46: =G46 -> 0.065137615 | I46: =H46 -> 0.065137615 | J46: =I46 -> 0.065137615
B47: Other current assets % of sales | C47: =BalSheet!C19/IncState!C16 -> 0.018908532 | D47: =BalSheet!D19/IncState!D16 -> 0.016946739 | E47: =BalSheet!E19/IncState!E16 -> 0.012847966 | F47: =E47 -> 0.012847966 | G47: =F47 -> 0.012847966 | H47: =G47 -> 0.012847966 | I47: =H47 -> 0.012847966 | J47: =I47 -> 0.012847966
B48: Other long-term assets % of sales | C48: =BalSheet!C24/IncState!C16 -> 0.15172944 | D48: =BalSheet!D24/IncState!D16 -> 0.17972088 | E48: =BalSheet!E24/IncState!E16 -> 0.16107542 | F48: =E48 -> 0.16107542 | G48: =F48 -> 0.16107542 | H48: =G48 -> 0.16107542 | I48: =H48 -> 0.16107542 | J48: =I48 -> 0.16107542
A50: * | B50: Balance Sheet - Liabilities | C50: =C42 -> 2022 | D50: =D42 -> 2023 | E50: =E42 -> 2024 | F50: =F42 -> 2025 | G50: =G42 -> 2026 | H50: =H42 -> 2027 | I50: =I42 -> 2028 | J50: =J42 -> 2029
B52: Accounts payable % of COGS | C52: =BalSheet!C30/IncState!C17 -> 0.80209758 | D52: =BalSheet!D30/IncState!D17 -> 1.3516566 | E52: =BalSheet!E30/IncState!E17 -> 0.87431193 | F52: =E52 -> 0.87431193 | G52: =F52 -> 0.87431193 | H52: =G52 -> 0.87431193 | I52: =H52 -> 0.87431193 | J52: =I52 -> 0.87431193
B53: Other current liabilities % of sales | C53: =BalSheet!C31/IncState!C16 -> 0.035357417 | D53: =BalSheet!D31/IncState!D16 -> 0.035317573 | E53: =BalSheet!E31/IncState!E16 -> 0.028075184 | F53: =E53 -> 0.028075184 | G53: =F53 -> 0.028075184 | H53: =G53 -> 0.028075184 | I53: =H53 -> 0.028075184 | J53: =I53 -> 0.028075184
B54: Other long-term liabilities % of sales | C54: =BalSheet!C35/IncState!C16 -> 0.5415834 | D54: =BalSheet!D35/IncState!D16 -> 0.52164625 | E54: =BalSheet!E35/IncState!E16 -> 0.4722817 | F54: =E54 -> 0.4722817 | G54: =F54 -> 0.4722817 | H54: =G54 -> 0.4722817 | I54: =H54 -> 0.4722817 | J54: =I54 -> 0.4722817

Sheet Calcs
A1: =CoName -> Resturant Brands International Inc | C1: Hist. | D1: Hist. | E1: Hist. | F1: Proj. | G1: Proj. | H1: Proj. | I1: Proj. | J1: Proj.
A2: Net PP&E | C2: 2022 | D2: =C2+1 -> 2023 | E2: =D2+1 -> 2024 | F2: =E2+1 -> 2025 | G2: =F2+1 -> 2026 | H2: =G2+1 -> 2027 | I2: =H2+1 -> 2028 | J2: =I2+1 -> 2029
B3: Capital expenditure % of sales | F3: =Assumptions!F32 -> 0.030733835 | G3: =Assumptions!G32 -> 0.037556179 | H3: =Assumptions!H32 -> 0.044378522 | I3: =Assumptions!I32 -> 0.051200865 | J3: =Assumptions!J32 -> 0.058023209
B4: Depreciation % of PP&E | F4: =Assumptions!F33 -> 0.085881588 | G4: =F4 -> 0.085881588 | H4: =G4 -> 0.085881588 | I4: =H4 -> 0.085881588 | J4: =I4 -> 0.085881588
B6: Beginning PP&E | F6: =E9 -> 4088 | G6: =F9 -> 4025.5486 | H6: =G9 -> 4050.1359 | I6: =H9 -> 4160.3281 | J6: =I9 -> 4354.4572
B7: Capex | F7: =F3*IncState!F16 -> 288.63257 | G7: =G3*IncState!G16 -> 370.3078 | H7: =H3*IncState!H16 -> 458.02432 | I7: =I3*IncState!I16 -> 551.42469 | J7: =J3*IncState!J16 -> 650.06751
B8: Depreciation | F8: =F6*F4 -> 351.08393 | G8: =G6*G4 -> 345.72051 | H8: =H6*H4 -> 347.8321 | I8: =I6*I4 -> 357.29559 | J8: =J6*J4 -> 373.9677
B9: Ending PP&E | E9: =BalSheet!E22 -> 4088 | F9: =F6+F7-F8 -> 4025.5486 | G9: =G6+G7-G8 -> 4050.1359 | H9: =H6+H7-H8 -> 4160.3281 | I9: =I6+I7-I8 -> 4354.4572 | J9: =J6+J7-J8 -> 4630.5571
A10: Equity | C10: =C2 -> 2022 | D10: =D2 -> 2023 | E10: =E2 -> 2024 | F10: =F2 -> 2025 | G10: =G2 -> 2026 | H10: =H2 -> 2027 | I10: =I2 -> 2028 | J10: =J2 -> 2029
B11: Share issuance/(repurchases) | F11: =Assumptions!F34 -> 0 | G11: =Assumptions!G34 -> 0 | H11: =Assumptions!H34 -> 0 | I11: =Assumptions!I34 -> 0 | J11: =Assumptions!J34 -> 0
B13: Beginning balance | F13: =E17 -> 4843 | G13: =F17 -> 5965.6733 | H13: =G17 -> 7181.2562 | I13: =H17 -> 8489.3702 | J13: =I17 -> 9888.6991
B14: Net income | F14: =IncState!F34 -> 2183.5733 | G14: =IncState!G34 -> 2308.3829 | H14: =IncState!H34 -> 2432.814 | I14: =IncState!I34 -> 2555.929 | J14: =IncState!J34 -> 2676.8461
B15: Dividends paid | F15: =-IncState!F36 -> -1060.9 | G15: =-IncState!G36 -> -1092.8 | H15: =-IncState!H36 -> -1124.7 | I15: =-IncState!I36 -> -1156.6 | J15: =-IncState!J36 -> -1188.5
B16: Share issuance / (repurchase) | F16: =F11 -> 0 | G16: =G11 -> 0 | H16: =H11 -> 0 | I16: =I11 -> 0 | J16: =J11 -> 0
B17: Ending balance | E17: =BalSheet!E38 -> 4843 | F17: =SUM(F13:F16) -> 5965.6733 | G17: =SUM(G13:G16) -> 7181.2562 | H17: =SUM(H13:H16) -> 8489.3702 | I17: =SUM(I13:I16) -> 9888.6991 | J17: =SUM(J13:J16) -> 11377.045
A18: OWC | C18: =C10 -> 2022 | D18: =D10 -> 2023 | E18: =E10 -> 2024 | F18: =F10 -> 2025 | G18: =G10 -> 2026 | H18: =H10 -> 2027 | I18: =I10 -> 2028 | J18: =J10 -> 2029
B19: Operating Cash | E19: =BalSheet!E15 -> 168.12 | F19: =BalSheet!F15 -> 187.82724 | G19: =BalSheet!G15 -> 197.20206 | H19: =BalSheet!H15 -> 206.41711 | I19: =BalSheet!I15 -> 215.39663 | J19: =BalSheet!J15 -> 224.07155
B20: Accounts receivable | E20: =BalSheet!E17 -> 698 | F20: =BalSheet!F17 -> 779.82044 | G20: =BalSheet!G17 -> 818.74281 | H20: =BalSheet!H17 -> 857.00181 | I20: =BalSheet!I17 -> 894.28294 | J20: =BalSheet!J17 -> 930.29943
B21: Inventories | E21: =BalSheet!E18 -> 142 | F21: =BalSheet!F18 -> 611.73091 | G21: =BalSheet!G18 -> 642.2636 | H21: =BalSheet!H18 -> 672.27591 | I21: =BalSheet!I18 -> 701.52113 | J21: =BalSheet!J18 -> 729.7743
B22: Other current assets | E22: =BalSheet!E19 -> 108 | F22: =BalSheet!F19 -> 120.6599 | G22: =BalSheet!G19 -> 126.68227 | H22: =BalSheet!H19 -> 132.602 | I22: =BalSheet!I19 -> 138.37043 | J22: =BalSheet!J19 -> 143.94318
B23: Accounts payables | E23: =BalSheet!E30 -> 1906 | F23: =BalSheet!F30 -> 2121.2127 | G23: =BalSheet!G30 -> 2218.4658 | H23: =BalSheet!H30 -> 2313.1088 | I23: =BalSheet!I30 -> 2404.317 | J23: =BalSheet!J30 -> 2491.3534
B24: Other current liabilities | E24: =BalSheet!E31 -> 236 | F24: =BalSheet!F31 -> 263.66422 | G24: =BalSheet!G31 -> 276.82422 | H24: =BalSheet!H31 -> 289.75992 | I24: =BalSheet!I31 -> 302.365 | J24: =BalSheet!J31 -> 314.5425
A25: * | B25: OWC | E25: =SUM(E19:E22)-SUM(E23:E24) -> -1025.88 | F25: =SUM(F19:F22)-SUM(F23:F24) -> -684.83847 | G25: =SUM(G19:G22)-SUM(G23:G24) -> -710.3993 | H25: =SUM(H19:H22)-SUM(H23:H24) -> -734.57187 | I25: =SUM(I19:I22)-SUM(I23:I24) -> -757.11089 | J25: =SUM(J19:J22)-SUM(J23:J24) -> -777.80746
B26: Change in OWC | F26: =E25-F25 -> -341.04153 | G26: =F25-G25 -> 25.560824 | H26: =G25-H25 -> 24.172576 | I26: =H25-I25 -> 22.539013 | J26: =I25-J25 -> 20.69658

Sheet Debt
A1: =CoName -> Resturant Brands International Inc | C1: Hist. | D1: Hist. | E1: Hist. | F1: Proj. | G1: Proj. | H1: Proj. | I1: Proj. | J1: Proj.
A2: Assumptions | C2: 2022 | D2: =C2 -> 2022 | E2: =D2 -> 2022 | F2: =E2 -> 2022 | G2: =F2 -> 2022 | H2: =G2 -> 2022 | I2: =H2 -> 2022 | J2: =I2 -> 2022
B4: Interest rate on revolver | F4: =Assumptions!F23 -> 0.0695 | G4: =Assumptions!G23 -> 0.0695 | H4: =Assumptions!H23 -> 0.0695 | I4: =Assumptions!I23 -> 0.0695 | J4: =Assumptions!J23 -> 0.0695
B5: Interest rate on long-term debt | F5: =Assumptions!F24 -> 0.045 | G5: =Assumptions!G24 -> 0.045 | H5: =Assumptions!H24 -> 0.045 | I5: =Assumptions!I24 -> 0.045 | J5: =Assumptions!J24 -> 0.045
B6: Interest rate on cash | F6: =Assumptions!F25 -> 0.029235382 | G6: =Assumptions!G25 -> 0.029235382 | H6: =Assumptions!H25 -> 0.029235382 | I6: =Assumptions!I25 -> 0.029235382 | J6: =Assumptions!J25 -> 0.029235382
B8: Issuance of long-term debt | F8: =Assumptions!F27 -> 0 | G8: =Assumptions!G27 -> 0 | H8: =Assumptions!H27 -> 0 | I8: =Assumptions!I27 -> 0 | J8: =Assumptions!J27 -> 0
B9: Repayment of long-term debt | F9: -222 | G9: =Assumptions!G28 -> 0 | H9: =Assumptions!H28 -> 0 | I9: =Assumptions!I28 -> 0 | J9: =Assumptions!J28 -> 0
A11: Revolver | C11: =C2 -> 2022 | D11: =D2 -> 2022 | E11: =E2 -> 2022 | F11: =F2 -> 2022 | G11: =G2 -> 2022 | H11: =H2 -> 2022 | I11: =I2 -> 2022 | J11: =J2 -> 2022
B12: Balance | F12: 0 | G12: 0 | H12: 0 | I12: 0 | J12: 0
B13: Interest rate
B14: Interest expense
A16: Long term debt | C16: =C11 -> 2022 | D16: =D11 -> 2022 | E16: =E11 -> 2022 | F16: =F11 -> 2022 | G16: =G11 -> 2022 | H16: =H11 -> 2022 | I16: =I11 -> 2022 | J16: =J11 -> 2022
B17: Beginning balance | F17: =E20 -> 13677 | G17: =F20 -> 13455 | H17: =G20 -> 13455 | I17: =H20 -> 13455 | J17: =I20 -> 13455
B18: Issuance | F18: =F8 -> 0 | G18: =G8 -> 0 | H18: =H8 -> 0 | I18: =I8 -> 0 | J18: =J8 -> 0
B19: Repayment | F19: =F9 -> -222 | G19: =G9 -> 0 | H19: =H9 -> 0 | I19: =I9 -> 0 | J19: =J9 -> 0
B20: Ending balance | E20: =BalSheet!E34 -> 13677 | F20: =SUM(F17:F19) -> 13455 | G20: =SUM(G17:G19) -> 13455 | H20: =SUM(H17:H19) -> 13455 | I20: =SUM(I17:I19) -> 13455 | J20: =SUM(J17:J19) -> 13455
B21: Interest rate | F21: =F5 -> 0.045 | G21: =G5 -> 0.045 | H21: =H5 -> 0.045 | I21: =I5 -> 0.045 | J21: =J5 -> 0.045
B22: Interest expense | F22: =F20*F21 -> 605.475 | G22: =G20*G21 -> 605.475 | H22: =H20*H21 -> 605.475 | I22: =I20*I21 -> 605.475 | J22: =J20*J21 -> 605.475
A24: Debt summary | C24: =C16 -> 2022 | D24: =D16 -> 2022 | E24: =E16 -> 2022 | F24: =F16 -> 2022 | G24: =G16 -> 2022 | H24: =H16 -> 2022 | I24: =I16 -> 2022 | J24: =J16 -> 2022
B25: Revolver | F25: =F12 -> 0 | G25: =G12 -> 0 | H25: =H12 -> 0 | I25: =I12 -> 0 | J25: =J12 -> 0
B26: Total long term debt | F26: =F20 -> 13455 | G26: =G20 -> 13455 | H26: =H20 -> 13455 | I26: =I20 -> 13455 | J26: =J20 -> 13455
B27: Total debt | F27: =SUM(F25:F26) -> 13455 | G27: =SUM(G25:G26) -> 13455 | H27: =SUM(H25:H26) -> 13455 | I27: =SUM(I25:I26) -> 13455 | J27: =SUM(J25:J26) -> 13455
B28: Total interest expense | F28: =F22 -> 605.475 | G28: =G22 -> 605.475 | H28: =H22 -> 605.475 | I28: =I22 -> 605.475 | J28: =J22 -> 605.475
A30: Interest income | C30: =C11 -> 2022 | D30: =D11 -> 2022 | E30: =E11 -> 2022 | F30: =F11 -> 2022 | G30: =G11 -> 2022 | H30: =H11 -> 2022 | I30: =I11 -> 2022 | J30: =J11 -> 2022
B31: Excess Cash | F31: =BalSheet!F16 -> 2094.6139 | G31: =BalSheet!G16 -> 3457.0456 | H31: =BalSheet!H16 -> 4822.529 | I31: =BalSheet!I16 -> 6189.9919 | J31: =BalSheet!J16 -> 7557.9192
B32: Interest rate | F32: =F6 -> 0.029235382 | G32: =G6 -> 0.029235382 | H32: =H6 -> 0.029235382 | I32: =I6 -> 0.029235382 | J32: =J6 -> 0.029235382
B33: Interest income | F33: =F31*F32 -> 61.236838 | G33: =G31*G32 -> 101.06805 | H33: =H31*H32 -> 140.98848 | I33: =I31*I32 -> 180.96678 | J33: =J31*J32 -> 220.95866

Sheet IncState
A1: =CoName -> Resturant Brands International Inc | C1: Hist. | D1: Hist. | E1: Hist. | F1: Proj. | G1: Proj. | H1: Proj. | I1: Proj. | J1: Proj.
A2: Assumptions | C2: 2022 | D2: =C2+1 -> 2023 | E2: =D2+1 -> 2024 | F2: =E2+1 -> 2025 | G2: =F2+1 -> 2026 | H2: =G2+1 -> 2027 | I2: =H2+1 -> 2028 | J2: =I2+1 -> 2029
B4: Revenue growth | F4: =Assumptions!F10 -> 0.11722126 | G4: =Assumptions!G10 -> 0.049911959 | H4: =Assumptions!H10 -> 0.046728964 | I4: =Assumptions!I10 -> 0.043501809 | J4: =Assumptions!J10 -> 0.040274155
B5: Cost of goods sold as % of sales | F5: =Assumptions!F11 -> 0.25833857 | G5: =Assumptions!G11 -> 0.25733857 | H5: =Assumptions!H11 -> 0.25633857 | I5: =Assumptions!I11 -> 0.25533857 | J5: =Assumptions!J11 -> 0.25433857
B6: SG&A % of sales | F6: =Assumptions!F12 -> 0.45189079 | G6: =Assumptions!G12 -> 0.45089079 | H6: =Assumptions!H12 -> 0.44989079 | I6: =Assumptions!I12 -> 0.44889079 | J6: =Assumptions!J12 -> 0.44789079
B7: Amortization amount | F7: =Assumptions!F13 -> 0 | G7: =Assumptions!G13 -> 0 | H7: =Assumptions!H13 -> 0 | I7: =Assumptions!I13 -> 0 | J7: =Assumptions!J13 -> 0
B8: Non recurring items, amount | F8: =Assumptions!F14 -> 0 | G8: =Assumptions!G14 -> 0 | H8: =Assumptions!H14 -> 0 | I8: =Assumptions!I14 -> 0 | J8: =Assumptions!J14 -> 0
B9: Other income (expense), amt | F9: =Assumptions!F15 -> 0 | G9: =Assumptions!G15 -> 0 | H9: =Assumptions!H15 -> 0 | I9: =Assumptions!I15 -> 0 | J9: =Assumptions!J15 -> 0
B10: Effective tax rate | F10: =Assumptions!F16 -> 0.19761129 | G10: =Assumptions!G16 -> 0.19761129 | H10: =Assumptions!H16 -> 0.19761129 | I10: =Assumptions!I16 -> 0.19761129 | J10: =Assumptions!J16 -> 0.19761129
B11: Dividend Payout Rate | F11: =Assumptions!F17 -> 3.3257053 | G11: =Assumptions!G17 -> 3.4257053 | H11: =Assumptions!H17 -> 3.5257053 | I11: =Assumptions!I17 -> 3.6257053 | J11: =Assumptions!J17 -> 3.7257053
B12: Basic WASO | F12: =Assumptions!F18 -> 319 | G12: =Assumptions!G18 -> 319 | H12: =Assumptions!H18 -> 319 | I12: =Assumptions!I18 -> 319 | J12: =Assumptions!J18 -> 319
B13: Diluted WASO | F13: =Assumptions!F19 -> 454 | G13: =Assumptions!G19 -> 454 | H13: =Assumptions!H19 -> 454 | I13: =Assumptions!I19 -> 454 | J13: =Assumptions!J19 -> 454
A15: Income statement | C15: =C37 -> 44926 | D15: =D37 -> 45291 | E15: =E37 -> 45657 | F15: =F37 -> 46022 | G15: =G37 -> 46022 | H15: =H37 -> 46022 | I15: =I37 -> 46022 | J15: =J37 -> 46022
B16: Revenue | C16: 6505 | D16: 7022 | E16: 8406 | F16: =E16*(1+F4) -> 9391.3619 | G16: =F16*(1+G4) -> 9860.1032 | H16: =G16*(1+H4) -> 10320.856 | I16: =H16*(1+I4) -> 10769.831 | J16: =I16*(1+J4) -> 11203.577
B17: COGS | C17: 2193 | D17: 1328 | E17: 2180 | F17: =F16*F5 -> 2426.151 | G17: =G16*G5 -> 2537.3848 | H17: =H16*H5 -> 2645.6333 | I17: =I16*I5 -> 2749.9533 | J17: =J16*J5 -> 2849.5018
B18: SG&A | C18: =4607-C17 -> 2414 | D18: =4971-D17 -> 3643 | E18: =5987-E17 -> 3807 | F18: =F16*F6 -> 4243.87 | G18: =G16*G6 -> 4445.8297 | H18: =H16*H6 -> 4643.2579 | I18: =I16*I6 -> 4834.4782 | J18: =J16*J6 -> 5017.9791
A19: * | B19: EBIT | C19: =C16-SUM(C17:C18) -> 1898 | D19: =D16-SUM(D17:D18) -> 2051 | E19: =E16-SUM(E17:E18) -> 2419 | F19: =F16-SUM(F17:F18) -> 2721.341 | G19: =G16-SUM(G17:G18) -> 2876.8886 | H19: =H16-SUM(H17:H18) -> 3031.9644 | I19: =I16-SUM(I17:I18) -> 3185.4 | J19: =J16-SUM(J17:J18) -> 3336.0964
B21: Depreciation | C21: 190 | D21: 191 | E21: 264 | F21: =Calcs!F8 -> 351.08393 | G21: =Calcs!G8 -> 345.72051 | H21: =Calcs!H8 -> 347.8321 | I21: =Calcs!I8 -> 357.29559 | J21: =Calcs!J8 -> 373.9677
B22: Amortization | C22: 0 | D22: 0 | E22: 0 | F22: =F7 -> 0 | G22: =G7 -> 0 | H22: =H7 -> 0 | I22: =I7 -> 0 | J22: =J7 -> 0
A23: * | B23: EBITDA | C23: =SUM(C19,C21:C22) -> 2088 | D23: =SUM(D19,D21:D22) -> 2242 | E23: =SUM(E19,E21:E22) -> 2683 | F23: =SUM(F19,F21:F22) -> 3072.4249 | G23: =SUM(G19,G21:G22) -> 3222.6091 | H23: =SUM(H19,H21:H22) -> 3379.7965 | I23: =SUM(I19,I21:I22) -> 3542.6955 | J23: =SUM(J19,J21:J22) -> 3710.0641
B25: Non-recurring items | C25: 0 | D25: 0 | E25: 0 | F25: =F8 -> 0 | G25: =G8 -> 0 | H25: =H8 -> 0 | I25: =I8 -> 0 | J25: =J8 -> 0
B26: Other income (expense) | C26: 0 | D26: 0 | E26: 0 | F26: =F9 -> 0 | G26: =G9 -> 0 | H26: =H9 -> 0 | I26: =I9 -> 0 | J26: =J9 -> 0
B28: Interest income | C28: 7 | D28: 40 | E28: 39 | F28: =IF(circ=1,Debt!F33,0) -> 0 | G28: =IF(circ=1,Debt!G33,0) -> 0 | H28: =IF(circ=1,Debt!H33,0) -> 0 | I28: =IF(circ=1,Debt!I33,0) -> 0 | J28: =IF(circ=1,Debt!J33,0) -> 0
B29: Interest expense | C29: =-493-19-28 -> -540 | D29: =-576-19-27 -> -622 | E29: =-572-19-25 -> -616 | F29: =IF(circ=1,-Debt!F22,0) -> 0 | G29: =IF(circ=1,-Debt!G22,0) -> 0 | H29: =IF(circ=1,-Debt!H22,0) -> 0 | I29: =IF(circ=1,-Debt!I22,0) -> 0 | J29: =IF(circ=1,-Debt!J22,0) -> 0
A31: * | B31: Pretax Income | C31: =C19+SUM(C26:C29) -> 1365 | D31: =D19+SUM(D26:D29) -> 1469 | E31: =E19+SUM(E25:E29) -> 1842 | F31: =F19+SUM(F25:F29) -> 2721.341 | G31: =G19+SUM(G25:G29) -> 2876.8886 | H31: =H19+SUM(H25:H29) -> 3031.9644 | I31: =I19+SUM(I25:I29) -> 3185.4 | J31: =J19+SUM(J25:J29) -> 3336.0964
B33: Tax expense | C33: -117 | D33: -265 | E33: 364 | F33: =F31*F10 -> 537.7677 | G33: =G31*G10 -> 568.50568 | H33: =H31*H10 -> 599.15039 | I33: =I31*I10 -> 629.471 | J33: =J31*J10 -> 659.25032
A34: * | B34: Net income | C34: =C31-C33 -> 1482 | D34: =D31-D33 -> 1734 | E34: =E31-E33 -> 1478 | F34: =F31-F33 -> 2183.5733 | G34: =G31-G33 -> 2308.3829 | H34: =H31-H33 -> 2432.814 | I34: =I31-I33 -> 2555.929 | J34: =J31-J33 -> 2676.8461
B35: Dividend payout rate | C35: =C36/C38 -> 3.1628664 | D35: =D36/D38 -> 3.1730769 | E35: =E36/E38 -> 3.2257053 | F35: =F11 -> 3.3257053 | G35: =G11 -> 3.4257053 | H35: =H11 -> 3.5257053 | I35: =I11 -> 3.6257053 | J35: =J11 -> 3.7257053
B36: Dividends | C36: 971 | D36: 990 | E36: 1029 | F36: =F35*F38 -> 1060.9 | G36: =G35*G38 -> 1092.8 | H36: =H35*H38 -> 1124.7 | I36: =I35*I38 -> 1156.6 | J36: =J35*J38 -> 1188.5
A37: Shareholder information | C37: 44926 | D37: 45291 | E37: 45657 | F37: 46022 | G37: 46022 | H37: 46022 | I37: 46022 | J37: 46022
B38: Basic WASO | C38: 307 | D38: 312 | E38: 319 | F38: =F12 -> 319 | G38: =G12 -> 319 | H38: =H12 -> 319 | I38: =I12 -> 319 | J38: =J12 -> 319
B39: Diluted WASO | C39: 455 | D39: 456 | E39: 454 | F39: =F13 -> 454 | G39: =G13 -> 454 | H39: =H13 -> 454 | I39: =I13 -> 454 | J39: =J13 -> 454
B40: Basic earnings per share | C40: =C34/C38 -> 4.8273616 | D40: =D34/D38 -> 5.5576923 | E40: =E34/E38 -> 4.6332288 | F40: =F34/F38 -> 6.8450572 | G40: =G34/G38 -> 7.2363102 | H40: =H34/H38 -> 7.626376 | I40: =I34/I38 -> 8.0123165 | J40: =J34/J38 -> 8.391367
A41: * | B41: Diluted earnings per share | C41: =C34/C39 -> 3.2571429 | D41: =D34/D39 -> 3.8026316 | E41: =E34/E39 -> 3.2555066 | F41: =F34/F39 -> 4.8096327 | G41: =G34/G39 -> 5.0845439 | H41: =H34/H39 -> 5.3586211 | I41: =I34/I39 -> 5.6297995 | J41: =J34/J39 -> 5.8961367

Sheet BalSheet
A1: =CoName -> Resturant Brands International Inc | C1: Hist. | D1: Hist. | E1: Hist. | F1: Proj. | G1: Proj. | H1: Proj. | I1: Proj. | J1: Proj.
A2: Assumptions | C2: 2022 | D2: =C2+1 -> 2023 | E2: =D2+1 -> 2024 | F2: =E2+1 -> 2025 | G2: =F2+1 -> 2026 | H2: =G2+1 -> 2027 | I2: =H2+1 -> 2028 | J2: =I2+1 -> 2029
B4: Operating Cash % of sales | F4: =Assumptions!F44 -> 0.02 | G4: =F4 -> 0.02 | H4: =G4 -> 0.02 | I4: =H4 -> 0.02 | J4: =I4 -> 0.02
B5: Accounts receivable % of sales | F5: =Assumptions!F45 -> 0.083035927 | G5: =Assumptions!G45 -> 0.083035927 | H5: =Assumptions!H45 -> 0.083035927 | I5: =Assumptions!I45 -> 0.083035927 | J5: =Assumptions!J45 -> 0.083035927
B6: Inventories % of COGS | F6: =Assumptions!F46 -> 0.065137615 | G6: =Assumptions!G46 -> 0.065137615 | H6: =Assumptions!H46 -> 0.065137615 | I6: =Assumptions!I46 -> 0.065137615 | J6: =Assumptions!J46 -> 0.065137615
B7: Other current assets % of sales | F7: =Assumptions!F47 -> 0.012847966 | G7: =Assumptions!G47 -> 0.012847966 | H7: =Assumptions!H47 -> 0.012847966 | I7: =Assumptions!I47 -> 0.012847966 | J7: =Assumptions!J47 -> 0.012847966
B8: Other long-term assets % of sales | F8: =Assumptions!F48 -> 0.16107542 | G8: =Assumptions!G48 -> 0.16107542 | H8: =Assumptions!H48 -> 0.16107542 | I8: =Assumptions!I48 -> 0.16107542 | J8: =Assumptions!J48 -> 0.16107542
B10: Accounts payable/Accural % of COGS | F10: =Assumptions!F52 -> 0.87431193 | G10: =Assumptions!G52 -> 0.87431193 | H10: =Assumptions!H52 -> 0.87431193 | I10: =Assumptions!I52 -> 0.87431193 | J10: =Assumptions!J52 -> 0.87431193
B11: Other current liabilities % of sales | F11: =Assumptions!F53 -> 0.028075184 | G11: =Assumptions!G53 -> 0.028075184 | H11: =Assumptions!H53 -> 0.028075184 | I11: =Assumptions!I53 -> 0.028075184 | J11: =Assumptions!J53 -> 0.028075184
B12: Other long-term liabilities % of sales | F12: =Assumptions!F54 -> 0.4722817 | G12: =Assumptions!G54 -> 0.4722817 | H12: =Assumptions!H54 -> 0.4722817 | I12: =Assumptions!I54 -> 0.4722817 | J12: =Assumptions!J54 -> 0.4722817
A14: Balance sheet | C14: =C2 -> 2022 | D14: =D2 -> 2023 | E14: =E2 -> 2024 | F14: =F2 -> 2025 | G14: =G2 -> 2026 | H14: =H2 -> 2027 | I14: =I2 -> 2028 | J14: =J2 -> 2029
B15: Operating Cash | C15: =2%*IncState!C16 -> 130.1 | D15: =2%*IncState!D16 -> 140.44 | E15: =2%*IncState!E16 -> 168.12 | F15: =F4*IncState!F16 -> 187.82724 | G15: =G4*IncState!G16 -> 197.20206 | H15: =H4*IncState!H16 -> 206.41711 | I15: =I4*IncState!I16 -> 215.39663 | J15: =J4*IncState!J16 -> 224.07155
B16: Excess cash | C16: =1178-C15 -> 1047.9 | D16: =1139-D15 -> 998.56 | E16: =1334-E15 -> 1165.88 | F16: =MAX(CashFlow!F23,0) -> 2094.6139 | G16: =MAX(CashFlow!G23,0) -> 3457.0456 | H16: =MAX(CashFlow!H23,0) -> 4822.529 | I16: =MAX(CashFlow!I23,0) -> 6189.9919 | J16: =MAX(CashFlow!J23,0) -> 7557.9192
B17: Accounts receivable | C17: 614 | D17: 749 | E17: 698 | F17: =F5*IncState!F16 -> 779.82044 | G17: =G5*IncState!G16 -> 818.74281 | H17: =H5*IncState!H16 -> 857.00181 | I17: =I5*IncState!I16 -> 894.28294 | J17: =J5*IncState!J16 -> 930.29943
B18: Inventories | C18: 133 | D18: 166 | E18: 142 | F18: =F6*IncState!F16 -> 611.73091 | G18: =G6*IncState!G16 -> 642.2636 | H18: =H6*IncState!H16 -> 672.27591 | I18: =I6*IncState!I16 -> 701.52113 | J18: =J6*IncState!J16 -> 729.7743
B19: Other current assets | C19: 123 | D19: 119 | E19: 108 | F19: =F7*IncState!F16 -> 120.6599 | G19: =G7*IncState!G16 -> 126.68227 | H19: =H7*IncState!H16 -> 132.602 | I19: =I7*IncState!I16 -> 138.37043 | J19: =J7*IncState!J16 -> 143.94318
B20: Total current assets | C20: =SUM(C15:C19) -> 2048 | D20: =SUM(D15:D19) -> 2173 | E20: =SUM(E15:E19) -> 2282 | F20: =SUM(F15:F19) -> 3794.6524 | G20: =SUM(G15:G19) -> 5241.9363 | H20: =SUM(H15:H19) -> 6690.8258 | I20: =SUM(I15:I19) -> 8139.5631 | J20: =SUM(J15:J19) -> 9586.0077
B22: Property, plant & equipment, net | C22: =1950+1082 -> 3032 | D22: =1952+1122 -> 3074 | E22: =2236+1852 -> 4088 | F22: =Calcs!F9 -> 4025.5486 | G22: =Calcs!G9 -> 4050.1359 | H22: =Calcs!H9 -> 4160.3281 | I22: =Calcs!I9 -> 4354.4572 | J22: =Calcs!J9 -> 4630.5571
B23: Intangible assets | C23: =10991+5688 -> 16679 | D23: =11107+5775 -> 16882 | E23: =10922+5986 -> 16908 | F23: =E23-IncState!F22 -> 16908 | G23: =F23-IncState!G22 -> 16908 | H23: =G23-IncState!H22 -> 16908 | I23: =H23-IncState!I22 -> 16908 | J23: =I23-IncState!J22 -> 16908
B24: Other assets | C24: 987 | D24: 1262 | E24: =1354 -> 1354 | F24: =F8*IncState!F16 -> 1512.7176 | G24: =G8*IncState!G16 -> 1588.2203 | H24: =H8*IncState!H16 -> 1662.4362 | I24: =I8*IncState!I16 -> 1734.7552 | J24: =J8*IncState!J16 -> 1804.621
B25: Total non-current assets | C25: =SUM(C22:C24) -> 20698 | D25: =SUM(D22:D24) -> 21218 | E25: =SUM(E22:E24) -> 22350 | F25: =SUM(F22:F24) -> 22446.266 | G25: =SUM(G22:G24) -> 22546.356 | H25: =SUM(H22:H24) -> 22730.764 | I25: =SUM(I22:I24) -> 22997.212 | J25: =SUM(J22:J24) -> 23343.178
A27: * | B27: TOTAL ASSETS | C27: =SUM(C25,C20) -> 22746 | D27: =SUM(D25,D20) -> 23391 | E27: =SUM(E25,E20) -> 24632 | F27: =SUM(F25,F20) -> 26240.919 | G27: =SUM(G25,G20) -> 27788.293 | H27: =SUM(H25,H20) -> 29421.59 | I27: =SUM(I25,I20) -> 31136.775 | J27: =SUM(J25,J20) -> 32929.186
B29: Revolver/Short term debt | C29: 0 | D29: 0 | E29: 0 | F29: =MIN(CashFlow!F23,0) -> 0 | G29: =MIN(CashFlow!G23,0) -> 0 | H29: =MIN(CashFlow!H23,0) -> 0 | I29: =MIN(CashFlow!I23,0) -> 0 | J29: =MIN(CashFlow!J23,0) -> 0
B30: Accounts payable/Accurals | C30: =758+1001 -> 1759 | D30: =1005+790 -> 1795 | E30: =765+1141 -> 1906 | F30: =F10*IncState!F17 -> 2121.2127 | G30: =G10*IncState!G17 -> 2218.4658 | H30: =H10*IncState!H17 -> 2313.1088 | I30: =I10*IncState!I17 -> 2404.317 | J30: =J10*IncState!J17 -> 2491.3534
B31: Other current liabilities | C31: 230 | D31: =248 -> 248 | E31: =236 -> 236 | F31: =F11*IncState!F16 -> 263.66422 | G31: =G11*IncState!G16 -> 276.82422 | H31: =H11*IncState!H16 -> 289.75992 | I31: =I11*IncState!I16 -> 302.365 | J31: =J11*IncState!J16 -> 314.5425
B32: Total current liabilities | C32: =SUM(C29:C31) -> 1989 | D32: =SUM(D29:D31) -> 2043 | E32: =SUM(E29:E31) -> 2142 | F32: =SUM(F29:F31) -> 2384.877 | G32: =SUM(G29:G31) -> 2495.29 | H32: =SUM(H29:H31) -> 2602.8687 | I32: =SUM(I29:I31) -> 2706.682 | J32: =SUM(J29:J31) -> 2805.8959
B34: Long-term debt, including current maturities | C34: =127+12839 -> 12966 | D34: =12854+101 -> 12955 | E34: =13455+222 -> 13677 | F34: =Debt!F20 -> 13455 | G34: =Debt!G20 -> 13455 | H34: =Debt!H20 -> 13455 | I34: =Debt!I20 -> 13455 | J34: =Debt!J20 -> 13455
B35: Other long-term liabilities | C35: =311+1027+872+1313 -> 3523 | D35: =312+1059+996+1296 -> 3663 | E35: =286+1770+706+1208 -> 3970 | F35: =F12*IncState!F16 -> 4435.3684 | G35: =G12*IncState!G16 -> 4656.7463 | H35: =H12*IncState!H16 -> 4874.3513 | I35: =I12*IncState!I16 -> 5086.3944 | J35: =J12*IncState!J16 -> 5291.2446
B36: Total non-current liabilities | C36: =SUM(C34:C35) -> 16489 | D36: =SUM(D34:D35) -> 16618 | E36: =SUM(E34:E35) -> 17647 | F36: =SUM(F34:F35) -> 17890.368 | G36: =SUM(G34:G35) -> 18111.746 | H36: =SUM(H34:H35) -> 18329.351 | I36: =SUM(I34:I35) -> 18541.394 | J36: =SUM(J34:J35) -> 18746.245
B38: Equity | C38: 4268 | D38: 4730 | E38: 4843 | F38: =Calcs!F17 -> 5965.6733 | G38: =Calcs!G17 -> 7181.2562 | H38: =Calcs!H17 -> 8489.3702 | I38: =Calcs!I17 -> 9888.6991 | J38: =Calcs!J17 -> 11377.045
A39: * | B39: TOTAL LIABILITIES & EQUITY | C39: =SUM(C38,C36,C32) -> 22746 | D39: =SUM(D38,D36,D32) -> 23391 | E39: =SUM(E38,E36,E32) -> 24632 | F39: =SUM(F38,F36,F32) -> 26240.919 | G39: =SUM(G38,G36,G32) -> 27788.293 | H39: =SUM(H38,H36,H32) -> 29421.59 | I39: =SUM(I38,I36,I32) -> 31136.775 | J39: =SUM(J38,J36,J32) -> 32929.186
A41: * | B41: Balance check | C41: =C39-C27 -> 0 | D41: =D39-D27 -> 0 | E41: =E39-E27 -> 0 | F41: =F39-F27 -> 0 | G41: =G39-G27 -> 0 | H41: =H39-H27 -> 0 | I41: =I39-I27 -> 0 | J41: =J39-J27 -> 0

Sheet CashFlow
A1: =CoName -> Resturant Brands International Inc | C1: Hist. | D1: Hist. | E1: Hist. | F1: Proj. | G1: Proj. | H1: Proj. | I1: Proj. | J1: Proj.
A2: Cash flow statement | C2: 2022 | D2: =C2+1 -> 2023 | E2: =D2+1 -> 2024 | F2: =E2+1 -> 2025 | G2: =F2+1 -> 2026 | H2: =G2+1 -> 2027 | I2: =H2+1 -> 2028 | J2: =I2+1 -> 2029
B3: Net Income | F3: =IncState!F34 -> 2183.5733 | G3: =IncState!G34 -> 2308.3829 | H3: =IncState!H34 -> 2432.814 | I3: =IncState!I34 -> 2555.929 | J3: =IncState!J34 -> 2676.8461
B4: Depreciation | F4: =IncState!F21 -> 351.08393 | G4: =IncState!G21 -> 345.72051 | H4: =IncState!H21 -> 347.8321 | I4: =IncState!I21 -> 357.29559 | J4: =IncState!J21 -> 373.9677
B5: Amortization | F5: =IncState!F22 -> 0 | G5: =IncState!G22 -> 0 | H5: =IncState!H22 -> 0 | I5: =IncState!I22 -> 0 | J5: =IncState!J22 -> 0
B6: (inc) / dec in OWC | F6: =Calcs!F26 -> -341.04153 | G6: =Calcs!G26 -> 25.560824 | H6: =Calcs!H26 -> 24.172576 | I6: =Calcs!I26 -> 22.539013 | J6: =Calcs!J26 -> 20.69658
B7: (inc) / dec in LT assets | F7: =BalSheet!E24-BalSheet!F24 -> -158.71759 | G7: =BalSheet!F24-BalSheet!G24 -> -75.502699 | H7: =BalSheet!G24-BalSheet!H24 -> -74.215888 | I7: =BalSheet!H24-BalSheet!I24 -> -72.318981 | J7: =BalSheet!I24-BalSheet!J24 -> -69.865797
B8: inc / (dec) in LT liabilities | F8: =BalSheet!F35-BalSheet!E35 -> 465.3684 | G8: =BalSheet!G35-BalSheet!F35 -> 221.37793 | H8: =BalSheet!H35-BalSheet!G35 -> 217.60493 | I8: =BalSheet!I35-BalSheet!H35 -> 212.0431 | J8: =BalSheet!J35-BalSheet!I35 -> 204.85023
B9: CFFO | F9: =SUM(F3:F8) -> 2500.2665 | G9: =SUM(G3:G8) -> 2825.5395 | H9: =SUM(H3:H8) -> 2948.2077 | I9: =SUM(I3:I8) -> 3075.4877 | J9: =SUM(J3:J8) -> 3206.4948
B11: Capex | F11: =Calcs!F7 -> 288.63257 | G11: =Calcs!G7 -> 370.3078 | H11: =Calcs!H7 -> 458.02432 | I11: =Calcs!I7 -> 551.42469 | J11: =Calcs!J7 -> 650.06751
B12: CFFI | F12: =-F11 -> -288.63257 | G12: =-G11 -> -370.3078 | H12: =-H11 -> -458.02432 | I12: =-I11 -> -551.42469 | J12: =-J11 -> -650.06751
B14: Dividends Paid | F14: =-IncState!F36 -> -1060.9 | G14: =-IncState!G36 -> -1092.8 | H14: =-IncState!H36 -> -1124.7 | I14: =-IncState!I36 -> -1156.6 | J14: =-IncState!J36 -> -1188.5
B15: Debt issuance / (repayments) | F15: =SUM(Debt!F8:F9) -> -222 | G15: =SUM(Debt!G8:G9) -> 0 | H15: =SUM(Debt!H8:H9) -> 0 | I15: =SUM(Debt!I8:I9) -> 0 | J15: =SUM(Debt!J8:J9) -> 0
B16: Share issuance / (repurchases) | F16: =Calcs!F11 -> 0 | G16: =Calcs!G11 -> 0 | H16: =Calcs!H11 -> 0 | I16: =Calcs!I11 -> 0 | J16: =Calcs!J11 -> 0
B17: CFFF | F17: =SUM(F14:F16) -> -1282.9 | G17: =SUM(G14:G16) -> -1092.8 | H17: =SUM(H14:H16) -> -1124.7 | I17: =SUM(I14:I16) -> -1156.6 | J17: =SUM(J14:J16) -> -1188.5
B19: Net changes In cash | F19: =SUM(F17,F12,F9) -> 928.7339 | G19: =SUM(G17,G12,G9) -> 1362.4317 | H19: =SUM(H17,H12,H9) -> 1365.4834 | I19: =SUM(I17,I12,I9) -> 1367.463 | J19: =SUM(J17,J12,J9) -> 1367.9273
B21: Beginning cash | F21: =BalSheet!E16 -> 1165.88 | G21: =BalSheet!F16 -> 2094.6139 | H21: =BalSheet!G16 -> 3457.0456 | I21: =BalSheet!H16 -> 4822.529 | J21: =BalSheet!I16 -> 6189.9919
B22: =B19 -> Net changes In cash | F22: =F19 -> 928.7339 | G22: =G19 -> 1362.4317 | H22: =H19 -> 1365.4834 | I22: =I19 -> 1367.463 | J22: =J19 -> 1367.9273
B23: Ending cash | F23: =SUM(F21:F22) -> 2094.6139 | G23: =SUM(G21:G22) -> 3457.0456 | H23: =SUM(H21:H22) -> 4822.529 | I23: =SUM(I21:I22) -> 6189.9919 | J23: =SUM(J21:J22) -> 7557.9192

Sheet Free Cash Flow
A1: =CoName -> Resturant Brands International Inc | C1: Hist. | D1: Hist. | E1: Hist. | F1: Proj. | G1: Proj. | H1: Proj. | I1: Proj. | J1: Proj.
A2: Free Cash Flows | C2: 2022 | D2: =C2+1 -> 2023 | E2: =D2+1 -> 2024 | F2: =E2+1 -> 2025 | G2: =F2+1 -> 2026 | H2: =G2+1 -> 2027 | I2: =H2+1 -> 2028 | J2: =I2+1 -> 2029
A3: * | B3: Sales | F3: =IncState!F16 -> 9391.3619 | G3: =IncState!G16 -> 9860.1032 | H3: =IncState!H16 -> 10320.856 | I3: =IncState!I16 -> 10769.831 | J3: =IncState!J16 -> 11203.577
B4: EBIT | F4: =IncState!F19 -> 2721.341 | G4: =IncState!G19 -> 2876.8886 | H4: =IncState!H19 -> 3031.9644 | I4: =IncState!I19 -> 3185.4 | J4: =IncState!J19 -> 3336.0964
B5: Effective Tax Rate | F5: =Assumptions!F16 -> 0.19761129 | G5: =Assumptions!G16 -> 0.19761129 | H5: =Assumptions!H16 -> 0.19761129 | I5: =Assumptions!I16 -> 0.19761129 | J5: =Assumptions!J16 -> 0.19761129
A7: * | B7: NOPAT | F7: =F4*(1-F5) -> 2183.5733 | G7: =G4*(1-G5) -> 2308.3829 | H7: =H4*(1-H5) -> 2432.814 | I7: =I4*(1-I5) -> 2555.929 | J7: =J4*(1-J5) -> 2676.8461
B8: Depreciation | F8: =CashFlow!F4 -> 351.08393 | G8: =CashFlow!G4 -> 345.72051 | H8: =CashFlow!H4 -> 347.8321 | I8: =CashFlow!I4 -> 357.29559 | J8: =CashFlow!J4 -> 373.9677
B9: Amortization | F9: =CashFlow!F5 -> 0 | G9: =CashFlow!G5 -> 0 | H9: =CashFlow!H5 -> 0 | I9: =CashFlow!I5 -> 0 | J9: =CashFlow!J5 -> 0
B10: (inc) / dec in OWC | F10: =CashFlow!F6 -> -341.04153 | G10: =CashFlow!G6 -> 25.560824 | H10: =CashFlow!H6 -> 24.172576 | I10: =CashFlow!I6 -> 22.539013 | J10: =CashFlow!J6 -> 20.69658
B11: (inc) / dec in other long-term assets | F11: =CashFlow!F7 -> -158.71759 | G11: =CashFlow!G7 -> -75.502699 | H11: =CashFlow!H7 -> -74.215888 | I11: =CashFlow!I7 -> -72.318981 | J11: =CashFlow!J7 -> -69.865797
B12: inc / (dec) other long-term liabilities | F12: =CashFlow!F8 -> 465.3684 | G12: =CashFlow!G8 -> 221.37793 | H12: =CashFlow!H8 -> 217.60493 | I12: =CashFlow!I8 -> 212.0431 | J12: =CashFlow!J8 -> 204.85023
B13: (Capex) | F13: =CashFlow!F12 -> -288.63257 | G13: =CashFlow!G12 -> -370.3078 | H13: =CashFlow!H12 -> -458.02432 | I13: =CashFlow!I12 -> -551.42469 | J13: =CashFlow!J12 -> -650.06751
A15: * | B15: Free Cash Flow | F15: =SUM(F7:F13) -> 2211.6339 | G15: =SUM(G7:G13) -> 2455.2317 | H15: =SUM(H7:H13) -> 2490.1834 | I15: =SUM(I7:I13) -> 2524.063 | J15: =SUM(J7:J13) -> 2556.4273
B17: Net operating assets | F17: =SUM(BalSheet!F15,BalSheet!F17:F19,BalSheet!F22:F24) -> 24146.305 | G17: =SUM(BalSheet!G15,BalSheet!G17:G19,BalSheet!G22:G24) -> 24331.247 | H17: =SUM(BalSheet!H15,BalSheet!H17:H19,BalSheet!H22:H24) -> 24599.061 | I17: =SUM(BalSheet!I15,BalSheet!I17:I19,BalSheet!I22:I24) -> 24946.784 | J17: =SUM(BalSheet!J15,BalSheet!J17:J19,BalSheet!J22:J24) -> 25371.266
B18: Net operating liabilities (excluding long term) | F18: =SUM(BalSheet!F30:F31) -> 2384.877 | G18: =SUM(BalSheet!G30:G31) -> 2495.29 | H18: =SUM(BalSheet!H30:H31) -> 2602.8687 | I18: =SUM(BalSheet!I30:I31) -> 2706.682 | J18: =SUM(BalSheet!J30:J31) -> 2805.8959
B19: Net working capital | F19: =F17-F18 -> 21761.428 | G19: =G17-G18 -> 21835.957 | H19: =H17-H18 -> 21996.192 | I19: =I17-I18 -> 22240.102 | J19: =J17-J18 -> 22565.371
B20: ROIC | F20: =F7/F19 -> 0.10034145 | G20: =G7/G19 -> 0.10571476 | H20: =H7/H19 -> 0.11060159 | I20: =I7/I19 -> 0.11492434 | J20: =J7/J19 -> 0.11862628

Sheet WACC
A1: =CoName -> Resturant Brands International Inc
A3: * | B3: WACC | G3: Comp | H3: Levered beta | I3: Gross debt | J3: Market cap | K3: Debt/Mcap | L3: MTR | M3: Unlevered beta
B4: Tax Rate | E4: =Assumptions!F16 -> 0.19761129 | L4: =E4 -> 0.19761129 | M4: =H4/((1+K4*(1-L4))) -> 0
B5: Risk free rate | E5: 0.041 | L5: =L4 -> 0.19761129 | M5: =H5/((1+K5*(1-L5))) -> 0
B6: Market risk Premium | E6: 0.05 | L6: =L5 -> 0.19761129 | M6: =H6/((1+K6*(1-L6))) -> 0
B7: Beta | E7: 0.82 | L7: =L6 -> 0.19761129 | M7: =H7/((1+K7*(1-L7))) -> 0
B8: Cost of Equity | E8: =E5+E6*E7 -> 0.082
B9: % Equity | E9: =1-E10 -> 0.594882 | G9: Industry beta (average) | M9: =AVERAGE(M4:M7) -> 0
B10: % Debt | E10: =MAIN!F8/MAIN!F6 -> 0.405118
B11: Cost of debt | E11: =Assumptions!F24 -> 0.045 | G11: Re-levered beta | M11: =M9*(1+E10*(1-E4)) -> 0
B12: Post tax cost of debt | E12: =E11*(1-E4) -> 0.036107492
A13: * | B13: WACC | E13: =WACC!E8*WACC!E9+WACC!E12*WACC!E10 -> 0.063408119
B14: Long Term growth rate | E14: 0.025

Sheet DCF Model
A1: =CoName -> Resturant Brands International Inc | D1: Proj. | E1: Proj. | F1: Proj. | G1: Proj. | H1: Proj.
A2: Discount Model Year count | D2: 1 | E2: =D2+1 -> 2 | F2: =E2+1 -> 3 | G2: =F2+1 -> 4 | H2: =G2+1 -> 5
B3: Discount Factor | D3: =1/(1+$K$17)^D2 -> 0.94037273 | E3: =1/(1+$K$17)^E2 -> 0.88430088 | F3: =1/(1+$K$17)^F2 -> 0.83157244 | G3: =1/(1+$K$17)^G2 -> 0.78198804 | H3: =1/(1+$K$17)^H2 -> 0.73536024
B4: PV FCF | D4: =D3*'Free Cash Flow'!F15 -> 2079.7602 | E4: =E3*'Free Cash Flow'!G15 -> 2171.1636 | F4: =F3*'Free Cash Flow'!H15 -> 2070.7678 | G4: =G3*'Free Cash Flow'!I15 -> 1973.7871 | H4: =H3*'Free Cash Flow'!J15 -> 1879.895 | I4: =(H4*(1+K18))/(K17-K18) -> 50168.881
A6: Value Calculation | E6: Multiples Calculation | I6: Dividend Discount Model
B7: Total PV of FCFs | C7: =SUM(D4:H4) -> 10175.374 | E7: Total PV of FCFs | G7: =C7 -> 10175.374 | I7: FY Dividends | K7: =IncState!J36 -> 1188.5
B8: PV of TV | C8: =I4*H3 -> 36892.2 | E8: Multiple TV | G8: =G10*H3*IncState!J23 -> 40923.504 | I8: Equity Value | K8: =K7/(K17-K18) -> 30943.979
B9: EV | C9: =SUM(C7:C8) -> 47067.574 | E9: EV | G9: =SUM(G7:G8) -> 51098.878
E10: Implied EBITDA multiple | G10: 15 | I10: Diluted S/O | K10: =G17 -> 454.795
I11: Implied Share Price | K11: =K8/K10 -> 68.039399
B12: Cash & Cash Equiv | C12: =MAIN!F7 -> 1206 | E12: Cash & Cash Equiv | G12: =C12 -> 1206
B13: Debt & Claims | C13: =MAIN!F8 -> 13531 | E13: Debt & Claims | G13: =C13 -> 13531
B14: NCI | C14: 0 | E14: NCI | G14: =C14 -> 0
B15: Equity Value | C15: =C9+C12-SUM(C13:C14) -> 34742.574 | E15: Equity Value | G15: =G9+G12-SUM(G13:G14) -> 38773.878
B17: Diluted S/O | C17: =MAIN!F5 -> 454.795 | E17: Diluted S/O | G17: =C17 -> 454.795 | I17: WACC | K17: =WACC!E13 -> 0.063408119
A18: * | B18: Implied Share Price | C18: =C15/C17 -> 76.391724 | E18: Implied Share Price | G18: =G15/G17 -> 85.255726 | I18: Long Term growth rate | K18: 0.025
A20: Sensitivity analysis
C22: Discount rate variance | E22: 0.005 | I22: Discount rate variance | K22: 0.005
C23: Implied growth rate variance | E23: 0.0025 | I23: TV multiple variance | K23: 2
E25: LTGR | K25: Exit Mult.
C26: =C18 -> 76.391724 | D26: =E26-E23 -> 0.0225 | E26: 0.025 | F26: =E26+E23 -> 0.0275 | I26: =G18 -> 85.255726 | J26: =K26-K23 -> 13 | K26: 15 | L26: =K26+K23 -> 17
C27: =C28+$E$22 -> 0.073408119 | D27: 50.263962 | E27: 53.278138 | F27: 56.620598 | I27: =C27 -> 0.073408119 | J27: 69.086891 | K27: 80.535991 | L27: 91.985091
C28: =C29+$E$22 -> 0.068408119 | D28: 59.565426 | E28: 63.452857 | F28: 67.815429 | I28: =C28 -> 0.068408119 | J28: 71.1442 | K28: 82.86372 | L28: 94.58324
C29: 0.063408119 | D29: 71.248618 | E29: 76.391724 | F29: 82.250978 | I29: =C29 -> 0.063408119 | J29: 73.258085 | K29: 85.255726 | L29: 97.253367
C30: =C29-$E$22 -> 0.058408119 | D30: 86.31745 | E30: 93.345497 | F30: 101.51047 | I30: =C30 -> 0.058408119 | J30: 75.4304 | K30: 87.71412 | L30: 99.997841
C31: =C30-$E$22 -> 0.053408119 | D31: 106.42618 | E31: 116.44629 | F31: 128.40019 | I31: =C31 -> 0.053408119 | J31: 77.663073 | K31: 90.241097 | L31: 102.81912
