Workbook
Name Ccy: MAIN!$C$6
Name circ: MAIN!$C$9
Name CoName: MAIN!$C$4
Name g: #REF!
Name IQ_CH: 110000
Name IQ_CQ: 5000
Name IQ_CY: 10000
Name IQ_DAILY: 500000
Name IQ_FH: 100000
Name IQ_FQ: 500
Name IQ_FY: 1000
Name IQ_LTM: 2000
Name IQ_MONTH: 15000
Name IQ_NTM: 6000
Name IQ_WEEK: 50000
Name IQ_YTD: 3000
Name OpCase: [1]DCF!$E$98
Name ScenarioREV: Assumptions!$D$4
Name TTS: #REF!
Name Units: MAIN!$C$7

Sheet MAIN
A1: =CoName -> Shake Shack, Inc.
A2: Model Details
B4: Company name | C4: Shake Shack, Inc. | E4: Current Stock Price | F4: 82.12 | H4: Operating Case One | I4: Terminal Mult | J4: Perpetuity | K4: Average
B5: Latest BS date | C5: 247.43 | E5: Diluted s/o | F5: =40.253589+2.434789 -> 42.688378 | H5: Implied Price | I5: ='DCF Model'!G18 -> 90.971701 | J5: ='DCF Model'!C18 -> 57.169081 | K5: =AVERAGE(I5:J5) -> 74.070391
B6: Currency | C6: USD | E6: Mkt Cap | F6: =F5*F4 -> 3505.5696 | H6: Difference | I6: =I5/$F$4-1 -> 0.10778984 | J6: =J5/$F$4-1 -> -0.30383486 | K6: =K5/$F$4-1 -> -0.098022513
B7: Units | C7: m | E7: Cash | F7: =357.757 -> 357.757
B8: Analyst name | C8: Alan Chen | E8: Debt | F8: =247.469+540.248 -> 787.717
B9: Circular switch | C9: 0 | E9: EV | F9: =F6-F7+F8 -> 3935.5296

Sheet Quarterly Projections

Sheet Assumptions
A1: =CoName -> Shake Shack, Inc. | C1: Hist. | D1: Hist. | E1: Hist. | F1: Proj. | G1: Proj. | H1: Proj. | I1: Proj. | J1: Proj.
A2: * | B2: Income Statement | C2: 2022 | D2: =C2+1 -> 2023 | E2: =D2+1 -> 2024 | F2: =E2+1 -> 2025 | G2: =F2+1 -> 2026 | H2: =G2+1 -> 2027 | I2: =H2+1 -> 2028 | J2: =I2+1 -> 2029
B4: Operating Case | D4: 1
D5: Variance
B6: Street Case | D6: 0 | F6: 0.161 | G6: 0.135 | H6: 0.14 | I6: 0.15 | J6: 0.16
B7: Optimistic Case | D7: 0.025 | F7: =F6+$D$7 -> 0.186 | G7: =G6+$D$7 -> 0.16 | H7: =H6+$D$7 -> 0.165 | I7: =I6+$D$7 -> 0.175 | J7: =J6+$D$7 -> 0.185
B8: Pessimistic Case | D8: -0.025 | F8: =F6+$D$8 -> 0.136 | G8: =G6+$D$8 -> 0.11 | H8: =H6+$D$8 -> 0.115 | I8: =I6+$D$8 -> 0.125 | J8: =J6+$D$8 -> 0.135
B10: Revenue Growth | D10: =IncState!D15/IncState!C15-1 -> 0.20771783 | E10: =IncState!E15/IncState!D15-1 -> 0.1517885 | F10: =CHOOSE(ScenarioREV,F6,F7,F8) -> 0.161 | G10: =CHOOSE(ScenarioREV,G6,G7,G8) -> 0.135 | H10: =CHOOSE(ScenarioREV,H6,H7,H8) -> 0.14 | I10: =CHOOSE(ScenarioREV,I6,I7,I8) -> 0.15 | J10: =CHOOSE(ScenarioREV,J6,J7,J8) -> 0.16
B11: COGS % of sales | C11: =IncState!C16/IncState!C15 -> 0.79634775 | D11: =IncState!D16/IncState!D15 -> 0.77109384 | E11: =IncState!E16/IncState!E15 -> 0.7585294 | F11: =E11-0.005 -> 0.7535294 | G11: =F11-0.005 -> 0.7485294 | H11: =G11-0.005 -> 0.7435294 | I11: =H11-0.005 -> 0.7385294 | J11: =I11-0.005 -> 0.7335294
B12: SG&A % of sales | C12: =IncState!C17/IncState!C15 -> 0.23082535 | D12: =IncState!D17/IncState!D15 -> 0.22069675 | E12: =IncState!E17/IncState!E15 -> 0.21324469 | F12: =E12-0.005 -> 0.20824469 | G12: =F12-0.005 -> 0.20324469 | H12: =G12-0.005 -> 0.19824469 | I12: =H12-0.005 -> 0.19324469 | J12: =I12-0.005 -> 0.18824469
B13: Amortization $ Amt | C13: =IncState!C21 -> 0 | D13: =IncState!D21 -> 0 | E13: =IncState!E21 -> 0 | F13: =E13 -> 0 | G13: =F13 -> 0 | H13: =G13 -> 0 | I13: =H13 -> 0 | J13: =I13 -> 0
B14: Non recurring income / (expense) | C14: =IncState!C24 -> -2.425 | D14: =IncState!D24 -> -3.007 | E14: =IncState!E24 -> -32.368 | F14: 0 | G14: 0 | H14: 0 | I14: 0 | J14: 0
B15: Other Income / (expense) | C15: =IncState!C25 -> 4.127 | D15: =IncState!D25 -> 12.776 | E15: =IncState!E25 -> 13.251 | F15: 0 | G15: 0 | H15: 0 | I15: 0 | J15: 0
B16: Effective tax rate | C16: =IncState!C32/IncState!C30 -> 0.053979872 | D16: =IncState!D32/IncState!D30 -> 0.03632361 | E16: =IncState!E32/IncState!E30 -> 0.24122869 | F16: =E16 -> 0.24122869 | G16: =F16 -> 0.24122869 | H16: =G16 -> 0.24122869 | I16: =H16 -> 0.24122869 | J16: =I16 -> 0.24122869
B17: Basic WASO | C17: =IncState!C35 -> 39.237 | D17: =IncState!D35 -> 39.419 | E17: =IncState!E35 -> 39.83 | F17: =E17 -> 39.83 | G17: =F17 -> 39.83 | H17: =G17 -> 39.83 | I17: =H17 -> 39.83 | J17: =I17 -> 39.83
B18: Diluted WASO | C18: =IncState!C36 -> 39.237 | D18: =IncState!D36 -> 43.899 | E18: =IncState!E36 -> 44.203 | F18: =E18 -> 44.203 | G18: =F18 -> 44.203 | H18: =G18 -> 44.203 | I18: =H18 -> 44.203 | J18: =I18 -> 44.203
A20: * | B20: Debt | C20: =C2 -> 2022 | D20: =D2 -> 2023 | E20: =E2 -> 2024 | F20: =F2 -> 2025 | G20: =G2 -> 2026 | H20: =H2 -> 2027 | I20: =I2 -> 2028 | J20: =J2 -> 2029
B22: Interest rate on Revolver | E22: 0.05 | F22: =E22 -> 0.05 | G22: =F22 -> 0.05 | H22: =G22 -> 0.05 | I22: =H22 -> 0.05 | J22: =I22 -> 0.05
B23: Interest rate on long-term debt | E23: 0.05 | F23: =E23 -> 0.05 | G23: =F23 -> 0.05 | H23: =G23 -> 0.05 | I23: =H23 -> 0.05 | J23: =I23 -> 0.05
B24: Interest rate on cash | E24: 0.04 | F24: =E24 -> 0.04 | G24: =F24 -> 0.04 | H24: =G24 -> 0.04 | I24: =H24 -> 0.04 | J24: =I24 -> 0.04
B26: Issuance of long-term debt | F26: 0 | G26: 0 | H26: 0 | I26: 0 | J26: 0
B27: Repayment of long-term debt | F27: 0 | G27: 0 | H27: 0 | I27: 0 | J27: 0
A29: * | B29: Calcs | C29: =C20 -> 2022 | D29: =D20 -> 2023 | E29: =E20 -> 2024 | F29: =F20 -> 2025 | G29: =G20 -> 2026 | H29: =H20 -> 2027 | I29: =I20 -> 2028 | J29: =J20 -> 2029
B31: CapEx % of Sales | C31: =142.599/IncState!C15 -> 0.15835782 | D31: =146.167/IncState!D15 -> 0.13440236 | E31: =135.499/IncState!E15 -> 0.10817351 | F31: =E31-0.005 -> 0.10317351 | G31: =F31-0.005 -> 0.098173507 | H31: =G31-0.005 -> 0.093173507 | I31: =H31-0.005 -> 0.088173507 | J31: =I31-0.005 -> 0.083173507
B32: Depreciation % of beginning PP&E | D32: =IncState!D20/BalSheet!C23 -> 0.10933484 | E32: =IncState!E20/BalSheet!D23 -> 0.16044167 | F32: =AVERAGE(D32:E32) -> 0.13488825 | G32: =F32 -> 0.13488825 | H32: =G32 -> 0.13488825 | I32: =H32 -> 0.13488825 | J32: =I32 -> 0.13488825
B33: Share issuance / (repurchases) | F33: 0 | G33: 0 | H33: 0 | I33: 0 | J33: 0
A35: * | B35: Balance Sheet - Assets | C35: =C29 -> 2022 | D35: =D29 -> 2023 | E35: =E29 -> 2024 | F35: =F29 -> 2025 | G35: =G29 -> 2026 | H35: =H29 -> 2027 | I35: =I29 -> 2028 | J35: =J29 -> 2029
B37: Operating Cash % of sales | C37: =BalSheet!C16/IncState!C15 -> 0.02 | D37: =BalSheet!D16/IncState!D15 -> 0.02 | E37: =BalSheet!E16/IncState!E15 -> 0.02 | F37: =E37 -> 0.02 | G37: =F37 -> 0.02 | H37: =G37 -> 0.02 | I37: =H37 -> 0.02 | J37: =I37 -> 0.02
B38: Accounts receivable % of sales | C38: =BalSheet!C18/IncState!C15 -> 0.015410567 | D38: =BalSheet!D18/IncState!D15 -> 0.015491024 | E38: =BalSheet!E18/IncState!E15 -> 0.015716808 | F38: =E38 -> 0.015716808 | G38: =F38 -> 0.015716808 | H38: =G38 -> 0.015716808 | I38: =H38 -> 0.015716808 | J38: =I38 -> 0.015716808
B39: Inventories % of COGS | C39: =BalSheet!C19/IncState!C16 -> 0.0058346116 | D39: =BalSheet!D19/IncState!D16 -> 0.0064441503 | E39: =BalSheet!E19/IncState!E16 -> 0.0063295935 | F39: =E39 -> 0.0063295935 | G39: =F39 -> 0.0063295935 | H39: =G39 -> 0.0063295935 | I39: =H39 -> 0.0063295935 | J39: =I39 -> 0.0063295935
B40: Other current assets % of sales | C40: =BalSheet!C20/IncState!C15 -> 0.016323408 | D40: =BalSheet!D20/IncState!D15 -> 0.01744039 | E40: =BalSheet!E20/IncState!E15 -> 0.017404487 | F40: =E40 -> 0.017404487 | G40: =F40 -> 0.017404487 | H40: =G40 -> 0.017404487 | I40: =H40 -> 0.017404487 | J40: =I40 -> 0.017404487
B42: Investments in unconsolidated entities | C42: =BalSheet!#REF! -> #REF! | D42: =BalSheet!#REF! -> #REF! | E42: =BalSheet!#REF! -> #REF! | F42: =E42 -> #REF! | G42: =F42 -> #REF! | H42: =G42 -> #REF! | I42: =H42 -> #REF! | J42: =I42 -> #REF!
B43: Other long-term assets % of sales | C43: =BalSheet!C25/IncState!C15 -> 0.017564959 | D43: =BalSheet!D25/IncState!D15 -> 0.014644153 | E43: =BalSheet!E25/IncState!E15 -> 0.28144799 | F43: =E43 -> 0.28144799 | G43: =F43 -> 0.28144799 | H43: =G43 -> 0.28144799 | I43: =H43 -> 0.28144799 | J43: =I43 -> 0.28144799
A45: * | B45: Balance Sheet - Liabilities | C45: =C35 -> 2022 | D45: =D35 -> 2023 | E45: =E35 -> 2024 | F45: =F35 -> 2025 | G45: =G35 -> 2026 | H45: =H35 -> 2027 | I45: =I35 -> 2028 | J45: =J35 -> 2029
B47: Accounts payable % of COGS | C47: =BalSheet!C31/IncState!C16 -> 0.11982708 | D47: =BalSheet!D31/IncState!D16 -> 0.11681513 | E47: =BalSheet!E31/IncState!E16 -> 0.11791525 | F47: =E47 -> 0.11791525 | G47: =F47 -> 0.11791525 | H47: =G47 -> 0.11791525 | I47: =H47 -> 0.11791525 | J47: =I47 -> 0.11791525
B48: Other current liabilities % of sales | C48: =BalSheet!C32/IncState!C15 -> 0.068618502 | D48: =BalSheet!D32/IncState!D15 -> 0.060786201 | E48: =BalSheet!E32/IncState!E15 -> 0.060096215 | F48: =E48 -> 0.060096215 | G48: =F48 -> 0.060096215 | H48: =G48 -> 0.060096215 | I48: =H48 -> 0.060096215 | J48: =I48 -> 0.060096215
B49: Other long-term liabilities % of sales | C49: =BalSheet!C36/IncState!C15 -> 0.75826498 | D49: =BalSheet!D36/IncState!D15 -> 0.66828685 | E49: =BalSheet!E36/IncState!E15 -> 0.61419774 | F49: =E49 -> 0.61419774 | G49: =F49 -> 0.61419774 | H49: =G49 -> 0.61419774 | I49: =H49 -> 0.61419774 | J49: =I49 -> 0.61419774

Sheet Calcs
A1: =CoName -> Shake Shack, Inc. | C1: Hist. | D1: Hist. | E1: Hist. | F1: Proj. | G1: Proj. | H1: Proj. | I1: Proj. | J1: Proj.
A2: Net PP&E | C2: 2022 | D2: =C2+1 -> 2023 | E2: =D2+1 -> 2024 | F2: =E2+1 -> 2025 | G2: =F2+1 -> 2026 | H2: =G2+1 -> 2027 | I2: =H2+1 -> 2028 | J2: =I2+1 -> 2029
B3: Capital expenditure % of sales | F3: =Assumptions!F31 -> 0.10317351 | G3: =Assumptions!G31 -> 0.098173507 | H3: =Assumptions!H31 -> 0.093173507 | I3: =Assumptions!I31 -> 0.088173507 | J3: =Assumptions!J31 -> 0.083173507
B4: Depreciation % of PP&E | F4: =Assumptions!F32 -> 0.13488825 | G4: =F4 -> 0.13488825 | H4: =G4 -> 0.13488825 | I4: =H4 -> 0.13488825 | J4: =I4 -> 0.13488825
B6: Beginning PP&E | F6: =E9 -> 976.211 | G6: =F9 -> 994.57455 | H6: =G9 -> 1022.4638 | I6: =H9 -> 1059.8692 | J6: =I9 -> 1107.7078
B7: Capex | F7: =F3*IncState!F15 -> 150.04295 | G7: =G3*IncState!G15 -> 162.04572 | H7: =H3*IncState!H15 -> 175.32367 | I7: =I3*IncState!I15 -> 190.8025 | J7: =J3*IncState!J15 -> 208.78003
B8: Depreciation | F8: =F6*F4 -> 131.6794 | G8: =G6*G4 -> 134.15643 | H8: =H6*H4 -> 137.91836 | I8: =I6*I4 -> 142.9639 | J8: =J6*J4 -> 149.41677
B9: Ending PP&E | E9: =BalSheet!E23 -> 976.211 | F9: =F6+F7-F8 -> 994.57455 | G9: =G6+G7-G8 -> 1022.4638 | H9: =H6+H7-H8 -> 1059.8692 | I9: =I6+I7-I8 -> 1107.7078 | J9: =J6+J7-J8 -> 1167.071
A10: Equity | C10: =C2 -> 2022 | D10: =D2 -> 2023 | E10: =E2 -> 2024 | F10: =F2 -> 2025 | G10: =G2 -> 2026 | H10: =H2 -> 2027 | I10: =I2 -> 2028 | J10: =J2 -> 2029
B11: Share issuance/(repurchases) | F11: =Assumptions!F33 -> 0 | G11: =Assumptions!G33 -> 0 | H11: =Assumptions!H33 -> 0 | I11: =Assumptions!I33 -> 0 | J11: =Assumptions!J33 -> 0
B13: Beginning balance | F13: =E16 -> 493.626 | G13: =F16 -> 535.80693 | H13: =G16 -> 596.2066 | I13: =H16 -> 679.33995 | J13: =I16 -> 791.36269
B14: Net income | F14: =IncState!F33 -> 42.180928 | G14: =IncState!G33 -> 60.399674 | H14: =IncState!H33 -> 83.133353 | I14: =IncState!I33 -> 112.02274 | J14: =IncState!J33 -> 148.99286
B15: Share issuance / (repurchase) | F15: =F11 -> 0 | G15: =G11 -> 0 | H15: =H11 -> 0 | I15: =I11 -> 0 | J15: =J11 -> 0
B16: Ending balance | E16: =BalSheet!E39 -> 493.626 | F16: =SUM(F13:F15) -> 535.80693 | G16: =SUM(G13:G15) -> 596.2066 | H16: =SUM(H13:H15) -> 679.33995 | I16: =SUM(I13:I15) -> 791.36269 | J16: =SUM(J13:J15) -> 940.35556
A17: OWC | C17: =C10 -> 2022 | D17: =D10 -> 2023 | E17: =E10 -> 2024 | F17: =F10 -> 2025 | G17: =G10 -> 2026 | H17: =H10 -> 2027 | I17: =I10 -> 2028 | J17: =J10 -> 2029
B18: Operating Cash | E18: =BalSheet!E16 -> 25.05216 | F18: =BalSheet!F16 -> 29.085558 | G18: =BalSheet!G16 -> 33.012108 | H18: =BalSheet!H16 -> 37.633803 | I18: =BalSheet!I16 -> 43.278874 | J18: =BalSheet!J16 -> 50.203493
B19: =BalSheet!B18 -> Accounts receivable | E19: =BalSheet!E18 -> 19.687 | F19: =BalSheet!F18 -> 22.856607 | G19: =BalSheet!G18 -> 25.942249 | H19: =BalSheet!H18 -> 29.574164 | I19: =BalSheet!I18 -> 34.010288 | J19: =BalSheet!J18 -> 39.451935
B20: =BalSheet!B19 -> Inventories | E20: =BalSheet!E19 -> 6.014 | F20: =BalSheet!F19 -> 6.9362291 | G20: =BalSheet!G19 -> 7.8203817 | H20: =BalSheet!H19 -> 8.8556834 | I20: =BalSheet!I19 -> 10.115552 | J20: =BalSheet!J19 -> 11.654598
B21: Other current assets | E21: =BalSheet!E20 -> 21.801 | F21: =BalSheet!F20 -> 25.310961 | G21: =BalSheet!G20 -> 28.727941 | H21: =BalSheet!H20 -> 32.749852 | I21: =BalSheet!I20 -> 37.66233 | J21: =BalSheet!J20 -> 43.688303
B22: Accounts payables | E22: =BalSheet!E31 -> 112.036 | F22: =BalSheet!F31 -> 129.21639 | G22: =BalSheet!G31 -> 145.68744 | H22: =BalSheet!H31 -> 164.97429 | I22: =BalSheet!I31 -> 188.44462 | J22: =BalSheet!J31 -> 217.11582
B23: Other current liabilities | E23: =BalSheet!E32 -> 75.277 | F23: =BalSheet!F32 -> 87.396597 | G23: =BalSheet!G32 -> 99.195138 | H23: =BalSheet!H32 -> 113.08246 | I23: =BalSheet!I32 -> 130.04483 | J23: =BalSheet!J32 -> 150.852
A24: * | B24: OWC | E24: =SUM(E18:E21)-SUM(E22:E23) -> -114.75884 | F24: =SUM(F18:F21)-SUM(F22:F23) -> -132.42363 | G24: =SUM(G18:G21)-SUM(G22:G23) -> -149.3799 | H24: =SUM(H18:H21)-SUM(H22:H23) -> -169.24324 | I24: =SUM(I18:I21)-SUM(I22:I23) -> -193.4224 | J24: =SUM(J18:J21)-SUM(J22:J23) -> -222.96949
B25: Change in OWC | F25: =E24-F24 -> 17.66479 | G25: =F24-G24 -> 16.956271 | H25: =G24-H24 -> 19.863338 | I25: =H24-I24 -> 24.17916 | J25: =I24-J24 -> 29.547086

Sheet Debt
A1: =CoName -> Shake Shack, Inc. | C1: Hist. | D1: Hist. | E1: Hist. | F1: Proj. | G1: Proj. | H1: Proj. | I1: Proj. | J1: Proj.
A2: Assumptions | C2: 2022 | D2: =C2+1 -> 2023 | E2: =D2+1 -> 2024 | F2: =E2+1 -> 2025 | G2: =F2+1 -> 2026 | H2: =G2+1 -> 2027 | I2: =H2+1 -> 2028 | J2: =I2+1 -> 2029
B4: Interest rate on revolver | F4: =Assumptions!F22 -> 0.05 | G4: =Assumptions!G22 -> 0.05 | H4: =Assumptions!H22 -> 0.05 | I4: =Assumptions!I22 -> 0.05 | J4: =Assumptions!J22 -> 0.05
B5: Interest rate on long-term debt | F5: =Assumptions!F23 -> 0.05 | G5: =Assumptions!G23 -> 0.05 | H5: =Assumptions!H23 -> 0.05 | I5: =Assumptions!I23 -> 0.05 | J5: =Assumptions!J23 -> 0.05
B6: Interest rate on cash | F6: =Assumptions!F24 -> 0.04 | G6: =Assumptions!G24 -> 0.04 | H6: =Assumptions!H24 -> 0.04 | I6: =Assumptions!I24 -> 0.04 | J6: =Assumptions!J24 -> 0.04
B8: Issuance of long-term debt | F8: =Assumptions!F26 -> 0 | G8: =Assumptions!G26 -> 0 | H8: =Assumptions!H26 -> 0 | I8: =Assumptions!I26 -> 0 | J8: =Assumptions!J26 -> 0
B9: Repayment of long-term debt | F9: =Assumptions!F27 -> 0 | G9: =Assumptions!G27 -> 0 | H9: =Assumptions!H27 -> 0 | I9: =Assumptions!I27 -> 0 | J9: =Assumptions!J27 -> 0
A11: Revolver | C11: =C2 -> 2022 | D11: =D2 -> 2023 | E11: =E2 -> 2024 | F11: =F2 -> 2025 | G11: =G2 -> 2026 | H11: =H2 -> 2027 | I11: =I2 -> 2028 | J11: =J2 -> 2029
B12: Balance | F12: 0 | G12: 0 | H12: 0 | I12: 0 | J12: 0
B13: Interest rate
B14: Interest expense
A16: Long term debt | C16: =C11 -> 2022 | D16: =D11 -> 2023 | E16: =E11 -> 2024 | F16: =F11 -> 2025 | G16: =G11 -> 2026 | H16: =H11 -> 2027 | I16: =I11 -> 2028 | J16: =J11 -> 2029
B17: Beginning balance | F17: =E20 -> 246.683 | G17: =F20 -> 246.683 | H17: =G20 -> 246.683 | I17: =H20 -> 246.683 | J17: =I20 -> 246.683
B18: Issuance | F18: =F8 -> 0 | G18: =G8 -> 0 | H18: =H8 -> 0 | I18: =I8 -> 0 | J18: =J8 -> 0
B19: Repayment | F19: =F9 -> 0 | G19: =G9 -> 0 | H19: =H9 -> 0 | I19: =I9 -> 0 | J19: =J9 -> 0
B20: Ending balance | E20: =BalSheet!E35 -> 246.683 | F20: =SUM(F17:F19) -> 246.683 | G20: =SUM(G17:G19) -> 246.683 | H20: =SUM(H17:H19) -> 246.683 | I20: =SUM(I17:I19) -> 246.683 | J20: =SUM(J17:J19) -> 246.683
B21: Interest rate | F21: =F5 -> 0.05 | G21: =G5 -> 0.05 | H21: =H5 -> 0.05 | I21: =I5 -> 0.05 | J21: =J5 -> 0.05
B22: Interest expense | F22: =F20*-F21 -> -12.33415 | G22: =G20*-G21 -> -12.33415 | H22: =H20*-H21 -> -12.33415 | I22: =I20*-I21 -> -12.33415 | J22: =J20*-J21 -> -12.33415
A24: Debt summary | C24: =C16 -> 2022 | D24: =D16 -> 2023 | E24: =E16 -> 2024 | F24: =F16 -> 2025 | G24: =G16 -> 2026 | H24: =H16 -> 2027 | I24: =I16 -> 2028 | J24: =J16 -> 2029
B25: Revolver | F25: =F12 -> 0 | G25: =G12 -> 0 | H25: =H12 -> 0 | I25: =I12 -> 0 | J25: =J12 -> 0
B26: Total long term debt | F26: =F20 -> 246.683 | G26: =G20 -> 246.683 | H26: =H20 -> 246.683 | I26: =I20 -> 246.683 | J26: =J20 -> 246.683
B27: Total debt | F27: =SUM(F25:F26) -> 246.683 | G27: =SUM(G25:G26) -> 246.683 | H27: =SUM(H25:H26) -> 246.683 | I27: =SUM(I25:I26) -> 246.683 | J27: =SUM(J25:J26) -> 246.683
B28: Total interest expense | F28: =F22 -> -12.33415 | G28: =G22 -> -12.33415 | H28: =H22 -> -12.33415 | I28: =I22 -> -12.33415 | J28: =J22 -> -12.33415
A30: Interest income | C30: =C11 -> 2022 | D30: =D11 -> 2023 | E30: =E11 -> 2024 | F30: =F11 -> 2025 | G30: =G11 -> 2026 | H30: =H11 -> 2027 | I30: =I11 -> 2028 | J30: =J11 -> 2029
B31: Excess Cash | F31: =BalSheet!F17 -> 404.24961 | G31: =BalSheet!G17 -> 519.04419 | H31: =BalSheet!H17 -> 661.52897 | I31: =BalSheet!I17 -> 843.81206 | J31: =BalSheet!J17 -> 1078.197
B32: Interest rate | F32: =F6 -> 0.04 | G32: =G6 -> 0.04 | H32: =H6 -> 0.04 | I32: =I6 -> 0.04 | J32: =J6 -> 0.04
B33: Interest income | F33: =F31*F32 -> 16.169984 | G33: =G31*G32 -> 20.761768 | H33: =H31*H32 -> 26.461159 | I33: =I31*I32 -> 33.752482 | J33: =J31*J32 -> 43.127881

Sheet IncState
A1: =CoName -> Shake Shack, Inc. | C1: Hist. | D1: Hist. | E1: Hist. | F1: Proj. | G1: Proj. | H1: Proj. | I1: Proj. | J1: Proj.
A2: Assumptions | C2: 2022 | D2: =C2+1 -> 2023 | E2: =D2+1 -> 2024 | F2: =E2+1 -> 2025 | G2: =F2+1 -> 2026 | H2: =G2+1 -> 2027 | I2: =H2+1 -> 2028 | J2: =I2+1 -> 2029
B4: Revenue growth | F4: =Assumptions!F10 -> 0.161 | G4: =Assumptions!G10 -> 0.135 | H4: =Assumptions!H10 -> 0.14 | I4: =Assumptions!I10 -> 0.15 | J4: =Assumptions!J10 -> 0.16
B5: Cost of goods sold as % of sales | F5: =Assumptions!F11 -> 0.7535294 | G5: =Assumptions!G11 -> 0.7485294 | H5: =Assumptions!H11 -> 0.7435294 | I5: =Assumptions!I11 -> 0.7385294 | J5: =Assumptions!J11 -> 0.7335294
B6: SG&A % of sales | F6: =Assumptions!F12 -> 0.20824469 | G6: =Assumptions!G12 -> 0.20324469 | H6: =Assumptions!H12 -> 0.19824469 | I6: =Assumptions!I12 -> 0.19324469 | J6: =Assumptions!J12 -> 0.18824469
B7: Amortization amount | F7: =Assumptions!F13 -> 0 | G7: =Assumptions!G13 -> 0 | H7: =Assumptions!H13 -> 0 | I7: =Assumptions!I13 -> 0 | J7: =Assumptions!J13 -> 0
B8: Non recurring items, amount | F8: =Assumptions!F14 -> 0 | G8: =Assumptions!G14 -> 0 | H8: =Assumptions!H14 -> 0 | I8: =Assumptions!I14 -> 0 | J8: =Assumptions!J14 -> 0
B9: Other income (expense), amt | F9: =Assumptions!F15 -> 0 | G9: =Assumptions!G15 -> 0 | H9: =Assumptions!H15 -> 0 | I9: =Assumptions!I15 -> 0 | J9: =Assumptions!J15 -> 0
B10: Effective tax rate | F10: =Assumptions!F16 -> 0.24122869 | G10: =Assumptions!G16 -> 0.24122869 | H10: =Assumptions!H16 -> 0.24122869 | I10: =Assumptions!I16 -> 0.24122869 | J10: =Assumptions!J16 -> 0.24122869
B11: Basic WASO | F11: =Assumptions!F17 -> 39.83 | G11: =Assumptions!G17 -> 39.83 | H11: =Assumptions!H17 -> 39.83 | I11: =Assumptions!I17 -> 39.83 | J11: =Assumptions!J17 -> 39.83
B12: Diluted WASO | F12: =Assumptions!F18 -> 44.203 | G12: =Assumptions!G18 -> 44.203 | H12: =Assumptions!H18 -> 44.203 | I12: =Assumptions!I18 -> 44.203 | J12: =Assumptions!J18 -> 44.203
A14: Income statement | C14: =C34 -> 44926 | D14: =D34 -> 45291 | E14: =E34 -> 45657 | F14: =F34 -> 46022 | G14: =G34 -> 46022 | H14: =H34 -> 46022 | I14: =I34 -> 46022 | J14: =J34 -> 46022
B15: Revenue | C15: 900.486 | D15: =1087.533 -> 1087.533 | E15: 1252.608 | F15: =E15*(1+F4) -> 1454.2779 | G15: =F15*(1+G4) -> 1650.6054 | H15: =G15*(1+H4) -> 1881.6902 | I15: =H15*(1+I4) -> 2163.9437 | J15: =I15*(1+J4) -> 2510.1747
B16: COGS | C16: =261.584+257.358+129.65+68.508 -> 717.1 | D16: =305.041+304.254+149.449+79.846 -> 838.59 | E16: =339.94+178.381+93.069+338.75 -> 950.14 | F16: =F15*F5 -> 1095.8412 | G16: =G15*G5 -> 1235.5267 | H16: =H15*H5 -> 1399.092 | I16: =I15*I5 -> 1598.136 | J16: =J15*J5 -> 1841.2869
B17: SG&A | C17: =120.009+15.05+72.796 -> 207.855 | D17: =129.542+91.242+19.231 -> 240.015 | E17: =149.097+102.468+15.547 -> 267.112 | F17: =F15*F6 -> 302.84564 | G17: =G15*G6 -> 335.47678 | H17: =H15*H6 -> 373.03508 | I17: =I15*I6 -> 418.17062 | J17: =J15*J6 -> 472.52704
A18: * | B18: EBIT | C18: =C15-SUM(C16:C17) -> -24.469 | D18: =D15-SUM(D16:D17) -> 8.928 | E18: =E15-SUM(E16:E17) -> 35.356 | F18: =F15-SUM(F16:F17) -> 55.591095 | G18: =G15-SUM(G16:G17) -> 79.601947 | H18: =H15-SUM(H16:H17) -> 109.56312 | I18: =I15-SUM(I16:I17) -> 147.63703 | J18: =J15-SUM(J16:J17) -> 196.3607
B20: Depreciation | C20: =72.796 -> 72.796 | D20: 91.242 | E20: 149.097 | F20: =Calcs!F8 -> 131.6794 | G20: =Calcs!G8 -> 134.15643 | H20: =Calcs!H8 -> 137.91836 | I20: =Calcs!I8 -> 142.9639 | J20: =Calcs!J8 -> 149.41677
B21: Amortization | C21: 0 | D21: 0 | E21: 0 | F21: =F7 -> 0 | G21: =G7 -> 0 | H21: =H7 -> 0 | I21: =I7 -> 0 | J21: =J7 -> 0
A22: * | B22: EBITDA | C22: =SUM(C18,C20:C21) -> 48.327 | D22: =SUM(D18,D20:D21) -> 100.17 | E22: =SUM(E18,E20:E21) -> 184.453 | F22: =SUM(F18,F20:F21) -> 187.27049 | G22: =SUM(G18,G20:G21) -> 213.75837 | H22: =SUM(H18,H20:H21) -> 247.48148 | I22: =SUM(I18,I20:I21) -> 290.60093 | J22: =SUM(J18,J20:J21) -> 345.77746
B24: Non-recurring items | C24: -2.425 | D24: -3.007 | E24: -32.368 | F24: =F8 -> 0 | G24: =G8 -> 0 | H24: =H8 -> 0 | I24: =I8 -> 0 | J24: =J8 -> 0
B25: Other income (expense) | C25: 4.127 | D25: 12.776 | E25: 13.251 | F25: =F9 -> 0 | G25: =G9 -> 0 | H25: =H9 -> 0 | I25: =I9 -> 0 | J25: =J9 -> 0
B27: Interest income | F27: =IF(circ=1,Debt!F33,0) -> 0 | G27: =IF(circ=1,Debt!G33,0) -> 0 | H27: =IF(circ=1,Debt!H33,0) -> 0 | I27: =IF(circ=1,Debt!I33,0) -> 0 | J27: =IF(circ=1,Debt!J33,0) -> 0
B28: Interest expense | C28: -1.518 | D28: -1.717 | E28: -2.045 | F28: =IF(circ=1,Debt!F22,0) -> 0 | G28: =IF(circ=1,Debt!G22,0) -> 0 | H28: =IF(circ=1,Debt!H22,0) -> 0 | I28: =IF(circ=1,Debt!I22,0) -> 0 | J28: =IF(circ=1,Debt!J22,0) -> 0
A30: * | B30: Pretax Income | C30: =C18+SUM(C25:C28) -> -21.86 | D30: =D18+SUM(D25:D28) -> 19.987 | E30: =E18+SUM(E24:E28) -> 14.194 | F30: =F18+SUM(F24:F28) -> 55.591095 | G30: =G18+SUM(G24:G28) -> 79.601947 | H30: =H18+SUM(H24:H28) -> 109.56312 | I30: =I18+SUM(I24:I28) -> 147.63703 | J30: =J18+SUM(J24:J28) -> 196.3607
B32: Tax expense | C32: -1.18 | D32: 0.726 | E32: 3.424 | F32: =F10*F30 -> 13.410167 | G32: =G10*G30 -> 19.202273 | H32: =H10*H30 -> 26.429768 | I32: =I10*I30 -> 35.614286 | J32: =J10*J30 -> 47.367833
A33: * | B33: Net income | C33: =C30-C32 -> -20.68 | D33: =D30-D32 -> 19.261 | E33: =E30-E32 -> 10.77 | F33: =F30-F32 -> 42.180928 | G33: =G30-G32 -> 60.399674 | H33: =H30-H32 -> 83.133353 | I33: =I30-I32 -> 112.02274 | J33: =J30-J32 -> 148.99286
A34: Shareholder information | C34: 44926 | D34: 45291 | E34: 45657 | F34: 46022 | G34: 46022 | H34: 46022 | I34: 46022 | J34: 46022
B35: Basic WASO | C35: 39.237 | D35: 39.419 | E35: 39.83 | F35: =F11 -> 39.83 | G35: =G11 -> 39.83 | H35: =H11 -> 39.83 | I35: =I11 -> 39.83 | J35: =J11 -> 39.83
B36: Diluted WASO | C36: 39.237 | D36: 43.899 | E36: 44.203 | F36: 44.203 | G36: 44.203 | H36: 44.203 | I36: 44.203 | J36: 44.203
B37: Basic earnings per share | C37: =C33/C35 -> -0.52705355 | D37: =D33/D35 -> 0.48862224 | E37: =E33/E35 -> 0.2703992 | F37: =F33/F35 -> 1.0590241 | G37: =G33/G35 -> 1.5164367 | H37: =H33/H35 -> 2.0872044 | I37: =I33/I35 -> 2.8125217 | J37: =J33/J35 -> 3.7407196
A38: * | B38: Diluted earnings per share | C38: =C33/C36 -> -0.52705355 | D38: =D33/D36 -> 0.43875715 | E38: =E33/E36 -> 0.24364862 | F38: =F33/F36 -> 0.95425487 | G38: =G33/G36 -> 1.3664157 | H38: =H33/H36 -> 1.8807174 | I38: =I33/I36 -> 2.5342791 | J38: =J33/J36 -> 3.3706505

Sheet BalSheet
A1: =CoName -> Shake Shack, Inc. | C1: Hist. | D1: Hist. | E1: Hist. | F1: Proj. | G1: Proj. | H1: Proj. | I1: Proj. | J1: Proj.
A2: Assumptions | C2: 2022 | D2: =C2+1 -> 2023 | E2: =D2+1 -> 2024 | F2: =E2+1 -> 2025 | G2: =F2+1 -> 2026 | H2: =G2+1 -> 2027 | I2: =H2+1 -> 2028 | J2: =I2+1 -> 2029
B4: Operating Cash % of sales | F4: =Assumptions!F37 -> 0.02 | G4: =F4 -> 0.02 | H4: =G4 -> 0.02 | I4: =H4 -> 0.02 | J4: =I4 -> 0.02
B5: Accounts receivable % of sales | F5: =Assumptions!F38 -> 0.015716808 | G5: =Assumptions!G38 -> 0.015716808 | H5: =Assumptions!H38 -> 0.015716808 | I5: =Assumptions!I38 -> 0.015716808 | J5: =Assumptions!J38 -> 0.015716808
B6: Inventories % of COGS | F6: =Assumptions!F39 -> 0.0063295935 | G6: =Assumptions!G39 -> 0.0063295935 | H6: =Assumptions!H39 -> 0.0063295935 | I6: =Assumptions!I39 -> 0.0063295935 | J6: =Assumptions!J39 -> 0.0063295935
B7: Other current assets % of sales | F7: =Assumptions!F40 -> 0.017404487 | G7: =Assumptions!G40 -> 0.017404487 | H7: =Assumptions!H40 -> 0.017404487 | I7: =Assumptions!I40 -> 0.017404487 | J7: =Assumptions!J40 -> 0.017404487
B9: Other long-term assets % of sales | F9: =Assumptions!F43 -> 0.28144799 | G9: =Assumptions!G43 -> 0.28144799 | H9: =Assumptions!H43 -> 0.28144799 | I9: =Assumptions!I43 -> 0.28144799 | J9: =Assumptions!J43 -> 0.28144799
B11: Accounts payable/Accural % of COGS | F11: =Assumptions!F47 -> 0.11791525 | G11: =Assumptions!G47 -> 0.11791525 | H11: =Assumptions!H47 -> 0.11791525 | I11: =Assumptions!I47 -> 0.11791525 | J11: =Assumptions!J47 -> 0.11791525
B12: Other current liabilities % of sales | F12: =Assumptions!F48 -> 0.060096215 | G12: =Assumptions!G48 -> 0.060096215 | H12: =Assumptions!H48 -> 0.060096215 | I12: =Assumptions!I48 -> 0.060096215 | J12: =Assumptions!J48 -> 0.060096215
B13: Other long-term liabilities % of sales | F13: =Assumptions!F49 -> 0.61419774 | G13: =Assumptions!G49 -> 0.61419774 | H13: =Assumptions!H49 -> 0.61419774 | I13: =Assumptions!I49 -> 0.61419774 | J13: =Assumptions!J49 -> 0.61419774
A15: Balance sheet | C15: =C2 -> 2022 | D15: =D2 -> 2023 | E15: =E2 -> 2024 | F15: =F2 -> 2025 | G15: =G2 -> 2026 | H15: =H2 -> 2027 | I15: =I2 -> 2028 | J15: =J2 -> 2029
B16: Operating Cash | C16: =2%*IncState!C15 -> 18.00972 | D16: =2%*IncState!D15 -> 21.75066 | E16: =2%*IncState!E15 -> 25.05216 | F16: =F4*IncState!F15 -> 29.085558 | G16: =G4*IncState!G15 -> 33.012108 | H16: =H4*IncState!H15 -> 37.633803 | I16: =I4*IncState!I15 -> 43.278874 | J16: =J4*IncState!J15 -> 50.203493
B17: Excess cash | C17: =230.521+80.707-C16 -> 293.21828 | D17: =224.653-D16+68.561 -> 271.46334 | E17: =320.714-E16 -> 295.66184 | F17: =MAX(CashFlow!F23,0) -> 404.24961 | G17: =MAX(CashFlow!G23,0) -> 519.04419 | H17: =MAX(CashFlow!H23,0) -> 661.52897 | I17: =MAX(CashFlow!I23,0) -> 843.81206 | J17: =MAX(CashFlow!J23,0) -> 1078.197
B18: Accounts receivable | C18: 13.877 | D18: 16.847 | E18: 19.687 | F18: =F5*IncState!F15 -> 22.856607 | G18: =G5*IncState!G15 -> 25.942249 | H18: =H5*IncState!H15 -> 29.574164 | I18: =I5*IncState!I15 -> 34.010288 | J18: =J5*IncState!J15 -> 39.451935
B19: Inventories | C19: 4.184 | D19: 5.404 | E19: 6.014 | F19: =F6*IncState!F16 -> 6.9362291 | G19: =G6*IncState!G16 -> 7.8203817 | H19: =H6*IncState!H16 -> 8.8556834 | I19: =I6*IncState!I16 -> 10.115552 | J19: =J6*IncState!J16 -> 11.654598
B20: Other current assets | C20: 14.699 | D20: 18.967 | E20: 21.801 | F20: =F7*IncState!F15 -> 25.310961 | G20: =G7*IncState!G15 -> 28.727941 | H20: =H7*IncState!H15 -> 32.749852 | I20: =I7*IncState!I15 -> 37.66233 | J20: =J7*IncState!J15 -> 43.688303
B21: Total current assets | C21: =SUM(C16:C20) -> 343.988 | D21: =SUM(D16:D20) -> 334.432 | E21: =SUM(E16:E20) -> 368.216 | F21: =SUM(F16:F20) -> 488.43897 | G21: =SUM(G16:G20) -> 614.54687 | H21: =SUM(H16:H20) -> 770.34247 | I21: =SUM(I16:I20) -> 968.8791 | J21: =SUM(J16:J20) -> 1223.1953
B23: Property, plant & equipment, net | C23: =467.031+367.488 -> 834.519 | D23: =530.995+398.296 -> 929.291 | E23: =551.6+424.611 -> 976.211 | F23: =Calcs!F9 -> 994.57455 | G23: =Calcs!G9 -> 1022.4638 | H23: =Calcs!H9 -> 1059.8692 | I23: =Calcs!I9 -> 1107.7078 | J23: =Calcs!J9 -> 1167.071
B24: Intangible assets | C24: 317.626 | D24: =326.208 -> 326.208 | E24: 0 | F24: =E24-IncState!F21 -> 0 | G24: =F24-IncState!G21 -> 0 | H24: =G24-IncState!H21 -> 0 | I24: =H24-IncState!I21 -> 0 | J24: =I24-IncState!J21 -> 0
B25: Other assets | C25: 15.817 | D25: 15.926 | E25: =341.586+10.958 -> 352.544 | F25: =F9*IncState!F15 -> 409.30358 | G25: =G9*IncState!G15 -> 464.55957 | H25: =H9*IncState!H15 -> 529.59791 | I25: =I9*IncState!I15 -> 609.03759 | J25: =J9*IncState!J15 -> 706.48361
B26: Total non-current assets | C26: =SUM(C23:C25) -> 1167.962 | D26: =SUM(D23:D25) -> 1271.425 | E26: =SUM(E23:E25) -> 1328.755 | F26: =SUM(F23:F25) -> 1403.8781 | G26: =SUM(G23:G25) -> 1487.0234 | H26: =SUM(H23:H25) -> 1589.4671 | I26: =SUM(I23:I25) -> 1716.7454 | J26: =SUM(J23:J25) -> 1873.5546
A28: * | B28: TOTAL ASSETS | C28: =SUM(C26,C21) -> 1511.95 | D28: =SUM(D26,D21) -> 1605.857 | E28: =SUM(E26,E21) -> 1696.971 | F28: =SUM(F26,F21) -> 1892.3171 | G28: =SUM(G26,G21) -> 2101.5703 | H28: =SUM(H26,H21) -> 2359.8095 | I28: =SUM(I26,I21) -> 2685.6245 | J28: =SUM(J26,J21) -> 3096.75
B30: Revolver/Short term debt | C30: 0 | D30: 0 | E30: 0 | F30: =MIN(CashFlow!F23,0) -> 0 | G30: =MIN(CashFlow!G23,0) -> 0 | H30: =MIN(CashFlow!H23,0) -> 0 | I30: =MIN(CashFlow!I23,0) -> 0 | J30: =MIN(CashFlow!J23,0) -> 0
B31: Accounts payable/Accurals | C31: =20.407+47.945+17.576 -> 85.928 | D31: =22.273+54.742+20.945 -> 97.96 | E31: =23.609+63.005+25.422 -> 112.036 | F31: =F11*IncState!F16 -> 129.21639 | G31: =G11*IncState!G16 -> 145.68744 | H31: =H11*IncState!H16 -> 164.97429 | I31: =I11*IncState!I16 -> 188.44462 | J31: =J11*IncState!J16 -> 217.11582
B32: Other current liabilities | C32: =42.238+19.552 -> 61.79 | D32: =49.004+17.103 -> 66.107 | E32: =55.739+19.538 -> 75.277 | F32: =F12*IncState!F15 -> 87.396597 | G32: =G12*IncState!G15 -> 99.195138 | H32: =H12*IncState!H15 -> 113.08246 | I32: =I12*IncState!I15 -> 130.04483 | J32: =J12*IncState!J15 -> 150.852
B33: Total current liabilities | C33: =SUM(C30:C32) -> 147.718 | D33: =SUM(D30:D32) -> 164.067 | E33: =SUM(E30:E32) -> 187.313 | F33: =SUM(F30:F32) -> 216.61299 | G33: =SUM(G30:G32) -> 244.88258 | H33: =SUM(H30:H32) -> 278.05674 | I33: =SUM(I30:I32) -> 318.48944 | J33: =SUM(J30:J32) -> 367.96781
B35: Long-term debt, including current maturities | C35: 244.589 | D35: =245.636 -> 245.636 | E35: 246.683 | F35: =Debt!F20 -> 246.683 | G35: =Debt!G20 -> 246.683 | H35: =Debt!H20 -> 246.683 | I35: =Debt!I20 -> 246.683 | J35: =Debt!J20 -> 246.683
B36: Other long-term liabilities | C36: =427.227+234.893+20.687 -> 682.807 | D36: =464.533+235.613+26.638 -> 726.784 | E36: =494.499+247.017+27.833 -> 769.349 | F36: =F13*IncState!F15 -> 893.21419 | G36: =G13*IncState!G15 -> 1013.7981 | H36: =H13*IncState!H15 -> 1155.7298 | I36: =I13*IncState!I15 -> 1329.0893 | J36: =J13*IncState!J15 -> 1541.7436
B37: Total non-current liabilities | C37: =SUM(C35:C36) -> 927.396 | D37: =SUM(D35:D36) -> 972.42 | E37: =SUM(E35:E36) -> 1016.032 | F37: =SUM(F35:F36) -> 1139.8972 | G37: =SUM(G35:G36) -> 1260.4811 | H37: =SUM(H35:H36) -> 1402.4128 | I37: =SUM(I35:I36) -> 1575.7723 | J37: =SUM(J35:J36) -> 1788.4266
B39: Equity | C39: 436.836 | D39: 469.37 | E39: 493.626 | F39: =Calcs!F16 -> 535.80693 | G39: =Calcs!G16 -> 596.2066 | H39: =Calcs!H16 -> 679.33995 | I39: =Calcs!I16 -> 791.36269 | J39: =Calcs!J16 -> 940.35556
A40: * | B40: TOTAL LIABILITIES & EQUITY | C40: =SUM(C39,C37,C33) -> 1511.95 | D40: =SUM(D39,D37,D33) -> 1605.857 | E40: =SUM(E39,E37,E33) -> 1696.971 | F40: =SUM(F39,F37,F33) -> 1892.3171 | G40: =SUM(G39,G37,G33) -> 2101.5703 | H40: =SUM(H39,H37,H33) -> 2359.8095 | I40: =SUM(I39,I37,I33) -> 2685.6245 | J40: =SUM(J39,J37,J33) -> 3096.75
A42: * | B42: Balance check | C42: =C40-C28 -> 0 | D42: =D40-D28 -> 0 | E42: =E40-E28 -> 0 | F42: =F40-F28 -> 0 | G42: =G40-G28 -> 0 | H42: =H40-H28 -> 0 | I42: =I40-I28 -> 0 | J42: =J40-J28 -> 0

Sheet CashFlow
A1: =CoName -> Shake Shack, Inc. | C1: Hist. | D1: Hist. | E1: Hist. | F1: Proj. | G1: Proj. | H1: Proj. | I1: Proj. | J1: Proj.
A2: Cash flow statement | C2: 2022 | D2: =C2+1 -> 2023 | E2: =D2+1 -> 2024 | F2: =E2+1 -> 2025 | G2: =F2+1 -> 2026 | H2: =G2+1 -> 2027 | I2: =H2+1 -> 2028 | J2: =I2+1 -> 2029
B3: Net Income | F3: =IncState!F33 -> 42.180928 | G3: =IncState!G33 -> 60.399674 | H3: =IncState!H33 -> 83.133353 | I3: =IncState!I33 -> 112.02274 | J3: =IncState!J33 -> 148.99286
B4: Depreciation | F4: =IncState!F20 -> 131.6794 | G4: =IncState!G20 -> 134.15643 | H4: =IncState!H20 -> 137.91836 | I4: =IncState!I20 -> 142.9639 | J4: =IncState!J20 -> 149.41677
B5: Amortization | F5: =IncState!F21 -> 0 | G5: =IncState!G21 -> 0 | H5: =IncState!H21 -> 0 | I5: =IncState!I21 -> 0 | J5: =IncState!J21 -> 0
B6: (inc) / dec in OWC | F6: =Calcs!F25 -> 17.66479 | G6: =Calcs!G25 -> 16.956271 | H6: =Calcs!H25 -> 19.863338 | I6: =Calcs!I25 -> 24.17916 | J6: =Calcs!J25 -> 29.547086
B7: (inc) / dec in LT assets | F7: =BalSheet!E25-BalSheet!F25 -> -56.759584 | G7: =BalSheet!F25-BalSheet!G25 -> -55.255984 | H7: =BalSheet!G25-BalSheet!H25 -> -65.038339 | I7: =BalSheet!H25-BalSheet!I25 -> -79.439686 | J7: =BalSheet!I25-BalSheet!J25 -> -97.446015
B8: inc / (dec) in LT liabilities | F8: =BalSheet!F36-BalSheet!E36 -> 123.86519 | G8: =BalSheet!G36-BalSheet!F36 -> 120.58392 | H8: =BalSheet!H36-BalSheet!G36 -> 141.93173 | I8: =BalSheet!I36-BalSheet!H36 -> 173.35948 | J8: =BalSheet!J36-BalSheet!I36 -> 212.65429
B9: CFFO | F9: =SUM(F3:F8) -> 258.63072 | G9: =SUM(G3:G8) -> 276.8403 | H9: =SUM(H3:H8) -> 317.80845 | I9: =SUM(I3:I8) -> 373.08559 | J9: =SUM(J3:J8) -> 443.16499
B11: Capex | F11: =-Calcs!F7 -> -150.04295 | G11: =-Calcs!G7 -> -162.04572 | H11: =-Calcs!H7 -> -175.32367 | I11: =-Calcs!I7 -> -190.8025 | J11: =-Calcs!J7 -> -208.78003
B12: CFFI | F12: =SUM(F11) -> -150.04295 | G12: =SUM(G11) -> -162.04572 | H12: =SUM(H11) -> -175.32367 | I12: =SUM(I11) -> -190.8025 | J12: =SUM(J11) -> -208.78003
B14: Dividends Paid | F14: 0 | G14: 0 | H14: 0 | I14: 0 | J14: 0
B15: Share issuances | F15: =Calcs!F11 -> 0 | G15: =Calcs!G11 -> 0 | H15: =Calcs!H11 -> 0 | I15: =Calcs!I11 -> 0 | J15: =Calcs!J11 -> 0
B16: Debt Issuances | F16: =SUM(Debt!F8:F9) -> 0 | G16: =SUM(Debt!G8:G9) -> 0 | H16: =SUM(Debt!H8:H9) -> 0 | I16: =SUM(Debt!I8:I9) -> 0 | J16: =SUM(Debt!J8:J9) -> 0
B17: CFFF | F17: =SUM(F14:F16) -> 0 | G17: =SUM(G14:G16) -> 0 | H17: =SUM(H14:H16) -> 0 | I17: =SUM(I14:I16) -> 0 | J17: =SUM(J14:J16) -> 0
B19: Net changes in cash | F19: =SUM(F17,F12,F9) -> 108.58777 | G19: =SUM(G17,G12,G9) -> 114.79458 | H19: =SUM(H17,H12,H9) -> 142.48478 | I19: =SUM(I17,I12,I9) -> 182.28309 | J19: =SUM(J17,J12,J9) -> 234.38496
B21: Beginning cash | F21: =BalSheet!E17 -> 295.66184 | G21: =BalSheet!F17 -> 404.24961 | H21: =BalSheet!G17 -> 519.04419 | I21: =BalSheet!H17 -> 661.52897 | J21: =BalSheet!I17 -> 843.81206
B22: =B19 -> Net changes in cash | F22: =F19 -> 108.58777 | G22: =G19 -> 114.79458 | H22: =H19 -> 142.48478 | I22: =I19 -> 182.28309 | J22: =J19 -> 234.38496
B23: Ending cash | F23: =SUM(F21:F22) -> 404.24961 | G23: =SUM(G21:G22) -> 519.04419 | H23: =SUM(H21:H22) -> 661.52897 | I23: =SUM(I21:I22) -> 843.81206 | J23: =SUM(J21:J22) -> 1078.197

Sheet Free Cash Flow
A1: =CoName -> Shake Shack, Inc. | C1: Hist. | D1: Hist. | E1: Hist. | F1: Proj. | G1: Proj. | H1: Proj. | I1: Proj. | J1: Proj.
A2: Free Cash Flows | C2: 2022 | D2: =C2+1 -> 2023 | E2: =D2+1 -> 2024 | F2: =E2+1 -> 2025 | G2: =F2+1 -> 2026 | H2: =G2+1 -> 2027 | I2: =H2+1 -> 2028 | J2: =I2+1 -> 2029
A3: * | B3: Sales | F3: =IncState!F15 -> 1454.2779 | G3: =IncState!G15 -> 1650.6054 | H3: =IncState!H15 -> 1881.6902 | I3: =IncState!I15 -> 2163.9437 | J3: =IncState!J15 -> 2510.1747
B4: EBIT | F4: =IncState!F18 -> 55.591095 | G4: =IncState!G18 -> 79.601947 | H4: =IncState!H18 -> 109.56312 | I4: =IncState!I18 -> 147.63703 | J4: =IncState!J18 -> 196.3607
B5: Effective Tax Rate | F5: =Assumptions!F16 -> 0.24122869 | G5: =Assumptions!G16 -> 0.24122869 | H5: =Assumptions!H16 -> 0.24122869 | I5: =Assumptions!I16 -> 0.24122869 | J5: =Assumptions!J16 -> 0.24122869
A7: * | B7: NOPAT | F7: =F4*(1-F5) -> 42.180928 | G7: =G4*(1-G5) -> 60.399674 | H7: =H4*(1-H5) -> 83.133353 | I7: =I4*(1-I5) -> 112.02274 | J7: =J4*(1-J5) -> 148.99286
B8: Depreciation | F8: =CashFlow!F4 -> 131.6794 | G8: =CashFlow!G4 -> 134.15643 | H8: =CashFlow!H4 -> 137.91836 | I8: =CashFlow!I4 -> 142.9639 | J8: =CashFlow!J4 -> 149.41677
B9: Amortization | F9: =CashFlow!F5 -> 0 | G9: =CashFlow!G5 -> 0 | H9: =CashFlow!H5 -> 0 | I9: =CashFlow!I5 -> 0 | J9: =CashFlow!J5 -> 0
B10: (inc) / dec in OWC | F10: =CashFlow!F6 -> 17.66479 | G10: =CashFlow!G6 -> 16.956271 | H10: =CashFlow!H6 -> 19.863338 | I10: =CashFlow!I6 -> 24.17916 | J10: =CashFlow!J6 -> 29.547086
B11: (inc) / dec in other long-term assets | F11: =CashFlow!F7 -> -56.759584 | G11: =CashFlow!G7 -> -55.255984 | H11: =CashFlow!H7 -> -65.038339 | I11: =CashFlow!I7 -> -79.439686 | J11: =CashFlow!J7 -> -97.446015
B12: inc / (dec) other long-term liabilities | F12: =CashFlow!F8 -> 123.86519 | G12: =CashFlow!G8 -> 120.58392 | H12: =CashFlow!H8 -> 141.93173 | I12: =CashFlow!I8 -> 173.35948 | J12: =CashFlow!J8 -> 212.65429
B13: (Capex) | F13: =CashFlow!F12 -> -150.04295 | G13: =CashFlow!G12 -> -162.04572 | H13: =CashFlow!H12 -> -175.32367 | I13: =CashFlow!I12 -> -190.8025 | J13: =CashFlow!J12 -> -208.78003
A15: * | B15: Free Cash Flow | F15: =SUM(F7:F13) -> 108.58777 | G15: =SUM(G7:G13) -> 114.79458 | H15: =SUM(H7:H13) -> 142.48478 | I15: =SUM(I7:I13) -> 182.28309 | J15: =SUM(J7:J13) -> 234.38496

Sheet WACC
A1: =CoName -> Shake Shack, Inc.
A3: * | B3: WACC | G3: Comp | H3: Levered beta | I3: Gross debt | J3: Market cap | K3: Debt/Mcap | L3: MTR | M3: Unlevered beta
B4: Tax Rate | E4: =Assumptions!F16 -> 0.24122869 | L4: =E4 -> 0.24122869 | M4: =H4/((1+K4*(1-L4))) -> 0
B5: Risk free rate | E5: 0.041 | L5: =L4 -> 0.24122869 | M5: =H5/((1+K5*(1-L5))) -> 0
B6: Market risk Premium | E6: 0.05 | L6: =L5 -> 0.24122869 | M6: =H6/((1+K6*(1-L6))) -> 0
B7: Beta | E7: 1 | L7: =L6 -> 0.24122869 | M7: =H7/((1+K7*(1-L7))) -> 0
B8: Cost of Equity | E8: =E5+E6*E7 -> 0.091
B9: % Equity | E9: =1-E10 -> 0.77529558 | G9: Industry beta (average) | M9: =AVERAGE(M4:M7) -> 0
B10: % Debt | E10: =MAIN!F8/MAIN!F6 -> 0.22470442
B11: Cost of debt | E11: =Assumptions!F23 -> 0.05 | G11: Re-levered beta | M11: =M9*(1+E10*(1-E4)) -> 0
B12: Post tax cost of debt | E12: =E11*(1-E4) -> 0.037938566
A13: * | B13: WACC | E13: =WACC!E8*WACC!E9+WACC!E12*WACC!E10 -> 0.079076861
B14: Long Term growth rate | E14: 0.025

Sheet DCF Model
A1: =CoName -> Shake Shack, Inc. | D1: Proj. | E1: Proj. | F1: Proj. | G1: Proj. | H1: Proj.
A2: Discount Model Year count | D2: 0.5 | E2: =D2+1 -> 1.5 | F2: =E2+1 -> 2.5 | G2: =F2+1 -> 3.5 | H2: =G2+1 -> 4.5
B3: Discount Factor | D3: =1/(1+$K$17)^D2 -> 0.96266196 | E3: =1/(1+$K$17)^E2 -> 0.89211621 | F3: =1/(1+$K$17)^F2 -> 0.82674019 | G3: =1/(1+$K$17)^G2 -> 0.76615505 | H3: =1/(1+$K$17)^H2 -> 0.71000971
B4: PV FCF | D4: =D3*'Free Cash Flow'!F15 -> 104.53332 | E4: =E3*'Free Cash Flow'!G15 -> 102.41011 | F4: =F3*'Free Cash Flow'!H15 -> 117.79789 | G4: =G3*'Free Cash Flow'!I15 -> 139.65711 | H4: =H3*'Free Cash Flow'!J15 -> 166.4156 | I4: =(H4*(1+K18))/(K17-K18) -> 3154.3249
A6: Value Calculation | E6: Multiples Calculation
B7: Total PV of FCFs | C7: =SUM(D4:H4) -> 630.81402 | E7: Total PV of FCFs | G7: =C7 -> 630.81402
B8: PV of TV | C8: =I4*H3 -> 2239.6013 | E8: Multiple TV | G8: =G10*H3*IncState!J22 -> 3682.5804
B9: EV | C9: =SUM(C7:C8) -> 2870.4153 | E9: EV | G9: =SUM(G7:G8) -> 4313.3944
E10: Implied EBITDA multiple | G10: 15
B12: Cash & Cash Equiv | C12: =MAIN!F7 -> 357.757 | E12: Cash & Cash Equiv | G12: =C12 -> 357.757
B13: Debt & Claims | C13: =MAIN!F8 -> 787.717 | E13: Debt & Claims | G13: =C13 -> 787.717
B14: NCI | C14: 0 | E14: NCI | G14: =C14 -> 0
B15: Equity Value | C15: =C9+C12-SUM(C13:C14) -> 2440.4553 | E15: Equity Value | G15: =G9+G12-SUM(G13:G14) -> 3883.4344
B17: Diluted S/O | C17: =MAIN!F5 -> 42.688378 | E17: Diluted S/O | G17: =C17 -> 42.688378 | I17: WACC | K17: =WACC!E13 -> 0.079076861
A18: * | B18: Implied Share Price | C18: =C15/C17 -> 57.169081 | E18: Implied Share Price | G18: =G15/G17 -> 90.971701 | I18: Long Term growth rate | K18: 0.025
A20: Sensitivity analysis
C22: Discount rate variance | E22: 0.005 | H22: Discount rate variance | J22: 0.005
C23: Implied growth rate variance | E23: 0.0025 | H23: TV multiple variance | J23: 2
E25: LTGR | J25: Exit Mult.
C26: =C18 -> 57.169081 | D26: =E26-E23 -> 0.0225 | E26: 0.025 | F26: =E26+E23 -> 0.0275 | H26: =G18 -> 90.971701 | I26: =J26-J23 -> 13 | J26: 15 | K26: =J26+J23 -> 17
C27: =C28+$E$22 -> 0.089076861 | D27: 43.458636 | E27: 45.084436 | F27: 46.842251 | H27: =C27 -> 0.089076861 | I27: 76.059942 | J27: 87.094467 | K27: 98.128992
C28: =C29+$E$22 -> 0.084076861 | D28: 48.6069 | E28: 50.584983 | F28: 52.73788 | H28: =C28 -> 0.084076861 | I28: 77.743526 | J28: 89.008927 | K28: 100.27433
C29: 0.079076861 | D29: 54.728514 | E29: 57.169081 | F29: 59.846243 | H29: =C29 -> 0.079076861 | I29: 79.469491 | J29: 90.971701 | K29: 102.47391
C30: =C29-$E$22 -> 0.074076861 | D30: 62.110806 | E30: 65.172385 | F30: 68.562623 | H30: =C30 -> 0.074076861 | I30: 81.239117 | J30: 92.984249 | K30: 104.72938
C31: =C30-$E$22 -> 0.069076861 | D31: 71.164771 | E31: 75.083162 | F31: 79.472776 | H31: =C31 -> 0.069076861 | I31: 83.05373 | J31: 95.048083 | K31: 107.04244
