Workbook
Name Ccy: MAIN!$C$6
Name circ: MAIN!$C$9
Name CoName: MAIN!$C$4
Name g: #REF!
Name IQ_CH: 110000
Name IQ_CQ: 5000
Name IQ_CY: 10000
Name IQ_DAILY: 500000
Name IQ_FH: 100000
Name IQ_FQ: 500
Name IQ_FY: 1000
Name IQ_LTM: 2000
Name IQ_MONTH: 15000
Name IQ_NTM: 6000
Name IQ_WEEK: 50000
Name IQ_YTD: 3000
Name OpCase: [1]DCF!$E$98
Name ScenarioREV: Assumptions!$D$4
Name TTS: #REF!
Name Units: MAIN!$C$7

Sheet MAIN
A1: =CoName -> Texas Roadhouse Inc
A2: Model Details
B4: Company name | C4: Texas Roadhouse Inc | E4: Current Stock Price | F4: 170 | H4: Operating Case One | I4: Perpetuity | J4: Terminal Mult | K4: DDM | L4: Average
B5: Latest BS date | C5: 247.43 | E5: Diluted s/o | F5: 66146 | H5: Implied Price | I5: ='DCF Model'!C18 -> 187.20703 | J5: ='DCF Model'!G18 -> 286.15222 | K5: ='DCF Model'!H18 -> 0 | L5: =AVERAGE(I5:K5) -> 157.78642
B6: Currency | C6: USD | E6: Mkt Cap | F6: =F5*F4 -> 11244820 | H6: Difference | I6: =I5/$F$4-1 -> 0.10121785 | J6: =J5/$F$4-1 -> 0.68324838 | K6: =K5/$F$4-1 -> -1 | L6: =L5/$F$4-1 -> -0.07184459
B7: Units | C7: m | E7: Cash | F7: 108172
B8: Analyst name | C8: Alan Chen | E8: Debt | F8: =903788+29956 -> 933744
B9: Circular switch | C9: 0 | E9: EV | F9: =F6-F7+F8 -> 12070392

Sheet Quarterly Projections

Sheet Assumptions
A1: =CoName -> Texas Roadhouse Inc | C1: Hist. | D1: Hist. | E1: Hist. | F1: Proj. | G1: Proj. | H1: Proj. | I1: Proj. | J1: Proj.
A2: * | B2: Income Statement | C2: 2022 | D2: =C2+1 -> 2023 | E2: =D2+1 -> 2024 | F2: =E2+1 -> 2025 | G2: =F2+1 -> 2026 | H2: =G2+1 -> 2027 | I2: =H2+1 -> 2028 | J2: =I2+1 -> 2029
B4: Operating Case | D4: 1
D5: Variance
B6: Street Case | D6: 0 | F6: 0.097 | G6: 0.106 | H6: =G6-0.005 -> 0.101 | I6: =H6-0.005 -> 0.096 | J6: =I6-0.005 -> 0.091
B7: Optimistic Case | D7: 0.025 | F7: =F6+$D$7 -> 0.122 | G7: =G6+$D$7 -> 0.131 | H7: =H6+$D$7 -> 0.126 | I7: =I6+$D$7 -> 0.121 | J7: =J6+$D$7 -> 0.116
B8: Pessimistic Case | D8: -0.025 | F8: =F6+$D$8 -> 0.072 | G8: =G6+$D$8 -> 0.081 | H8: =H6+$D$8 -> 0.076 | I8: =I6+$D$8 -> 0.071 | J8: =J6+$D$8 -> 0.066
B10: Revenue Growth | D10: =IncState!D16/IncState!C16-1 -> 0.1536153 | E10: =IncState!E16/IncState!D16-1 -> 0.16012792 | F10: =CHOOSE(ScenarioREV,F6,F7,F8) -> 0.097 | G10: =CHOOSE(ScenarioREV,G6,G7,G8) -> 0.106 | H10: =CHOOSE(ScenarioREV,H6,H7,H8) -> 0.101 | I10: =CHOOSE(ScenarioREV,I6,I7,I8) -> 0.096 | J10: =CHOOSE(ScenarioREV,J6,J7,J8) -> 0.091
B11: COGS % of sales | C11: =IncState!C17/IncState!C16 -> 0.87683214 | D11: =IncState!D17/IncState!D16 -> 0.8806811 | E11: =IncState!E17/IncState!E16 -> 0.86209507 | F11: =E11-0.01 -> 0.85209507 | G11: =F11-0.01 -> 0.84209507 | H11: =G11-0.01 -> 0.83209507 | I11: =H11-0.01 -> 0.82209507 | J11: =I11-0.01 -> 0.81209507
B12: SG&A % of sales | C12: =IncState!C18/IncState!C16 -> 0.043017555 | D12: =IncState!D18/IncState!D16 -> 0.042831617 | E12: =IncState!E18/IncState!E16 -> 0.041550383 | F12: =E12-0.0005 -> 0.041050383 | G12: =F12-0.0005 -> 0.040550383 | H12: =G12-0.0005 -> 0.040050383 | I12: =H12-0.0005 -> 0.039550383 | J12: =I12-0.0005 -> 0.039050383
B13: Amortization $ Amt | C13: =IncState!C22 -> 0 | D13: =IncState!D22 -> 0 | E13: =IncState!E22 -> 0 | F13: =E13 -> 0 | G13: =F13 -> 0 | H13: =G13 -> 0 | I13: =H13 -> 0 | J13: =I13 -> 0
B14: Non recurring income / (expense) | C14: =IncState!C25 -> -1600 | D14: =IncState!D25 -> -275 | E14: =IncState!E25 -> -1226 | F14: 0 | G14: 0 | H14: 0 | I14: 0 | J14: 0
B15: Other Income / (expense) | C15: =IncState!C26 -> 1239 | D15: =IncState!D26 -> 1351 | E15: =IncState!E26 -> 1197 | F15: 0 | G15: 0 | H15: 0 | I15: 0 | J15: 0
B16: Effective tax rate | C16: =IncState!C33/IncState!C31 -> 0.13537744 | D16: =IncState!D33/IncState!D31 -> 0.12450955 | E16: =IncState!E33/IncState!E31 -> 0.15280558 | F16: 0.21 | G16: =F16 -> 0.21 | H16: =G16 -> 0.21 | I16: =H16 -> 0.21 | J16: =I16 -> 0.21
B17: Dividend Payout Rate | C17: =IncState!C35 -> 1.84 | D17: =IncState!D35 -> 2.2 | E17: =IncState!E35 -> 2.44 | F17: =E17+0.5 -> 2.94 | G17: =F17+0.5 -> 3.44 | H17: =G17+0.5 -> 3.94 | I17: =H17+0.5 -> 4.44 | J17: =I17+0.5 -> 4.94
B18: Basic WASO | C18: =IncState!C38 -> 67643 | D18: =IncState!D38 -> 66893 | E18: =IncState!E38 -> 66752 | F18: =E18 -> 66752 | G18: =F18 -> 66752 | H18: =G18 -> 66752 | I18: =H18 -> 66752 | J18: =I18 -> 66752
B19: Diluted WASO | C19: =IncState!C39 -> 67920 | D19: =IncState!D39 -> 67149 | E19: =IncState!E39 -> 67011 | F19: =E19 -> 67011 | G19: =F19 -> 67011 | H19: =G19 -> 67011 | I19: =H19 -> 67011 | J19: =I19 -> 67011
A21: * | B21: Debt | C21: =C2 -> 2022 | D21: =D2 -> 2023 | E21: =E2 -> 2024 | F21: =F2 -> 2025 | G21: =G2 -> 2026 | H21: =H2 -> 2027 | I21: =I2 -> 2028 | J21: =J2 -> 2029
B23: Interest rate on Revolver | E23: 0.05 | F23: =E23 -> 0.05 | G23: =F23 -> 0.05 | H23: =G23 -> 0.05 | I23: =H23 -> 0.05 | J23: =I23 -> 0.05
B24: Interest rate on long-term debt | E24: 0.04 | F24: =E24 -> 0.04 | G24: =F24 -> 0.04 | H24: =G24 -> 0.04 | I24: =H24 -> 0.04 | J24: =I24 -> 0.04
B25: Interest rate on cash | E25: 0.04 | F25: =E25 -> 0.04 | G25: =F25 -> 0.04 | H25: =G25 -> 0.04 | I25: =H25 -> 0.04 | J25: =I25 -> 0.04
B27: Issuance of long-term debt | F27: 0 | G27: 0 | H27: 0 | I27: 0 | J27: 0
B28: Repayment of long-term debt | F28: 0 | G28: 0 | H28: 0 | I28: 0 | J28: 0
A30: * | B30: Calcs | C30: =C21 -> 2022 | D30: =D21 -> 2023 | E30: =E21 -> 2024 | F30: =F21 -> 2025 | G30: =G21 -> 2026 | H30: =H21 -> 2027 | I30: =I21 -> 2028 | J30: =J21 -> 2029
B32: CapEx % of Sales | C32: =246121/IncState!C16 -> 0.06130161 | D32: =347034/IncState!D16 -> 0.07492629 | E32: =354341/IncState!E16 -> 0.065944371 | F32: =AVERAGE(C32:E32) -> 0.067390757 | G32: =F32 -> 0.067390757 | H32: =G32 -> 0.067390757 | I32: =H32 -> 0.067390757 | J32: =I32 -> 0.067390757
B33: Depreciation % of beginning PP&E | D33: =IncState!D21/BalSheet!C23 -> 0.08060688 | E33: =IncState!E21/BalSheet!D23 -> 0.08214785 | F33: =E33 -> 0.08214785 | G33: =F33 -> 0.08214785 | H33: =G33 -> 0.08214785 | I33: =H33 -> 0.08214785 | J33: =I33 -> 0.08214785
B34: Share issuance / (repurchases) | F34: 0 | G34: 0 | H34: 0 | I34: 0 | J34: 0
A36: * | B36: Balance Sheet - Assets | C36: =C30 -> 2022 | D36: =D30 -> 2023 | E36: =E30 -> 2024 | F36: =F30 -> 2025 | G36: =G30 -> 2026 | H36: =H30 -> 2027 | I36: =I30 -> 2028 | J36: =J30 -> 2029
B38: Operating Cash % of sales | C38: =BalSheet!C16/IncState!C16 -> 0.01 | D38: =BalSheet!D16/IncState!D16 -> 0.01 | E38: =BalSheet!E16/IncState!E16 -> 0.01 | F38: =E38 -> 0.01 | G38: =F38 -> 0.01 | H38: =G38 -> 0.01 | I38: =H38 -> 0.01 | J38: =I38 -> 0.01
B39: Accounts receivable % of sales | C39: =BalSheet!C18/IncState!C16 -> 0.037426409 | D39: =BalSheet!D18/IncState!D16 -> 0.037885671 | E39: =BalSheet!E18/IncState!E16 -> 0.035949761 | F39: =E39 -> 0.035949761 | G39: =F39 -> 0.035949761 | H39: =G39 -> 0.035949761 | I39: =H39 -> 0.035949761 | J39: =I39 -> 0.035949761
B40: Inventories % of COGS | C40: =BalSheet!C19/IncState!C17 -> 0.010798458 | D40: =BalSheet!D19/IncState!D17 -> 0.0093943995 | E40: =BalSheet!E19/IncState!E17 -> 0.0087981775 | F40: =E40 -> 0.0087981775 | G40: =F40 -> 0.0087981775 | H40: =G40 -> 0.0087981775 | I40: =H40 -> 0.0087981775 | J40: =I40 -> 0.0087981775
B41: Other current assets % of sales | C41: =BalSheet!C20/IncState!C16 -> 0.0086430137 | D41: =BalSheet!D20/IncState!D16 -> 0.0082980833 | E41: =BalSheet!E20/IncState!E16 -> 0.0069634633 | F41: =E41 -> 0.0069634633 | G41: =F41 -> 0.0069634633 | H41: =G41 -> 0.0069634633 | I41: =H41 -> 0.0069634633 | J41: =I41 -> 0.0069634633
B43: Other long-term assets % of sales | C43: =BalSheet!C25/IncState!C16 -> 0.018400869 | D43: =BalSheet!D25/IncState!D16 -> 0.020510736 | E43: =BalSheet!E25/IncState!E16 -> 0.02153673 | F43: =E43 -> 0.02153673 | G43: =F43 -> 0.02153673 | H43: =G43 -> 0.02153673 | I43: =H43 -> 0.02153673 | J43: =I43 -> 0.02153673
A45: * | B45: Balance Sheet - Liabilities | C45: =C36 -> 2022 | D45: =D36 -> 2023 | E45: =E36 -> 2024 | F45: =F36 -> 2025 | G45: =G36 -> 2026 | H45: =H36 -> 2027 | I45: =I36 -> 2028 | J45: =J36 -> 2029
B47: Accounts payable % of COGS | C47: =BalSheet!C31/IncState!C17 -> 0.029985144 | D47: =BalSheet!D31/IncState!D17 -> 0.03227192 | E47: =BalSheet!E31/IncState!E17 -> 0.031256672 | F47: =E47 -> 0.031256672 | G47: =F47 -> 0.031256672 | H47: =G47 -> 0.031256672 | I47: =H47 -> 0.031256672 | J47: =I47 -> 0.031256672
B48: Other current liabilities % of sales | C48: =BalSheet!C32/IncState!C16 -> 0.13610486 | D48: =BalSheet!D32/IncState!D16 -> 0.13252147 | E48: =BalSheet!E32/IncState!E16 -> 0.1271723 | F48: =E48 -> 0.1271723 | G48: =F48 -> 0.1271723 | H48: =G48 -> 0.1271723 | I48: =H48 -> 0.1271723 | J48: =I48 -> 0.1271723
B49: Other long-term liabilities % of sales | C49: =BalSheet!C36/IncState!C16 -> 0.21071235 | D49: =BalSheet!D36/IncState!D16 -> 0.19224829 | E49: =BalSheet!E36/IncState!E16 -> 0.18404335 | F49: =E49 -> 0.18404335 | G49: =F49 -> 0.18404335 | H49: =G49 -> 0.18404335 | I49: =H49 -> 0.18404335 | J49: =I49 -> 0.18404335

Sheet Calcs
A1: =CoName -> Texas Roadhouse Inc | C1: Hist. | D1: Hist. | E1: Hist. | F1: Proj. | G1: Proj. | H1: Proj. | I1: Proj. | J1: Proj.
A2: Net PP&E | C2: 2022 | D2: =C2+1 -> 2023 | E2: =D2+1 -> 2024 | F2: =E2+1 -> 2025 | G2: =F2+1 -> 2026 | H2: =G2+1 -> 2027 | I2: =H2+1 -> 2028 | J2: =I2+1 -> 2029
B3: Capital expenditure % of sales | F3: =Assumptions!F32 -> 0.067390757 | G3: =Assumptions!G32 -> 0.067390757 | H3: =Assumptions!H32 -> 0.067390757 | I3: =Assumptions!I32 -> 0.067390757 | J3: =Assumptions!J32 -> 0.067390757
B4: Depreciation % of PP&E | F4: =Assumptions!F33 -> 0.08214785 | G4: =F4 -> 0.08214785 | H4: =G4 -> 0.08214785 | I4: =H4 -> 0.08214785 | J4: =I4 -> 0.08214785
B6: Beginning PP&E | F6: =E9 -> 2387538 | G6: =F9 -> 2588644.8 | H6: =G9 -> 2815338.2 | I6: =H9 -> 3067783.2 | J6: =I9 -> 3345927.3
B7: Capex | F7: =F3*IncState!F16 -> 397237.86 | G7: =G3*IncState!G16 -> 439345.08 | H7: =H3*IncState!H16 -> 483718.93 | I7: =I3*IncState!I16 -> 530155.95 | J7: =J3*IncState!J16 -> 578400.14
B8: Depreciation | F8: =F6*F4 -> 196131.11 | G8: =G6*G4 -> 212651.6 | H8: =H6*H4 -> 231273.98 | I8: =I6*I4 -> 252011.79 | J8: =J6*J4 -> 274860.74
B9: Ending PP&E | E9: =BalSheet!E23 -> 2387538 | F9: =F6+F7-F8 -> 2588644.8 | G9: =G6+G7-G8 -> 2815338.2 | H9: =H6+H7-H8 -> 3067783.2 | I9: =I6+I7-I8 -> 3345927.3 | J9: =J6+J7-J8 -> 3649466.7
A10: Equity | C10: =C2 -> 2022 | D10: =D2 -> 2023 | E10: =E2 -> 2024 | F10: =F2 -> 2025 | G10: =G2 -> 2026 | H10: =H2 -> 2027 | I10: =I2 -> 2028 | J10: =J2 -> 2029
B11: Share issuance/(repurchases) | F11: =Assumptions!F34 -> 0 | G11: =Assumptions!G34 -> 0 | H11: =Assumptions!H34 -> 0 | I11: =Assumptions!I34 -> 0 | J11: =Assumptions!J34 -> 0
B13: Beginning balance | F13: =E17 -> 1373723 | G13: =F17 -> 1675060.7 | H13: =G17 -> 2049845 | I13: =H17 -> 2511838.8 | J13: =I17 -> 3075312.2
B14: Net income | F14: =IncState!F34 -> 497588.6 | G14: =IncState!G34 -> 604411.14 | H14: =IncState!H34 -> 724996.71 | I14: =IncState!I34 -> 859852.28 | J14: =IncState!J34 -> 1009293
B15: Dividends paid | F15: =-IncState!F36 -> -196250.88 | G15: =-IncState!G36 -> -229626.88 | H15: =-IncState!H36 -> -263002.88 | I15: =-IncState!I36 -> -296378.88 | J15: =-IncState!J36 -> -329754.88
B16: Share issuance / (repurchase) | F16: =F11 -> 0 | G16: =G11 -> 0 | H16: =H11 -> 0 | I16: =I11 -> 0 | J16: =J11 -> 0
B17: Ending balance | E17: =BalSheet!E39 -> 1373723 | F17: =SUM(F13:F16) -> 1675060.7 | G17: =SUM(G13:G16) -> 2049845 | H17: =SUM(H13:H16) -> 2511838.8 | I17: =SUM(I13:I16) -> 3075312.2 | J17: =SUM(J13:J16) -> 3754850.3
A18: OWC | C18: =C10 -> 2022 | D18: =D10 -> 2023 | E18: =E10 -> 2024 | F18: =F10 -> 2025 | G18: =G10 -> 2026 | H18: =H10 -> 2027 | I18: =I10 -> 2028 | J18: =J10 -> 2029
B19: Operating Cash | E19: =BalSheet!E16 -> 53733.32 | F19: =BalSheet!F16 -> 58945.452 | G19: =BalSheet!G16 -> 65193.67 | H19: =BalSheet!H16 -> 71778.231 | I19: =BalSheet!I16 -> 78668.941 | J19: =BalSheet!J16 -> 85827.814
B20: =BalSheet!B18 -> Accounts receivable | E20: =BalSheet!E18 -> 193170 | F20: =BalSheet!F18 -> 211907.49 | G20: =BalSheet!G18 -> 234369.68 | H20: =BalSheet!H18 -> 258041.02 | I20: =BalSheet!I18 -> 282812.96 | J20: =BalSheet!J18 -> 308548.94
B21: =BalSheet!B19 -> Inventories | E21: =BalSheet!E19 -> 40756 | F21: =BalSheet!F19 -> 44190.719 | G21: =BalSheet!G19 -> 48301.35 | H21: =BalSheet!H19 -> 52548.269 | I21: =BalSheet!I19 -> 56900.76 | J21: =BalSheet!J19 -> 61323.6
B22: Other current assets | E22: =BalSheet!E20 -> 37417 | F22: =BalSheet!F20 -> 41046.449 | G22: =BalSheet!G20 -> 45397.373 | H22: =BalSheet!H20 -> 49982.507 | I22: =BalSheet!I20 -> 54780.828 | J22: =BalSheet!J20 -> 59765.883
B23: Accounts payables | E23: =BalSheet!E31 -> 144791 | F23: =BalSheet!F31 -> 156993.29 | G23: =BalSheet!G31 -> 171596.84 | H23: =BalSheet!H31 -> 186684.57 | I23: =BalSheet!I31 -> 202147.36 | J23: =BalSheet!J31 -> 217860.08
B24: Other current liabilities | E24: =BalSheet!E32 -> 683339 | F24: =BalSheet!F32 -> 749622.88 | G24: =BalSheet!G32 -> 829082.91 | H24: =BalSheet!H32 -> 912820.28 | I24: =BalSheet!I32 -> 1000451 | J24: =BalSheet!J32 -> 1091492.1
A25: * | B25: OWC | E25: =SUM(E19:E22)-SUM(E23:E24) -> -503053.68 | F25: =SUM(F19:F22)-SUM(F23:F24) -> -550526.06 | G25: =SUM(G19:G22)-SUM(G23:G24) -> -607417.67 | H25: =SUM(H19:H22)-SUM(H23:H24) -> -667154.83 | I25: =SUM(I19:I22)-SUM(I23:I24) -> -729434.9 | J25: =SUM(J19:J22)-SUM(J23:J24) -> -793885.92
B26: Change in OWC | F26: =E25-F25 -> 47472.381 | G26: =F25-G25 -> 56891.611 | H26: =G25-H25 -> 59737.154 | I26: =H25-I25 -> 62280.077 | J26: =I25-J25 -> 64451.013

Sheet Debt
A1: =CoName -> Texas Roadhouse Inc | C1: Hist. | D1: Hist. | E1: Hist. | F1: Proj. | G1: Proj. | H1: Proj. | I1: Proj. | J1: Proj.
A2: Assumptions | C2: 2022 | D2: =C2+1 -> 2023 | E2: =D2+1 -> 2024 | F2: =E2+1 -> 2025 | G2: =F2+1 -> 2026 | H2: =G2+1 -> 2027 | I2: =H2+1 -> 2028 | J2: =I2+1 -> 2029
B4: Interest rate on revolver | F4: =Assumptions!F23 -> 0.05 | G4: =Assumptions!G23 -> 0.05 | H4: =Assumptions!H23 -> 0.05 | I4: =Assumptions!I23 -> 0.05 | J4: =Assumptions!J23 -> 0.05
B5: Interest rate on long-term debt | F5: =Assumptions!F24 -> 0.04 | G5: =Assumptions!G24 -> 0.04 | H5: =Assumptions!H24 -> 0.04 | I5: =Assumptions!I24 -> 0.04 | J5: =Assumptions!J24 -> 0.04
B6: Interest rate on cash | F6: =Assumptions!F25 -> 0.04 | G6: =Assumptions!G25 -> 0.04 | H6: =Assumptions!H25 -> 0.04 | I6: =Assumptions!I25 -> 0.04 | J6: =Assumptions!J25 -> 0.04
B8: Issuance of long-term debt | F8: =Assumptions!F27 -> 0 | G8: =Assumptions!G27 -> 0 | H8: =Assumptions!H27 -> 0 | I8: =Assumptions!I27 -> 0 | J8: =Assumptions!J27 -> 0
B9: Repayment of long-term debt | F9: =Assumptions!F28 -> 0 | G9: =Assumptions!G28 -> 0 | H9: =Assumptions!H28 -> 0 | I9: =Assumptions!I28 -> 0 | J9: =Assumptions!J28 -> 0
A11: Revolver | C11: =C2 -> 2022 | D11: =D2 -> 2023 | E11: =E2 -> 2024 | F11: =F2 -> 2025 | G11: =G2 -> 2026 | H11: =H2 -> 2027 | I11: =I2 -> 2028 | J11: =J2 -> 2029
B12: Balance | F12: =BalSheet!F30 -> 0 | G12: =BalSheet!G30 -> 0 | H12: =BalSheet!H30 -> 0 | I12: =BalSheet!I30 -> 0 | J12: =BalSheet!J30 -> 0
B13: Interest rate | F13: =F4 -> 0.05 | G13: =G4 -> 0.05 | H13: =H4 -> 0.05 | I13: =I4 -> 0.05 | J13: =J4 -> 0.05
B14: Interest expense | F14: =F12*-F13 -> 0 | G14: =G12*-G13 -> 0 | H14: =H12*-H13 -> 0 | I14: =I12*-I13 -> 0 | J14: =J12*-J13 -> 0
A16: Long term debt | C16: =C11 -> 2022 | D16: =D11 -> 2023 | E16: =E11 -> 2024 | F16: =F11 -> 2025 | G16: =G11 -> 2026 | H16: =H11 -> 2027 | I16: =I11 -> 2028 | J16: =J11 -> 2029
B17: Beginning balance | F17: =E20 -> 0 | G17: =F20 -> 0 | H17: =G20 -> 0 | I17: =H20 -> 0 | J17: =I20 -> 0
B18: Issuance | F18: =F8 -> 0 | G18: =G8 -> 0 | H18: =H8 -> 0 | I18: =I8 -> 0 | J18: =J8 -> 0
B19: Repayment | F19: =F9 -> 0 | G19: =G9 -> 0 | H19: =H9 -> 0 | I19: =I9 -> 0 | J19: =J9 -> 0
B20: Ending balance | E20: =BalSheet!E30 -> 0 | F20: =SUM(F17:F19) -> 0 | G20: =SUM(G17:G19) -> 0 | H20: =SUM(H17:H19) -> 0 | I20: =SUM(I17:I19) -> 0 | J20: =SUM(J17:J19) -> 0
B21: Interest rate | F21: =F5 -> 0.04 | G21: =G5 -> 0.04 | H21: =H5 -> 0.04 | I21: =I5 -> 0.04 | J21: =J5 -> 0.04
B22: Interest expense | F22: =F20*-F21 -> 0 | G22: =G20*-G21 -> 0 | H22: =H20*-H21 -> 0 | I22: =I20*-I21 -> 0 | J22: =J20*-J21 -> 0
A24: Debt summary | C24: =C16 -> 2022 | D24: =D16 -> 2023 | E24: =E16 -> 2024 | F24: =F16 -> 2025 | G24: =G16 -> 2026 | H24: =H16 -> 2027 | I24: =I16 -> 2028 | J24: =J16 -> 2029
B25: Revolver | F25: =F12 -> 0 | G25: =G12 -> 0 | H25: =H12 -> 0 | I25: =I12 -> 0 | J25: =J12 -> 0
B26: Total long term debt | F26: =F20 -> 0 | G26: =G20 -> 0 | H26: =H20 -> 0 | I26: =I20 -> 0 | J26: =J20 -> 0
B27: Total debt | F27: =SUM(F25:F26) -> 0 | G27: =SUM(G25:G26) -> 0 | H27: =SUM(H25:H26) -> 0 | I27: =SUM(I25:I26) -> 0 | J27: =SUM(J25:J26) -> 0
B28: Total interest expense | F28: =SUM(F22,F14) -> 0 | G28: =SUM(G22,G14) -> 0 | H28: =SUM(H22,H14) -> 0 | I28: =SUM(I22,I14) -> 0 | J28: =SUM(J22,J14) -> 0
A30: Interest income | C30: =C11 -> 2022 | D30: =D11 -> 2023 | E30: =E11 -> 2024 | F30: =F11 -> 2025 | G30: =G11 -> 2026 | H30: =H11 -> 2027 | I30: =I11 -> 2028 | J30: =J11 -> 2029
B31: Excess Cash | F31: =BalSheet!F17 -> 423895.63 | G31: =BalSheet!G17 -> 730415.7 | H31: =BalSheet!H17 -> 1106705.2 | I31: =BalSheet!I17 -> 1566293.1 | J31: =BalSheet!J17 -> 2123079.3
B32: Interest rate | F32: =F6 -> 0.04 | G32: =G6 -> 0.04 | H32: =H6 -> 0.04 | I32: =I6 -> 0.04 | J32: =J6 -> 0.04
B33: Interest income | F33: =F31*F32 -> 16955.825 | G33: =G31*G32 -> 29216.628 | H33: =H31*H32 -> 44268.208 | I33: =I31*I32 -> 62651.725 | J33: =J31*J32 -> 84923.172

Sheet IncState
A1: =CoName -> Texas Roadhouse Inc | C1: Hist. | D1: Hist. | E1: Hist. | F1: Proj. | G1: Proj. | H1: Proj. | I1: Proj. | J1: Proj.
A2: Assumptions | C2: 2022 | D2: =C2+1 -> 2023 | E2: =D2+1 -> 2024 | F2: =E2+1 -> 2025 | G2: =F2+1 -> 2026 | H2: =G2+1 -> 2027 | I2: =H2+1 -> 2028 | J2: =I2+1 -> 2029
B4: Revenue growth | F4: =Assumptions!F10 -> 0.097 | G4: =Assumptions!G10 -> 0.106 | H4: =Assumptions!H10 -> 0.101 | I4: =Assumptions!I10 -> 0.096 | J4: =Assumptions!J10 -> 0.091
B5: Cost of goods sold as % of sales | F5: =Assumptions!F11 -> 0.85209507 | G5: =Assumptions!G11 -> 0.84209507 | H5: =Assumptions!H11 -> 0.83209507 | I5: =Assumptions!I11 -> 0.82209507 | J5: =Assumptions!J11 -> 0.81209507
B6: SG&A % of sales | F6: =Assumptions!F12 -> 0.041050383 | G6: =Assumptions!G12 -> 0.040550383 | H6: =Assumptions!H12 -> 0.040050383 | I6: =Assumptions!I12 -> 0.039550383 | J6: =Assumptions!J12 -> 0.039050383
B7: Amortization amount | F7: =Assumptions!F13 -> 0 | G7: =Assumptions!G13 -> 0 | H7: =Assumptions!H13 -> 0 | I7: =Assumptions!I13 -> 0 | J7: =Assumptions!J13 -> 0
B8: Non recurring items, amount | F8: =Assumptions!F14 -> 0 | G8: =Assumptions!G14 -> 0 | H8: =Assumptions!H14 -> 0 | I8: =Assumptions!I14 -> 0 | J8: =Assumptions!J14 -> 0
B9: Other income (expense), amt | F9: =Assumptions!F15 -> 0 | G9: =Assumptions!G15 -> 0 | H9: =Assumptions!H15 -> 0 | I9: =Assumptions!I15 -> 0 | J9: =Assumptions!J15 -> 0
B10: Effective tax rate | F10: =Assumptions!F16 -> 0.21 | G10: =Assumptions!G16 -> 0.21 | H10: =Assumptions!H16 -> 0.21 | I10: =Assumptions!I16 -> 0.21 | J10: =Assumptions!J16 -> 0.21
B11: Dividend Payout Rate | F11: =Assumptions!F17 -> 2.94 | G11: =Assumptions!G17 -> 3.44 | H11: =Assumptions!H17 -> 3.94 | I11: =Assumptions!I17 -> 4.44 | J11: =Assumptions!J17 -> 4.94
B12: Basic WASO | F12: =Assumptions!F18 -> 66752 | G12: =Assumptions!G18 -> 66752 | H12: =Assumptions!H18 -> 66752 | I12: =Assumptions!I18 -> 66752 | J12: =Assumptions!J18 -> 66752
B13: Diluted WASO | F13: =Assumptions!F19 -> 67011 | G13: =Assumptions!G19 -> 67011 | H13: =Assumptions!H19 -> 67011 | I13: =Assumptions!I19 -> 67011 | J13: =Assumptions!J19 -> 67011
A15: Income statement | C15: =C37 -> 44926 | D15: =D37 -> 45291 | E15: =E37 -> 45657 | F15: =F37 -> 46022 | G15: =G37 -> 46022 | H15: =H37 -> 46022 | I15: =I37 -> 46022 | J15: =J37 -> 46022
B16: Revenue | C16: 4014919 | D16: 4631672 | E16: 5373332 | F16: =E16*(1+F4) -> 5894545.2 | G16: =F16*(1+G4) -> 6519367 | H16: =G16*(1+H4) -> 7177823.1 | I16: =H16*(1+I4) -> 7866894.1 | J16: =I16*(1+J4) -> 8582781.4
B17: COGS | C17: =3694722-172712-1600 -> 3520410 | D17: =4277683-198382-275 -> 4079026 | E17: =4856813-223264-1226 -> 4632323 | F17: =F16*F5 -> 5022712.9 | G17: =G16*G5 -> 5489926.8 | H17: =H16*H5 -> 5972631.1 | I17: =I16*I5 -> 6467334.8 | J17: =J16*J5 -> 6970034.4
B18: SG&A | C18: 172712 | D18: 198382 | E18: 223264 | F18: =F16*F6 -> 241973.34 | G18: =G16*G6 -> 264362.83 | H18: =H16*H6 -> 287474.56 | I18: =I16*I6 -> 311138.67 | J18: =J16*J6 -> 335160.9
A19: * | B19: EBIT | C19: =C16-SUM(C17:C18) -> 321797 | D19: =D16-SUM(D17:D18) -> 354264 | E19: =E16-SUM(E17:E18) -> 517745 | F19: =F16-SUM(F17:F18) -> 629858.99 | G19: =G16-SUM(G17:G18) -> 765077.4 | H19: =H16-SUM(H17:H18) -> 917717.36 | I19: =I16-SUM(I17:I18) -> 1088420.6 | J19: =J16-SUM(J17:J18) -> 1277586.1
B21: Depreciation | C21: 137237 | D21: 153202 | E21: 178157 | F21: =Calcs!F8 -> 196131.11 | G21: =Calcs!G8 -> 212651.6 | H21: =Calcs!H8 -> 231273.98 | I21: =Calcs!I8 -> 252011.79 | J21: =Calcs!J8 -> 274860.74
B22: Amortization | C22: 0 | D22: 0 | E22: 0 | F22: =F7 -> 0 | G22: =G7 -> 0 | H22: =H7 -> 0 | I22: =I7 -> 0 | J22: =J7 -> 0
A23: * | B23: EBITDA | C23: =SUM(C19,C21:C22) -> 459034 | D23: =SUM(D19,D21:D22) -> 507466 | E23: =SUM(E19,E21:E22) -> 695902 | F23: =SUM(F19,F21:F22) -> 825990.1 | G23: =SUM(G19,G21:G22) -> 977729 | H23: =SUM(H19,H21:H22) -> 1148991.3 | I23: =SUM(I19,I21:I22) -> 1340432.4 | J23: =SUM(J19,J21:J22) -> 1552446.8
B25: Non-recurring items | C25: -1600 | D25: -275 | E25: -1226 | F25: =F8 -> 0 | G25: =G8 -> 0 | H25: =H8 -> 0 | I25: =I8 -> 0 | J25: =J8 -> 0
B26: Other income (expense) | C26: 1239 | D26: 1351 | E26: 1197 | F26: =F9 -> 0 | G26: =G9 -> 0 | H26: =H9 -> 0 | I26: =I9 -> 0 | J26: =J9 -> 0
B28: Interest income | D28: 2984 | E28: 6774 | F28: =IF(circ=1,Debt!F33,0) -> 0 | G28: =IF(circ=1,Debt!G33,0) -> 0 | H28: =IF(circ=1,Debt!H33,0) -> 0 | I28: =IF(circ=1,Debt!I33,0) -> 0 | J28: =IF(circ=1,Debt!J33,0) -> 0
B29: Interest expense | C29: -124 | F29: =IF(circ=1,Debt!F22,0) -> 0 | G29: =IF(circ=1,Debt!G22,0) -> 0 | H29: =IF(circ=1,Debt!H22,0) -> 0 | I29: =IF(circ=1,Debt!I22,0) -> 0 | J29: =IF(circ=1,Debt!J22,0) -> 0
A31: * | B31: Pretax Income | C31: =C19+SUM(C26:C29) -> 322912 | D31: =D19+SUM(D26:D29) -> 358599 | E31: =E19+SUM(E25:E29) -> 524490 | F31: =F19+SUM(F25:F29) -> 629858.99 | G31: =G19+SUM(G25:G29) -> 765077.4 | H31: =H19+SUM(H25:H29) -> 917717.36 | I31: =I19+SUM(I25:I29) -> 1088420.6 | J31: =J19+SUM(J25:J29) -> 1277586.1
B33: Tax expense | C33: 43715 | D33: 44649 | E33: 80145 | F33: =F31*F10 -> 132270.39 | G33: =G31*G10 -> 160666.25 | H33: =H31*H10 -> 192720.64 | I33: =I31*I10 -> 228568.33 | J33: =J31*J10 -> 268293.08
A34: * | B34: Net income | C34: =C31-C33 -> 279197 | D34: =D31-D33 -> 313950 | E34: =E31-E33 -> 444345 | F34: =F31-F33 -> 497588.6 | G34: =G31-G33 -> 604411.14 | H34: =H31-H33 -> 724996.71 | I34: =I31-I33 -> 859852.28 | J34: =J31-J33 -> 1009293
B35: Dividend payout rate | C35: 1.84 | D35: 2.2 | E35: 2.44 | F35: =F11 -> 2.94 | G35: =G11 -> 3.44 | H35: =H11 -> 3.94 | I35: =I11 -> 4.44 | J35: =J11 -> 4.94
B36: Dividends | C36: =C35*C38 -> 124463.12 | D36: =D35*D38 -> 147164.6 | E36: =E35*E38 -> 162874.88 | F36: =F35*F38 -> 196250.88 | G36: =G35*G38 -> 229626.88 | H36: =H35*H38 -> 263002.88 | I36: =I35*I38 -> 296378.88 | J36: =J35*J38 -> 329754.88
A37: Shareholder information | C37: 44926 | D37: 45291 | E37: 45657 | F37: 46022 | G37: 46022 | H37: 46022 | I37: 46022 | J37: 46022
B38: Basic WASO | C38: 67643 | D38: 66893 | E38: 66752 | F38: =F12 -> 66752 | G38: =G12 -> 66752 | H38: =H12 -> 66752 | I38: =I12 -> 66752 | J38: =J12 -> 66752
B39: Diluted WASO | C39: 67920 | D39: 67149 | E39: 67011 | F39: =F13 -> 67011 | G39: =G13 -> 67011 | H39: =H13 -> 67011 | I39: =I13 -> 67011 | J39: =J13 -> 67011
B40: Basic earnings per share | C40: =C34/C38 -> 4.1275077 | D40: =D34/D38 -> 4.6933162 | E40: =E34/E38 -> 6.6566545 | F40: =F34/F38 -> 7.4542875 | G40: =G34/G38 -> 9.0545773 | H40: =H34/H38 -> 10.861049 | I40: =I34/I38 -> 12.881296 | J40: =J34/J38 -> 15.120042
A41: * | B41: Diluted earnings per share | C41: =C34/C39 -> 4.1106743 | D41: =D34/D39 -> 4.6754233 | E41: =E34/E39 -> 6.6309263 | F41: =F34/F39 -> 7.4254764 | G41: =G34/G39 -> 9.019581 | H41: =H34/H39 -> 10.81907 | I41: =I34/I39 -> 12.831509 | J41: =J34/J39 -> 15.061602

Sheet BalSheet
A1: =CoName -> Texas Roadhouse Inc | C1: Hist. | D1: Hist. | E1: Hist. | F1: Proj. | G1: Proj. | H1: Proj. | I1: Proj. | J1: Proj.
A2: Assumptions | C2: 2022 | D2: =C2+1 -> 2023 | E2: =D2+1 -> 2024 | F2: =E2+1 -> 2025 | G2: =F2+1 -> 2026 | H2: =G2+1 -> 2027 | I2: =H2+1 -> 2028 | J2: =I2+1 -> 2029
B4: Operating Cash % of sales | F4: =Assumptions!F38 -> 0.01 | G4: =F4 -> 0.01 | H4: =G4 -> 0.01 | I4: =H4 -> 0.01 | J4: =I4 -> 0.01
B5: Accounts receivable % of sales | F5: =Assumptions!F39 -> 0.035949761 | G5: =Assumptions!G39 -> 0.035949761 | H5: =Assumptions!H39 -> 0.035949761 | I5: =Assumptions!I39 -> 0.035949761 | J5: =Assumptions!J39 -> 0.035949761
B6: Inventories % of COGS | F6: =Assumptions!F40 -> 0.0087981775 | G6: =Assumptions!G40 -> 0.0087981775 | H6: =Assumptions!H40 -> 0.0087981775 | I6: =Assumptions!I40 -> 0.0087981775 | J6: =Assumptions!J40 -> 0.0087981775
B7: Other current assets % of sales | F7: =Assumptions!F41 -> 0.0069634633 | G7: =Assumptions!G41 -> 0.0069634633 | H7: =Assumptions!H41 -> 0.0069634633 | I7: =Assumptions!I41 -> 0.0069634633 | J7: =Assumptions!J41 -> 0.0069634633
B9: Other long-term assets % of sales | F9: =Assumptions!F43 -> 0.02153673 | G9: =Assumptions!G43 -> 0.02153673 | H9: =Assumptions!H43 -> 0.02153673 | I9: =Assumptions!I43 -> 0.02153673 | J9: =Assumptions!J43 -> 0.02153673
B11: Accounts payable/Accural % of COGS | F11: =Assumptions!F47 -> 0.031256672 | G11: =Assumptions!G47 -> 0.031256672 | H11: =Assumptions!H47 -> 0.031256672 | I11: =Assumptions!I47 -> 0.031256672 | J11: =Assumptions!J47 -> 0.031256672
B12: Other current liabilities % of sales | F12: =Assumptions!F48 -> 0.1271723 | G12: =Assumptions!G48 -> 0.1271723 | H12: =Assumptions!H48 -> 0.1271723 | I12: =Assumptions!I48 -> 0.1271723 | J12: =Assumptions!J48 -> 0.1271723
B13: Other long-term liabilities % of sales | F13: =Assumptions!F49 -> 0.18404335 | G13: =Assumptions!G49 -> 0.18404335 | H13: =Assumptions!H49 -> 0.18404335 | I13: =Assumptions!I49 -> 0.18404335 | J13: =Assumptions!J49 -> 0.18404335
A15: Balance sheet | C15: =C2 -> 2022 | D15: =D2 -> 2023 | E15: =E2 -> 2024 | F15: =F2 -> 2025 | G15: =G2 -> 2026 | H15: =H2 -> 2027 | I15: =I2 -> 2028 | J15: =J2 -> 2029
B16: Operating Cash | C16: =1%*IncState!C16 -> 40149.19 | D16: =1%*IncState!D16 -> 46316.72 | E16: =1%*IncState!E16 -> 53733.32 | F16: =F4*IncState!F16 -> 58945.452 | G16: =G4*IncState!G16 -> 65193.67 | H16: =H4*IncState!H16 -> 71778.231 | I16: =I4*IncState!I16 -> 78668.941 | J16: =J4*IncState!J16 -> 85827.814
B17: Excess cash | C17: =173861-C16 -> 133711.81 | D17: =104246-D16 -> 57929.28 | E17: =245225-E16 -> 191491.68 | F17: =MAX(CashFlow!F23,0) -> 423895.63 | G17: =MAX(CashFlow!G23,0) -> 730415.7 | H17: =MAX(CashFlow!H23,0) -> 1106705.2 | I17: =MAX(CashFlow!I23,0) -> 1566293.1 | J17: =MAX(CashFlow!J23,0) -> 2123079.3
B18: Accounts receivable | C18: 150264 | D18: 175474 | E18: 193170 | F18: =F5*IncState!F16 -> 211907.49 | G18: =G5*IncState!G16 -> 234369.68 | H18: =H5*IncState!H16 -> 258041.02 | I18: =I5*IncState!I16 -> 282812.96 | J18: =J5*IncState!J16 -> 308548.94
B19: Inventories | C19: 38015 | D19: 38320 | E19: 40756 | F19: =F6*IncState!F17 -> 44190.719 | G19: =G6*IncState!G17 -> 48301.35 | H19: =H6*IncState!H17 -> 52548.269 | I19: =I6*IncState!I17 -> 56900.76 | J19: =J6*IncState!J17 -> 61323.6
B20: Other current assets | C20: =5097+29604 -> 34701 | D20: =3262+35172 -> 38434 | E20: 37417 | F20: =F7*IncState!F16 -> 41046.449 | G20: =G7*IncState!G16 -> 45397.373 | H20: =H7*IncState!H16 -> 49982.507 | I20: =I7*IncState!I16 -> 54780.828 | J20: =J7*IncState!J16 -> 59765.883
B21: Total current assets | C21: =SUM(C16:C20) -> 396841 | D21: =SUM(D16:D20) -> 356474 | E21: =SUM(E16:E20) -> 516568 | F21: =SUM(F16:F20) -> 779985.74 | G21: =SUM(G16:G20) -> 1123677.8 | H21: =SUM(H16:H20) -> 1539055.2 | I21: =SUM(I16:I20) -> 2039456.6 | J21: =SUM(J16:J20) -> 2638545.5
B23: Property, plant & equipment, net | C23: =1270349+630258 -> 1900607 | D23: =1474722+694014 -> 2168736 | E23: =1617673+769865 -> 2387538 | F23: =Calcs!F9 -> 2588644.8 | G23: =Calcs!G9 -> 2815338.2 | H23: =Calcs!H9 -> 3067783.2 | I23: =Calcs!I9 -> 3345927.3 | J23: =Calcs!J9 -> 3649466.7
B24: Intangible assets | C24: =148732+5607 -> 154339 | D24: =169684+3483 -> 173167 | E24: =169684+1265 -> 170949 | F24: =E24-IncState!F22 -> 170949 | G24: =F24-IncState!G22 -> 170949 | H24: =G24-IncState!H22 -> 170949 | I24: =H24-IncState!I22 -> 170949 | J24: =I24-IncState!J22 -> 170949
B25: Other assets | C25: 73878 | D25: 94999 | E25: 115724 | F25: =F9*IncState!F16 -> 126949.23 | G25: =G9*IncState!G16 -> 140405.85 | H25: =H9*IncState!H16 -> 154586.84 | I25: =I9*IncState!I16 -> 169427.17 | J25: =J9*IncState!J16 -> 184845.05
B26: Total non-current assets | C26: =SUM(C23:C25) -> 2128824 | D26: =SUM(D23:D25) -> 2436902 | E26: =SUM(E23:E25) -> 2674211 | F26: =SUM(F23:F25) -> 2886543 | G26: =SUM(G23:G25) -> 3126693.1 | H26: =SUM(H23:H25) -> 3393319 | I26: =SUM(I23:I25) -> 3686303.5 | J26: =SUM(J23:J25) -> 4005260.8
A28: * | B28: TOTAL ASSETS | C28: =SUM(C26,C21) -> 2525665 | D28: =SUM(D26,D21) -> 2793376 | E28: =SUM(E26,E21) -> 3190779 | F28: =SUM(F26,F21) -> 3666528.7 | G28: =SUM(G26,G21) -> 4250370.8 | H28: =SUM(H26,H21) -> 4932374.2 | I28: =SUM(I26,I21) -> 5725760.1 | J28: =SUM(J26,J21) -> 6643806.3
B30: Revolver/Short term debt | C30: 0 | D30: 0 | E30: 0 | F30: =-MIN(CashFlow!F23,0) -> 0 | G30: =-MIN(CashFlow!G23,0) -> 0 | H30: =-MIN(CashFlow!H23,0) -> 0 | I30: =-MIN(CashFlow!I23,0) -> 0 | J30: =-MIN(CashFlow!J23,0) -> 0
B31: Accounts payable/Accurals | C31: 105560 | D31: 131638 | E31: 144791 | F31: =F11*IncState!F17 -> 156993.29 | G31: =G11*IncState!G17 -> 171596.84 | H31: =H11*IncState!H17 -> 186684.57 | I31: =I11*IncState!I17 -> 202147.36 | J31: =J11*IncState!J17 -> 217860.08
B32: Other current liabilities | C32: =652010-C31 -> 546450 | D32: =745434-D31 -> 613796 | E32: =828130-E31 -> 683339 | F32: =F12*IncState!F16 -> 749622.88 | G32: =G12*IncState!G16 -> 829082.91 | H32: =H12*IncState!H16 -> 912820.28 | I32: =I12*IncState!I16 -> 1000451 | J32: =J12*IncState!J16 -> 1091492.1
B33: Total current liabilities | C33: =SUM(C30:C32) -> 652010 | D33: =SUM(D30:D32) -> 745434 | E33: =SUM(E30:E32) -> 828130 | F33: =SUM(F30:F32) -> 906616.17 | G33: =SUM(G30:G32) -> 1000679.7 | H33: =SUM(H30:H32) -> 1099504.9 | I33: =SUM(I30:I32) -> 1202598.4 | J33: =SUM(J30:J32) -> 1309352.2
B35: Long-term debt, including current maturities | C35: 0 | D35: 0 | E35: 0 | F35: =Debt!F20 -> 0 | G35: =Debt!G20 -> 0 | H35: =Debt!H20 -> 0 | I35: =Debt!I20 -> 0 | J35: =Debt!J20 -> 0
B36: Other long-term liabilities | C36: =1498003-C33 -> 845993 | D36: =743476+8893+23104+114958 -> 890431 | E36: =826300+9288+8184+145154 -> 988926 | F36: =BalSheet!F13*IncState!F16 -> 1084851.8 | G36: =BalSheet!G13*IncState!G16 -> 1199846.1 | H36: =BalSheet!H13*IncState!H16 -> 1321030.6 | I36: =BalSheet!I13*IncState!I16 -> 1447849.5 | J36: =BalSheet!J13*IncState!J16 -> 1579603.8
B37: Total non-current liabilities | C37: =SUM(C35:C36) -> 845993 | D37: =SUM(D35:D36) -> 890431 | E37: =SUM(E35:E36) -> 988926 | F37: =SUM(F35:F36) -> 1084851.8 | G37: =SUM(G35:G36) -> 1199846.1 | H37: =SUM(H35:H36) -> 1321030.6 | I37: =SUM(I35:I36) -> 1447849.5 | J37: =SUM(J35:J36) -> 1579603.8
B39: Equity | C39: 1027662 | D39: 1157511 | E39: 1373723 | F39: =Calcs!F17 -> 1675060.7 | G39: =Calcs!G17 -> 2049845 | H39: =Calcs!H17 -> 2511838.8 | I39: =Calcs!I17 -> 3075312.2 | J39: =Calcs!J17 -> 3754850.3
A40: * | B40: TOTAL LIABILITIES & EQUITY | C40: =SUM(C39,C37,C33) -> 2525665 | D40: =SUM(D39,D37,D33) -> 2793376 | E40: =SUM(E39,E37,E33) -> 3190779 | F40: =SUM(F39,F37,F33) -> 3666528.7 | G40: =SUM(G39,G37,G33) -> 4250370.8 | H40: =SUM(H39,H37,H33) -> 4932374.2 | I40: =SUM(I39,I37,I33) -> 5725760.1 | J40: =SUM(J39,J37,J33) -> 6643806.3
A42: * | B42: Balance check | C42: =C40-C28 -> 0 | D42: =D40-D28 -> 0 | E42: =E40-E28 -> 0 | F42: =F40-F28 -> 0 | G42: =G40-G28 -> 0 | H42: =H40-H28 -> 0 | I42: =I40-I28 -> 0 | J42: =J40-J28 -> 0

Sheet CashFlow
A1: =CoName -> Texas Roadhouse Inc | C1: Hist. | D1: Hist. | E1: Hist. | F1: Proj. | G1: Proj. | H1: Proj. | I1: Proj. | J1: Proj.
A2: Cash flow statement | C2: 2022 | D2: =C2+1 -> 2023 | E2: =D2+1 -> 2024 | F2: =E2+1 -> 2025 | G2: =F2+1 -> 2026 | H2: =G2+1 -> 2027 | I2: =H2+1 -> 2028 | J2: =I2+1 -> 2029
B3: Net Income | F3: =IncState!F34 -> 497588.6 | G3: =IncState!G34 -> 604411.14 | H3: =IncState!H34 -> 724996.71 | I3: =IncState!I34 -> 859852.28 | J3: =IncState!J34 -> 1009293
B4: Depreciation | F4: =IncState!F21 -> 196131.11 | G4: =IncState!G21 -> 212651.6 | H4: =IncState!H21 -> 231273.98 | I4: =IncState!I21 -> 252011.79 | J4: =IncState!J21 -> 274860.74
B5: Amortization | F5: =IncState!F22 -> 0 | G5: =IncState!G22 -> 0 | H5: =IncState!H22 -> 0 | I5: =IncState!I22 -> 0 | J5: =IncState!J22 -> 0
B6: (inc) / dec in OWC | F6: =Calcs!F26 -> 47472.381 | G6: =Calcs!G26 -> 56891.611 | H6: =Calcs!H26 -> 59737.154 | I6: =Calcs!I26 -> 62280.077 | J6: =Calcs!J26 -> 64451.013
B7: (inc) / dec in LT Assets | F7: =BalSheet!E25-BalSheet!F25 -> -11225.228 | G7: =BalSheet!F25-BalSheet!G25 -> -13456.618 | H7: =BalSheet!G25-BalSheet!H25 -> -14180.99 | I7: =BalSheet!H25-BalSheet!I25 -> -14840.336 | J7: =BalSheet!I25-BalSheet!J25 -> -15417.873
B8: inc / (dec) in LT liabilities | F8: =BalSheet!F36-BalSheet!E36 -> 95925.822 | G8: =BalSheet!G36-BalSheet!F36 -> 114994.29 | H8: =BalSheet!H36-BalSheet!G36 -> 121184.46 | I8: =BalSheet!I36-BalSheet!H36 -> 126818.93 | J8: =BalSheet!J36-BalSheet!I36 -> 131754.31
B9: CFFO | F9: =SUM(F3:F8) -> 825892.69 | G9: =SUM(G3:G8) -> 975492.03 | H9: =SUM(H3:H8) -> 1123011.3 | I9: =SUM(I3:I8) -> 1286122.7 | J9: =SUM(J3:J8) -> 1464941.2
B11: Capex | F11: =-Calcs!F7 -> -397237.86 | G11: =-Calcs!G7 -> -439345.08 | H11: =-Calcs!H7 -> -483718.93 | I11: =-Calcs!I7 -> -530155.95 | J11: =-Calcs!J7 -> -578400.14
B12: CFFI | F12: =SUM(F11) -> -397237.86 | G12: =SUM(G11) -> -439345.08 | H12: =SUM(H11) -> -483718.93 | I12: =SUM(I11) -> -530155.95 | J12: =SUM(J11) -> -578400.14
B14: Dividends Paid | F14: =-IncState!F36 -> -196250.88 | G14: =-IncState!G36 -> -229626.88 | H14: =-IncState!H36 -> -263002.88 | I14: =-IncState!I36 -> -296378.88 | J14: =-IncState!J36 -> -329754.88
B15: Debt Issuance / (repayments) | F15: =SUM(Debt!F8:F9) -> 0 | G15: =SUM(Debt!G8:G9) -> 0 | H15: =SUM(Debt!H8:H9) -> 0 | I15: =SUM(Debt!I8:I9) -> 0 | J15: =SUM(Debt!J8:J9) -> 0
B16: Share issuance / (repurchases) | F16: =Calcs!F11 -> 0 | G16: =Calcs!G11 -> 0 | H16: =Calcs!H11 -> 0 | I16: =Calcs!I11 -> 0 | J16: =Calcs!J11 -> 0
B17: CFFF | F17: =SUM(F14:F16) -> -196250.88 | G17: =SUM(G14:G16) -> -229626.88 | H17: =SUM(H14:H16) -> -263002.88 | I17: =SUM(I14:I16) -> -296378.88 | J17: =SUM(J14:J16) -> -329754.88
B19: Net changes in cash | F19: =SUM(F17,F12,F9) -> 232403.95 | G19: =SUM(G17,G12,G9) -> 306520.07 | H19: =SUM(H17,H12,H9) -> 376289.5 | I19: =SUM(I17,I12,I9) -> 459587.92 | J19: =SUM(J17,J12,J9) -> 556786.17
B21: Beginning cash | F21: =E23 -> 191491.68 | G21: =F23 -> 423895.63 | H21: =G23 -> 730415.7 | I21: =H23 -> 1106705.2 | J21: =I23 -> 1566293.1
B22: =B19 -> Net changes in cash | F22: =F19 -> 232403.95 | G22: =G19 -> 306520.07 | H22: =H19 -> 376289.5 | I22: =I19 -> 459587.92 | J22: =J19 -> 556786.17
B23: Ending cash | E23: =BalSheet!E17 -> 191491.68 | F23: =SUM(F21:F22) -> 423895.63 | G23: =SUM(G21:G22) -> 730415.7 | H23: =SUM(H21:H22) -> 1106705.2 | I23: =SUM(I21:I22) -> 1566293.1 | J23: =SUM(J21:J22) -> 2123079.3

Sheet Free Cash Flow
A1: =CoName -> Texas Roadhouse Inc | C1: Hist. | D1: Hist. | E1: Hist. | F1: Proj. | G1: Proj. | H1: Proj. | I1: Proj. | J1: Proj.
A2: Free Cash Flows | C2: 2022 | D2: =C2+1 -> 2023 | E2: =D2+1 -> 2024 | F2: =E2+1 -> 2025 | G2: =F2+1 -> 2026 | H2: =G2+1 -> 2027 | I2: =H2+1 -> 2028 | J2: =I2+1 -> 2029
A3: * | B3: Sales | F3: =IncState!F16 -> 5894545.2 | G3: =IncState!G16 -> 6519367 | H3: =IncState!H16 -> 7177823.1 | I3: =IncState!I16 -> 7866894.1 | J3: =IncState!J16 -> 8582781.4
B4: EBIT | F4: =IncState!F19 -> 629858.99 | G4: =IncState!G19 -> 765077.4 | H4: =IncState!H19 -> 917717.36 | I4: =IncState!I19 -> 1088420.6 | J4: =IncState!J19 -> 1277586.1
B5: Effective Tax Rate | F5: =Assumptions!F16 -> 0.21 | G5: =Assumptions!G16 -> 0.21 | H5: =Assumptions!H16 -> 0.21 | I5: =Assumptions!I16 -> 0.21 | J5: =Assumptions!J16 -> 0.21
A7: * | B7: NOPAT | F7: =F4*(1-F5) -> 497588.6 | G7: =G4*(1-G5) -> 604411.14 | H7: =H4*(1-H5) -> 724996.71 | I7: =I4*(1-I5) -> 859852.28 | J7: =J4*(1-J5) -> 1009293
B8: Depreciation | F8: =CashFlow!F4 -> 196131.11 | G8: =CashFlow!G4 -> 212651.6 | H8: =CashFlow!H4 -> 231273.98 | I8: =CashFlow!I4 -> 252011.79 | J8: =CashFlow!J4 -> 274860.74
B9: Amortization | F9: =CashFlow!F5 -> 0 | G9: =CashFlow!G5 -> 0 | H9: =CashFlow!H5 -> 0 | I9: =CashFlow!I5 -> 0 | J9: =CashFlow!J5 -> 0
B10: (inc) / dec in OWC | F10: =CashFlow!F6 -> 47472.381 | G10: =CashFlow!G6 -> 56891.611 | H10: =CashFlow!H6 -> 59737.154 | I10: =CashFlow!I6 -> 62280.077 | J10: =CashFlow!J6 -> 64451.013
B11: (inc) / dec in other long-term assets | F11: =CashFlow!F7 -> -11225.228 | G11: =CashFlow!G7 -> -13456.618 | H11: =CashFlow!H7 -> -14180.99 | I11: =CashFlow!I7 -> -14840.336 | J11: =CashFlow!J7 -> -15417.873
B12: inc / (dec) other long-term liabilities | F12: =CashFlow!F8 -> 95925.822 | G12: =CashFlow!G8 -> 114994.29 | H12: =CashFlow!H8 -> 121184.46 | I12: =CashFlow!I8 -> 126818.93 | J12: =CashFlow!J8 -> 131754.31
B13: (Capex) | F13: =CashFlow!F11 -> -397237.86 | G13: =CashFlow!G11 -> -439345.08 | H13: =CashFlow!H11 -> -483718.93 | I13: =CashFlow!I11 -> -530155.95 | J13: =CashFlow!J11 -> -578400.14
A15: * | B15: Free Cash Flow | F15: =SUM(F7:F13) -> 428654.83 | G15: =SUM(G7:G13) -> 536146.95 | H15: =SUM(H7:H13) -> 639292.38 | I15: =SUM(I7:I13) -> 755966.8 | J15: =SUM(J7:J13) -> 886541.05

Sheet WACC
A1: =CoName -> Texas Roadhouse Inc
A3: * | B3: WACC | G3: Comp | H3: Levered beta | I3: Gross debt | J3: Market cap | K3: Debt/Mcap | L3: MTR | M3: Unlevered beta
B4: Tax Rate | E4: =Assumptions!F16 -> 0.21 | L4: =E4 -> 0.21 | M4: =H4/((1+K4*(1-L4))) -> 0
B5: Risk free rate | E5: 0.0415 | L5: =L4 -> 0.21 | M5: =H5/((1+K5*(1-L5))) -> 0
B6: Market risk Premium | E6: 0.05 | L6: =L5 -> 0.21 | M6: =H6/((1+K6*(1-L6))) -> 0
B7: Beta | E7: 0.67 | L7: =L6 -> 0.21 | M7: =H7/((1+K7*(1-L7))) -> 0
B8: Cost of Equity | E8: =E5+E6*E7 -> 0.075
B9: % Equity | E9: =1-E10 -> 0.9169623 | G9: Industry beta (average) | M9: =AVERAGE(M4:M7) -> 0
B10: % Debt | E10: =MAIN!F8/MAIN!F6 -> 0.083037701
B11: Cost of debt | E11: =Assumptions!F24 -> 0.04 | G11: Re-levered beta | M11: =M9*(1+E10*(1-E4)) -> 0
B12: Post tax cost of debt | E12: =E11*(1-E4) -> 0.0316
A13: * | B13: WACC | E13: =WACC!E8*WACC!E9+WACC!E12*WACC!E10 -> 0.071396164
B14: Long Term growth rate | E14: 0.025

Sheet DCF Model
A1: =CoName -> Texas Roadhouse Inc | D1: Proj. | E1: Proj. | F1: Proj. | G1: Proj. | H1: Proj.
A2: Discount Model Year count | D2: 0.5 | E2: =D2+1 -> 1.5 | F2: =E2+1 -> 2.5 | G2: =F2+1 -> 3.5 | H2: =G2+1 -> 4.5
B3: Discount Factor | D3: =1/(1+$K$17)^D2 -> 0.96610639 | E3: =1/(1+$K$17)^E2 -> 0.90172658 | F3: =1/(1+$K$17)^F2 -> 0.84163693 | G3: =1/(1+$K$17)^G2 -> 0.78555156 | H3: =1/(1+$K$17)^H2 -> 0.73320363
B4: PV FCF | D4: =D3*'Free Cash Flow'!F15 -> 414126.17 | E4: =E3*'Free Cash Flow'!G15 -> 483457.95 | F4: =F3*'Free Cash Flow'!H15 -> 538052.08 | G4: =G3*'Free Cash Flow'!I15 -> 593850.9 | H4: =H3*'Free Cash Flow'!J15 -> 650015.12
H5: =(H4*(1+K18))/(K17-K18) -> 14360358
A6: Value Calculation | E6: Multiples Calculation
B7: Total PV of FCFs | C7: =SUM(D4:H4) -> 2679502.2 | E7: Total PV of FCFs | G7: =C7 -> 2679502.2
B8: PV of TV | C8: =H5*H3 -> 10529066 | E8: Multiple TV | G8: =G10*H3*IncState!J23 -> 17073895
B9: EV | C9: =SUM(C7:C8) -> 13208569 | E9: EV | G9: =SUM(G7:G8) -> 19753397
E10: Implied EBITDA multiple | G10: 15
B12: Cash & Cash Equiv | C12: =MAIN!F7 -> 108172 | E12: Cash & Cash Equiv | G12: =C12 -> 108172
B13: Debt & Claims | C13: =MAIN!F8 -> 933744 | E13: Debt & Claims | G13: =C13 -> 933744
B14: NCI | C14: 0 | E14: NCI | G14: =C14 -> 0
B15: Equity Value | C15: =C9+C12-SUM(C13:C14) -> 12382997 | E15: Equity Value | G15: =G9+G12-SUM(G13:G14) -> 18927825
B17: Diluted S/O | C17: =MAIN!F5 -> 66146 | E17: Diluted S/O | G17: =C17 -> 66146 | I17: WACC | K17: =WACC!E13 -> 0.071396164
A18: * | B18: Implied Share Price | C18: =C15/C17 -> 187.20703 | E18: Implied Share Price | G18: =G15/G17 -> 286.15222 | I18: Long Term growth rate | K18: 0.025
A20: Sensitivity analysis
C22: Discount rate variance | E22: 0.005 | H22: Discount rate variance | J22: 0.005
C23: Implied growth rate variance | E23: 0.0025 | H23: TV multiple variance | J23: 2
E25: LTGR | J25: Exit Mult.
C26: =C18 -> 187.20703 | D26: =E26-E23 -> 0.0225 | E26: 0.025 | F26: =E26+E23 -> 0.0275 | H26: =G18 -> 286.15222 | I26: =J26-J23 -> 13 | J26: 15 | K26: =J26+J23 -> 17
C27: =C28+$E$22 -> 0.081396164 | D27: 142.07705 | E27: 147.47116 | F27: 153.3657 | H27: =C27 -> 0.081396164 | I27: 241.5695 | J27: 274.57691 | K27: 307.58432
C28: =C29+$E$22 -> 0.076396164 | D28: 158.60396 | E28: 165.31623 | F28: 172.71488 | H28: =C28 -> 0.076396164 | I28: 246.5889 | J28: 280.29189 | K28: 313.99489
C29: 0.071396164 | D29: 178.70001 | E29: 187.20703 | F29: 196.68305 | H29: =C29 -> 0.071396164 | I29: 251.73564 | J29: 286.15222 | K29: 320.56881
C30: =C29-$E$22 -> 0.066396164 | D30: 203.598 | E30: 214.62355 | F30: 227.0664 | H30: =C30 -> 0.066396164 | I30: 257.01361 | J30: 292.16233 | K30: 327.31105
C31: =C30-$E$22 -> 0.061396164 | D31: 235.16558 | E31: 249.86001 | F31: 266.722 | H31: =C31 -> 0.061396164 | I31: 262.42681 | J31: 298.3268 | K31: 334.22679
